Workbook
Name \P: #REF!
Name _: #REF!
Name __PF1: #REF!
Name _cbf1: #REF!
Name _cth1: #REF!
Name _cxe1: #REF!
Name _new97: #REF!
Name _PF2: #REF!
Name _PG1: #REF!
Name _PG2: #REF!
Name A: #N/A
Name Accounts: #REF!
Name Accounts1: #REF!
Name accts: #REF!
Name ACDATE: #REF!
Name acq: #REF!
Name Acquisition_Total_Cost: #REF!
Name Acres_Acquired: #REF!
Name address: #REF!
Name AliasTable: #REF!
Name Amenity: #REF!
Name Amenroof: #REF!
Name amo: #REF!
Name Amount: #REF!
Name Analysis_End_Date: #REF!
Name Analysis_End_Month: #REF!
Name Analysis_Length_Years: #REF!
Name Analysis_Start_Date: #REF!
Name Argus: ROW()-ROW([1]!rrFirstRow)-1
Name Argus: ROW()-ROW([1]!rrFirstRow)-1
Name Argus: ROW()-ROW([1]!rrFirstRow)-1
Name Argus: ROW()-ROW([1]!rrFirstRow)-1
Name ASDATE: #REF!
Name AsOf: #REF!
Name Asset_Number: #REF!
Name AssetChart: [1]!AssetChart
Name ASSUMP1: #REF!
Name ASSUMP2: #REF!
Name AveUnitSize: #REF!
Name Avg_Sales_Lead_Time: #REF!
Name AVILAFEES: #REF!
Name B: #N/A
Name BB_HC: #REF!
Name Beg_Bal: #REF!
Name BGRSF: #REF!
Name BillTo: #REF!
Name BillToAddress: #REF!
Name BillToCitySt: #REF!
Name BillToContact: #REF!
Name BillToCustomer: #REF!
Name BillToName: #REF!
Name BillToPhone: #REF!
Name BillToZip: #REF!
Name Blah: #REF!
Name blah8: #REF!
Name BNRSF: #REF!
Name Bud_Yr: #REF!
Name Budget_Year: #REF!
Name buildcount: '[2]Deal Sheet Inputs'!$C$77
Name buildcount: Inputs!$C$76

Sheet LENDER
B2: =[3]Inputs!D5 -> 2, 4-A & 4 Henderson Dr. | C2: =[3]Inputs!D6 -> Travelers Rest SC
B4: Lot/Unit Count : | C4: 5
B6: LTV : | C6: 0.7 | D6: Extension : | E6: 2 x 6 months x .5%
B7: LTC : | C7: 0.9 | D7: Guaranty Type : | E7: Limited Recourse
B9: Origination : | C9: 0.01
B10: Rate : | C10: 0.0925 | J10: Close | K10: Holdback | L10: Total
B11: Term : | C11: 18 | H11: Lender | I11: Lot Advance | J11: =D31 -> 59933.53 | K11: =D32 -> 302472.35 | L11: =J11+K11+J12 -> 384725.12
I12: IR + Closing | J12: =D24+D25+D26 -> 22319.234
D13: Per Unit | H13: Cash | J13: =D34 -> 65066.47 | L13: =J13+K13 -> 65066.47
B14: ARV : | C14: =D14*C4 -> 2995000 | D14: =[3]Inputs!I72 -> 599000 | E14: =C22/C14 -> 0.64227899 | F14: Lender LTV | J14: =SUM(J11:J13) -> 147319.23 | K14: =SUM(K11:K13) -> 302472.35 | L14: =SUM(L11:L13) -> 449791.59
B16: Land Purchase : | C16: 625000 | D16: =C16/$C$4 -> 125000
B18: Sitework/Horizontal Development : | C18: =D18*C4 -> 98800 | D18: ='[3]Acquisition Summary'!D22 -> 19760
B19: Vertical Construction Reserve : | C19: =D19*C4 -> 1413561.8 | D19: ='[3]Acquisition Summary'!D30 -> 282712.35
B20: Total Construction : | C20: =C19+C18 -> 1512361.8 | D20: =D19+D18 -> 302472.35
B22: Total Loan: | C22: =MIN((C14*C6),C28*C7) -> 1923625.6 | D22: =C22/$C$4 -> 384725.12
B24: Interest Reserve : | C24: =D24*$C$4 -> 82984.916 | D24: =[3]Inputs!O29 -> 16596.983
B25: Origination : | C25: =C22*C9 -> 19236.256 | D25: =C25/$C$4 -> 3847.2512
B26: Est. Closing Cost : | C26: =D26*C4 -> 9375 | D26: =[3]Inputs!D18 -> 1875
B27: Total Costs : | C27: =C28+C25+C26+C24 -> 2248957.9 | D27: =C27/$C$4 -> 449791.59
B28: Total Mortgageable Costs : | C28: =C20+C16 -> 2137361.8 | D28: =D20+D16 -> 427472.35 | E28: =C22/C28 -> 0.9 | F28: Lender LTC
B30: Net Loan after closing costs and IR: | C30: =C22-C24-C25-C26 -> 1812029.4 | D30: =D22-D24-D25-D26 -> 362405.88
B31: Lot Advance : | C31: =C30-C32 -> 299667.65 | D31: =C31/$C$4 -> 59933.53
B32: Construction Holdback : | C32: =C20 -> 1512361.8 | D32: =C32/$C$4 -> 302472.35
B34: Cash required at Close : | C34: =C28-C30 -> 325332.35 | D34: =C34/$C$4 -> 65066.47

Sheet Inputs
H1: Legend | I1: All cells need to be filled
B2: =D5 & " - Deal Sheet Inputs" -> 241 Willard Street - Deal Sheet Inputs | L2: Vertical Sources & Uses
B4: General Data | F4: Notes | L4: SOURCES | Z4: Acquistions Breakdown
B5: Address | D5: 241 Willard Street | O5: Total | P5: Cash at Close | Q5: Remaining | Z5: Commission | AA5: =D19 -> 0
B6: City, State, Zip | D6: Greenville, SC | L6: =+'Acquisition Summary'!B13 -> Renovo Loan | N6: =+O6/O8 -> 0.84722065 | O6: =+D96*buildcount -> 267728.88 | P6: =+IF(M23="Manual",P32-O7,D100) -> 77000 | Q6: =+IF(M23="Manual",Q32,O6-P6) -> 190728.88 | Z6: PHC Agent | AA6: =$AA$5*AB6 -> 0 | AB6: =1/3 -> 0.33333333 | AC6: =AC8=AA8 -> TRUE
B7: Seller Names | D7: Henderson Place LLC | L7: Total Required Equity | N7: =+O7/O8 -> 0.15277935 | O7: =+O32-O6 -> 48279.565 | P7: =+IF(M23="Manual",O7,P32-P6) -> 48279.565 | Q7: =+IF(M23="Manual",0,O7-P7) -> 0 | Z7: PHC Profit | AA7: =$AA$5*AB7 -> 0 | AB7: =2/3 -> 0.66666667 | AC7: Check
B8: Seller Mailing Address | L8: Total Sources | O8: =+O7+O6 -> 316008.44 | P8: =SUM(P6:P7) -> 125279.57 | Q8: =SUM(Q6:Q7) -> 190728.88 | Z8: Total | AA8: =SUM(AA6:AA7) -> 0 | AB8: =SUM(AB6:AB7) -> 1 | AC8: =Inputs!D19 -> 0
B9: Parcel # | D9: 54000404100 | Z9: Sales Breakdown
B10: MLS Listed | L10: USES | Z10: Sale Price | AA10: ='Investor Summary'!E12 -> 450000
B11: Home Type | D11: SFH | O11: Total | P11: Cost at Close | Q11: Remaining | R11: Per Unit | S11: Per SF Total | Z11: Agent | AA11: =$AA$10*AB11 -> 6750 | AB11: 0.015 | AC11: =AC13=AA13 -> TRUE
B12: Attorney | L12: Equity OverSubscription | O12: 0 | P12: =+O12 -> 0 | Q12: =+O12-P12 -> 0 | Z12: RCR Profit | AA12: =$AA$10*AB12 -> 4500 | AB12: 0.01 | AC12: Check
B13: Settlement Date | D13: 46081 | L13: Land Purchase | O13: =D16 -> 110000 | P13: =+O13 -> 110000 | Q13: =+O13-P13 -> 0 | R13: =O13/buildcount -> 110000 | S13: =(O13/$D$76)/buildcount -> 70.785071 | T13: <---Model assumes purchase commission is part of the land purchase price. If seller is not covering, make sure PP is inflated accordingly | Z13: RCR Total | AA13: =SUM(AA11:AA12) -> 11250 | AB13: =SUM(AB11:AB12) -> 0.025 | AC13: =Inputs!D86 -> 11250
L14: =+B19 -> Buyer Commission (RCR/PHC) | N14: =+C19 -> 0 | O14: =+D19 -> 0 | P14: =+O14 -> 0 | Q14: =+O14-P14 -> 0 | R14: =O14/buildcount -> 0 | S14: =(O14/$D$76)/buildcount -> 0
B15: Land Purchase & Closing Costs | F15: Notes | L15: PHC Fees | O15: =D20 -> 0 | P15: =+O15 -> 0 | Q15: =+O15-P15 -> 0 | R15: =O15/buildcount -> 0 | S15: =(O15/$D$76)/buildcount -> 0
B16: Contract Purchase Price (Total Project) | D16: 110000 | L16: Closing Costs | N16: =+C18 -> 0.015 | O16: =+(D17+D18+(D21*(C21="Nonapplicable"))) -> 1650 | P16: =+O16 -> 1650 | Q16: =+O16-P16 -> 0 | R16: =O16/buildcount -> 1650 | S16: =(O16/$D$76)/buildcount -> 1.0617761
B17: Seller Closing Costs | D17: 0 | L17: Total Acq Costs | O17: =+SUBTOTAL(9,O13:O16) -> 111650 | P17: =+SUBTOTAL(9,P13:P16) -> 111650 | Q17: =+O17-P17 -> 0 | R17: =O17/buildcount -> 111650 | S17: =(O17/$D$76)/buildcount -> 71.846847
B18: Buyer Closing Costs | C18: 0.015 | D18: =+D16*C18 -> 1650
B19: Buyer Commission (RCR/PHC) | C19: 0 | D19: =D16*C19 -> 0 | L19: Acquisitions Due Dilligence & Horizontal Costs | O19: =D45*buildcount -> 6850 | P19: 0 | Q19: =+O19-P19 -> 6850 | R19: =O19/buildcount -> 6850 | S19: =(O19/$D$76)/buildcount -> 4.4079794
B20: PHC Fees | L20: Site Specific Costs | O20: =D58*buildcount -> 12200 | P20: 0 | Q20: =+O20-P20 -> 12200 | R20: =O20/buildcount -> 12200 | S20: =(O20/$D$76)/buildcount -> 7.8507079
B21: Due Diligence Fee | C21: Applicable | D21: =IF(C21="Applicable",500,0) -> 500 | L21: Vertical Build | O21: =+SUBTOTAL(9,O22:O23) -> 160462.21 | P21: 0 | Q21: =+O21-P21 -> 160462.21 | R21: =O21/buildcount -> 160462.21 | S21: =(O21/$D$76)/buildcount -> 103.25754
B22: Due Diligence Date | D22: 46037 | L22: Sticks & Bricks | O22: =E76 -> 133718.51 | P22: 0 | Q22: =+O22-P22 -> 133718.51 | R22: =O22/buildcount -> 133718.51 | S22: =(O22/$D$76)/buildcount -> 86.047947
B23: Due Diligence Check Delivery Method | D23: Check | L23: =+F71 -> Builder Profit | M23: Manual | N23: 0.2 | O23: =IF(M23="Manual",O22*N23,IFERROR(MAX(0.15*O22,(Q6-SUM(Q20,Q22,Q24,Q25))),0)) -> 26743.702 | P23: 0 | Q23: =+O23-P23 -> 26743.702 | R23: =O23/buildcount -> 26743.702 | S23: =(O23/$D$76)/buildcount -> 17.209589
B24: Earnest Money | D24: 1000 | L24: Soft Costs (survey, eng, tap fees, ins, tax, etc.) | O24: =D68*buildcount -> 11216.667 | P24: 0 | Q24: =+O24-P24 -> 11216.667 | R24: =O24/buildcount -> 11216.667 | S24: =(O24/$D$76)/buildcount -> 7.2179322
B25: Earnest Money Delivery Method | D25: Wire | L25: General Conditions | N25: 0 | O25: =+O22*N25 -> 0 | P25: 0 | Q25: =+O25-P25 -> 0 | R25: =O25/buildcount -> 0 | S25: =(O25/$D$76)/buildcount -> 0
L26: Total Development Costs | O26: =+O21+O20+O24+O25+O19 -> 190728.88 | P26: =+P21+P20+P24+P25+P19 -> 0 | Q26: =+O26-P26 -> 190728.88 | R26: =O26/buildcount -> 190728.88 | S26: =(O26/$D$76)/buildcount -> 122.73416
B27: Acquisitions Due Dilligence & Horizontal Costs
B28: Subdivision Costs? | C28: N/A | D28: =+IF(C28="applicable", (725+1100+500+1200)/buildcount,0) -> 0 | L28: =+D92 & " Loan Origination" -> Renovo Loan Origination | N28: =+D94 -> 0.01 | O28: =+N28*O6 -> 2677.2888 | P28: =+O28 -> 2677.2888 | Q28: =+O28-P28 -> 0 | R28: =O28/buildcount -> 2677.2888 | S28: =(O28/$D$76)/buildcount -> 1.7228371
B29: Grading Lot / Clearing & Hauling | D29: =SUMIF('Brix Actual Budget'!D:D,Inputs!B29,'Brix Actual Budget'!C:C)+1500 -> 1500 | F29: Plus Tree clearing | L29: =+IF(D93="Yes","Interest Reserve","Interest Carry Expense") -> Interest Reserve | N29: =+D95 -> 0.1025 | O29: =+IFERROR(SUM('Monthly CF'!D35:AB35),0) -> 10952.277 | P29: =+IF(D93="Yes",O29,0) -> 10952.277 | Q29: =+O29-P29 -> 0 | R29: =O29/buildcount -> 10952.277 | S29: =(O29/$D$76)/buildcount -> 7.047797
B30: Demolition | D30: =SUMIF('Brix Actual Budget'!D:D,Inputs!B30,'Brix Actual Budget'!C:C) -> 0 | L30: Total Financing Costs | O30: =+SUBTOTAL(9,O28:O29) -> 13629.565 | P30: =+SUBTOTAL(9,P28:P29) -> 13629.565 | Q30: =+O30-P30 -> 0 | R30: =O30/buildcount -> 13629.565 | S30: =(O30/$D$76)/buildcount -> 8.7706341
B31: Survey - Initial Physical + Plot Plans | D31: =SUMIF('Brix Actual Budget'!D:D,Inputs!B31,'Brix Actual Budget'!C:C) -> 1800
B32: Survey - Set Pins (Rough Stake) | D32: =SUMIF('Brix Actual Budget'!D:D,Inputs!B32,'Brix Actual Budget'!C:C) -> 400 | L32: Total Uses | O32: =+O17+O26+O30 -> 316008.44 | P32: =+P17+P26+P30 -> 125279.57 | Q32: =+O32-P32 -> 190728.88 | R32: =O32/buildcount -> 316008.44 | S32: =(O32/$D$76)/buildcount -> 203.35164
B33: Survey - Stake Footings | D33: =SUMIF('Brix Actual Budget'!D:D,Inputs!B33,'Brix Actual Budget'!C:C) -> 450 | L33: Total Mortgageable Cost | O33: =+O13+O26 -> 300728.88 | P33: =+P13+P26 -> 110000 | Q33: =+Q13+Q26 -> 190728.88 | R33: =O33/buildcount -> 300728.88
B34: UDO Requiremenets | D34: =SUMIF('Brix Actual Budget'!D:D,Inputs!B34,'Brix Actual Budget'!C:C) -> 0
B35: LDIRL | D35: =SUMIF('Brix Actual Budget'!D:D,Inputs!B35,'Brix Actual Budget'!C:C) -> 0 | L35: PROJECT SCHEDULE
B36: Temp Drive | D36: =SUMIF('Brix Actual Budget'!D:D,Inputs!B36,'Brix Actual Budget'!C:C) -> 500 | L36: Purchase Date | P36: =Inputs!D13 -> 46081 | Q36: *If purchase date falls on any day other than the last day of the month, this will round to the end of the month first before adding the add'l construction start delay
B37: Erosion Control | D37: =SUMIF('Brix Actual Budget'!D:D,Inputs!B37,'Brix Actual Budget'!C:C) -> 2000 | L37: Construction Start | O37: 1 | P37: =+EDATE(P36,O37)+1 -> 46110
B38: Additional Driveway | D38: =SUMIF('Brix Actual Budget'!D:D,Inputs!B38,'Brix Actual Budget'!C:C) -> 0 | L38: Construction Complete | O38: =_xlfn.XLOOKUP(B72,'Reference Tab'!B5:B44,'Reference Tab'!M5:M44) -> 150 | P38: =+P37+O38 -> 46260
B39: Driveway Culvert | D39: =SUMIF('Brix Actual Budget'!D:D,Inputs!B39,'Brix Actual Budget'!C:C) -> 0 | L39: Marketing/Sale Complete | O39: 1 | P39: =+P38+(O39*30) -> 46290
B40: Soil Testing | D40: =SUMIF('Brix Actual Budget'!D:D,Inputs!B40,'Brix Actual Budget'!C:C) -> 200 | L40: TOTAL PROJECT DURATION | O40: =+P39-P36 -> 209
B41: Heritage Tree Mitigation | D41: =SUMIF('Brix Actual Budget'!D:D,Inputs!B41,'Brix Actual Budget'!C:C) -> 0
B42: Portable Toilet | D42: =SUMIF('Brix Actual Budget'!D:D,Inputs!B42,'Brix Actual Budget'!C:C) -> 0
B43: =IF(D64="Gaston Co. (NC)","As-Built Survey (Gaston County Only)","")
B44: Miscellaneous
B45: Total | D45: =SUM(D28:E44) -> 6850
B47: Site Specific | F47: Notes
B48: Demolition | D48: =SUMIF('Brix Actual Budget'!D:D,Inputs!B48,'Brix Actual Budget'!C:C) -> 0
B49: Survey Set Pins | D49: =SUMIF('Brix Actual Budget'!D:D,Inputs!B49,'Brix Actual Budget'!C:C) -> 0
B50: Stake House | D50: =SUMIF('Brix Actual Budget'!D:D,Inputs!B50,'Brix Actual Budget'!C:C) -> 0
B51: Rough & Final Grading | D51: =SUMIF('Brix Actual Budget'!D:D,Inputs!B51,'Brix Actual Budget'!C:C) -> 1700
B52: Erosion Control Repair | D52: =SUMIF('Brix Actual Budget'!D:D,Inputs!B52,'Brix Actual Budget'!C:C) -> 0
B53: Temp Drive Repair | D53: =SUMIF('Brix Actual Budget'!D:D,Inputs!B53,'Brix Actual Budget'!C:C) -> 0
B54: Landscaping | D54: =SUMIF('Brix Actual Budget'!D:D,Inputs!B54,'Brix Actual Budget'!C:C) -> 2500
B55: Flatwork | D55: =SUMIF('Brix Actual Budget'!D:D,Inputs!B55,'Brix Actual Budget'!C:C) -> 0
B56: Privacy Fence | D56: =SUMIF('Brix Actual Budget'!D:D,Inputs!B56,'Brix Actual Budget'!C:C) -> 8000
B57: Miscellaneous | D57: =SUMIF('Brix Actual Budget'!D:D,Inputs!B57,'Brix Actual Budget'!C:C) -> 0
B58: Total Site Specific | D58: =SUM(D48:D57) -> 12200
B60: Soft Costs | F60: Notes
B61: Building Permits | D61: =SUMIF('Brix Actual Budget'!D:D,Inputs!B61,'Brix Actual Budget'!C:C) -> 2050
B62: Engineering | D62: =SUMIF('Brix Actual Budget'!D:D,Inputs!B62,'Brix Actual Budget'!C:C) -> 1000
B63: Draw Fees | D63: 0
B64: Water Tap | C64: 1 | D64: Greenville, SC | E64: =VLOOKUP(D64,'Reference Tab'!$B$114:$G$139,5,FALSE)*C64 -> 6000
B65: Sewer Tap | C65: 1 | D65: Greenville, SC | E65: =VLOOKUP(D65,'Reference Tab'!$B$144:$E$168,4,FALSE)*C65 -> 1500
B66: Annual Insurance | D66: 500 | E66: =(D66/12)*'Acquisition Summary'!$K$9 -> 333.33333
B67: Annual Property Taxes | D67: 500 | E67: =(D67/12)*'Acquisition Summary'!$K$9 -> 333.33333
B68: Total Soft Costs | D68: =+(E65+E64+D63+D61+D62+(SUM(D66,D67)/12*'Acquisition Summary'!K9)) -> 11216.667
B70: Projected Unit Mix
B71: Plan | C71: # of Units | D71: SF | E71: Total S&B | F71: Builder Profit | G71: Total Vertical | H71: Estimated List Price | I71: ARV | J71: Links
B72: Atlas II - SC | C72: 1 | D72: =IFERROR(_xlfn.XLOOKUP(B72,'Reference Tab'!$B$5:$B$44,'Reference Tab'!$D$5:$D$44),"") -> 1554 | E72: =IFERROR(J79*C72,0) -> 133718.51 | F72: =+IFERROR($F$76*(E72/$E$76),) -> 26743.702 | G72: =+E72+F72 -> 160462.21 | H72: =IF(ISBLANK(B72),"",IFERROR(($R$17+$R$20+F79+$R$24+G79+F72/C72)*(1+0.333334),0)) -> 394038.7 | I72: 450000 | J72: =HYPERLINK(_xlfn.XLOOKUP(B72,'Reference Tab'!B:B,'Reference Tab'!N:N))
D73: =IFERROR(_xlfn.XLOOKUP(B73,'Reference Tab'!$B$5:$B$44,'Reference Tab'!$D$5:$D$44),"") | E73: =IFERROR(J80*C73,0) -> 0 | F73: =+IFERROR($F$76*(E73/$E$76),) -> 0 | G73: =+E73+F73 -> 0 | H73: =IF(ISBLANK(B73),"",IFERROR(($R$17+$R$20+F80+$R$24+G80+F73/C73)*(1+0.333334),0)) | J73: =HYPERLINK(_xlfn.XLOOKUP(B73,'Reference Tab'!B:B,'Reference Tab'!N:N))
D74: =IFERROR(_xlfn.XLOOKUP(B74,'Reference Tab'!$B$5:$B$44,'Reference Tab'!$D$5:$D$44),"") | E74: =IFERROR(J81*C74,0) -> 0 | F74: =+IFERROR($F$76*(E74/$E$76),) -> 0 | G74: =+E74+F74 -> 0 | H74: =IF(ISBLANK(B74),"",IFERROR(($R$17+$R$20+F81+$R$24+G81+F74/C74)*(1+0.333334),0)) | J74: =HYPERLINK(_xlfn.XLOOKUP(B74,'Reference Tab'!B:B,'Reference Tab'!N:N))
D75: =IFERROR(_xlfn.XLOOKUP(B75,'Reference Tab'!$B$5:$B$44,'Reference Tab'!$D$5:$D$44),"") | E75: =IFERROR(J82*C75,0) -> 0 | F75: =+IFERROR($F$76*(E75/$E$76),) -> 0 | G75: =+E75+F75 -> 0 | H75: =IF(ISBLANK(B75),"",IFERROR(($R$17+$R$20+F82+$R$24+G82+F75/C75)*(1+0.333334),0)) | J75: =HYPERLINK(_xlfn.XLOOKUP(B75,'Reference Tab'!B:B,'Reference Tab'!N:N))
B76: Total | C76: =SUM(C72:C75) -> 1 | D76: =SUMPRODUCT(C72:C75,D72:D75)/SUM(C72:C75) -> 1554 | E76: =SUM(E72:E75) -> 133718.51 | F76: =O23 -> 26743.702 | G76: =SUM(G72:G75) -> 160462.21 | H76: =SUMPRODUCT(C72:C75,H72:H75)/SUM(C72:C75) -> 394038.7 | I76: =SUMPRODUCT(C72:C75,I72:I75)/SUM(C72:C75) -> 450000
B77: S&B | D77: =SUMIF('Brix Actual Budget'!D:D,Inputs!B77,'Brix Actual Budget'!C:C) -> 133718.51
B78: Option Adders | C78: Option Package | D78: Slab/Crawl | E78: Detached Garage | F78: Sticks & Bricks (Base) | G78: Option Package | H78: Slab/Crawl | I78: Detached Garage | J78: Total S&B
B79: =IF(ISBLANK(B72),"",B72) -> Atlas II - SC | C79: Comfort | D79: Slab | E79: No | F79: =D77 -> 133718.51 | G79: =IFERROR(INDEX('Reference Tab'!$B$4:$N$44,MATCH(Inputs!B79,'Reference Tab'!$B$4:$B$44,0),MATCH(Inputs!C79,'Reference Tab'!$B$4:$N$4,0)),0) -> 0 | H79: =IF(ISBLANK(D79),0,VLOOKUP(D79,'Reference Tab'!$C$110:$D$111,2,0)) -> 0 | I79: =IF(E79="Yes",30000,0) -> 0 | J79: =SUM(F79:I79) -> 133718.51 | K79: Custom S&B per Brix budget on last tab
B80: =IF(ISBLANK(B73),"",B73) | C80: Comfort | D80: Slab | E80: No | F80: =IFERROR(_xlfn.XLOOKUP(Inputs!B73,'Reference Tab'!$B$4:$B$44,'Reference Tab'!$H$4:$H$44),0) -> 0 | G80: =IFERROR(INDEX('Reference Tab'!$B$4:$N$44,MATCH(Inputs!B80,'Reference Tab'!$B$4:$B$44,0),MATCH(Inputs!C80,'Reference Tab'!$B$4:$N$4,0)),0) -> 0 | H80: =IF(ISBLANK(D80),0,VLOOKUP(D80,'Reference Tab'!$C$110:$D$111,2,0)) -> 0 | I80: =IF(E80="Yes",30000,0) -> 0 | J80: =SUM(F80:I80) -> 0
B81: =IF(ISBLANK(B74),"",B74) | C81: Comfort | D81: Slab | E81: No | F81: =IFERROR(_xlfn.XLOOKUP(Inputs!B74,'Reference Tab'!$B$4:$B$44,'Reference Tab'!$H$4:$H$44),0) -> 0 | G81: =IFERROR(INDEX('Reference Tab'!$B$4:$N$44,MATCH(Inputs!B81,'Reference Tab'!$B$4:$B$44,0),MATCH(Inputs!C81,'Reference Tab'!$B$4:$N$4,0)),0) -> 0 | H81: =IF(ISBLANK(D81),0,VLOOKUP(D81,'Reference Tab'!$C$110:$D$111,2,0)) -> 0 | I81: =IF(E81="Yes",30000,0) -> 0 | J81: =SUM(F81:I81) -> 0
B82: =IF(ISBLANK(B75),"",B75) | C82: Comfort | D82: Slab | E82: No | F82: =IFERROR(_xlfn.XLOOKUP(Inputs!B75,'Reference Tab'!$B$4:$B$44,'Reference Tab'!$H$4:$H$44),0) -> 0 | G82: =IFERROR(INDEX('Reference Tab'!$B$4:$N$44,MATCH(Inputs!B82,'Reference Tab'!$B$4:$B$44,0),MATCH(Inputs!C82,'Reference Tab'!$B$4:$N$4,0)),0) -> 0 | H82: =IF(ISBLANK(D82),0,VLOOKUP(D82,'Reference Tab'!$C$110:$D$111,2,0)) -> 0 | I82: =IF(E82="Yes",30000,0) -> 0 | J82: =SUM(F82:I82) -> 0
B84: Sales Closing Costs
B85: Buyer Commissions (Outside) | C85: 0.025 | D85: =+I76*C85*(1+'Acquisition Summary'!$R$1)*C76 -> 11250
B86: Sales Commissions / Marketing | C86: 0.025 | D86: =+I76*C86*(1+'Acquisition Summary'!$R$1)*C76 -> 11250
B87: PHC Fee | D87: 2500
B88: Incentives | C88: 10000 | D88: =C76*C88 -> 10000
B89: Title Recording at Sale | C89: 0.005 | D89: =+I76*C89*(1+'Acquisition Summary'!$R$1)*C76 -> 2250
B91: Lender Financing | F91: Notes
B92: Lender | D92: Renovo
B93: Interest Reserve | D93: Yes
B94: Origination | D94: =VLOOKUP($D$92,'Reference Tab'!$B$53:$H$76,2,0) -> 0.01
B95: Rate | D95: =+_xlfn.XLOOKUP(D92,'Reference Tab'!B56:B77,'Reference Tab'!D56:D77) -> 0.1025
B96: Loan Amount | D96: =IF(D99>0,MIN(D97:D99,MIN(D97:D98))) -> 267728.88
B97: LTC max | C97: =VLOOKUP($D$92,'Reference Tab'!$B$53:$H$76,4,0) -> 0.9 | D97: =+IFERROR(C97*O33/C76,) -> 270655.99
B98: LTV max | C98: =VLOOKUP($D$92,'Reference Tab'!$B$54:$G$78,6,0) -> 0.7 | D98: =C98*I76*(1+'Acquisition Summary'!R1) -> 315000
B99: =IF(D92="Renovo","Structured LTC (Custom Cap)","") -> Structured LTC (Custom Cap) | D99: =IF(B99="", "", ((O13*C98)+O26)/buildcount) -> 267728.88
B100: Lot Advance | C100: =+_xlfn.XLOOKUP(D92,'Reference Tab'!B56:B77,'Reference Tab'!F56:F77) -> 0.7 | D100: =+D16*C100 -> 77000
B102: Mezzanine Debt/Equity | F102: Notes
B103: Investor | D103: Red Cedar SLFII
B104: Origination | D104: =IFERROR(VLOOKUP(D103,'Reference Tab'!$B$81:$E$96,2,0),0) -> 0
B105: Preferred Rate | D105: =IFERROR(VLOOKUP(D103,'Reference Tab'!$B$81:$E$96,3,0),0) -> 0.16
B106: Profit Split | D106: =IFERROR(VLOOKUP(D103,'Reference Tab'!$B$81:$E$96,4,0),0) -> 0
B107: Amount | D107: =P7 -> 48279.565
...

Sheet Fee Build Dashboard
B1: =+ "DEAL SHEET | "&D6 -> DEAL SHEET | 241 Willard Street | M1: Builder Profit | N1: 0.4 | P1: =+K6 -> 46081 | Q1: =+K7 -> 46110 | R1: =+EOMONTH(Q1,1) -> 46142 | S1: =+EOMONTH(R1,1) -> 46173 | T1: =+EOMONTH(S1,1) -> 46203 | U1: =+EOMONTH(T1,1) -> 46234 | V1: =+EOMONTH(U1,1) -> 46265 | W1: =+EOMONTH(V1,1) -> 46295 | X1: =+EOMONTH(W1,1) -> 46326 | Y1: =+EOMONTH(X1,1) -> 46356 | ... AA1: =+EOMONTH(Z1,1) -> 46418
M2: Builder Profit $ / Unit | N2: =+E24-'Acquisition Summary'!E26 -> 53487.404 | P2: 1 | Q2: 2 | R2: 3 | S2: 4 | T2: 5 | U2: 6 | V2: 7 | W2: 8 | X2: 9 | Y2: 10 | Z2: 11 | AA2: 12
M3: Fee Sticks & Bricks / SF | N3: =+E24/VLOOKUP(Inputs!#REF!,'Reference Tab'!B4:M44,3,0) -> #REF! | P3: =-D14 -> -69341.823 | Q3: =+IF(Q2=$J$9,$J$16,0) -> 0 | R3: =+IF(R2=$J$9,$J$16,0) -> 0 | S3: =+IF(S2=$J$9,$J$16,0) -> 0 | T3: =+IF(T2=$J$9,$J$16,0) -> 0 | U3: =+IF(U2=$J$9,$J$16,0) -> 0 | V3: =+IF(V2=$J$9,$J$16,0) -> 0 | W3: =+IF(W2=$J$9,$J$16,0) -> #REF! | X3: =+IF(X2=$J$9,$J$16,0) -> 0 | ... AA3: =+IF(AA2=$J$9,$J$16,0) -> 0
B5: Project Information | H5: Project Timeline / Milestones | J5: Month # | K5: Date | P5: XIRR | Q5: =+XIRR(P3:AA3,P1:AA1) -> #REF!
B6: Project Name | D6: =+Inputs!D5 -> 241 Willard Street | H6: =+Inputs!L36 -> Purchase Date | J6: 1 | K6: =+Inputs!P36 -> 46081
B7: Plan Name & # of Builds | D7: =+Inputs!#REF! & " x " & buildcount -> #REF! | H7: =+Inputs!L37 -> Construction Start | J7: =+J6+Inputs!O37 -> 2 | K7: =+Inputs!P37 -> 46110
B8: Link to Plans | D8: =+IFERROR(HYPERLINK(_xlfn.XLOOKUP(Inputs!#REF!,'Reference Tab'!B6:B35,'Reference Tab'!#REF!),Inputs!#REF! & " Plans"),"Not Available") -> Not Available | H8: =+Inputs!L38 -> Construction Complete | J8: =+ROUND(J7+(Inputs!O38/30),) -> 7 | K8: =+Inputs!P38 -> 46260
B9: Home Type & SF | D9: =VLOOKUP(Inputs!#REF!,'Reference Tab'!B4:M44,2,0)& " | " & VLOOKUP(Inputs!#REF!,'Reference Tab'!B4:M44,3,0) & " HSF" -> #REF! | H9: =TEXT(Inputs!L39,) -> Marketing/Sale Complete | J9: =+J8+Inputs!O39 -> 8 | K9: =+Inputs!P39 -> 46290
B11: Sources/Uses | C11: % of Total | D11: Amount | E11: Amount/Unit | F11: Funds at Close | H11: Cash at Sale Analysis | J11: Amount | K11: Amount/Unit
B12: Sources of Funds | H12: Gross Sales Price | J12: =+Inputs!O43 -> 0 | K12: =+J12/buildcount -> 0
B13: Construction Loan | C13: =SUM(D13)/D15 -> 0.79356541 | D13: =+(D18*0.7)+(D26*0.9) -> 266560.32 | E13: =+D13/buildcount -> 266560.32 | F13: =+F31-F14 -> 55937.742 | H13: Less: Sales Commission & Closing Costs | J13: =+Inputs!O43+Inputs!#REF! -> #REF! | K13: =+J13/buildcount -> #REF!
B14: Cash Equity | C14: =SUM(D14:D14)/D15 -> 0.20643459 | D14: =+D31-D13 -> 69341.823 | E14: =+D14/buildcount -> 69341.823 | F14: =+D14 -> 69341.823 | H14: Net Sales Proceeds | J14: =+J12+J13 -> #REF! | K14: =+K12+K13 -> #REF!
B15: Total Sources of Funds | D15: =SUM(D13:D14) -> 335902.15 | E15: =+D15/buildcount -> 335902.15 | F15: =SUM(F13:F14) -> 125279.57 | H15: Less: Senior Debt Repayment | J15: =-D13 -> -266560.32 | K15: =-E13 -> -266560.32
E16: =+D16/buildcount -> 0 | H16: Net Cash | J16: =+J14+J15 -> #REF! | K16: =+K14+K15 -> #REF!
B17: Uses of Funds | E17: =+D17/buildcount -> 0 | H17: Less: Upfront Equity | J17: =-D14 -> -69341.823 | K17: =-E14 -> -69341.823
B18: Land Purchase | D18: =+Inputs!O13 -> 110000 | E18: =+D18/buildcount -> 110000 | F18: =+Inputs!P13 -> 110000 | H18: Net Profit on Equity | J18: =+J16+J17 -> #REF! | K18: =+K16+K17 -> #REF!
B19: Acquisition Fee | D19: =+Inputs!O14 -> 0 | E19: =+D19/buildcount -> 0 | F19: =+Inputs!P14 -> 0
B20: Closing Costs | D20: =+Inputs!O16 -> 1650 | E20: =+D20/buildcount -> 1650 | F20: =+Inputs!P16 -> 1650 | H20: Return Metrics
B21: Total Acq Costs | D21: =+Inputs!O17 -> 111650 | E21: =+D21/buildcount -> 111650 | F21: =+Inputs!P17 -> 111650 | H21: XIRR | K21: =+Q5 -> #REF!
E22: =+D22/buildcount -> 0 | H22: Return Multiple | K22: =+J16/-J17 -> #REF!
B23: =+Inputs!L20 -> Site Specific Costs | D23: =+Inputs!O20 -> 12200 | E23: =+D23/buildcount -> 12200 | F23: =+Inputs!P20 -> 0
B24: Sticks & Bricks | D24: =+Inputs!O22*(1+N1) -> 187205.91 | E24: =+D24/buildcount -> 187205.91 | F24: =+Inputs!P22 -> 0
B25: =+Inputs!L24 -> Soft Costs (survey, eng, tap fees, ins, tax, etc.) | D25: =+Inputs!O24 -> 11216.667 | E25: =+D25/buildcount -> 11216.667 | F25: =+Inputs!P24 -> 0
B26: Total Development Costs | D26: =SUM(D23:D25) -> 210622.58 | E26: =SUM(E23:E25) -> 210622.58 | F26: =SUM(F23:F25) -> 0
B28: Loan Origination Fee | D28: =+Inputs!O28 -> 2677.2888 | E28: =+D28/buildcount -> 2677.2888 | F28: =+Inputs!P28 -> 2677.2888
B29: Estimated Loan Interest | D29: =+Inputs!O29 -> 10952.277 | E29: =+D29/buildcount -> 10952.277 | F29: =+Inputs!P29 -> 10952.277
B30: Total Financing Costs | D30: =+Inputs!O30 -> 13629.565 | E30: =+D30/buildcount -> 13629.565 | F30: =SUM(F28:F29) -> 13629.565
B31: Total Uses of Funds | D31: =+D21+D26+D30 -> 335902.15 | E31: =+E21+E26+E30 -> 335902.15 | F31: =+F30+F26+F21 -> 125279.57
B32: **Assumes X LTV / etc.

Sheet Acquisition Summary
B1: =+ "DEAL SHEET | "&D6 -> DEAL SHEET | 241 Willard Street | Q1: Sales Price Sensitivity | R1: 0
B5: Project Information | H5: Project Timeline / Milestones | K5: Month # | L5: Date
B6: Project Name | D6: =IF(ISBLANK(Inputs!D5),"",Inputs!D5) -> 241 Willard Street | H6: =+Inputs!L36 -> Purchase Date | K6: 1 | L6: =+Inputs!P36 -> 46081
B7: Plan Name & # of Builds | D7: =_xlfn.TEXTJOIN(" | ",TRUE,IF(AND(Inputs!B72<>"",Inputs!C72<>""),Inputs!B72 & " x " & Inputs!C72,""),IF(AND(Inputs!B73<>"",Inputs!C73<>""),Inputs!B73 & " x " & Inputs!C73,""),IF(AND(Inputs!B74<>"",Inputs!C74<>""),Inputs!B74 & " x " & Inputs!C74,""),IF(AND(Inputs!B75<>"",Inputs!C75<>""),Inputs!B75 & " x " & Inputs!C75,"")) -> Atlas II - SC x 1 | H7: =+Inputs!L37 -> Construction Start | K7: =+K6+Inputs!O37 -> 2 | L7: =+Inputs!P37 -> 46110
B8: Location | D8: =Inputs!D6 -> Greenville, SC | H8: =+Inputs!L38 -> Construction Complete | K8: =+ROUND(K7+(Inputs!O38/30),) -> 7 | L8: =+Inputs!P38 -> 46260
B9: Home Type | D9: =Inputs!D11 -> SFH | H9: =TEXT(Inputs!L39,) -> Marketing/Sale Complete | K9: =+K8+Inputs!O39 -> 8 | L9: =+Inputs!P39 -> 46290
B11: Sources/Uses | C11: % of Total | D11: Amount | E11: Amount/Build | F11: Funds at Close | H11: Profit Analysis | I11: Benchmark | J11: % | K11: Amount | L11: Amount/Unit | M11: Notes
B12: Sources of Funds | H12: Projected Sales Price | I12: 1 | J12: 1 | K12: =SUM('Monthly CF'!D26:AB26) -> 450000 | L12: =K12/buildcount -> 450000
B13: =+Inputs!D92& " Loan" -> Renovo Loan | C13: =SUM(D13)/D15 -> 0.84722065 | D13: =+Inputs!O6 -> 267728.88 | E13: =+D13/buildcount -> 267728.88 | F13: =+Inputs!P6 -> 77000 | H13: Less: Total Pad Cost | I13: =IF($D$9="SFH",_xlfn.XLOOKUP(H13,'CFO Summary'!C:C,'CFO Summary'!G:G),IF('Acquisition Summary'!$D$9="TH",_xlfn.XLOOKUP('Acquisition Summary'!H13,'CFO Summary'!C:C,'CFO Summary'!H:H))) -> 0.23 | J13: =K13/$K$12 -> 0.26333333 | K13: =D23 -> 118500 | L13: =K13/buildcount -> 118500
B14: Common Equity | C14: =SUM(D14:D14)/D15 -> 0.15277935 | D14: =+Inputs!O7 -> 48279.565 | E14: =+D14/buildcount -> 48279.565 | F14: =-'Monthly CF'!D45 -> 48279.565 | H14: Less: Total Direct Vertical | I14: =IF($D$9="SFH",_xlfn.XLOOKUP(H14,'CFO Summary'!C:C,'CFO Summary'!G:G),IF('Acquisition Summary'!$D$9="TH",_xlfn.XLOOKUP('Acquisition Summary'!H14,'CFO Summary'!C:C,'CFO Summary'!H:H))) -> 0.5 | J14: =K14/$K$12 -> 0.34918928 | K14: =D28 -> 157135.18 | L14: =K14/buildcount -> 157135.18
B15: Total Homebuilding Sources | D15: =SUM(D13:D14) -> 316008.44 | E15: =+D15/buildcount -> 316008.44 | F15: =SUM(F13:F14) -> 125279.57 | H15: Direct Profit | I15: =I12-I13-I14 -> 0.27 | J15: =J12-J13-J14 -> 0.38747739 | K15: =K12-K13-K14 -> 174364.82 | L15: =K15/buildcount -> 174364.82
H16: Less: Closing Costs | I16: 0.003 | J16: =K16/$K$12 -> 0.005 | K16: =Inputs!D89 -> 2250 | L16: =K16/buildcount -> 2250
B17: Uses of Funds | H17: Less: Incentives | I17: 0.015 | J17: =K17/$K$12 -> 0.022222222 | K17: =Inputs!D88 -> 10000 | L17: =K17/buildcount -> 10000
B18: Land Purchase | D18: =+Inputs!O13 -> 110000 | E18: =+D18/buildcount -> 110000 | F18: =+Inputs!P13 -> 110000 | H18: Less: Commissions (in-House & Outside) | I18: 0.05 | J18: =K18/$K$12 -> 0.05 | K18: =SUM(Inputs!D85:D86) -> 22500 | L18: =K18/buildcount -> 22500
B19: Acquisition Fee | D19: =+Inputs!O14 -> 0 | E19: =+D19/buildcount -> 0 | F19: =+Inputs!P14 -> 0 | H19: Gross Profit | I19: =I15-I16-I17-I18 -> 0.202 | J19: =J15-J16-J17-J18 -> 0.31025516 | K19: =K15-SUM(K16:K18) -> 139614.82 | L19: =K19/buildcount -> 139614.82
B20: Closing Costs | D20: =+Inputs!O16 -> 1650 | E20: =+D20/buildcount -> 1650 | F20: =+Inputs!P16 -> 1650
B21: Total Land Acq | D21: =+Inputs!O17 -> 111650 | E21: =+D21/buildcount -> 111650 | F21: =+Inputs!P17 -> 111650 | H21: Cash at Sale Analysis | K21: Amount | L21: Amount/Unit
B22: =Inputs!L19 -> Acquisitions Due Dilligence & Horizontal Costs | D22: =Inputs!O19 -> 6850 | E22: =+D22/buildcount -> 6850 | F22: =+Inputs!P18 -> 0 | H22: Net Sales Proceeds | K22: =K12-K16-K17-K18 -> 415250 | L22: =K22/buildcount -> 415250
B23: Total Pad Cost | C23: =+D23/D36 -> 0.37498998 | D23: =+D21+D22 -> 118500 | E23: =+E21+E22 -> 118500 | F23: =+F21+F22 -> 111650 | H23: Less: Senior Debt Repayment | K23: =D13 -> 267728.88 | L23: =K23/buildcount -> 267728.88
H24: Less: Equity/Mezz Capital Repayment | K24: =D14 -> 48279.565 | L24: =K24/buildcount -> 48279.565
B25: =+Inputs!L20 -> Site Specific Costs | D25: =+Inputs!O20 -> 12200 | E25: =+D25/buildcount -> 12200 | F25: =+Inputs!P20 -> 0 | H25: Less: Preferred Return/Mezz Interest Payment | K25: ='Monthly CF'!C51 -> 4549.0079 | L25: =K25/buildcount -> 4549.0079
B26: Sticks & Bricks | D26: =+Inputs!O22 -> 133718.51 | E26: =+D26/buildcount -> 133718.51 | F26: =+Inputs!P22 -> 0 | H26: Less: Profit Split to LP/Mezz | K26: ='Monthly CF'!C52 -> 0 | L26: =K26/buildcount -> 0
B27: =+Inputs!L24 -> Soft Costs (survey, eng, tap fees, ins, tax, etc.) | D27: =+Inputs!O24 -> 11216.667 | E27: =+D27/buildcount -> 11216.667 | F27: =+Inputs!P24 -> 0 | H27: Net Cash to RCH | K27: =K22-SUM(K23:K26) -> 94692.548 | L27: =L22-SUM(L23:L26) -> 94692.548
B28: Total Direct Vertical | D28: =D26+D27+D25 -> 157135.18 | E28: =+E26+E27+E25 -> 157135.18 | F28: =+F26+F27+F25 -> 0
B29: =+Inputs!L23 -> Builder Profit | C29: =+D29/D26 -> 0.2 | D29: =+Inputs!O23 -> 26743.702 | E29: =+D29/buildcount -> 26743.702 | F29: =+Inputs!P23 -> 0 | H29: Return Metrics
B30: Total Vertical Cost | C30: =+D30/D36 -> 0.58187964 | D30: =D28+D29 -> 183878.88 | E30: =+E28+E29 -> 183878.88 | F30: =+F28+F29 -> 0 | K30: XIRR | L30: CF Multiple
H31: Deal-Level | K31: =+XIRR('Monthly CF'!D45:AB45,'Monthly CF'!D2:AB2) -> 5.8419517 | L31: =IFERROR(SUM('Monthly CF'!D45:AB45)/-SUMIF('Monthly CF'!D45:AB45,"<0")+1, "N/A") -> 3.0555603
B32: =+Inputs!L28 -> Renovo Loan Origination | D32: =+Inputs!O28 -> 2677.2888 | E32: =+D32/buildcount -> 2677.2888 | F32: =+Inputs!P28 -> 2677.2888 | H32: =Inputs!D103 & " Equity/Mezz" -> Red Cedar SLFII Equity/Mezz | K32: =+Inputs!D108 -> 0.16769096 | L32: =+K35/J35 -> 1.0942222
B33: =+Inputs!L29 -> Interest Reserve | D33: =+Inputs!O29 -> 10952.277 | E33: =+D33/buildcount -> 10952.277 | F33: =+Inputs!P29 -> 10952.277 | H33: Red Cedar Equity | K33: =IFERROR(IRR('Monthly CF'!D58:AB58),"N/A") -> N/A
B34: Total Financing Costs | C34: =+D34/D36 -> 0.043130383 | D34: =+Inputs!O30 -> 13629.565 | E34: =+D34/buildcount -> 13629.565 | F34: =SUM(F32:F33) -> 13629.565 | J34: Contribution | K34: Total Cash Return | L34: Net Cash Return
H35: =+H32 -> Red Cedar SLFII Equity/Mezz | J35: =-'Monthly CF'!C49 -> 48279.565 | K35: =+'Monthly CF'!C53+'Acquisition Summary'!J35 -> 52828.573 | L35: =+K35-J35 -> 4549.0079
B36: Total Homebuilding Uses | D36: =+D23+D30+D34 -> 316008.44 | E36: =+E23+E30+E34 -> 316008.44 | F36: =+F23+F30+F34 -> 125279.57 | H36: RCH Promote | J36: 0 | K36: =+'Monthly CF'!C58 -> 94692.548 | L36: =+K36 -> 94692.548
B38: Sales Price Sensitivity | C38: 0 | D38: 0 | F38: 0
B39: % Change | C39: Sales Price/Build | D39: RCC Profit | E39: =+Inputs!D103 -> Red Cedar SLFII | F39: RCH Profit
B40: 0 | C40: =+K12/buildcount -> 450000 | D40: =Inputs!O23 -> 26743.702 | E40: =+L32 -> 1.0942222 | F40: =K27 -> 94692.548
B41: 0.05 | C41: 472500 | D41: 26743.702 | E41: 1.0942222 | F41: 115955.05
B42: 0.025 | C42: 461250 | D42: 26743.702 | E42: 1.0942222 | F42: 105323.8
B43: 0 | C43: 450000 | D43: 26743.702 | E43: 1.0942222 | F43: 94692.548
B44: -0.025 | C44: 438750 | D44: 26743.702 | E44: 1.0942222 | F44: 84061.298
B45: -0.05 | C45: 427500 | D45: 26743.702 | E45: 1.0942222 | F45: 73430.048
B47: Monthly Burn Upon Construction Completion
B48: Senior Debt | D48: =_xlfn.XLOOKUP(K8,'Monthly CF'!D1:AB1,'Monthly CF'!D35:AB35) -> 2286.8508
B49: Preferred Return | D49: =D14*J53/12 -> 643.72754
B50: Total Monthly Burn | D50: =SUM(D48:D49) -> 2930.5784
H51: Common Equity Structure
H52: Tier Structure | J52: Tier Hurdle | K52: =+H32 -> Red Cedar SLFII Equity/Mezz | L52: RCH
H53: Preferred Return | J53: =+IF(OR(Inputs!D103="RCH",Inputs!D103=""),100,Inputs!D105) -> 0.16 | K53: 1 | L53: =1-K53 -> 0
H54: Promote | K54: =+Inputs!D106 -> 0 | L54: =1-K54 -> 1
H55: Second Hurdle | J55: 0.55 | K55: 0.1 | L55: =1-K55 -> 0.9
H56: Remainder To Hurdle Three | K56: 0.05 | L56: =1-K56 -> 0.95
H57: Calculate Waterfall Thru Hurdle: | J57: Preferred
J58: Ownership | K58: Contribution
H59: =+H32 -> Red Cedar SLFII Equity/Mezz | J59: =1-SUM(J60:J60) -> 1 | K59: =+J59*D14 -> 48279.565
H60: RCH Equity | J60: 0 | K60: =+J60*D14 -> 0
H61: Total | J61: =SUM(J59:J60) -> 1 | K61: =SUM(K59:K60) -> 48279.565

Sheet Investor Summary
B1: =+ "INVESTMENT DEAL SHEET | "&C6 -> INVESTMENT DEAL SHEET | 241 Willard Street
B5: Project Information | G5: Project Timeline / Milestones | I5: Month # | J5: Date
B6: Project Name | C6: =IF(ISBLANK(Inputs!D5),"",Inputs!D5) -> 241 Willard Street | G6: =+Inputs!L36 -> Purchase Date | I6: 1 | J6: =+Inputs!P36 -> 46081
B7: Plan Name & # of Builds | C7: =_xlfn.TEXTJOIN(" | ",TRUE,IF(AND(Inputs!B72<>"",Inputs!C72<>""),Inputs!B72 & " x " & Inputs!C72,""),IF(AND(Inputs!B73<>"",Inputs!C73<>""),Inputs!B73 & " x " & Inputs!C73,""),IF(AND(Inputs!B74<>"",Inputs!C74<>""),Inputs!B74 & " x " & Inputs!C74,""),IF(AND(Inputs!B75<>"",Inputs!C75<>""),Inputs!B75 & " x " & Inputs!C75,"")) -> Atlas II - SC x 1 | G7: =+Inputs!L37 -> Construction Start | I7: =+I6+Inputs!O37 -> 2 | J7: =+Inputs!P37 -> 46110
B8: Project Location | C8: =Inputs!D6 -> Greenville, SC | G8: =+Inputs!L38 -> Construction Complete | I8: =+ROUND(I7+(Inputs!O38/30),) -> 7 | J8: =+Inputs!P38 -> 46260
B9: Home Type & SF | C9: =_xlfn.TEXTJOIN(" | ",TRUE, IF(Inputs!B72<>"",Inputs!B72 & ", " & _xlfn.XLOOKUP(Inputs!B72,'Reference Tab'!B:B,'Reference Tab'!D:D,""),""), IF(Inputs!B73<>"",Inputs!B73 & ", " & _xlfn.XLOOKUP(Inputs!B73,'Reference Tab'!B:B,'Reference Tab'!D:D,""),""), IF(Inputs!B74<>"",Inputs!B74 & ", " & _xlfn.XLOOKUP(Inputs!B74,'Reference Tab'!B:B,'Reference Tab'!D:D,""),""), IF(Inputs!B75<>"",Inputs!B75 & ", " & _xlfn.XLOOKUP(Inputs!B75,'Reference Tab'!B:B,'Reference Tab'!D:D,""),"")) -> Atlas II - SC, 1554 | G9: =TEXT(Inputs!L39,) -> Marketing/Sale Complete | I9: =+I8+Inputs!O39 -> 8 | J9: =+Inputs!P39 -> 46290
B11: Profit Analysis | D11: % | E11: Amount | G11: Sources/Uses | H11: Amount | I11: Amount/Build | J11: Amount/SF
B12: Projected Sales Price | E12: =SUM('Monthly CF'!D26:AB26) -> 450000 | G12: Sources of Funds
B13: Less: Land Acquisition | E13: ='Acquisition Summary'!D21 -> 111650 | G13: =+Inputs!D92& " Loan" -> Renovo Loan | H13: =+Inputs!O6 -> 267728.88 | I13: =+H13/buildcount -> 267728.88 | J13: =I13/Inputs!$D$76 -> 172.28371
B14: Less: Site Specific Costs | E14: ='Acquisition Summary'!D25 -> 12200 | G14: Common Equity | H14: =+Inputs!O7 -> 48279.565 | I14: =+H14/buildcount -> 48279.565 | J14: =I14/Inputs!$D$76 -> 31.067931
B15: Less: Total Sticks & Bricks | E15: ='Acquisition Summary'!D26+'Acquisition Summary'!D29 -> 160462.21 | G15: Total Sources of Funds | H15: =SUM(H13:H14) -> 316008.44 | I15: =+H15/buildcount -> 316008.44 | J15: =I15/Inputs!$D$76 -> 203.35164
B16: Less: Soft Costs | E16: ='Acquisition Summary'!D27-'Acquisition Summary'!D31 -> 11216.667 | J16: =I16/Inputs!$D$76 -> 0
B17: Less: Acquisition DD, Horizontal Costs | E17: =Inputs!O19 -> 6850 | G17: Uses of Funds | J17: =I17/Inputs!$D$76 -> 0
B18: Direct Profit | D18: =E18/E12 -> 0.32804694 | E18: =E12-SUM(E13:E17) -> 147621.12 | G18: Acquisition & Closing Costs | H18: =+Inputs!O17 -> 111650 | I18: =+H18/buildcount -> 111650 | J18: =I18/Inputs!$D$76 -> 71.846847
B19: Less: Closing Costs & Incentives | E19: ='Acquisition Summary'!K16 -> 2250 | G19: Acquisition DD, Horizontal Costs | H19: =Inputs!O19 -> 6850 | I19: =H19/buildcount -> 6850 | J19: =I19/Inputs!$D$76 -> 4.4079794
B20: Less: Incentives | E20: ='Acquisition Summary'!K17 -> 10000 | G20: =+Inputs!L20 -> Site Specific Costs | H20: =+Inputs!O20 -> 12200 | I20: =+H20/buildcount -> 12200 | J20: =I20/Inputs!$D$76 -> 7.8507079
B21: Less: Commissions (in-House & Outside) | E21: ='Acquisition Summary'!K18 -> 22500 | G21: Total Sticks & Bricks | H21: =+Inputs!O22+Inputs!O23 -> 160462.21 | I21: =+H21/buildcount -> 160462.21 | J21: =I21/Inputs!$D$76 -> 103.25754
B22: Adusted Gross Gross Profit | D22: =E22/E12 -> 0.25082471 | E22: =E18-SUM(E19:E21) -> 112871.12 | G22: =+Inputs!L24 -> Soft Costs (survey, eng, tap fees, ins, tax, etc.) | H22: =+Inputs!O24 -> 11216.667 | I22: =+H22/buildcount -> 11216.667 | J22: =I22/Inputs!$D$76 -> 7.2179322
B23: Less: Financing Costs | E23: ='Acquisition Summary'!D34 -> 13629.565 | G23: Development Costs | H23: =+Inputs!O26 -> 190728.88 | I23: =+H23/buildcount -> 190728.88 | J23: =I23/Inputs!$D$76 -> 122.73416
B24: Net Sale Proceeds | D24: =E24/E12 -> 0.22053679 | E24: =E22-E23 -> 99241.556 | G24: Financing Costs | H24: =+Inputs!O30 -> 13629.565 | I24: =+H24/buildcount -> 13629.565 | J24: =I24/Inputs!$D$76 -> 8.7706341
G25: Total Uses of Funds | H25: =+H24+H23+H18 -> 316008.44 | I25: =+H25/buildcount -> 316008.44 | J25: =I25/Inputs!$D$76 -> 203.35164
B27: Investor Return Metrics
D28: XIRR | E28: CF Multiple
B29: Investor Returns | D29: =Inputs!D108 -> 0.16769096 | E29: ='Acquisition Summary'!L32 -> 1.0942222
B30: Investment Contribution | E30: =-'Acquisition Summary'!K59 -> -48279.565
B31: Accrued Preferred Return | E31: ='Monthly CF'!C51 -> 4549.0079
B32: Return of Capital | E32: =-E30 -> 48279.565
B33: Profit Split | E33: ='Monthly CF'!C52 -> 0
B34: Net Return | E34: =SUM(E30:E33) -> 4549.0079

Sheet Financing Summary
B3: =Inputs!D5 & " - Financing Summary" -> 241 Willard Street - Financing Summary
B8: Capital Stack | C8: $ | D8: %
B9: Senior Loan | C9: =Inputs!D96 -> 267728.88 | D9: =C9/$C$12 -> 0.84722065
B10: Mezzanine | C10: =IF(Inputs!D103="RCH",0,Inputs!D107) -> 48279.565 | D10: =C10/$C$12 -> 0.15277935
B11: RC Equity | C11: =IF(Inputs!D103="RCH",Inputs!D107,0) -> 0 | D11: =C11/$C$12 -> 0
B12: Total Equity | C12: =SUM(C9:C11) -> 316008.44 | D12: =SUM(D9:D11) -> 1
B15: Senior Lender | C15: =Inputs!D92 -> Renovo | D15: %
B16: Interest Reserve | C16: =Inputs!D93 -> Yes | D16: =Inputs!D95 -> 0.1025
B17: Origination | C17: =C9*D17 -> 2677.2888 | D17: =Inputs!D94 -> 0.01
B18: LTC | C18: =Inputs!D97 -> 270655.99 | D18: =Inputs!C97 -> 0.9
B19: LTV | C19: =Inputs!D98 -> 315000 | D19: =Inputs!C98 -> 0.7
B20: Custom Cap (Renovo Only) | C20: =Inputs!D99 -> 267728.88
B21: Term | C21: =DATEDIF(Inputs!P36,Inputs!P39,"M")&" MONTHS" -> 6 MONTHS
B23: Mezz Equity | C23: =Inputs!D103 -> Red Cedar SLFII | D23: %
B24: Investment | C24: =C10 -> 48279.565
B25: Preferred Return | C25: ='Acquisition Summary'!K25 -> 4549.0079 | D25: =Inputs!D105 -> 0.16
B26: Profit Split | C26: ='Acquisition Summary'!K26 -> 0 | D26: =Inputs!D106 -> 0
B27: Origination | C27: =Inputs!D104 -> 0
B28: Target Hold Time | C28: =C21 -> 6 MONTHS

Sheet CFO Summary
N1: Red Cedar Cash Flow | O1: Returns
G2: Benchmarks | N2: RCH Profit Split | O2: ='Monthly CF'!C58 -> 94692.548
F3: Actual | G3: SFH | H3: TH | N3: RCC Builder Profit | O3: ='Monthly CF'!C63 -> 26743.702
D4: Total | E4: Per Unit | F4: % | G4: % | H4: % | N4: RCH/PHC Fees & Commission | O4: ='Monthly CF'!C68 -> 4500
N5: RCCP Total Return | O5: =SUM(O2:O4) -> 125936.25
C6: Closings | D6: =buildcount -> 1
C7: ASP | D7: =IFERROR(D13/D6, "") -> 440000
C10: Revenue:
C11: Projected Sales Price | D11: ='Acquisition Summary'!K12 -> 450000 | E11: =IFERROR(D11/D$6, 0) -> 450000 | F11: =D11/D11 -> 1 | G11: 1 | H11: 1
C12: Less: Projected Sales Incentives | D12: ='Acquisition Summary'!K17 -> 10000 | E12: =IFERROR(D12/D$6, 0) -> 10000 | F12: =IFERROR(D12/D$11, "") -> 0.022222222 | G12: =0.001 -> 0.001 | H12: =0.001 -> 0.001
C13: Revenue | D13: =D11-D12 -> 440000 | E13: =E11-E12 -> 440000 | F13: =F11-F12 -> 0.97777778 | G13: =G11-G12 -> 0.999 | H13: =H11-H12 -> 0.999
C14: Cost Of Sales:
C15: Less: Total Pad Cost | D15: =Inputs!O13+Inputs!O14+Inputs!O15+Inputs!O20 -> 122200 | E15: =IFERROR(D15/D$6, 0) -> 122200 | F15: =IFERROR(D15/D$11, "") -> 0.27155556 | G15: 0.23 | H15: 0.3
C16: Less: Total Direct Vertical | D16: =Inputs!O26-Inputs!O20 -> 178528.88 | E16: =IFERROR(D16/D$6, 0) -> 178528.88 | F16: =IFERROR(D16/D$11, "") -> 0.39673084 | G16: 0.5 | H16: 0.43
C17: Less: Closing & Transaction Costs | D17: =Inputs!O16 -> 1650 | E17: =IFERROR(D17/D$6, 0) -> 1650 | F17: =IFERROR(D17/D$11, "") -> 0.0036666667 | G17: 0.003 | H17: 0.003
C18: Total Cost of Sales | D18: =SUM(D15:D17) -> 302378.88 | E18: =SUM(E15:E17) -> 302378.88 | F18: =SUM(F15:F17) -> 0.67195306 | G18: =SUM(G15:G17) -> 0.733 | H18: =SUM(H15:H17) -> 0.733
C19: Contribution Profit | D19: =D13-D18 -> 137621.12 | E19: =E13-E18 -> 137621.12 | F19: =F13-F18 -> 0.30582471 | G19: =G13-G18 -> 0.266 | H19: =H13-H18 -> 0.266
C21: Indirect Construction Expenses
C22: Less: Construction Field Management | D22: =$D$11*G22 -> 9900 | E22: =IFERROR(D22/D$6, 0) -> 9900 | F22: =D22/$D$11 -> 0.022 | G22: 0.022 | H22: 0.022
C23: Less: Office Production Support | D23: =$D$11*G23 -> 2700 | E23: =IFERROR(D23/D$6, 0) -> 2700 | F23: =D23/$D$11 -> 0.006 | G23: 0.006 | H23: 0.006
C24: Less: Warranty | D24: =$D$11*G24 -> 1575 | E24: =IFERROR(D24/D$6, 0) -> 1575 | F24: =D24/$D$11 -> 0.0035 | G24: 0.0035 | H24: 0.0035
C25: Total Indirect & Warranty | D25: =SUM(D22:D24) -> 14175 | E25: =SUM(E22:E24) -> 14175 | F25: =SUM(F22:F24) -> 0.0315 | G25: =SUM(G22:G24) -> 0.0315 | H25: =SUM(H22:H24) -> 0.0315
C27: Gross Profit | D27: =D19-D25 -> 123446.12 | E27: =E19-E25 -> 123446.12 | F27: =F19-F25 -> 0.27432471 | G27: =G19-G25 -> 0.2345 | H27: =H19-H25 -> 0.2345
C28: SG&A:
C29: Less: Outside Commissions | D29: =Inputs!D85 -> 11250 | E29: =IFERROR(D29/D$6, 0) -> 11250 | F29: =IFERROR(D29/D$13, "") -> 0.025568182 | G29: 0.025 | H29: 0.025
C30: Less: In-House Commissions | D30: =Inputs!D86 -> 11250 | E30: =IFERROR(D30/D$6, 0) -> 11250 | F30: =IFERROR(D30/D$13, "") -> 0.025568182 | G30: 0.025 | H30: 0.025
C31: Less: Advertising | D31: =$D$11*G31 -> 5400 | E31: =IFERROR(D31/D$6, 0) -> 5400 | F31: =IFERROR(D31/D$13, "") -> 0.012272727 | G31: 0.012 | H31: 0.012
C32: Less: Models | D32: =$D$11*G32 -> 0 | E32: =IFERROR(D32/D$6, 0) -> 0 | F32: =IFERROR(D32/D$13, "") -> 0 | G32: 0 | H32: 0
C33: Less: Other Sales & Marketing Expense | D33: =$D$11*G33 -> 1350 | E33: =IFERROR(D33/D$6, 0) -> 1350 | F33: =IFERROR(D33/D$13, "") -> 0.0030681818 | G33: 0.003 | H33: 0.003
C34: G & A | D34: =$D$11*G34 -> 20250 | E34: =IFERROR(D34/D$6, 0) -> 20250 | F34: =IFERROR(D34/D$13, "") -> 0.046022727 | G34: 0.045 | H34: 0.045
C35: Total SG&A | D35: =SUM(D29:D34) -> 49500 | E35: =SUM(E29:E34) -> 49500 | F35: =SUM(F29:F34) -> 0.1125 | G35: =SUM(G29:G34) -> 0.11 | H35: =SUM(H29:H34) -> 0.11
C36: EBITDA | D36: =D27-D35 -> 73946.121 | E36: =E27-E35 -> 73946.121 | F36: =IFERROR(D36/D$13, "") -> 0.16805937 | G36: =G27-G35 -> 0.1245 | H36: =H27-H35 -> 0.1245
C37: Interest, Depreciation & Amortization:
C38: Less: Senior Debt Financing Costs (Orgination & IR) | D38: =Inputs!O30 -> 13629.565 | E38: =D38/$D$6 -> 13629.565 | F38: =IFERROR(D38/D$13, "") -> 0.030976285
C39: Less: Mezz Pref | D39: ='Acquisition Summary'!K25 -> 4549.0079 | E39: =D39/$D$6 -> 4549.0079 | F39: =IFERROR(D39/D$13, "") -> 0.010338654
C40: Less: Mezz Profit Split | D40: ='Acquisition Summary'!L26 -> 0 | E40: =D40/$D$6 -> 0 | F40: =IFERROR(D40/D$13, "") -> 0
C41: Less: Depreciation | F41: =IFERROR(D41/D$13, "") -> 0 | G41: 0 | H41: 0
C42: Less: Amortization | F42: =IFERROR(D42/D$13, "") -> 0 | G42: 0 | H42: 0
C43: Total Interest, Depreciation & Amortization | D43: =SUM(D38:D42) -> 18178.573 | E43: =SUM(E38:E42) -> 18178.573 | F43: =IFERROR(D43/D$13,"") -> 0.041314939 | G43: =SUM(G41:G42) -> 0 | H43: =SUM(H41:H42) -> 0
C44: EBT From Operations [Pre-Tax Income] | D44: =D36-D43 -> 55767.548 | E44: =E36-E43 -> 55767.548 | F44: =IFERROR(D44/D$13, "") -> 0.12674443 | G44: =G36-G43 -> 0.1245 | H44: =H36-H43 -> 0.1245
C45: Non-Recurring & Other Expenses & (Income):
C46: Non-Recurring & Other (Income) | D46: 0 | E46: =IFERROR(D46/D$6, 0) -> 0 | F46: =IFERROR(D46/D$13, "") -> 0 | G46: =IFERROR(E46/E$13, "") -> 0 | H46: =IFERROR(F46/F$13, "") -> 0
C47: Non-Recurring & Other Expenses | D47: 0 | E47: =IFERROR(D47/D$6, 0) -> 0 | F47: =IFERROR(D47/D$13, "") -> 0 | G47: =IFERROR(E47/E$13, "") -> 0 | H47: =IFERROR(F47/F$13, "") -> 0
C48: Non-Recurring & Other Expenses & (Income) | D48: =SUM(D46:D47) -> 0 | E48: =SUM(E46:E47) -> 0 | F48: =IFERROR(D48/D$13,"") -> 0 | G48: =SUM(G46:G47) -> 0 | H48: =SUM(H46:H47) -> 0
C50: Fee Build Expenses & (Income):
C51: Fee Build Revenue | D51: 0 | E51: =IFERROR(D51/#REF!, 0) -> 0 | F51: =IFERROR(D51/D$13, "") -> 0 | G51: =IFERROR(E51/E$13, "") -> 0 | H51: =IFERROR(F51/F$13, "") -> 0
C52: Fee Build Over/Under Billings | D52: 0 | E52: =IFERROR(D52/#REF!, 0) -> 0 | F52: =IFERROR(D52/D$13, "") -> 0 | G52: =IFERROR(E52/E$13, "") -> 0 | H52: =IFERROR(F52/F$13, "") -> 0
C53: Fee Build Cost of Sales | D53: 0 | E53: =IFERROR(D53/#REF!, 0) -> 0 | F53: =IFERROR(D53/D$13, "") -> 0 | G53: =IFERROR(E53/E$13, "") -> 0 | H53: =IFERROR(F53/F$13, "") -> 0
C54: Fee Build G&A Allocation | D54: 0 | E54: =IFERROR(D54/#REF!, 0) -> 0 | F54: =IFERROR(D54/D$13, "") -> 0 | G54: =IFERROR(E54/E$13, "") -> 0 | H54: =IFERROR(F54/F$13, "") -> 0
C55: Fee Build Expenses & (Income) | D55: =SUM(D51:D54) -> 0 | E55: =SUM(E51:E54) -> 0 | F55: =IFERROR(D55/D$13,"") -> 0 | G55: =SUM(G51:G54) -> 0 | H55: =SUM(H51:H54) -> 0
C57: EBT After Other Expenses & (Income) | D57: =D44-D48-D55 -> 55767.548 | E57: =IFERROR(D57/(D6+#REF!),0) -> 0 | F57: =IFERROR(D57/D$13, "") -> 0.12674443 | G57: =G44-G48-G55 -> 0.1245 | H57: =H44-H48-H55 -> 0.1245
C59: Taxes | D59: =0.0525*D13 -> 23100 | E59: =IFERROR(D59/D$6, 0) -> 23100 | F59: =IFERROR(D59/D$13, "") -> 0.0525 | G59: 0 | H59: 0
C61: Net Income | D61: =D57-D59 -> 32667.548 | E61: =IFERROR(D61/(D6+#REF!),0) -> 0 | F61: =IFERROR(D61/D$13, "") -> 0.074244427 | G61: =G57-G59 -> 0.1245 | H61: =H57-H59 -> 0.1245

Sheet Monthly CF
D1: 1 | E1: =+D1+1 -> 2 | F1: =+E1+1 -> 3 | G1: =+F1+1 -> 4 | H1: =+G1+1 -> 5 | I1: =+H1+1 -> 6 | J1: =+I1+1 -> 7 | K1: =+J1+1 -> 8 | L1: =+K1+1 -> 9 | ... AB1: =+AA1+1 -> 25
D2: =+Inputs!D13 -> 46081 | E2: =+EDATE(D2,1) -> 46109 | F2: =+EDATE(E2,1) -> 46140 | G2: =+EDATE(F2,1) -> 46170 | H2: =+EDATE(G2,1) -> 46201 | I2: =+EDATE(H2,1) -> 46231 | J2: =+EDATE(I2,1) -> 46262 | K2: =+EDATE(J2,1) -> 46293 | L2: =+EDATE(K2,1) -> 46323 | ... AB2: =+EDATE(AA2,1) -> 46811
D3: CLOSING | E3: {=+IF(AND(E2>Inputs!$P$36,E2<Inputs!P37),"PREDEV",IF(AND(E2>Inputs!$P$37,E2<=Inputs!$P$38),"VERTICAL",IF(AND(E2>=Inputs!$P$39,$D$3:D3<>"SALE"),"SALE","")))} -> PREDEV | F3: {=+IF(AND(F2>Inputs!$P$36,F2<Inputs!Q37),"PREDEV",IF(AND(F2>Inputs!$P$37,F2<=Inputs!$P$38),"VERTICAL",IF(AND(F2>=Inputs!$P$39,$D$3:E3<>"SALE"),"SALE","")))} -> VERTICAL | G3: {=+IF(AND(G2>Inputs!$P$36,G2<Inputs!R37),"PREDEV",IF(AND(G2>Inputs!$P$37,G2<=Inputs!$P$38),"VERTICAL",IF(AND(G2>=Inputs!$P$39,$D$3:F3<>"SALE"),"SALE","")))} -> VERTICAL | H3: {=+IF(AND(H2>Inputs!$P$36,H2<Inputs!S37),"PREDEV",IF(AND(H2>Inputs!$P$37,H2<=Inputs!$P$38),"VERTICAL",IF(AND(H2>=Inputs!$P$39,$D$3:G3<>"SALE"),"SALE","")))} -> VERTICAL | I3: {=+IF(AND(I2>Inputs!$P$36,I2<Inputs!T36),"PREDEV",IF(AND(I2>Inputs!$P$37,I2<=Inputs!$P$38),"VERTICAL",IF(AND(I2>=Inputs!$P$39,$D$3:H3<>"SALE"),"SALE","")))} -> VERTICAL | J3: {=+IF(AND(J2>Inputs!$P$36,J2<Inputs!U35),"PREDEV",IF(AND(J2>Inputs!$P$37,J2<=Inputs!$P$38),"VERTICAL",IF(AND(J2>=Inputs!$P$39,$D$3:I3<>"SALE"),"SALE","")))} | K3: {=+IF(AND(K2>Inputs!$P$36,K2<Inputs!V34),"PREDEV",IF(AND(K2>Inputs!$P$37,K2<=Inputs!$P$38),"VERTICAL",IF(AND(K2>=Inputs!$P$39,$D$3:J3<>"SALE"),"SALE","")))} -> SALE | L3: {=+IF(AND(L2>Inputs!$P$36,L2<Inputs!W34),"PREDEV",IF(AND(L2>Inputs!$P$37,L2<=Inputs!$P$38),"VERTICAL",IF(AND(L2>=Inputs!$P$39,$D$3:K3<>"SALE"),"SALE","")))} | M3: {=+IF(AND(M2>Inputs!$P$36,M2<Inputs!X34),"PREDEV",IF(AND(M2>Inputs!$P$37,M2<=Inputs!$P$38),"VERTICAL",IF(AND(M2>=Inputs!$P$39,$D$3:L3<>"SALE"),"SALE","")))} | N3: {=+IF(AND(N2>Inputs!$P$36,N2<Inputs!Y36),"PREDEV",IF(AND(N2>Inputs!$P$37,N2<=Inputs!$P$38),"VERTICAL",IF(AND(N2>=Inputs!$P$39,$D$3:M3<>"SALE"),"SALE","")))} | O3: {=+IF(AND(O2>Inputs!$P$36,O2<Inputs!Z36),"PREDEV",IF(AND(O2>Inputs!$P$37,O2<=Inputs!$P$38),"VERTICAL",IF(AND(O2>=Inputs!$P$39,$D$3:N3<>"SALE"),"SALE","")))} | P3: {=+IF(AND(P2>Inputs!$P$36,P2<Inputs!AA36),"PREDEV",IF(AND(P2>Inputs!$P$37,P2<=Inputs!$P$38),"VERTICAL",IF(AND(P2>=Inputs!$P$39,$D$3:O3<>"SALE"),"SALE","")))} | Q3: {=+IF(AND(Q2>Inputs!$P$36,Q2<Inputs!AB36),"PREDEV",IF(AND(Q2>Inputs!$P$37,Q2<=Inputs!$P$38),"VERTICAL",IF(AND(Q2>=Inputs!$P$39,$D$3:P3<>"SALE"),"SALE","")))} | R3: {=+IF(AND(R2>Inputs!$P$36,R2<Inputs!AC36),"PREDEV",IF(AND(R2>Inputs!$P$37,R2<=Inputs!$P$38),"VERTICAL",IF(AND(R2>=Inputs!$P$39,$D$3:Q3<>"SALE"),"SALE","")))} | S3: {=+IF(AND(S2>Inputs!$P$36,S2<Inputs!AD36),"PREDEV",IF(AND(S2>Inputs!$P$37,S2<=Inputs!$P$38),"VERTICAL",IF(AND(S2>=Inputs!$P$39,$D$3:R3<>"SALE"),"SALE","")))} | T3: {=+IF(AND(T2>Inputs!$P$36,T2<Inputs!AE36),"PREDEV",IF(AND(T2>Inputs!$P$37,T2<=Inputs!$P$38),"VERTICAL",IF(AND(T2>=Inputs!$P$39,$D$3:S3<>"SALE"),"SALE","")))} | U3: {=+IF(AND(U2>Inputs!$P$36,U2<Inputs!AF35),"PREDEV",IF(AND(U2>Inputs!$P$37,U2<=Inputs!$P$38),"VERTICAL",IF(AND(U2>=Inputs!$P$39,$D$3:T3<>"SALE"),"SALE","")))} | V3: {=+IF(AND(V2>Inputs!$P$36,V2<Inputs!AG35),"PREDEV",IF(AND(V2>Inputs!$P$37,V2<=Inputs!$P$38),"VERTICAL",IF(AND(V2>=Inputs!$P$39,$D$3:U3<>"SALE"),"SALE","")))} | W3: {=+IF(AND(W2>Inputs!$P$36,W2<Inputs!AH35),"PREDEV",IF(AND(W2>Inputs!$P$37,W2<=Inputs!$P$38),"VERTICAL",IF(AND(W2>=Inputs!$P$39,$D$3:V3<>"SALE"),"SALE","")))} | X3: {=+IF(AND(X2>Inputs!$P$36,X2<Inputs!AI35),"PREDEV",IF(AND(X2>Inputs!$P$37,X2<=Inputs!$P$38),"VERTICAL",IF(AND(X2>=Inputs!$P$39,$D$3:W3<>"SALE"),"SALE","")))} | Y3: {=+IF(AND(Y2>Inputs!$P$36,Y2<Inputs!AJ35),"PREDEV",IF(AND(Y2>Inputs!$P$37,Y2<=Inputs!$P$38),"VERTICAL",IF(AND(Y2>=Inputs!$P$39,$D$3:X3<>"SALE"),"SALE","")))} | Z3: {=+IF(AND(Z2>Inputs!$P$36,Z2<Inputs!AK35),"PREDEV",IF(AND(Z2>Inputs!$P$37,Z2<=Inputs!$P$38),"VERTICAL",IF(AND(Z2>=Inputs!$P$39,$D$3:Y3<>"SALE"),"SALE","")))} | AA3: {=+IF(AND(AA2>Inputs!$P$36,AA2<Inputs!AL35),"PREDEV",IF(AND(AA2>Inputs!$P$37,AA2<=Inputs!$P$38),"VERTICAL",IF(AND(AA2>=Inputs!$P$39,$D$3:Z3<>"SALE"),"SALE","")))} | AB3: {=+IF(AND(AB2>Inputs!$P$36,AB2<Inputs!AM35),"PREDEV",IF(AND(AB2>Inputs!$P$37,AB2<=Inputs!$P$38),"VERTICAL",IF(AND(AB2>=Inputs!$P$39,$D$3:AA3<>"SALE"),"SALE","")))}
C4: Total
B5: Land Closing
B6: Land Purchase | C6: =+SUM(D6:AB6) -> 110000 | D6: =Inputs!O13 -> 110000 | E6: 0 | F6: 0 | G6: 0 | H6: 0 | I6: 0 | J6: 0 | K6: 0 | L6: 0 | M6: 0 | N6: 0 | O6: 0 | P6: 0 | Q6: 0 | R6: 0 | S6: 0 | T6: 0 | U6: 0 | V6: 0 | W6: 0 | X6: 0 | Y6: 0 | Z6: 0 | AA6: 0 | AB6: 0
B7: Purchase Commission (RCR/PHC) | C7: =+SUM(D7:AB7) -> 0 | D7: =Inputs!O14+Inputs!D20 -> 0 | E7: 0 | F7: 0 | G7: 0 | H7: 0 | I7: 0 | J7: 0 | K7: 0 | L7: 0 | M7: 0 | N7: 0 | O7: 0 | P7: 0 | Q7: 0 | R7: 0 | S7: 0 | T7: 0 | U7: 0 | V7: 0 | W7: 0 | X7: 0 | Y7: 0 | Z7: 0 | AA7: 0 | AB7: 0
B8: Closing Costs | C8: =+SUM(D8:AB8) -> 1650 | D8: =Inputs!O16 -> 1650 | E8: 0 | F8: 0 | G8: 0 | H8: 0 | I8: 0 | J8: 0 | K8: 0 | L8: 0 | M8: 0 | N8: 0 | O8: 0 | P8: 0 | Q8: 0 | R8: 0 | S8: 0 | T8: 0 | U8: 0 | V8: 0 | W8: 0 | X8: 0 | Y8: 0 | Z8: 0 | AA8: 0 | AB8: 0
B10: Predev & Sitework
B11: Acquisitions Due Dilligence & Horizontal Costs | C11: =+SUM(D11:AB11) -> 6850 | D11: 0 | E11: =+IF(E$3="PREDEV",$AD11,0) -> 6850 | F11: =+IF(F$3="PREDEV",$AD11,0) -> 0 | G11: =+IF(G$3="PREDEV",$AD11,0) -> 0 | H11: =+IF(H$3="PREDEV",$AD11,0) -> 0 | I11: =+IF(I$3="PREDEV",$AD11,0) -> 0 | J11: =+IF(J$3="PREDEV",$AD11,0) -> 0 | K11: =+IF(K$3="PREDEV",$AD11,0) -> 0 | L11: =+IF(L$3="PREDEV",$AD11,0) -> 0 | ... AB11: =+IF(AB$3="PREDEV",$AD11,0) -> 0 | AD11: =Inputs!O19/COUNTIF($D$3:$AB$3,"PREDEV") -> 6850
B12: Soft Costs | C12: =+SUM(D12:AB12) -> 11216.667 | D12: 0 | E12: =+IF(E$3="PREDEV",$AD12,0) -> 11216.667 | F12: =+IF(F$3="PREDEV",$AD12,0) -> 0 | G12: =+IF(G$3="PREDEV",$AD12,0) -> 0 | H12: =+IF(H$3="PREDEV",$AD12,0) -> 0 | I12: =+IF(I$3="PREDEV",$AD12,0) -> 0 | J12: =+IF(J$3="PREDEV",$AD12,0) -> 0 | K12: =+IF(K$3="PREDEV",$AD12,0) -> 0 | L12: =+IF(L$3="PREDEV",$AD12,0) -> 0 | ... AB12: =+IF(AB$3="PREDEV",$AD12,0) -> 0 | AD12: =Inputs!O24/COUNTIF($D$3:$AB$3,"PREDEV") -> 11216.667
B13: Site Specific | C13: =+SUM(D13:AB13) -> 12200 | D13: 0 | E13: =+IF(E$3="PREDEV",$AD13,0) -> 12200 | F13: =+IF(F$3="PREDEV",$AD13,0) -> 0 | G13: =+IF(G$3="PREDEV",$AD13,0) -> 0 | H13: =+IF(H$3="PREDEV",$AD13,0) -> 0 | I13: =+IF(I$3="PREDEV",$AD13,0) -> 0 | J13: =+IF(J$3="PREDEV",$AD13,0) -> 0 | K13: =+IF(K$3="PREDEV",$AD13,0) -> 0 | L13: =+IF(L$3="PREDEV",$AD13,0) -> 0 | ... AB13: =+IF(AB$3="PREDEV",$AD13,0) -> 0 | AD13: =Inputs!O20/COUNTIF($D$3:$AB$3,"PREDEV") -> 12200
B15: =+Inputs!L28 -> Renovo Loan Origination | C15: =+SUM(D15:AB15) -> 2677.2888 | D15: =Inputs!O28 -> 2677.2888 | E15: 0 | F15: 0 | G15: 0 | H15: 0 | I15: 0 | J15: 0 | K15: 0 | L15: 0 | M15: 0 | N15: 0 | O15: 0 | P15: 0 | Q15: 0 | R15: 0 | S15: 0 | T15: 0 | U15: 0 | V15: 0 | W15: 0 | X15: 0 | Y15: 0 | Z15: 0 | AA15: 0 | AB15: 0
B17: Vertical Construction
B18: Vertical Build | C18: =+SUM(D18:AB18) -> 133718.51 | D18: 0 | E18: =+IF(E3="VERTICAL",$AD$18,0) -> 0 | F18: =+IF(F3="VERTICAL",$AD$18,0) -> 33429.628 | G18: =+IF(G3="VERTICAL",$AD$18,0) -> 33429.628 | H18: =+IF(H3="VERTICAL",$AD$18,0) -> 33429.628 | I18: =+IF(I3="VERTICAL",$AD$18,0) -> 33429.628 | J18: =+IF(J3="VERTICAL",$AD$18,0) -> 0 | K18: =+IF(K3="VERTICAL",$AD$18,0) -> 0 | L18: =+IF(L3="VERTICAL",$AD$18,0) -> 0 | ... AB18: =+IF(AB3="VERTICAL",$AD$18,0) -> 0 | AD18: =Inputs!O22/COUNTIF($D$3:$AB$3,"VERTICAL") -> 33429.628
B19: =+Inputs!L23 -> Builder Profit | C19: =+SUM(D19:AB19) -> 26743.702 | D19: 0 | E19: =+IF(E$3="VERTICAL",$AD19,0) -> 0 | F19: =+IF(F$3="VERTICAL",$AD19,0) -> 6685.9255 | G19: =+IF(G$3="VERTICAL",$AD19,0) -> 6685.9255 | H19: =+IF(H$3="VERTICAL",$AD19,0) -> 6685.9255 | I19: =+IF(I$3="VERTICAL",$AD19,0) -> 6685.9255 | J19: =+IF(J$3="VERTICAL",$AD19,0) -> 0 | K19: =+IF(K$3="VERTICAL",$AD19,0) -> 0 | L19: =+IF(L$3="VERTICAL",$AD19,0) -> 0 | ... AB19: =+IF(AB$3="VERTICAL",$AD19,0) -> 0 | AD19: =Inputs!O23/COUNTIF($D$3:$AB$3,"VERTICAL") -> 6685.9255
B20: =+Inputs!L25 -> General Conditions | C20: =+SUM(D20:AB20) -> 0 | D20: 0 | E20: =+IF(E$3="VERTICAL",$AD20,0) -> 0 | F20: =+IF(F$3="VERTICAL",$AD20,0) -> 0 | G20: =+IF(G$3="VERTICAL",$AD20,0) -> 0 | H20: =+IF(H$3="VERTICAL",$AD20,0) -> 0 | I20: =+IF(I$3="VERTICAL",$AD20,0) -> 0 | J20: =+IF(J$3="VERTICAL",$AD20,0) -> 0 | K20: =+IF(K$3="VERTICAL",$AD20,0) -> 0 | L20: =+IF(L$3="VERTICAL",$AD20,0) -> 0 | ... AB20: =+IF(AB$3="VERTICAL",$AD20,0) -> 0 | AC20: =+IF(AND(AC3="VERTICAL",AB3="PREDEV"),-Inputs!$O$25,"") | AD20: =Inputs!O25/COUNTIF($D$3:$AB$3,"VERTICAL") -> 0
B21: Total Development Costs (w/o interest) | C21: =SUM(C6:C20) -> 305056.17 | D21: =SUM(D6:D20) -> 114327.29 | E21: =SUM(E6:E20) -> 30266.667 | F21: =SUM(F6:F20) -> 40115.553 | G21: =SUM(G6:G20) -> 40115.553 | H21: =SUM(H6:H20) -> 40115.553 | I21: =SUM(I6:I20) -> 40115.553 | J21: =SUM(J6:J20) -> 0 | ... AB21: =SUM(AB6:AB20) -> 0
B23: Equity Over Subscription | C23: =SUM(D23:K23) -> 0 | D23: =-Inputs!P12 -> 0 | E23: 0 | F23: 0 | G23: 0 | H23: 0 | I23: 0 | J23: 0 | K23: =-D23 -> 0
B25: Sales
B26: Gross Sales Price | C26: =+SUM(D26:AB26) -> 450000 | D26: =+IF(D3="SALE",Inputs!$I$76*buildcount*(1+'Acquisition Summary'!$R$1),"") | E26: =+IF(E3="SALE",Inputs!$I$76*buildcount*(1+'Acquisition Summary'!$R$1),"") | F26: =+IF(F3="SALE",Inputs!$I$76*buildcount*(1+'Acquisition Summary'!$R$1),"") | G26: =+IF(G3="SALE",Inputs!$I$76*buildcount*(1+'Acquisition Summary'!$R$1),"") | H26: =+IF(H3="SALE",Inputs!$I$76*buildcount*(1+'Acquisition Summary'!$R$1),"") | I26: =+IF(I3="SALE",Inputs!$I$76*buildcount*(1+'Acquisition Summary'!$R$1),"") | J26: =+IF(J3="SALE",Inputs!$I$76*buildcount*(1+'Acquisition Summary'!$R$1),"") | K26: =+IF(K3="SALE",Inputs!$I$76*buildcount*(1+'Acquisition Summary'!$R$1),"") -> 450000 | ... AB26: =+IF(AB3="SALE",Inputs!$I$76*buildcount*(1+'Acquisition Summary'!$R$1),"")
B27: Less: Incentives | C27: =+SUM(D27:AB27) -> -10000 | D27: =+IF(D3="SALE",-Inputs!$D$88,"") | E27: =+IF(E3="SALE",-Inputs!$D$88,"") | F27: =+IF(F3="SALE",-Inputs!$D$88,"") | G27: =+IF(G3="SALE",-Inputs!$D$88,"") | H27: =+IF(H3="SALE",-Inputs!$D$88,"") | I27: =+IF(I3="SALE",-Inputs!$D$88,"") | J27: =+IF(J3="SALE",-Inputs!$D$88,"") | K27: =+IF(K3="SALE",-Inputs!$D$88,"") -> -10000 | ... AB27: =+IF(AB3="SALE",-Inputs!$D$88,"")
B28: Less: Title Costs & Commissions | C28: =+SUM(D28:AB28) -> -24750 | D28: =IF(D3="SALE",-Inputs!$D$89,"") | E28: =IF(E3="SALE",-Inputs!$D$89-Inputs!$D$85-Inputs!$D$86,"") | F28: =IF(F3="SALE",-Inputs!$D$89-Inputs!$D$85-Inputs!$D$86,"") | G28: =IF(G3="SALE",-Inputs!$D$89-Inputs!$D$85-Inputs!$D$86,"") | H28: =IF(H3="SALE",-Inputs!$D$89-Inputs!$D$85-Inputs!$D$86,"") | I28: =IF(I3="SALE",-Inputs!$D$89-Inputs!$D$85-Inputs!$D$86,"") | J28: =IF(J3="SALE",-Inputs!$D$89-Inputs!$D$85-Inputs!$D$86,"") | K28: =IF(K3="SALE",-Inputs!$D$89-Inputs!$D$85-Inputs!$D$86,"") -> -24750 | L28: =IF(L3="SALE",-Inputs!$D$89-Inputs!$D$85-Inputs!$D$86,"") | ... AB28: =IF(AB3="SALE",-Inputs!$D$89-Inputs!$D$85-Inputs!$D$86,"")
B29: Net Sales Proceeds | C29: =+SUM(D29:AB29) -> 415250 | D29: =SUM(D26:D28) -> 0 | E29: =SUM(E26:E28) -> 0 | F29: =SUM(F26:F28) -> 0 | G29: =SUM(G26:G28) -> 0 | H29: =SUM(H26:H28) -> 0 | I29: =SUM(I26:I28) -> 0 | J29: =SUM(J26:J28) -> 0 | K29: =SUM(K26:K28) -> 415250 | ... AB29: =SUM(AB26:AB28) -> 0
B32: =+Inputs!D92 &" Vertical Loan" -> Renovo Vertical Loan | C32: =+Inputs!O6 -> 267728.88
B33: Beginning Balance | D33: 0 | E33: =+D38 -> 77000 | F33: =+E38 -> 107266.67 | G33: =+F38 -> 147382.22 | H33: =+G38 -> 187497.77 | I33: =+H38 -> 227613.33 | J33: =+I38 -> 267728.88 | K33: =+J38 -> 267728.88 | L33: =+K38 -> 0 | ... AB33: =+AA38 -> 0
B34: Current Month Draw | C34: =+SUM(D34:AB34) -> 267728.88 | D34: =+Inputs!P6 -> 77000 | E34: =+MIN(E21,$C$32-E33) -> 30266.667 | F34: =+MIN(F21,$C$32-F33) -> 40115.553 | G34: =+MIN(G21,$C$32-G33) -> 40115.553 | H34: =+MIN(H21,$C$32-H33) -> 40115.553 | I34: =+MIN(I21,$C$32-I33) -> 40115.553 | J34: =+MIN(J21,$C$32-J33) -> 0 | K34: =+MIN(K21,$C$32-K33) -> 0 | L34: =+MIN(L21,$C$32-L33) -> 0 | ... AB34: =+MIN(AB21,$C$32-AB33) -> 0
B35: Interest Accrual | C35: =+SUM(D35:AB35) -> 10952.277 | D35: 0 | E35: =+E33*Inputs!$N$29/12 -> 657.70833 | F35: =+F33*Inputs!$N$29/12 -> 916.23611 | G35: =+G33*Inputs!$N$29/12 -> 1258.8898 | H35: =+H33*Inputs!$N$29/12 -> 1601.5435 | I35: =+I33*Inputs!$N$29/12 -> 1944.1972 | J35: =+J33*Inputs!$N$29/12 -> 2286.8508 | K35: =+K33*Inputs!$N$29/12 -> 2286.8508 | L35: =+L33*Inputs!$N$29/12 -> 0 | ... AB35: =+AB33*Inputs!$N$29/12 -> 0
B36: Interest Payment | C36: =+SUM(D36:AB36) -> -10952.277 | D36: =-D35 -> 0 | E36: =-E35 -> -657.70833 | F36: =-F35 -> -916.23611 | G36: =-G35 -> -1258.8898 | H36: =-H35 -> -1601.5435 | I36: =-I35 -> -1944.1972 | J36: =-J35 -> -2286.8508 | K36: =-K35 -> -2286.8508 | ... AB36: =-AB35 -> 0
B37: Payoff | C37: =+SUM(D37:AB37) -> -267728.88 | D37: 0 | E37: =-IF(E29>0,MIN(SUM(E33:E36),E29),0) -> 0 | F37: =-IF(F29>0,MIN(SUM(F33:F36),F29),0) -> 0 | G37: =-IF(G29>0,MIN(SUM(G33:G36),G29),0) -> 0 | H37: =-IF(H29>0,MIN(SUM(H33:H36),H29),0) -> 0 | I37: =-IF(I29>0,MIN(SUM(I33:I36),I29),0) -> 0 | J37: =-IF(J29>0,MIN(SUM(J33:J36),J29),0) -> 0 | K37: =-IF(K29>0,MIN(SUM(K33:K36),K29),0) -> -267728.88 | L37: =-IF(L29>0,MIN(SUM(L33:L36),L29),0) -> 0 | ... AB37: =-IF(AB29>0,MIN(SUM(AB33:AB36),AB29),0) -> 0
B38: Ending Balance | D38: =SUM(D33:D37) -> 77000 | E38: =SUM(E33:E37) -> 107266.67 | F38: =SUM(F33:F37) -> 147382.22 | G38: =SUM(G33:G37) -> 187497.77 | H38: =SUM(H33:H37) -> 227613.33 | I38: =SUM(I33:I37) -> 267728.88 | J38: =SUM(J33:J37) -> 267728.88 | K38: =SUM(K33:K37) -> 0 | ... AB38: =SUM(AB33:AB37) -> 0
B40: Interest Reserve
B41: Beginning Balance | D41: =+IF(Inputs!$D$93="Yes",Inputs!$O$29,0) -> 10952.277 | E41: =+D43 -> 10952.277 | F41: =+E43 -> 10294.568 | G41: =+F43 -> 9378.3321 | H41: =+G43 -> 8119.4423 | I41: =+H43 -> 6517.8988 | J41: =+I43 -> 4573.7017 | K41: =+J43 -> 2286.8508 | L41: =+K43 -> 0 | ... AB41: =+AA43 -> 0
B42: Adjustments | C42: =+SUM(D42:AB42) -> -10952.277 | D42: =-MIN(D35,D41) -> 0 | E42: =-MIN(E35,E41) -> -657.70833 | F42: =-MIN(F35,F41) -> -916.23611 | G42: =-MIN(G35,G41) -> -1258.8898 | H42: =-MIN(H35,H41) -> -1601.5435 | I42: =-MIN(I35,I41) -> -1944.1972 | J42: =-MIN(J35,J41) -> -2286.8508 | K42: =-MIN(K35,K41) -> -2286.8508 | ... AB42: =-MIN(AB35,AB41) -> 0
B43: Ending Balanace | D43: =SUM(D41:D42) -> 10952.277 | E43: =SUM(E41:E42) -> 10294.568 | F43: =SUM(F41:F42) -> 9378.3321 | G43: =SUM(G41:G42) -> 8119.4423 | H43: =SUM(H41:H42) -> 6517.8988 | I43: =SUM(I41:I42) -> 4573.7017 | J43: =SUM(J41:J42) -> 2286.8508 | K43: =SUM(K41:K42) -> 0 | ... AB43: =SUM(AB41:AB42) -> 0
B45: Net CF to Equity Sources | C45: =+SUM(D45:AB45) -> 99241.556 | D45: =-Inputs!O7 -> -48279.565 | E45: =-E21+E29+E34-E35-E42+E37+E23 -> 0 | F45: =-F21+F29+F34-F35-F42+F37+F23 -> 0 | G45: =-G21+G29+G34-G35-G42+G37+G23 -> 0 | H45: =-H21+H29+H34-H35-H42+H37+H23 -> 0 | I45: =-I21+I29+I34-I35-I42+I37+I23 -> 0 | J45: =-J21+J29+J34-J35-J42+J37+J23 -> 0 | K45: =-K21+K29+K34-K35-K42+K37+K23 -> 147521.12 | L45: =IF(L3="SALE",-L21+L29+L34-L35-L42+L37+L23,0) -> 0 | M45: =IF(M3="SALE",-M21+M29+M34-M35-M42+M37+M23,0) -> 0 | N45: =IF(N3="SALE",-N21+N29+N34-N35-N42+N37+N23,0) -> 0 | O45: =IF(O3="SALE",-O21+O29+O34-O35-O42+O37+O23,0) -> 0 | P45: =IF(P3="SALE",-P21+P29+P34-P35-P42+P37+P23,0) -> 0 | Q45: =IF(Q3="SALE",-Q21+Q29+Q34-Q35-Q42+Q37+Q23,0) -> 0 | R45: =IF(R3="SALE",-R21+R29+R34-R35-R42+R37+R23,0) -> 0 | S45: =IF(S3="SALE",-S21+S29+S34-S35-S42+S37+S23,0) -> 0 | ... AB45: =IF(AB3="SALE",-AB21+AB29+AB34-AB35-AB42+AB37+AB23,0) -> 0
B47: Interested Parties Cash Flows
B48: Limited Partner/Mezzanine
B49: Equity In | C49: =+SUM(D49:AB49) -> -48279.565 | D49: =-IF(Inputs!D103<>"RCH", Inputs!D107, 0) -> -48279.565 | E49: 0 | F49: 0 | G49: 0 | H49: 0 | I49: 0 | J49: 0 | K49: =+IF(K45<0,K45,0) -> 0 | L49: =+IF(L45<0,L45,0) -> 0 | M49: =+IF(M45<0,M45,0) -> 0 | N49: =+IF(N45<0,N45,0) -> 0 | O49: =+IF(O45<0,O45,0) -> 0 | P49: =+IF(P45<0,P45,0) -> 0 | Q49: =+IF(Q45<0,Q45,0) -> 0 | R49: =+IF(R45<0,R45,0) -> 0 | ... AB49: =+IF(AB45<0,AB45,0) -> 0
B50: Return of Capital | C50: =+SUM(D50:AB50) -> 48279.565 | E50: =+IF(E3="SALE",-$C$49,) -> 0 | F50: =+IF(F3="SALE",-$C$49,) -> 0 | G50: =+IF(G3="SALE",-$C$49,) -> 0 | H50: =+IF(H3="SALE",-$C$49,) -> 0 | I50: =+IF(I3="SALE",-$C$49,) -> 0 | J50: =+IF(J3="SALE",-$C$49,) -> 0 | K50: =+IF(K3="SALE",-$C$49,) -> 48279.565 | L50: =+IF(L3="SALE",-$C$49,) -> 0 | ... AB50: =+IF(AB3="SALE",-$C$49,) -> 0
B51: Preferred Return Payment | C51: =+SUM(D51:AB51) -> 4549.0079 | E51: =+IF(E3="SALE",-$C$49*Inputs!$D$105/12*((E2-#REF!)/30),) -> 0 | F51: =+IF(F3="SALE",-$C$49*Inputs!$D$105/12*((F2-#REF!)/30),) -> 0 | G51: =+IF(G3="SALE",-$C$49*Inputs!$D$105/12*((G2-#REF!)/30),) -> 0 | H51: =+IF(H3="SALE",-$C$49*Inputs!$D$105/12*((H2-A2)/30),) -> 0 | I51: =+IF(I3="SALE",-$C$49*Inputs!$D$105/12*((I2-B2)/30),) -> 0 | J51: =+IF(J3="SALE",-$C$49*Inputs!$D$105/12*((J2-C2)/30),) -> 0 | K51: =+IF(K3="SALE",-$C$49*Inputs!$D$105/12*((K2-D2)/30),) -> 4549.0079 | L51: =+IF(L3="SALE",-$C$49*Inputs!$D$105/12*((L2-E2)/30),) -> 0 | M51: =+IF(M3="SALE",-$C$49*Inputs!$D$105/12*((M2-F2)/30),) -> 0 | N51: =+IF(N3="SALE",-$C$49*Inputs!$D$105/12*((N2-G2)/30),) -> 0 | O51: =+IF(O3="SALE",-$C$49*Inputs!$D$105/12*((O2-H2)/30),) -> 0 | ... AB51: =+IF(AB3="SALE",-$C$49*Inputs!$D$105/12*((AB2-U2)/30),) -> 0
B52: Promote | C52: =+SUM(D52:AB52) -> 0 | E52: =+IF(E3="SALE",(E45-E50-E51+#REF!)*Inputs!$D$106,) -> 0 | F52: =+IF(F3="SALE",(F45-F50-F51+#REF!)*Inputs!$D$106,) -> 0 | G52: =+IF(G3="SALE",(G45-G50-G51+#REF!)*Inputs!$D$106,) -> 0 | H52: =+IF(H3="SALE",(H45-H50-H51+#REF!)*Inputs!$D$106,) -> 0 | I52: =+IF(I3="SALE",(I45-I50-I51+A56)*Inputs!$D$106,) -> 0 | J52: =+IF(J3="SALE",(J45-J50-J51+B56)*Inputs!$D$106,) -> 0 | K52: =+IF(K3="SALE",(K45-K50-K51+C56)*Inputs!$D$106,) -> 0 | L52: =+IF(L3="SALE",(L45-L50-L51+D56)*Inputs!$D$106,) -> 0 | M52: =+IF(M3="SALE",(M45-M50-M51+E56)*Inputs!$D$106,) -> 0 | N52: =+IF(N3="SALE",(N45-N50-N51+F56)*Inputs!$D$106,) -> 0 | O52: =+IF(O3="SALE",(O45-O50-O51+G56)*Inputs!$D$106,) -> 0 | P52: =+IF(P3="SALE",(P45-P50-P51+H56)*Inputs!$D$106,) -> 0 | ... AB52: =+IF(AB3="SALE",(AB45-AB50-AB51+T56)*Inputs!$D$106,) -> 0
B53: Total LP Cash Flow | C53: =+SUM(D53:AB53) -> 4549.0079 | D53: =SUM(D49:D52) -> -48279.565 | E53: =SUM(E49:E52) -> 0 | F53: =SUM(F49:F52) -> 0 | G53: =SUM(G49:G52) -> 0 | H53: =SUM(H49:H52) -> 0 | I53: =SUM(I49:I52) -> 0 | J53: =SUM(J49:J52) -> 0 | K53: =SUM(K49:K52) -> 52828.573 | ... AB53: =SUM(AB49:AB52) -> 0
B55: Equity In | D55: =-IF(Inputs!D103="RCH",Inputs!D107,0) -> 0 | E55: 0 | F55: 0 | G55: 0 | H55: 0 | I55: 0 | J55: 0 | K55: =+IF(K51<0,K51,0) -> 0 | L55: =+IF(L51<0,L51,0) -> 0 | M55: =+IF(M51<0,M51,0) -> 0 | N55: =+IF(N51<0,N51,0) -> 0 | O55: =+IF(O51<0,O51,0) -> 0 | P55: =+IF(P51<0,P51,0) -> 0 | Q55: =+IF(Q51<0,Q51,0) -> 0 | R55: =+IF(R51<0,R51,0) -> 0 | ... AB55: =+IF(AB51<0,AB51,0) -> 0
B56: Interest Carry Expense | C56: =SUM(D56:AB56) -> 0 | D56: =+IF(Inputs!$D$93="No",'Monthly CF'!D36,0) -> 0 | E56: =+IF(Inputs!$D$93="No",'Monthly CF'!E36,0) -> 0 | F56: =+IF(Inputs!$D$93="No",'Monthly CF'!F36,0) -> 0 | G56: =+IF(Inputs!$D$93="No",'Monthly CF'!G36,0) -> 0 | H56: =+IF(Inputs!$D$93="No",'Monthly CF'!H36,0) -> 0 | I56: =+IF(Inputs!$D$93="No",'Monthly CF'!I36,0) -> 0 | J56: =+IF(Inputs!$D$93="No",'Monthly CF'!J36,0) -> 0 | K56: =+IF(Inputs!$D$93="No",'Monthly CF'!K36,0) -> 0 | ... AB56: =+IF(Inputs!$D$93="No",'Monthly CF'!AB36,0) -> 0
B57: RCH Promote | C57: =SUM(D57:AB57) -> 94692.548 | D57: =+IF(D45>0,'Acquisition Summary'!#REF!,0) -> 0 | E57: =+IF(E3="SALE", E45-E53,) -> 0 | F57: =+IF(F3="SALE", F45-F53,) -> 0 | G57: =+IF(G3="SALE", G45-G53,) -> 0 | H57: =+IF(H3="SALE", H45-H53,) -> 0 | I57: =+IF(I3="SALE", I45-I53,) -> 0 | J57: =+IF(J3="SALE", J45-J53,) -> 0 | K57: =+IF(K3="SALE", K45-K53,) -> 94692.548 | L57: =+IF(L3="SALE", L45-L53,) -> 0 | ... AB57: =+IF(AB3="SALE", AB45-AB53,) -> 0
B58: Net RCH CF | C58: =SUM(D58:AB58) -> 94692.548 | D58: =SUM(D55:D57) -> 0 | E58: =SUM(E55:E57) -> 0 | F58: =SUM(F55:F57) -> 0 | G58: =SUM(G55:G57) -> 0 | H58: =SUM(H55:H57) -> 0 | I58: =SUM(I55:I57) -> 0 | J58: =SUM(J55:J57) -> 0 | K58: =SUM(K55:K57) -> 94692.548 | ... AB58: =SUM(AB55:AB57) -> 0
B60: RCC Profits
B61: General Conditions | C61: =+SUM(D61:AB61) -> 0 | D61: =+D20 -> 0 | E61: =+E20 -> 0 | F61: =+F20 -> 0 | G61: =+G20 -> 0 | H61: =+H20 -> 0 | I61: =+I20 -> 0 | J61: =+J20 -> 0 | K61: =+K20 -> 0 | ... AB61: =+AB20 -> 0
B62: Builder Profit | C62: =+SUM(D62:AB62) -> 26743.702 | D62: =+D19 -> 0 | E62: =+E19 -> 0 | F62: =+F19 -> 6685.9255 | G62: =+G19 -> 6685.9255 | H62: =+H19 -> 6685.9255 | I62: =+I19 -> 6685.9255 | J62: =+J19 -> 0 | K62: =+K19 -> 0 | ... AB62: =+AB19 -> 0
B63: Total to RCC | C63: =+SUM(D63:AB63) -> 26743.702 | D63: =SUM(D61:D62) -> 0 | E63: =SUM(E61:E62) -> 0 | F63: =SUM(F61:F62) -> 6685.9255 | G63: =SUM(G61:G62) -> 6685.9255 | H63: =SUM(H61:H62) -> 6685.9255 | I63: =SUM(I61:I62) -> 6685.9255 | J63: =SUM(J61:J62) -> 0 | K63: =SUM(K61:K62) -> 0 | ... AB63: =SUM(AB61:AB62) -> 0
B65: RCR/PHC Profits
B66: Purchase Commission | C66: =+SUM(D66:AB66) -> 0 | D66: =+D7 -> 0 | E66: =+E7 -> 0 | F66: =+F7 -> 0 | G66: =+G7 -> 0 | H66: =+H7 -> 0 | I66: =+I7 -> 0 | J66: =+J7 -> 0 | K66: =+K7 -> 0 | ... AB66: =+AB7 -> 0
B67: Sales Commission | C67: =+SUM(D67:AB67) -> 4500 | D67: =+IF(D45>0,Inputs!$AA$12,0) -> 0 | E67: =+IF(E45>0,Inputs!$AA$12,0) -> 0 | F67: =+IF(F45>0,Inputs!$AA$12,0) -> 0 | G67: =+IF(G45>0,Inputs!$AA$12,0) -> 0 | H67: =+IF(H45>0,Inputs!$AA$12,0) -> 0 | I67: =+IF(I45>0,Inputs!$AA$12,0) -> 0 | J67: =+IF(J45>0,Inputs!$AA$12,0) -> 0 | K67: =+IF(K45>0,Inputs!$AA$12,0) -> 4500 | ... AB67: =+IF(AB45>0,Inputs!$AA$12,0) -> 0
B68: Total to RCR | C68: =+SUM(D68:AB68) -> 4500 | D68: =SUM(D66:D67) -> 0 | E68: =SUM(E66:E67) -> 0 | F68: =SUM(F66:F67) -> 0 | G68: =SUM(G66:G67) -> 0 | H68: =SUM(H66:H67) -> 0 | I68: =SUM(I66:I67) -> 0 | J68: =SUM(J66:J67) -> 0 | K68: =SUM(K66:K67) -> 4500 | ... AB68: =SUM(AB66:AB67) -> 0
B70: Total to RCCP | C70: =+SUM(D70:AB70) -> 125936.25 | D70: =+D68+D63+D58 -> 0 | E70: =+E68+E63+E58 -> 0 | F70: =+F68+F63+F58 -> 6685.9255 | G70: =+G68+G63+G58 -> 6685.9255 | H70: =+H68+H63+H58 -> 6685.9255 | I70: =+I68+I63+I58 -> 6685.9255 | J70: =+J68+J63+J58 -> 0 | K70: =+K68+K63+K58 -> 99192.548 | ... AB70: =+AB68+AB63+AB58 -> 0

Sheet Comps
A1: Comps below for Williard and Birnie: Some are over 1700 sqft, closer to 2000sqft I think our target is $450k - $475k Best comps: 109 Gates St (best comp) 1636 sqft $470k 15 Woodlawn $460k (1824 sqft) 15 E 5th st 26 b e main Old houses sold in the high $3's
A9: 109 Gates St (best comp) 1636 sqft $470k
A10: 15 Woodlawn $460k (1824 sqft)
A11: 15 E 5th st
A12: 26 b e main
A14: Old houses sold in the high $3's

Sheet Common Eq. WF
C2: COMMON EQUITY WATERFALL
D4: XIRR | E4: Multiple
C5: Deal-Level | D5: =+D11 -> 5.8419517 | E5: =+IFERROR(SUM(E15:AZ15)/-SUMIF(E15:AZ15,"<0")+1,"N/A") -> 3.0555603
C6: Common LP Equity | D6: =D9 -> 0.17307672 | E6: =+IFERROR(SUM(E51:AZ51)/-SUMIF(E51:AZ51,"<0")+1,"N/A") -> 1.0971507
A7: =IF('Acquisition Summary'!J57="Preferred",0,IF('Acquisition Summary'!J57="First Hurdle",1,IF('Acquisition Summary'!J57="Second Hurdle",2,3))) -> 0
E8: Year 0 | F8: 1 | G8: 2 | H8: 3 | I8: 4 | J8: 5 | K8: 6 | L8: 7 | M8: 8 | N8: 9 | O8: 10
C9: Common Equity LP Returns | D9: =+IFERROR(XIRR(E51:AZ51,E14:AZ14),"N/A") -> 0.17307672 | E9: =+E51 -> -48279.565 | F9: =+SUM(OFFSET($F$51,,(F8-1)*12,,12)) -> 52969.961 | G9: =+SUM(OFFSET($F$51,,(G8-1)*12,,12)) -> 0 | H9: =+SUM(OFFSET($F$51,,(H8-1)*12,,12)) -> 0 | I9: =+SUM(OFFSET($F$51,,(I8-1)*12,,12)) -> 0 | J9: =+SUM(OFFSET($F$51,,(J8-1)*12,,12)) -> 0 | K9: =+SUM(OFFSET($F$51,,(K8-1)*12,,12)) -> 0 | L9: =+SUM(OFFSET($F$51,,(L8-1)*12,,12)) -> 0 | M9: =+SUM(OFFSET($F$51,,(M8-1)*12,,12)) -> 0 | ... O9: =+SUM(OFFSET($F$51,,(O8-1)*12,,12)) -> 0
C10: Sponsor Total Returns | D10: =+IFERROR(IRR(E10:Q10),"N/A") -> N/A | E10: =+E52 -> 0 | F10: =+SUM(OFFSET($F$52,,(F8-1)*12,2,12)) -> 94551.16 | G10: =+SUM(OFFSET($F$52,,(G8-1)*12,2,12)) -> 0 | H10: =+SUM(OFFSET($F$52,,(H8-1)*12,2,12)) -> 0 | I10: =+SUM(OFFSET($F$52,,(I8-1)*12,2,12)) -> 0 | J10: =+SUM(OFFSET($F$52,,(J8-1)*12,2,12)) -> 0 | K10: =+SUM(OFFSET($F$52,,(K8-1)*12,2,12)) -> 0 | L10: =+SUM(OFFSET($F$52,,(L8-1)*12,2,12)) -> 0 | M10: =+SUM(OFFSET($F$52,,(M8-1)*12,2,12)) -> 0 | ... O10: =+SUM(OFFSET($F$52,,(O8-1)*12,2,12)) -> 0
C11: Deal-Level Returns | D11: =+XIRR(E15:AZ15,E14:AZ14) -> 5.8419517 | E11: =SUM(E9:E10) -> -48279.565 | F11: =SUM(F9:F10) -> 147521.12 | G11: =SUM(G9:G10) -> 0 | H11: =SUM(H9:H10) -> 0 | I11: =SUM(I9:I10) -> 0 | J11: =SUM(J9:J10) -> 0 | K11: =SUM(K9:K10) -> 0 | L11: =SUM(L9:L10) -> 0 | ... O11: =SUM(O9:O10) -> 0
C14: Month Number | E14: =+'Monthly CF'!D2 -> 46081 | F14: =+'Monthly CF'!E2 -> 46109 | G14: =+'Monthly CF'!F2 -> 46140 | H14: =+'Monthly CF'!G2 -> 46170 | I14: =+'Monthly CF'!H2 -> 46201 | J14: =+'Monthly CF'!I2 -> 46231 | K14: =+'Monthly CF'!J2 -> 46262 | L14: =+'Monthly CF'!K2 -> 46293 | ... AY14: =+'Monthly CF'!AX2 -> 0 | AZ14: 47057 | BB14: Exit Year | BD14: =+SUMIFS(E14:Q14,E16:Q16,">0") -> 0
C15: Project Cash Flow After Debt Service | E15: =+'Monthly CF'!D45 -> -48279.565 | F15: =+'Monthly CF'!E45 -> 0 | G15: =+'Monthly CF'!F45 -> 0 | H15: =+'Monthly CF'!G45 -> 0 | I15: =+'Monthly CF'!H45 -> 0 | J15: =+'Monthly CF'!I45 -> 0 | K15: =+'Monthly CF'!J45 -> 0 | L15: =+'Monthly CF'!K45 -> 147521.12 | ... AZ15: =+'Monthly CF'!AY45 -> 0
BB16: Cash Flow to Equity | BD16: =+HLOOKUP(BD14,E14:Q15,2,FALSE) -> #N/A
B17: x | C17: Preferred Return | BB17: Preferred Return
C18: LP Capital Account Balance | F18: =E20 -> -48279.565 | G18: =F22 -> -48923.293 | H18: =G22 -> -49575.603 | I18: =H22 -> -50236.611 | J18: =I22 -> -50906.433 | K18: =J22 -> -51585.185 | L18: =K22 -> -52272.988 | M18: =L22 -> 0 | N18: =M22 -> 0 | ... AZ18: =AY22 -> 0
C19: Pref Accrual | F19: =F18*'Acquisition Summary'!$J$53/12 -> -643.72754 | G19: =G18*'Acquisition Summary'!$J$53/12 -> -652.31057 | H19: =H18*'Acquisition Summary'!$J$53/12 -> -661.00805 | I19: =I18*'Acquisition Summary'!$J$53/12 -> -669.82149 | J19: =J18*'Acquisition Summary'!$J$53/12 -> -678.75244 | K19: =K18*'Acquisition Summary'!$J$53/12 -> -687.80247 | L19: =L18*'Acquisition Summary'!$J$53/12 -> -696.97317 | M19: =M18*'Acquisition Summary'!$J$53/12 -> 0 | ... AZ19: =AZ18*'Acquisition Summary'!$J$53/12 -> 0 | BB19: Pref Accrual | BD19: =+SUMIFS(F19:Q19,$F$14:$Q$14,$BD$14) -> 0
C20: Preferred CF | E20: =+E15 -> -48279.565 | F20: =+IF(F15>0,MIN(-SUM(F19),F15),F15) -> 0 | G20: =+IF(G15>0,MIN(-SUM(G19),G15),G15) -> 0 | H20: =+IF(H15>0,MIN(-SUM(H19),H15),H15) -> 0 | I20: =+IF(I15>0,MIN(-SUM(I19),I15),I15) -> 0 | J20: =+IF(J15>0,MIN(-SUM(J19),J15),J15) -> 0 | K20: =+IF(K15>0,MIN(-SUM(K19),K15),K15) -> 0 | L20: =+IF(L15>0,MIN(-SUM(L19),L15),L15) -> 696.97317 | M20: =+IF(M15>0,MIN(-SUM(M19),M15),M15) -> 0 | ... AZ20: =+IF(AZ15>0,MIN(-SUM(AZ19),AZ15),AZ15) -> 0 | BB20: Preferred CF | BD20: #N/A
C21: Net Sale Proceeds Payout | F21: =+IF(F15>0,MIN(F15-F20,-SUM(F18:F20)),0) -> 0 | G21: =+IF(G15>0,MIN(G15-G20,-SUM(G18:G20)),0) -> 0 | H21: =+IF(H15>0,MIN(H15-H20,-SUM(H18:H20)),0) -> 0 | I21: =+IF(I15>0,MIN(I15-I20,-SUM(I18:I20)),0) -> 0 | J21: =+IF(J15>0,MIN(J15-J20,-SUM(J18:J20)),0) -> 0 | K21: =+IF(K15>0,MIN(K15-K20,-SUM(K18:K20)),0) -> 0 | L21: =+IF(L15>0,MIN(L15-L20,-SUM(L18:L20)),0) -> 52272.988 | M21: =+IF(M15>0,MIN(M15-M20,-SUM(M18:M20)),0) -> 0 | ... AZ21: =+IF(AZ15>0,MIN(AZ15-AZ20,-SUM(AZ18:AZ20)),0) -> 0
C22: Ending Capital Account Balance | F22: =SUM(F18:F21) -> -48923.293 | G22: =SUM(G18:G21) -> -49575.603 | H22: =SUM(H18:H21) -> -50236.611 | I22: =SUM(I18:I21) -> -50906.433 | J22: =SUM(J18:J21) -> -51585.185 | K22: =SUM(K18:K21) -> -52272.988 | L22: =SUM(L18:L21) -> 0 | M22: =SUM(M18:M21) -> 0 | ... AZ22: =SUM(AZ18:AZ21) -> 0
BB23: Tier 1
C24: Remainder to Tier 1 | F24: =+F15+F16-F20-F21 -> 0 | G24: =+G15+G16-G20-G21 -> 0 | H24: =+H15+H16-H20-H21 -> 0 | I24: =+I15+I16-I20-I21 -> 0 | J24: =+J15+J16-J20-J21 -> 0 | K24: =+K15+K16-K20-K21 -> 0 | L24: =+L15+L16-L20-L21 -> 94551.16 | M24: =+M15+M16-M20-M21 -> 0 | ... AZ24: =+AZ15+AZ16-AZ20-AZ21 -> 0 | BB24: Pref Accrual | BD24: =+SUMIFS(F28:Q28,$F$14:$Q$14,$BD$14) -> 0
B25: x | C25: Tier 1 | D25: Passthru? | E25: No | BB25: Preferred CF | BD25: =+BD20 -> #N/A
BB26: Tier 1 CF | BD26: #REF!
C27: LP Capital Account Balance | F27: =E29 -> -48279.565 | G27: =F31 -> -48923.293 | H27: =G31 -> -49575.603 | I27: =H31 -> -50236.611 | J27: =I31 -> -50906.433 | K27: =J31 -> -51585.185 | L27: =K31 -> -52272.988 | M27: =L31 -> 0 | N27: =M31 -> 0 | ... AZ27: =AY31 -> 0
C28: Pref Accrual | F28: =IF($E$25="YES",F27*100%,F27*'Acquisition Summary'!$J$53/12) -> -643.72754 | G28: =IF($E$25="YES",G27*100%,G27*'Acquisition Summary'!$J$53/12) -> -652.31057 | H28: =IF($E$25="YES",H27*100%,H27*'Acquisition Summary'!$J$53/12) -> -661.00805 | I28: =IF($E$25="YES",I27*100%,I27*'Acquisition Summary'!$J$53/12) -> -669.82149 | J28: =IF($E$25="YES",J27*100%,J27*'Acquisition Summary'!$J$53/12) -> -678.75244 | K28: =IF($E$25="YES",K27*100%,K27*'Acquisition Summary'!$J$53/12) -> -687.80247 | L28: =IF($E$25="YES",L27*100%,L27*'Acquisition Summary'!$J$53/12) -> -696.97317 | M28: =IF($E$25="YES",M27*100%,M27*'Acquisition Summary'!$J$53/12) -> 0 | ... AZ28: =IF($E$25="YES",AZ27*100%,AZ27*'Acquisition Summary'!$J$53/12) -> 0 | BB28: CF to GP | BD28: #REF!
C29: Preferred CF | E29: =+E20 -> -48279.565 | F29: =+F20+F21 -> 0 | G29: =+G20+G21 -> 0 | H29: =+H20+H21 -> 0 | I29: =+I20+I21 -> 0 | J29: =+J20+J21 -> 0 | K29: =+K20+K21 -> 0 | L29: =+L20+L21 -> 52969.961 | M29: =+M20+M21 -> 0 | ... AZ29: =+AZ20+AZ21 -> 0 | BB29: Remainder to Tier 2 | BD29: =+#REF!-BD26-BD28 -> #REF!
C30: Tier 1 CF | F30: =+IFERROR(IF(F24>0,MIN(F24*'Acquisition Summary'!$K$54,-SUM(F27:F29)/'Acquisition Summary'!$K$54,-SUM(F27:F29)),0),0) -> 0 | G30: =+IFERROR(IF(G24>0,MIN(G24*'Acquisition Summary'!$K$54,-SUM(G27:G29)/'Acquisition Summary'!$K$54,-SUM(G27:G29)),0),0) -> 0 | H30: =+IFERROR(IF(H24>0,MIN(H24*'Acquisition Summary'!$K$54,-SUM(H27:H29)/'Acquisition Summary'!$K$54,-SUM(H27:H29)),0),0) -> 0 | I30: =+IFERROR(IF(I24>0,MIN(I24*'Acquisition Summary'!$K$54,-SUM(I27:I29)/'Acquisition Summary'!$K$54,-SUM(I27:I29)),0),0) -> 0 | J30: =+IFERROR(IF(J24>0,MIN(J24*'Acquisition Summary'!$K$54,-SUM(J27:J29)/'Acquisition Summary'!$K$54,-SUM(J27:J29)),0),0) -> 0 | K30: =+IFERROR(IF(K24>0,MIN(K24*'Acquisition Summary'!$K$54,-SUM(K27:K29)/'Acquisition Summary'!$K$54,-SUM(K27:K29)),0),0) -> 0 | L30: =+IFERROR(IF(L24>0,MIN(L24*'Acquisition Summary'!$K$54,-SUM(L27:L29)/'Acquisition Summary'!$K$54,-SUM(L27:L29)),0),0) -> 0 | M30: =+IFERROR(IF(M24>0,MIN(M24*'Acquisition Summary'!$K$54,-SUM(M27:M29)/'Acquisition Summary'!$K$54,-SUM(M27:M29)),0),0) -> 0 | ... AZ30: =+IFERROR(IF(AZ24>0,MIN(AZ24*'Acquisition Summary'!$K$54,-SUM(AZ27:AZ29)/'Acquisition Summary'!$K$54,-SUM(AZ27:AZ29)),0),0) -> 0
C31: Ending Capital Account Balance | F31: =SUM(F27:F30) -> -48923.293 | G31: =SUM(G27:G30) -> -49575.603 | H31: =SUM(H27:H30) -> -50236.611 | I31: =SUM(I27:I30) -> -50906.433 | J31: =SUM(J27:J30) -> -51585.185 | K31: =SUM(K27:K30) -> -52272.988 | L31: =SUM(L27:L30) -> 0 | M31: =SUM(M27:M30) -> 0 | ... AZ31: =SUM(AZ27:AZ30) -> 0 | BB31: Pref Accrual | BD31: =+SUMIFS(F38:Q38,$F$14:$Q$14,$BD$14) -> 0
BB32: Preferred CF | BD32: =+BD25 -> #N/A
C33: CF to GP Promote | F33: =+IFERROR(F30/'Acquisition Summary'!$K$54*'Acquisition Summary'!$L$54,F24-F30) -> 0 | G33: =+IFERROR(G30/'Acquisition Summary'!$K$54*'Acquisition Summary'!$L$54,G24-G30) -> 0 | H33: =+IFERROR(H30/'Acquisition Summary'!$K$54*'Acquisition Summary'!$L$54,H24-H30) -> 0 | I33: =+IFERROR(I30/'Acquisition Summary'!$K$54*'Acquisition Summary'!$L$54,I24-I30) -> 0 | J33: =+IFERROR(J30/'Acquisition Summary'!$K$54*'Acquisition Summary'!$L$54,J24-J30) -> 0 | K33: =+IFERROR(K30/'Acquisition Summary'!$K$54*'Acquisition Summary'!$L$54,K24-K30) -> 0 | L33: =+IFERROR(L30/'Acquisition Summary'!$K$54*'Acquisition Summary'!$L$54,L24-L30) -> 94551.16 | M33: =+IFERROR(M30/'Acquisition Summary'!$K$54*'Acquisition Summary'!$L$54,M24-M30) -> 0 | ... AZ33: =+IFERROR(AZ30/'Acquisition Summary'!$K$54*'Acquisition Summary'!$L$54,AZ24-AZ30) -> 0 | BB33: Tier 1 CF | BD33: =+BD26 -> #REF!
C34: Remainder to Tier 2 | F34: =+F24-F30-F33 -> 0 | G34: =+G24-G30-G33 -> 0 | H34: =+H24-H30-H33 -> 0 | I34: =+I24-I30-I33 -> 0 | J34: =+J24-J30-J33 -> 0 | K34: =+K24-K30-K33 -> 0 | L34: =+L24-L30-L33 -> 0 | M34: =+M24-M30-M33 -> 0 | ... AZ34: =+AZ24-AZ30-AZ33 -> 0 | BB34: Tier 2 CF | BD34: #REF!
B35: x | C35: Tier 2 | D35: Passthru? | E35: No
BB36: CF to GP | BD36: #REF!
C37: LP Capital Account Balance | F37: =E39 -> -48279.565 | G37: =F42 -> -50492.379 | H37: =G42 -> -52806.613 | I37: =H42 -> -55226.916 | J37: =I42 -> -57758.149 | K37: =J42 -> -60405.398 | L37: =K42 -> -63173.979 | M37: =L42 -> -13099.492 | N37: =M42 -> -13699.885 | ... AZ37: =AY42 -> -75212.696 | BB37: Remainder to Tier 3 | BD37: =+BD29-BD34-BD36 -> #REF!
C38: Pref Accrual | F38: =IF($E$35="YES",F37*100%,F37*'Acquisition Summary'!$J$55/12) -> -2212.8134 | G38: =IF($E$35="YES",G37*100%,G37*'Acquisition Summary'!$J$55/12) -> -2314.234 | H38: =IF($E$35="YES",H37*100%,H37*'Acquisition Summary'!$J$55/12) -> -2420.3031 | I38: =IF($E$35="YES",I37*100%,I37*'Acquisition Summary'!$J$55/12) -> -2531.2336 | J38: =IF($E$35="YES",J37*100%,J37*'Acquisition Summary'!$J$55/12) -> -2647.2485 | K38: =IF($E$35="YES",K37*100%,K37*'Acquisition Summary'!$J$55/12) -> -2768.5807 | L38: =IF($E$35="YES",L37*100%,L37*'Acquisition Summary'!$J$55/12) -> -2895.474 | M38: =IF($E$35="YES",M37*100%,M37*'Acquisition Summary'!$J$55/12) -> -600.39337 | ... AZ38: =IF($E$35="YES",AZ37*100%,AZ37*'Acquisition Summary'!$J$55/12) -> -3447.2486
C39: Preferred CF | E39: =+E29 -> -48279.565 | F39: =+F29 -> 0 | G39: =+G29 -> 0 | H39: =+H29 -> 0 | I39: =+I29 -> 0 | J39: =+J29 -> 0 | K39: =+K29 -> 0 | L39: =+L29 -> 52969.961 | ... AZ39: =+AZ29 -> 0 | BB39: Tier 3
C40: Tier 1 CF | F40: =+F30 -> 0 | G40: =+G30 -> 0 | H40: =+H30 -> 0 | I40: =+I30 -> 0 | J40: =+J30 -> 0 | K40: =+K30 -> 0 | L40: =+L30 -> 0 | M40: =+M30 -> 0 | ... AZ40: =+AZ30 -> 0 | BB40: Remainder to LP | BD40: #REF!
C41: Tier 2 CF | F41: =+IF(F15>0,MIN(F34*'Acquisition Summary'!$K$55,-SUM(F37:F40)/'Acquisition Summary'!$K$55,-SUM(F37:F40)),0) -> 0 | G41: =+IF(G15>0,MIN(G34*'Acquisition Summary'!$K$55,-SUM(G37:G40)/'Acquisition Summary'!$K$55,-SUM(G37:G40)),0) -> 0 | H41: =+IF(H15>0,MIN(H34*'Acquisition Summary'!$K$55,-SUM(H37:H40)/'Acquisition Summary'!$K$55,-SUM(H37:H40)),0) -> 0 | I41: =+IF(I15>0,MIN(I34*'Acquisition Summary'!$K$55,-SUM(I37:I40)/'Acquisition Summary'!$K$55,-SUM(I37:I40)),0) -> 0 | J41: =+IF(J15>0,MIN(J34*'Acquisition Summary'!$K$55,-SUM(J37:J40)/'Acquisition Summary'!$K$55,-SUM(J37:J40)),0) -> 0 | K41: =+IF(K15>0,MIN(K34*'Acquisition Summary'!$K$55,-SUM(K37:K40)/'Acquisition Summary'!$K$55,-SUM(K37:K40)),0) -> 0 | L41: =+IF(L15>0,MIN(L34*'Acquisition Summary'!$K$55,-SUM(L37:L40)/'Acquisition Summary'!$K$55,-SUM(L37:L40)),0) -> 0 | M41: =+IF(M15>0,MIN(M34*'Acquisition Summary'!$K$55,-SUM(M37:M40)/'Acquisition Summary'!$K$55,-SUM(M37:M40)),0) -> 0 | ... AZ41: =+IF(AZ15>0,MIN(AZ34*'Acquisition Summary'!$K$55,-SUM(AZ37:AZ40)/'Acquisition Summary'!$K$55,-SUM(AZ37:AZ40)),0) -> 0 | BB41: Remainder to GP | BD41: #REF!
C42: Ending Capital Account Balance | F42: =SUM(F37:F41) -> -50492.379 | G42: =SUM(G37:G41) -> -52806.613 | H42: =SUM(H37:H41) -> -55226.916 | I42: =SUM(I37:I41) -> -57758.149 | J42: =SUM(J37:J41) -> -60405.398 | K42: =SUM(K37:K41) -> -63173.979 | L42: =SUM(L37:L41) -> -13099.492 | M42: =SUM(M37:M41) -> -13699.885 | ... AZ42: =SUM(AZ37:AZ41) -> -78659.945
BB43: Total To External LP | BD43: #N/A
C44: CF to GP Promote | F44: =+F41/'Acquisition Summary'!$K$55*'Acquisition Summary'!$L$55 -> 0 | G44: 0 | H44: 0 | I44: 0 | J44: 0 | K44: 0 | L44: 0 | M44: 0 | N44: 0 | O44: 0 | P44: 0 | Q44: 0 | R44: 0 | S44: 0 | T44: 0 | U44: 0 | V44: 0 | W44: 0 | X44: 0 | Y44: 0 | Z44: 0 | AA44: 0 | AB44: 0 | AC44: 0 | AD44: 0 | AE44: 0 | AF44: 0 | AG44: 0 | AH44: 0 | AI44: 0 | AJ44: 0 | AK44: 0 | AL44: 0 | AM44: 0 | AN44: 0 | AO44: 0 | AP44: 0 | AQ44: 0 | AR44: 0 | AS44: 0 | AT44: 0 | AU44: 0 | AV44: 0 | AW44: 0 | AX44: 0 | AY44: 0 | AZ44: 0 | BB44: Total to Sponsor LP | BD44: #N/A
C45: Remainder to Tier 3 | F45: =+F34-F41-F44 -> 0 | G45: =+G34-G41-G44 -> 0 | H45: =+H34-H41-H44 -> 0 | I45: =+I34-I41-I44 -> 0 | J45: =+J34-J41-J44 -> 0 | K45: =+K34-K41-K44 -> 0 | L45: =+L34-L41-L44 -> 0 | M45: =+M34-M41-M44 -> 0 | ... AZ45: =+AZ34-AZ41-AZ44 -> 0 | BB45: Total To GP | BD45: =+SUM(BD28,BD36,BD41) -> #REF!
B46: x | C46: Tier 3
C48: Remainder to LP | F48: =+F45*'Acquisition Summary'!$K$56 -> 0 | G48: =+G45*'Acquisition Summary'!$K$56 -> 0 | H48: =+H45*'Acquisition Summary'!$K$56 -> 0 | I48: =+I45*'Acquisition Summary'!$K$56 -> 0 | J48: =+J45*'Acquisition Summary'!$K$56 -> 0 | K48: =+K45*'Acquisition Summary'!$K$56 -> 0 | L48: =+L45*'Acquisition Summary'!$K$56 -> 0 | M48: =+M45*'Acquisition Summary'!$K$56 -> 0 | ... AZ48: =+AZ45*'Acquisition Summary'!$K$56 -> 0 | BB48: External LP Yield | BD48: #N/A
C49: Remainder to GP | F49: =+F45-F48 -> 0 | G49: =+G45-G48 -> 0 | H49: =+H45-H48 -> 0 | I49: =+I45-I48 -> 0 | J49: =+J45-J48 -> 0 | K49: =+K45-K48 -> 0 | L49: =+L45-L48 -> 0 | M49: =+M45-M48 -> 0 | ... AZ49: =+AZ45-AZ48 -> 0 | BB49: Sponsor Total Yield | BD49: #N/A
C51: Total To LP | E51: =+E15*'Acquisition Summary'!$J$59 -> -48279.565 | F51: =+(F$20+F$30+F$41+F$48+F$21)*'Acquisition Summary'!$J$59 -> 0 | G51: =+(G20+G30+G41+G48+G21)*'Acquisition Summary'!$J$59 -> 0 | H51: =+(H20+H30+H41+H48+H21)*'Acquisition Summary'!$J$59 -> 0 | I51: =+(I20+I30+I41+I48+I21)*'Acquisition Summary'!$J$59 -> 0 | J51: =+(J20+J30+J41+J48+J21)*'Acquisition Summary'!$J$59 -> 0 | K51: =+(K20+K30+K41+K48+K21)*'Acquisition Summary'!$J$59 -> 0 | L51: =+(L20+L30+L41+L48+L21)*'Acquisition Summary'!$J$59 -> 52969.961 | M51: =+(M20+M30+M41+M48+M21)*'Acquisition Summary'!$J$59 -> 0 | N51: =+(N20+N30+N41+N48+N21)*'Acquisition Summary'!$J$59 -> 0 | ... AZ51: =+(AZ20+AZ30+AZ41+AZ48+AZ21)*'Acquisition Summary'!$J$59 -> 0
C52: Total to GP Equity | E52: =+E15-E51 -> 0 | F52: =+(F$20+F$30+F$41+F$48+F$21)*'Acquisition Summary'!$J$60 -> 0 | G52: =+(G$20+G$30+G$41+G$48+G$21)*'Acquisition Summary'!$J$60 -> 0 | H52: =+(H$20+H$30+H$41+H$48+H$21)*'Acquisition Summary'!$J$60 -> 0 | I52: =+(I$20+I$30+I$41+I$48+I$21)*'Acquisition Summary'!$J$60 -> 0 | J52: =+(J$20+J$30+J$41+J$48+J$21)*'Acquisition Summary'!$J$60 -> 0 | K52: =+(K$20+K$30+K$41+K$48+K$21)*'Acquisition Summary'!$J$60 -> 0 | L52: =+(L$20+L$30+L$41+L$48+L$21)*'Acquisition Summary'!$J$60 -> 0 | M52: =+(M$20+M$30+M$41+M$48+M$21)*'Acquisition Summary'!$J$60 -> 0 | ... AZ52: =+(AZ$20+AZ$30+AZ$41+AZ$48+AZ$21)*'Acquisition Summary'!$J$60 -> 0
C53: Total To GP Promote | F53: =+F33+F44+F49 -> 0 | G53: =+G33+G44+G49 -> 0 | H53: =+H33+H44+H49 -> 0 | I53: =+I33+I44+I49 -> 0 | J53: =+J33+J44+J49 -> 0 | K53: =+K33+K44+K49 -> 0 | L53: =+L33+L44+L49 -> 94551.16 | M53: =+M33+M44+M49 -> 0 | ... AZ53: =+AZ33+AZ44+AZ49 -> 0
E54: =+E52+E53 -> 0 | F54: =+F52+F53 -> 0 | G54: =+G52+G53 -> 0 | H54: =+H52+H53 -> 0 | I54: =+I52+I53 -> 0 | J54: =+J52+J53 -> 0 | K54: =+K52+K53 -> 0 | L54: =+L52+L53 -> 94551.16 | ... AZ54: =+AZ52+AZ53 -> 0
C56: Cumulative CF to LP | E56: =SUM($E$51:E51) -> -48279.565 | F56: =SUM($E$51:F51) -> -48279.565 | G56: =SUM($E$51:G51) -> -48279.565 | H56: =SUM($E$51:H51) -> -48279.565 | I56: =SUM($E$51:I51) -> -48279.565 | J56: =SUM($E$51:J51) -> -48279.565 | K56: =SUM($E$51:K51) -> -48279.565 | L56: =SUM($E$51:L51) -> 4690.3957 | ... AZ56: =SUM($E$51:AZ51) -> 4690.3957
C59: Common Equity LP Returns
C60: Profit | E60: =SUM(E51:AZ51) -> 4690.3957
C61: Peak Equity | E61: =MIN(E56:AZ56) -> -48279.565
C62: CFX | E62: =IFERROR(1+(-E60/E61),"N/A") -> 1.0971507
C63: XIRR | E63: =IFERROR(XIRR(E51:AZ51,E14:AZ14),"N/A") -> 0.17307672

Sheet Reference Tab
G1: Legend | H1: Manual Inputs | J1: Estimates
B2: Comfort is base house | U2: MODEL
U3: ACTIVITY | V3: Acacia | W3: Aspen 2-Story | X3: Atlas II | Y3: Banyan | Z3: Cherry | AA3: Dogwood | AB3: Hazel | AC3: Holly | AD3: Elm | AE3: Lilac | AF3: Lily | AG3: Magnolia | AH3: Spindle | AI3: Spruce | AJ3: Tulip | AK3: White Oak | AL3: Willow | AM3: Jasmine | AN3: Palm II | AO3: Palmetto | AP3: Palmetto II | AQ3: Linville | AR3: Bayberry | AS3: Alder | AT3: Boxelder | AU3: Bur Oak | AV3: Conifer | AW3: Pinyon | AX3: Cottonwood | AY3: Locust | AZ3: Fraser | BA3: Sycamore | BB3: Poplar | BC3: Fig | BD3: Aspen 3-Story | BE3: Atlas II - SC | BF3: Magnolia - SC | BG3: Conifer - SC | BH3: Palmetto II - SC
B4: Model | C4: SFH/TH | D4: SF | E4: Bed | F4: Bath | G4: Garage | H4: Sticks & Bricks | I4: Classic | J4: Elegance | K4: Harmony | L4: $/SF Sticks & Bricks | M4: Build Time | N4: Plans | R4: Site Specific | U4: Dumpster | V4: 3000 | W4: 3000 | X4: 3000 | Y4: 3000 | Z4: 3000 | AA4: 3000 | AB4: 3000 | AC4: 3000 | AD4: 3000 | AE4: 3000 | AF4: 3000 | AG4: 3000 | AH4: 3000 | AI4: 3000 | AJ4: 3000 | AK4: 3000 | AL4: 3000 | AM4: 1500 | AN4: 1500 | AO4: 1500 | AP4: 1500 | AQ4: 1500 | AR4: 1500 | AS4: 1500 | AT4: 1500 | AU4: 1500 | AV4: 1500 | AW4: 1500 | AX4: 1500 | AY4: 1500 | AZ4: 1500 | BA4: 1500 | BB4: 1500 | BC4: 1500 | BD4: 3000 | BE4: 3000 | BF4: 3000 | BG4: 1500 | BH4: 1500
A5: {=+_xlfn._xlws.SORT(B5:B44)} -> Acacia | B5: Acacia | C5: SFH | D5: 2236 | E5: 4 | F5: 3 | G5: 2 | H5: =INDEX($V$58:$CA$58,MATCH(B5,$V$3:$CA$3,0)) -> 162510.14 | I5: 4200 | J5: 10000 | K5: TBD | L5: =H5/D5 -> 72.678953 | M5: 150 | N5: Acacia | R5: Demolition | S5: 0 | U5: Utilities | V5: 300 | W5: 300 | X5: 300 | Y5: 300 | Z5: 300 | AA5: 300 | AB5: 300 | AC5: 300 | AD5: 300 | AE5: 300 | AF5: 300 | AG5: 300 | AH5: 300 | AI5: 300 | AJ5: 300 | AK5: 300 | AL5: 300 | AM5: 300 | AN5: 300 | AO5: 300 | AP5: 300 | AQ5: 300 | AR5: 300 | AS5: 300 | AT5: 300 | AU5: 300 | AV5: 300 | AW5: 300 | AX5: 300 | AY5: 300 | AZ5: 300 | BA5: 300 | BB5: 300 | BC5: 300 | BD5: 300 | BE5: 300 | BF5: 300 | BG5: 300 | BH5: 300
A6: Alder | B6: Aspen 2-Story | C6: SFH | D6: 1788 | E6: 3 | F6: 2.5 | G6: 2 | H6: =INDEX($V$58:$CA$58,MATCH(B6,$V$3:$CA$3,0)) -> 137618.63 | I6: 4750 | J6: 9600 | K6: TBD | L6: =H6/D6 -> 76.967914 | M6: 150 | N6: Aspen | R6: Survey Set Pins | S6: =V59 -> 1185 | U6: Portable toilet | V6: 875 | W6: 875 | X6: 875 | Y6: 875 | Z6: 875 | AA6: 875 | AB6: 875 | AC6: 875 | AD6: 875 | AE6: 875 | AF6: 875 | AG6: 875 | AH6: 875 | AI6: 875 | AJ6: 875 | AK6: 875 | AL6: 875 | AM6: 437.5 | AN6: 437.5 | AO6: 437.5 | AP6: 437.5 | AQ6: 437.5 | AR6: 437.5 | AS6: 437.5 | AT6: 437.5 | AU6: 437.5 | AV6: 437.5 | AW6: 437.5 | AX6: 437.5 | AY6: 437.5 | AZ6: 437.5 | BA6: 437.5 | BB6: 437.5 | BC6: 437.5 | BD6: 875 | BE6: 875 | BF6: 875 | BG6: 437.5 | BH6: 437.5
A7: Aspen 2-Story | B7: Aspen 3-Story | C7: SFH | D7: 2168 | E7: 3 | F7: 2.5 | G7: 2 | H7: =INDEX($V$58:$CA$58,MATCH(B7,$V$3:$CA$3,0)) -> 158618.63 | I7: 5050 | J7: 10100 | K7: TBD | L7: =H7/D7 -> 73.163575 | M7: 150 | N7: Aspen | R7: Stake House | S7: =V60 -> 0 | U7: Permit Box | V7: 50 | W7: 50 | X7: 50 | Y7: 50 | Z7: 50 | AA7: 50 | AB7: 50 | AC7: 50 | AD7: 50 | AE7: 50 | AF7: 50 | AG7: 50 | AH7: 50 | AI7: 50 | AJ7: 50 | AK7: 50 | AL7: 50 | AM7: 50 | AN7: 50 | AO7: 50 | AP7: 50 | AQ7: 50 | AR7: 50 | AS7: 50 | AT7: 50 | AU7: 50 | AV7: 50 | AW7: 50 | AX7: 50 | AY7: 50 | AZ7: 50 | BA7: 50 | BB7: 50 | BC7: 50 | BD7: 50 | BE7: 50 | BF7: 50 | BG7: 50 | BH7: 50
A8: Aspen 3-Story | B8: Atlas II | C8: SFH | D8: 1554 | E8: 3 | F8: 2.5 | G8: 0 | H8: =INDEX($V$58:$CA$58,MATCH(B8,$V$3:$CA$3,0)) -> 115967.93 | I8: 4200 | J8: 8800 | K8: TBD | L8: =H8/D8 -> 74.625438 | M8: 150 | N8: Atlas | R8: Grading/Lot Clear/Hauling | S8: =V61 -> 1700 | U8: Termite | V8: 185 | W8: 185 | X8: 185 | Y8: 185 | Z8: 185 | AA8: 185 | AB8: 185 | AC8: 185 | AD8: 185 | AE8: 185 | AF8: 185 | AG8: 185 | AH8: 185 | AI8: 185 | AJ8: 185 | AK8: 185 | AL8: 185 | AM8: 100 | AN8: 100 | AO8: 100 | AP8: 100 | AQ8: 100 | AR8: 100 | AS8: 100 | AT8: 100 | AU8: 100 | AV8: 100 | AW8: 100 | AX8: 100 | AY8: 100 | AZ8: 100 | BA8: 100 | BB8: 100 | BC8: 100 | BD8: 185 | BE8: 225 | BF8: 225 | BG8: 100 | BH8: 100
A9: Atlas II | B9: Banyan | C9: SFH | D9: 1400 | E9: 3 | F9: 3 | G9: 2 | H9: =INDEX($V$58:$CA$58,MATCH(B9,$V$3:$CA$3,0)) -> 132231.45 | I9: 4600 | J9: 10300 | K9: TBD | L9: =H9/D9 -> 94.451036 | M9: 150 | N9: Banyan | R9: Erosion Control Repair | S9: 1000 | U9: Lumber All Floors | V9: 11104.49 | W9: 9431.9 | X9: 7728.8 | Y9: 12383.01 | Z9: 10656.85 | AA9: 8339.21 | AB9: 8613.02 | AC9: 10133.56 | AD9: 9144.71 | AE9: 5318.1 | AF9: 8587.71 | AG9: 13138.51 | AH9: 13115.47 | AI9: 7498.5 | AJ9: 6015.42 | AK9: 9755.2 | AL9: 8475.6 | AM9: 12617.8 | AN9: 10871.89 | AO9: 10894.93 | AP9: 11713.79 | AQ9: 14894.86 | AR9: 13804.66 | AS9: 10871.89 | AT9: 13804.63 | AU9: 12899.26 | AV9: 19880.19 | AW9: 15866.78 | AX9: 18492.96 | AY9: 13255.91 | AZ9: 20740.06 | BA9: 13594.11 | BB9: 16271.86 | BC9: 20446.27 | BD9: 12931.9 | BE9: 6661.73 | BF9: 14249.76 | BG9: 20404.24 | BH9: 10551.74
A10: Atlas II - SC | B10: Cherry | C10: SFH | D10: 2214 | E10: 4 | F10: 3 | G10: 2 | H10: =INDEX($V$58:$CA$58,MATCH(B10,$V$3:$CA$3,0)) -> 154828.84 | I10: 5000 | J10: 11000 | K10: TBD | L10: =H10/D10 -> 69.931725 | M10: 150 | N10: Cherry | R10: Temp Drive | S10: =V63 -> 500 | U10: Framing Labor | V10: 11814 | W10: 9953.4 | X10: 7399.8 | Y10: 9775 | Z10: 11965.2 | AA10: 8890.8 | AB10: 9630 | AC10: 10848 | AD10: 9714 | AE10: 8378.4 | AF10: 8722.8 | AG10: 14014.8 | AH10: 9646.8 | AI10: 9272 | AJ10: 6936 | AK10: 10877.4 | AL10: 10244.8 | AM10: 11125.6 | AN10: 12164 | AO10: 8399.64 | AP10: 10275.76 | AQ10: 16075.7 | AR10: 11704 | AS10: 12164 | AT10: 13544.6 | AU10: 12196.11 | AV10: 16850.16 | AW10: 16065.46 | AX10: 15790 | AY10: 12057.8 | AZ10: 13539.9 | BA10: 14974.2 | BB10: 11939.8 | BC10: 14443.8 | BD10: 9953.4 | BE10: 7399.8 | BF10: 14014.8 | BG10: 16850.16 | BH10: 10275.76
A11: Banyan | B11: Dogwood | C11: SFH | D11: 1541 | E11: 3 | F11: 2.5 | G11: 2 | H11: =INDEX($V$58:$CA$58,MATCH(B11,$V$3:$CA$3,0)) -> 123366.66 | I11: 4000 | J11: 8300 | K11: TBD | L11: =H11/D11 -> 80.056236 | M11: 150 | N11: Dogwood | R11: Landscaping | S11: =V64 -> 2500 | U11: Floor Trusses | V11: 4155.94 | W11: 5696.33 | X11: 2669.74 | Y11: 6113.79 | Z11: 4821.04 | AA11: 4063.71 | AB11: 3755.36 | AC11: 5135.9 | AD11: 3981.09 | AE11: 3647.87 | AF11: 5616 | AG11: 5532.68 | AH11: 5428 | AI11: 0 | AJ11: 0 | AK11: 4905.78 | AL11: 3103.56 | AM11: 2858.58 | AN11: 3919.99 | AO11: 4152.77 | AP11: 2344.29 | AQ11: 3878.46 | AR11: 2168.84 | AS11: 3641.18 | AT11: 2168.84 | AU11: 3361 | AV11: 4405.23 | AW11: 6594.14 | AX11: 4405.23 | AY11: 2945.54 | AZ11: 3516.08 | BA11: 5207.47 | BB11: 3437.66 | BC11: 4698.64 | BD11: 5696.33 | BE11: 2616.73 | BF11: 5468.2 | BG11: 6863.5 | BH11: 3040.47
A12: Bayberry | B12: Hazel | C12: SFH | D12: 1713 | E12: 4 | F12: 2.5 | G12: 2 | H12: =INDEX($V$58:$CA$58,MATCH(B12,$V$3:$CA$3,0)) -> 129651.85 | I12: 4450 | J12: 9100 | K12: TBD | L12: =H12/D12 -> 75.687011 | M12: 150 | N12: Hazel | R12: Flatwork | S12: =V65 -> 2475 | U12: Stairs | V12: 580.59 | W12: 580.59 | X12: 580.59 | Y12: 1161.17 | Z12: 580.59 | AA12: 580.59 | AB12: 580.59 | AC12: 580.59 | AD12: 580.59 | AE12: 580.59 | AF12: 1161.17 | AG12: 580.59 | AH12: 580.59 | AI12: 0 | AJ12: 0 | AK12: 580.59 | AL12: 580.59 | AM12: 580.59 | AN12: 580.59 | AO12: 580.59 | AP12: 580.59 | AQ12: 580.59 | AR12: 580.59 | AS12: 580.59 | AT12: 580.59 | AU12: 580.59 | AV12: 1161.17 | AW12: 1161.17 | AX12: 1741.76 | AY12: 580.59 | AZ12: 580.59 | BA12: 580.59 | BB12: 580.59 | BC12: 1161.17 | BD12: 580.59 | BE12: 573.82 | BF12: 573.82 | BG12: 1147.64 | BH12: 580.59
A13: Boxelder | B13: Holly | C13: SFH | D13: 2000 | E13: 4 | F13: 2.5 | G13: 2 | H13: =INDEX($V$58:$CA$58,MATCH(B13,$V$3:$CA$3,0)) -> 141925.87 | I13: 4000 | J13: 8500 | K13: TBD | L13: =H13/D13 -> 70.962935 | M13: 150 | N13: Holly | S13: =SUM(S5:S12) -> 9360 | U13: Roof Trusses | V13: 6556.27 | W13: 4606.55 | X13: 2810.98 | Y13: 1549.23 | Z13: 4835.45 | AA13: 3782.21 | AB13: 3152.9 | AC13: 4450.17 | AD13: 3523.21 | AE13: 4737.39 | AF13: 3966.85 | AG13: 5567.64 | AH13: 3414.36 | AI13: 6700.77 | AJ13: 4959.1 | AK13: 3392.32 | AL13: 3694.53 | AM13: 3252.72 | AN13: 3893.18 | AO13: 2966.77 | AP13: 2302.33 | AQ13: 6450.79 | AR13: 3050.07 | AS13: 3758 | AT13: 3050.07 | AU13: 2789.7 | AV13: 2700.52 | AW13: 2541.57 | AX13: 2975.45 | AY13: 3221.91 | AZ13: 3149.92 | BA13: 3869.3 | BB13: 2823.48 | BC13: 2464.51 | BD13: 4606.55 | BE13: 2458.39 | BF13: 6490.15 | BG13: 2660.6 | BH13: 2621.54
A14: Bur Oak | B14: Elm | C14: SFH | D14: 1712 | E14: 4 | F14: 2.5 | G14: 2 | H14: =INDEX($V$58:$CA$58,MATCH(B14,$V$3:$CA$3,0)) -> 130967.62 | I14: 4300 | J14: 9000 | K14: TBD | L14: =H14/D14 -> 76.499778 | M14: 150 | N14: Elm | R14: Soft Costs | U14: I-Joist/EWP | V14: 0 | W14: 0 | X14: 0 | Y14: 0 | Z14: 0 | AA14: 0 | AB14: 0 | AC14: 0 | AD14: 0 | AE14: 0 | AF14: 0 | AG14: 0 | AH14: 0 | AI14: 0 | AJ14: 0 | AK14: 0 | AL14: 0 | AM14: 0 | AN14: 0 | AO14: 0 | AP14: 0 | AQ14: 0 | AR14: 0 | AS14: 0 | AT14: 0 | AU14: 0 | AV14: 0 | AW14: 0 | AX14: 0 | AY14: 0 | AZ14: 0 | BA14: 0 | BB14: 0 | BC14: 0 | BD14: 0 | BE14: 0 | BF14: 0 | BG14: 0 | BH14: 0
A15: Cherry | B15: Lilac | C15: SFH | D15: 1382 | E15: 3 | F15: 3 | G15: 1 | H15: =INDEX($V$58:$CA$58,MATCH(B15,$V$3:$CA$3,0)) -> 120703.39 | I15: 4000 | J15: 9000 | K15: TBD | L15: =H15/D15 -> 87.339645 | M15: 150 | N15: Lilac | R15: Building Permits | S15: =V67 -> 2050 | U15: Roofing Shingle | V15: 0 | W15: 0 | X15: 0 | Y15: 0 | Z15: 0 | AA15: 0 | AB15: 0 | AC15: 0 | AD15: 0 | AE15: 0 | AF15: 0 | AG15: 0 | AH15: 0 | AI15: 0 | AJ15: 0 | AK15: 0 | AL15: 0 | AM15: 0 | AN15: 0 | AO15: 0 | AP15: 0 | AQ15: 0 | AR15: 0 | AS15: 0 | AT15: 0 | AU15: 0 | AV15: 0 | AW15: 0 | AX15: 0 | AY15: 0 | AZ15: 0 | BA15: 0 | BB15: 0 | BC15: 0 | BD15: 0 | BE15: 0 | BF15: 0 | BG15: 0 | BH15: 0
A16: Conifer | B16: Lily | C16: SFH | D16: 2293 | E16: 4 | F16: 3.5 | G16: 0 | H16: =INDEX($V$58:$CA$58,MATCH(B16,$V$3:$CA$3,0)) -> 158070.49 | I16: 5400 | J16: 10700 | K16: TBD | L16: =H16/D16 -> 68.936106 | M16: 150 | N16: Lily | R16: Engineering | S16: =V70 -> 600 | U16: Roofing Metal | V16: 0 | W16: 0 | X16: 0 | Y16: 0 | Z16: 0 | AA16: 0 | AB16: 0 | AC16: 0 | AD16: 0 | AE16: 0 | AF16: 0 | AG16: 0 | AH16: 0 | AI16: 0 | AJ16: 0 | AK16: 0 | AL16: 0 | AM16: 0 | AN16: 0 | AO16: 0 | AP16: 0 | AQ16: 0 | AR16: 0 | AS16: 0 | AT16: 0 | AU16: 0 | AV16: 0 | AW16: 0 | AX16: 0 | AY16: 0 | AZ16: 0 | BA16: 0 | BB16: 0 | BC16: 0 | BD16: 0 | BE16: 0 | BF16: 0 | BG16: 0 | BH16: 0
A17: Conifer - SC | B17: Magnolia | C17: SFH | D17: 2771 | E17: 4 | F17: 3 | G17: 2 | H17: =INDEX($V$58:$CA$58,MATCH(B17,$V$3:$CA$3,0)) -> 174241.94 | I17: 4600 | J17: 11100 | K17: TBD | L17: =H17/D17 -> 62.880527 | M17: 150 | N17: Magnolia | S17: =SUM(S15:S16) -> 2650 | U17: Roofing Labor & Material | V17: 6424.32 | W17: 4236.58 | X17: 2920.44 | Y17: 2998.27 | Z17: 4800.84 | AA17: 3690.25 | AB17: 3672.91 | AC17: 4800.96 | AD17: 3536.45 | AE17: 4236.07 | AF17: 4236.36 | AG17: 5264.93 | AH17: 4712.86 | AI17: 5928.55 | AJ17: 4800.72 | AK17: 4612.8 | AL17: 4424.08 | AM17: 3337.32 | AN17: 3297.59 | AO17: 2433.06 | AP17: 4820.8 | AQ17: 4920.2 | AR17: 3381 | AS17: 3297.59 | AT17: 3184.04 | AU17: 3223.27 | AV17: 3939.4 | AW17: 2487.96 | AX17: 2214.15 | AY17: 2964.15 | AZ17: 4783.7 | BA17: 4066.01 | BB17: 3234.47 | BC17: 2523.36 | BD17: 4236.58 | BE17: 3070.51 | BF17: 5160.61 | BG17: 2162.6 | BH17: 2106.98
A18: Cottonwood | B18: Spindle | C18: SFH | D18: 1545 | E18: 3 | F18: 2 | G18: 0 | H18: =INDEX($V$58:$CA$58,MATCH(B18,$V$3:$CA$3,0)) -> 145757.73 | I18: 4100 | J18: 8800 | K18: TBD | L18: =H18/D18 -> 94.341573 | M18: 150 | N18: Spindle | U18: Siding Material | V18: 5209.64 | W18: 5257.76 | X18: 3929.56 | Y18: 6327.34 | Z18: 5756.82 | AA18: 4091.57 | AB18: 5034.13 | AC18: 4829.82 | AD18: 5131.78 | AE18: 3937.59 | AF18: 7550.19 | AG18: 5588.56 | AH18: 7127.73 | AI18: 4302.39 | AJ18: 3613.36 | AK18: 4868.08 | AL18: 4875.11 | AM18: 4652.06 | AN18: 3797.77 | AO18: 3765.31 | AP18: 2508.62 | AQ18: 5996.56 | AR18: 4003.86 | AS18: 3769.91 | AT18: 3850.98 | AU18: 3126.61 | AV18: 4500.75 | AW18: 6899.6 | AX18: 2383.2 | AY18: 3692.4 | AZ18: 4119.71 | BA18: 5304.01 | BB18: 4559.56 | BC18: 4755.98 | BD18: 5257.76 | BE18: 3883.77 | BF18: 5523.41 | BG18: 4448.33 | BH18: 2479.36
A19: CUSTOM | B19: Spruce | C19: SFH | D19: 1545 | E19: 3 | F19: 2 | G19: 2 | H19: =INDEX($V$58:$CA$58,MATCH(B19,$V$3:$CA$3,0)) -> 126615.36 | I19: 2800 | J19: 7300 | K19: TBD | L19: =H19/D19 -> 81.951689 | M19: 150 | N19: Spruce | U19: Siding Labor | V19: 3485 | W19: 3550 | X19: 2340 | Y19: 4805 | Z19: 3855 | AA19: 2845 | AB19: 3140 | AC19: 3350 | AD19: 3460 | AE19: 2650 | AF19: 5500 | AG19: 3760 | AH19: 4820 | AI19: 2720 | AJ19: 2345 | AK19: 2900 | AL19: 2900 | AM19: 2473 | AN19: 2600 | AO19: 2390 | AP19: 1650 | AQ19: 3400 | AR19: 1720 | AS19: 2600 | AT19: 2550 | AU19: 1696 | AV19: 2482 | AW19: 3885 | AX19: 2712.5 | AY19: 2460 | AZ19: 2426 | BA19: 3400 | BB19: 3212.5 | BC19: 3885 | BD19: 3550 | BE19: 2128.7 | BF19: 3483.67 | BG19: 1373 | BH19: 1126.32
A20: Dogwood | B20: Tulip | C20: SFH | D20: 1170 | E20: 3 | F20: 2 | G20: 1 | H20: =INDEX($V$58:$CA$58,MATCH(B20,$V$3:$CA$3,0)) -> 105321.66 | I20: 3000 | J20: 6500 | K20: TBD | L20: =H20/D20 -> 90.018513 | M20: 150 | N20: Tulip | U20: Window Material | V20: 3023.13 | W20: 2477.66 | X20: 2761.95 | Y20: 3205.85 | Z20: 3121.99 | AA20: 2123.41 | AB20: 2506.13 | AC20: 3898.44 | AD20: 2547.19 | AE20: 2225.4 | AF20: 5281.01 | AG20: 3823.99 | AH20: 3725.69 | AI20: 2445.22 | AJ20: 1274.11 | AK20: 2936.09 | AL20: 2741.53 | AM20: 2330.97 | AN20: 2654.72 | AO20: 2177.34 | AP20: 1767.17 | AQ20: 2874.28 | AR20: 2098.92 | AS20: 1951.74 | AT20: 1954.83 | AU20: 2443.92 | AV20: 2209.93 | AW20: 2786.05 | AX20: 2193.93 | AY20: 2360.09 | AZ20: 2671.15 | BA20: 1742.92 | BB20: 1486.2 | BC20: 2132.97 | BD20: 5977.66 | BE20: 2729.75 | BF20: 3779.43 | BG20: 2184.17 | BH20: 1746.58
A21: Elm | B21: White Oak | C21: SFH | D21: 2005 | E21: 4 | F21: 2.5 | G21: 2 | H21: =INDEX($V$58:$CA$58,MATCH(B21,$V$3:$CA$3,0)) -> 141504.81 | I21: 4400 | J21: 6700 | K21: TBD | L21: =H21/D21 -> 70.575965 | M21: 150 | N21: White Oak | U21: Exterior Door Material | V21: 1682.73 | W21: 1682.73 | X21: 1125.51 | Y21: 2035.11 | Z21: 1644.95 | AA21: 1794.95 | AB21: 1682.73 | AC21: 1621.39 | AD21: 1682.73 | AE21: 1644.95 | AF21: 3270.39 | AG21: 1832.73 | AH21: 1817.2 | AI21: 1644.95 | AJ21: 1860.56 | AK21: 1832.73 | AL21: 1473.96 | AM21: 1794.95 | AN21: 1693.76 | AO21: 959.15 | AP21: 1167.63 | AQ21: 3656.14 | AR21: 1794.95 | AS21: 1644.95 | AT21: 2611 | AU21: 1843.76 | AV21: 2113.22 | AW21: 2461 | AX21: 1279.38 | AY21: 2674.05 | AZ21: 931.6 | BA21: 931.6 | BB21: 931.6 | BC21: 1705.76 | BD21: 1682.73 | BE21: 1112.38 | BF21: 1663.11 | BG21: 2088.59 | BH21: 1154.02
A22: Fig | B22: Willow | C22: SFH | D22: 1857 | E22: 4 | F22: 2.5 | G22: 1 | H22: =INDEX($V$58:$CA$58,MATCH(B22,$V$3:$CA$3,0)) -> 131392.95 | I22: 4100 | J22: 9000 | K22: TBD | L22: =H22/D22 -> 70.755493 | M22: 150 | N22: Willow | U22: Exterior Door Labor | V22: 210 | W22: 173 | X22: 120 | Y22: 240 | Z22: 173 | AA22: 173 | AB22: 173 | AC22: 180 | AD22: 173 | AE22: 173 | AF22: 210 | AG22: 173 | AH22: 180 | AI22: 173 | AJ22: 256 | AK22: 173 | AL22: 180 | AM22: 173 | AN22: 173 | AO22: 180 | AP22: 120 | AQ22: 173 | AR22: 173 | AS22: 173 | AT22: 210 | AU22: 173 | AV22: 150 | AW22: 210 | AX22: 180 | AY22: 173 | AZ22: 120 | BA22: 120 | BB22: 120 | BC22: 173 | BD22: 173 | BE22: 120 | BF22: 173 | BG22: 150 | BH22: 120
A23: Fraser | B23: Jasmine | C23: TH | D23: 1500 | E23: 3 | F23: 2.5 | G23: 1 | H23: =INDEX($V$58:$CA$58,MATCH(B23,$V$3:$CA$3,0)) -> 124245.5 | I23: 3800 | J23: 8000 | K23: 4500 | L23: =H23/D23 -> 82.830333 | M23: 150 | N23: Jasmine | U23: Windows Labor | V23: 277 | W23: 308 | X23: 330 | Y23: 525 | Z23: 304 | AA23: 242 | AB23: 286 | AC23: 370 | AD23: 286 | AE23: 204 | AF23: 915 | AG23: 440 | AH23: 370 | AI23: 226 | AJ23: 240 | AK23: 352 | AL23: 308 | AM23: 264 | AN23: 330 | AO23: 166 | AP23: 220 | AQ23: 277 | AR23: 242 | AS23: 242 | AT23: 220 | AU23: 254 | AV23: 420 | AW23: 525 | AX23: 420 | AY23: 264 | AZ23: 330 | BA23: 198 | BB23: 144 | BC23: 182 | BD23: 308 | BE23: 330 | BF23: 440 | BG23: 264 | BH23: 220
A24: Hazel | B24: Bayberry | C24: TH | D24: 1500 | E24: 3 | F24: 2.5 | G24: 1F | H24: =INDEX($V$58:$CA$58,MATCH(B24,$V$3:$CA$3,0)) -> 123038.45 | I24: 3600 | J24: 5500 | K24: 6100 | L24: =H24/D24 -> 82.025633 | M24: 150 | N24: Bayberry | U24: Garage Door Labor & Material | V24: 1600 | W24: 1800 | X24: 0 | Y24: 1600 | Z24: 1600 | AA24: 1600 | AB24: 1600 | AC24: 1600 | AD24: 1600 | AE24: 1100 | AF24: 0 | AG24: 1600 | AH24: 0 | AI24: 1600 | AJ24: 1100 | AK24: 1600 | AL24: 1100 | AM24: 1100 | AN24: 1000 | AO24: 0 | AP24: 0 | AQ24: 1600 | AR24: 1100 | AS24: 1000 | AT24: 1600 | AU24: 1100 | AV24: 1600 | AW24: 1600 | AX24: 1000 | AY24: 1000 | AZ24: 1600 | BA24: 1600 | BB24: 1600 | BC24: 1100 | BD24: 1800 | BE24: 0 | BF24: 1600 | BG24: 1600 | BH24: 0
A25: Holly | B25: Cottonwood | C25: TH | D25: 1729 | E25: 3 | F25: 2.5 | G25: 1F | H25: =INDEX($V$58:$CA$58,MATCH(B25,$V$3:$CA$3,0)) -> 141829.36 | I25: 6500 | J25: 7100 | K25: TBD | L25: =H25/D25 -> 82.029705 | M25: 150 | N25: Cottonwood | U25: Plumbing Turnkey | V25: 13635 | W25: 12373 | X25: 12123 | Y25: 13451 | Z25: 15022 | AA25: 12111 | AB25: 12337 | AC25: 12111 | AD25: 12111 | AE25: 13524 | AF25: 16119 | AG25: 15589 | AH25: 12560 | AI25: 10261 | AJ25: 10398 | AK25: 12631 | AL25: 12671 | AM25: 12504 | AN25: 13256 | AO25: 11949 | AP25: 12560 | AQ25: 12463 | AR25: 12567 | AS25: 13256 | AT25: 9830 | AU25: 10552 | AV25: 13782 | AW25: 13695 | AX25: 12755 | AY25: 12429 | AZ25: 12615 | BA25: 13258 | BB25: 12489 | BC25: 14692 | BD25: 15873 | BE25: 10115 | BF25: 12620 | BG25: 12740 | BH25: 10135
A26: Jasmine | B26: Linville | C26: TH | D26: 2188 | E26: 4 | F26: 2.5 | G26: 2F | H26: =INDEX($V$58:$CA$58,MATCH(B26,$V$3:$CA$3,0)) -> 158682.42 | I26: 4700 | J26: 8900 | K26: 7300 | L26: =H26/D26 -> 72.523958 | M26: 150 | N26: Linville | U26: HVAC | V26: 10900 | W26: 10300 | X26: 10100 | Y26: 9600 | Z26: 10900 | AA26: 10200 | AB26: 10400 | AC26: 10400 | AD26: 10400 | AE26: 9200 | AF26: 14300 | AG26: 16500 | AH26: 10400 | AI26: 8700 | AJ26: 7200 | AK26: 10400 | AL26: 10400 | AM26: 9500 | AN26: 10400 | AO26: 9200 | AP26: 8470 | AQ26: 11300 | AR26: 9500 | AS26: 10200 | AT26: 10500 | AU26: 9900 | AV26: 11900 | AW26: 11700 | AX26: 11800 | AY26: 10100 | AZ26: 10200 | BA26: 10600 | BB26: 9700 | BC26: 13540 | BD26: 13800 | BE26: 8250 | BF26: 11950 | BG26: 8600 | BH26: 6250
A27: Lilac | B27: Locust | C27: TH | D27: 1700 | E27: 3 | F27: 2.5 | G27: 1 | H27: =INDEX($V$58:$CA$58,MATCH(B27,$V$3:$CA$3,0)) -> 128788.11 | I27: 4600 | J27: 7200 | K27: TBD | L27: =H27/D27 -> 75.757712 | M27: 150 | N27: Locust | U27: Electrical Rough & Trim | V27: 9475.97 | W27: 8397.78 | X27: 7191 | Y27: 6622.98 | Z27: 8947.9 | AA27: 6948.88 | AB27: 7859.77 | AC27: 8989.73 | AD27: 8022.68 | AE27: 8179.07 | AF27: 9830.34 | AG27: 9554.92 | AH27: 7197.38 | AI27: 6843.48 | AJ27: 5941.07 | AK27: 8876.69 | AL27: 8314.77 | AM27: 6878.46 | AN27: 8855 | AO27: 6120.79 | AP27: 8645 | AQ27: 9670 | AR27: 7510.54 | AS27: 9165 | AT27: 9035 | AU27: 8380 | AV27: 10435 | AW27: 9170 | AX27: 10802 | AY27: 7538.55 | AZ27: 7307.18 | BA27: 8632.36 | BB27: 9694 | BC27: 7050.01 | BD27: 11897.78 | BE27: 6270 | BF27: 8045 | BG27: 7900 | BH27: 6400
A28: Lily | B28: Palmetto | C28: TH | D28: 1304 | E28: 3 | F28: 2.5 | G28: 0 | H28: =INDEX($V$58:$CA$58,MATCH(B28,$V$3:$CA$3,0)) -> 109770.74 | I28: 3900 | J28: 8200 | K28: TBD | L28: =H28/D28 -> 84.180015 | M28: 150 | N28: Palmetto | U28: Blower Test | V28: 300.11 | W28: 300.11 | X28: 300.11 | Y28: 300.11 | Z28: 300.11 | AA28: 300.11 | AB28: 300.11 | AC28: 300.11 | AD28: 300.11 | AE28: 300.11 | AF28: 300.11 | AG28: 300.11 | AH28: 300.11 | AI28: 300.11 | AJ28: 300.11 | AK28: 300.11 | AL28: 300.11 | AM28: 300.11 | AN28: 300.11 | AO28: 300.11 | AP28: 300.11 | AQ28: 300 | AR28: 300.11 | AS28: 300.11 | AT28: 300.11 | AU28: 300.11 | AV28: 300.11 | AW28: 300.11 | AX28: 300.11 | AY28: 300.11 | AZ28: 300.11 | BA28: 300 | BB28: 300.11 | BC28: 300.11 | BD28: 300.11 | BE28: 275 | BF28: 275 | BG28: 275 | BH28: 275
A29: Linville | B29: Palmetto II | C29: TH | D29: 1424 | E29: 3 | F29: 2.5 | G29: 1F | H29: =INDEX($V$58:$CA$58,MATCH(B29,$V$3:$CA$3,0)) -> 111483.39 | I29: 4100 | J29: 7200 | K29: 5000 | L29: =H29/D29 -> 78.288897 | M29: 150 | N29: Palmetto II | U29: Low Voltage/AV | V29: 0 | W29: 0 | X29: 0 | Y29: 0 | Z29: 0 | AA29: 0 | AB29: 0 | AC29: 0 | AD29: 0 | AE29: 0 | AF29: 0 | AG29: 0 | AH29: 0 | AI29: 0 | AJ29: 0 | AK29: 0 | AL29: 0 | AM29: 0 | AN29: 0 | AO29: 0 | AP29: 0 | AQ29: 0 | AR29: 0 | AS29: 0 | AT29: 0 | AU29: 0 | AV29: 0 | AW29: 0 | AX29: 0 | AY29: 0 | AZ29: 0 | BA29: 0 | BB29: 0 | BC29: 0 | BD29: 0 | BE29: 0 | BF29: 0 | BG29: 0 | BH29: 0
A30: Locust | B30: Palm II | C30: TH | D30: 1689 | E30: 3 | F30: 2.5 | G30: 1F | H30: =INDEX($V$58:$CA$58,MATCH(B30,$V$3:$CA$3,0)) -> 130052.04 | I30: 5000 | J30: 8500 | K30: TBD | L30: =H30/D30 -> 76.999432 | M30: 150 | N30: Palm II | U30: Insulation | V30: 4067 | W30: 3356 | X30: 2890 | Y30: 2949 | Z30: 4139 | AA30: 3642 | AB30: 3671 | AC30: 3382 | AD30: 3535 | AE30: 3414 | AF30: 4640 | AG30: 4672 | AH30: 5523 | AI30: 2981 | AJ30: 2833 | AK30: 3698 | AL30: 3238 | AM30: 3784 | AN30: 4138.5 | AO30: 3872 | AP30: 2953 | AQ30: 5210 | AR30: 3588 | AS30: 3541 | AT30: 4245 | AU30: 3693 | AV30: 4227 | AW30: 3996 | AX30: 4560 | AY30: 3989 | AZ30: 3891 | BA30: 4098 | BB30: 3811 | BC30: 4939 | BD30: 3356 | BE30: 2800 | BF30: 4725 | BG30: 3975 | BH30: 3155
A31: Magnolia | B31: Fig | C31: TH | D31: 1798 | E31: 3 | F31: 3.5 | G31: 1 | H31: =INDEX($V$58:$CA$58,MATCH(B31,$V$3:$CA$3,0)) -> 151578.79 | I31: 3900 | J31: 8200 | K31: 9000 | L31: =H31/D31 -> 84.30411 | M31: 150 | N31: Fig | U31: Drywall Material | V31: 5765.79 | W31: 4501.41 | X31: 3724.58 | Y31: 3908.31 | Z31: 5393.62 | AA31: 4177.97 | AB31: 4637.4 | AC31: 4800.14 | AD31: 5153.13 | AE31: 3767.81 | AF31: 5046.53 | AG31: 5787.86 | AH31: 4058.81 | AI31: 4161.86 | AJ31: 3308.57 | AK31: 4923.94 | AL31: 4434.24 | AM31: 4417.93 | AN31: 3826.35 | AO31: 3390.09 | AP31: 2842.2 | AQ31: 4861.95 | AR31: 3531.73 | AS31: 3800.3 | AT31: 4658.49 | AU31: 4184.09 | AV31: 4766.57 | AW31: 4546.58 | AX31: 4370.54 | AY31: 4086.44 | AZ31: 3855.28 | BA31: 4605.61 | BB31: 3741.76 | BC31: 4724.69 | BD31: 4501.41 | BE31: 3181.59 | BF31: 4964.07 | BG31: 4151.93 | BH31: 2488.79
A32: Magnolia - SC | B32: Poplar | C32: TH | D32: 1483 | E32: 3 | F32: 2.5 | G32: 2R | H32: =INDEX($V$58:$CA$58,MATCH(B32,$V$3:$CA$3,0)) -> 129532.09 | I32: 3900 | J32: 8200 | K32: 3600 | L32: =H32/D32 -> 87.344633 | M32: 150 | N32: Poplar | U32: Drywall Labor | V32: 5700.78 | W32: 4709.34 | X32: 4195.26 | Y32: 4305.42 | Z32: 5777.28 | AA32: 4244.22 | AB32: 4684.86 | AC32: 4779.72 | AD32: 4580.82 | AE32: 3607.74 | AF32: 5437.62 | AG32: 6156.72 | AH32: 4559.4 | AI32: 4075.92 | AJ32: 3225.24 | AK32: 5088.78 | AL32: 4681.8 | AM32: 4189.14 | AN32: 4360.5 | AO32: 3167.1 | AP32: 3408.84 | AQ32: 5474.34 | AR32: 3962.7 | AS32: 4161.6 | AT32: 5027.58 | AU32: 4397.22 | AV32: 5254.02 | AW32: 4905.18 | AX32: 4617.54 | AY32: 4235.04 | AZ32: 4329.9 | BA32: 4850.1 | BB32: 4155.48 | BC32: 4571.64 | BD32: 4709.34 | BE32: 3783.96 | BF32: 5553.12 | BG32: 4738.92 | BH32: 3074.64
A33: Palm II | B33: Fraser | C33: TH | D33: 1689 | E33: 3 | F33: 2.5 | G33: 2R | H33: =INDEX($V$58:$CA$58,MATCH(B33,$V$3:$CA$3,0)) -> 137916.71 | I33: 3300 | J33: 2700 | K33: TBD | L33: =H33/D33 -> 81.655838 | M33: 150 | U33: Exterior Paint Labor & Material | V33: 25 | W33: 50 | X33: 50 | Y33: 400 | Z33: 275 | AA33: 100 | AB33: 75 | AC33: 100 | AD33: 75 | AE33: 50 | AF33: 25 | AG33: 250 | AH33: 200 | AI33: 75 | AJ33: 100 | AK33: 75 | AL33: 125 | AM33: 100 | AN33: 25 | AO33: 100 | AP33: 0 | AQ33: 50 | AR33: 75 | AS33: 0 | AT33: 275 | AU33: 330 | AV33: 0 | AW33: 0 | AX33: 350 | AY33: 100 | AZ33: 350 | BA33: 0 | BB33: 50 | BC33: 100 | BD33: 50 | BE33: 45 | BF33: 360 | BG33: 0 | BH33: 0
A34: Palmetto | B34: Sycamore | C34: TH | D34: 1993 | E34: 3 | F34: 2.5 | G34: 2R | H34: =INDEX($V$58:$CA$58,MATCH(B34,$V$3:$CA$3,0)) -> 144637.38 | I34: 5500 | J34: 8600 | K34: 4400 | L34: =H34/D34 -> 72.572694 | M34: 150 | N34: Sycamore | U34: Interior Paint | V34: 4114.24 | W34: 3289.92 | X34: 2923.28 | Y34: 2576 | Z34: 4073.76 | AA34: 2835.44 | AB34: 3151.92 | AC34: 3680 | AD34: 3150.08 | AE34: 2545.2 | AF34: 4219.12 | AG34: 5098.64 | AH34: 3601.8 | AI34: 2842.8 | AJ34: 2152.8 | AK34: 3689.2 | AL34: 3416.88 | AM34: 2760 | AN34: 3107.76 | AO34: 2399.36 | AP34: 2620.16 | AQ34: 4025.92 | AR34: 2760 | AS34: 3128 | AT34: 3304.64 | AU34: 2848.32 | AV34: 3481.28 | AW34: 3216.32 | AX34: 3387.44 | AY34: 3070.96 | AZ34: 3107.76 | BA34: 3667.12 | BB34: 2728.72 | BC34: 3236.4 | BD34: 3289.92 | BE34: 2786 | BF34: 4849.26 | BG34: 3311 | BH34: 2492
A35: Palmetto II | B35: Alder | C35: TH | D35: 1700 | E35: 3 | F35: 2.5 | G35: 1R | H35: =INDEX($V$58:$CA$58,MATCH(B35,$V$3:$CA$3,0)) -> 127244.34 | I35: 4600 | J35: 8800 | K35: 5900 | L35: =H35/D35 -> 74.849612 | M35: 150 | N35: Alder | U35: Interior Trim Material | V35: 0 | W35: 0 | X35: 0 | Y35: 0 | Z35: 0 | AA35: 0 | AB35: 0 | AC35: 0 | AD35: 0 | AE35: 0 | AF35: 0 | AG35: 0 | AH35: 0 | AI35: 0 | AJ35: 0 | AK35: 0 | AL35: 0 | AM35: 0 | AN35: 0 | AO35: 0 | AP35: 0 | AQ35: 0 | AR35: 0 | AS35: 0 | AT35: 0 | AU35: 0 | AV35: 0 | AW35: 0 | AX35: 0 | AY35: 0 | AZ35: 0 | BA35: 0 | BB35: 0 | BC35: 0 | BD35: 0 | BE35: 0 | BF35: 0 | BG35: 0 | BH35: 0
A36: Palmetto II - SC | B36: Boxelder | C36: TH | D36: 1796 | E36: 4 | F36: 2.5 | G36: 2 | H36: =INDEX($V$58:$CA$58,MATCH(B36,$V$3:$CA$3,0)) -> 131296.42 | I36: 6300 | J36: 9200 | K36: 4800 | L36: =H36/D36 -> 73.104911 | M36: 150 | U36: Interior Trim Turnkey | V36: 6581.37 | W36: 4352 | X36: 4068 | Y36: 4455 | Z36: 5005 | AA36: 3740 | AB36: 4384 | AC36: 4645 | AD36: 4243 | AE36: 3969 | AF36: 6600 | AG36: 5193 | AH36: 4604 | AI36: 3593 | AJ36: 2903 | AK36: 4637 | AL36: 4255 | AM36: 4176 | AN36: 4431 | AO36: 3775 | AP36: 4008 | AQ36: 4827 | AR36: 4718 | AS36: 4400 | AT36: 4333 | AU36: 5176 | AV36: 5492 | AW36: 4451 | AX36: 6562.49 | AY36: 4934.83 | AZ36: 3363.72 | BA36: 4939.73 | BB36: 4545.92 | BC36: 4250 | BD36: 4352 | BE36: 4068 | BF36: 5193 | BG36: 5492 | BH36: 4008
A37: Pinyon | B37: Bur Oak | C37: TH | D37: 1548 | E37: 3 | F37: 2.5 | G37: 1 | H37: =INDEX($V$58:$CA$58,MATCH(B37,$V$3:$CA$3,0)) -> 123507.16 | I37: 5700 | J37: 8500 | K37: 5200 | L37: =H37/D37 -> 79.784987 | M37: 150 | U37: Door Hardware | V37: 546.91 | W37: 454.35 | X37: 451.21 | Y37: 570.95 | Z37: 528.23 | AA37: 449.17 | AB37: 506.7 | AC37: 567.04 | AD37: 506.15 | AE37: 439.7 | AF37: 489.04 | AG37: 508.4 | AH37: 512.99 | AI37: 437.71 | AJ37: 394.23 | AK37: 507.85 | AL37: 510.06 | AM37: 456.94 | AN37: 508.53 | AO37: 471.89 | AP37: 619.39 | AQ37: 567.04 | AR37: 456.94 | AS37: 508.53 | AT37: 545.43 | AU37: 473.84 | AV37: 567.59 | AW37: 527.17 | AX37: 512.52 | AY37: 454.35 | AZ37: 409.3 | BA37: 449.17 | BB37: 449.17 | BC37: 471.12 | BD37: 454.35 | BE37: 451.21 | BF37: 508.4 | BG37: 567.59 | BH37: 432.4
A38: Poplar | B38: Conifer | C38: TH | D38: 1892 | E38: 0 | F38: 0 | G38: 2 | H38: =INDEX($V$58:$CA$58,MATCH(B38,$V$3:$CA$3,0)) -> 159080.34 | I38: 4700 | J38: 5900 | K38: 7700 | L38: =H38/D38 -> 84.080518 | M38: 150 | U38: Shelving | V38: 703.6 | W38: 248.4 | X38: 464.2 | Y38: 396.65 | Z38: 583.6 | AA38: 535.6 | AB38: 511.6 | AC38: 607.3 | AD38: 559 | AE38: 607.6 | AF38: 301.2 | AG38: 158 | AH38: 747.95 | AI38: 503.6 | AJ38: 440.8 | AK38: 726.7 | AL38: 560.2 | AM38: 255.6 | AN38: 295.2 | AO38: 416.2 | AP38: 464.5 | AQ38: 320.4 | AR38: 252 | AS38: 259.2 | AT38: 270 | AU38: 241.2 | AV38: 198 | AW38: 255.6 | AX38: 259.2 | AY38: 267 | AZ38: 147.6 | BA38: 259.2 | BB38: 511 | BC38: 543.35 | BD38: 248.4 | BE38: 259.2 | BF38: 432 | BG38: 198 | BH38: 316.8
A39: Spindle | B39: Pinyon | C39: TH | D39: 1748 | E39: 3 | F39: 3.5 | G39: 2 | H39: =INDEX($V$58:$CA$58,MATCH(B39,$V$3:$CA$3,0)) -> 149923.33 | I39: 6600 | J39: 11200 | K39: 6200 | L39: =H39/D39 -> 85.768495 | M39: 150 | U39: Interior Trim Labor | V39: 0 | W39: 0 | X39: 0 | Y39: 0 | Z39: 0 | AA39: 0 | AB39: 0 | AC39: 0 | AD39: 0 | AE39: 0 | AF39: 0 | AG39: 0 | AH39: 0 | AI39: 0 | AJ39: 0 | AK39: 0 | AL39: 0 | AM39: 0 | AN39: 0 | AO39: 0 | AP39: 0 | AQ39: 0 | AR39: 0 | AS39: 0 | AT39: 0 | AU39: 0 | AV39: 0 | AW39: 0 | AX39: 0 | AY39: 0 | AZ39: 0 | BA39: 0 | BB39: 0 | BC39: 0 | BD39: 0 | BE39: 0 | BF39: 0 | BG39: 0 | BH39: 0
A40: Spruce | B40: Atlas II - SC | C40: SFH | D40: 1554 | E40: 3 | F40: 2.5 | G40: 0 | H40: =INDEX($V$58:$CA$58,MATCH(B40,$V$3:$CA$3,0)) -> 106047.85 | I40: 4900 | J40: 9200 | K40: TBD | L40: =H40/D40 -> 68.24186 | M40: 150 | U40: Mirrors | V40: 689.96 | W40: 689.96 | X40: 689.96 | Y40: 689.96 | Z40: 689.96 | AA40: 689.96 | AB40: 689.96 | AC40: 689.96 | AD40: 689.96 | AE40: 689.96 | AF40: 909.94 | AG40: 799.95 | AH40: 689.06 | AI40: 579.97 | AJ40: 579.97 | AK40: 689.96 | AL40: 689.96 | AM40: 689.96 | AN40: 799.95 | AO40: 689.96 | AP40: 689.96 | AQ40: 799.95 | AR40: 689.96 | AS40: 799.95 | AT40: 799.95 | AU40: 686 | AV40: 799.95 | AW40: 799.95 | AX40: 689.96 | AY40: 689.96 | AZ40: 689.96 | BA40: 799.95 | BB40: 689.96 | BC40: 689.96 | BD40: 689.96 | BE40: 689.96 | BF40: 799.95 | BG40: 799.95 | BH40: 689.96
A41: Sycamore | B41: Magnolia - SC | C41: SFH | D41: 2771 | E41: 4 | F41: 3 | G41: 2 | H41: =INDEX($V$58:$CA$58,MATCH(B41,$V$3:$CA$3,0)) -> 162911.8 | I41: 5000 | J41: 11700 | K41: TBD | L41: =H41/D41 -> 58.7917 | M41: 150 | U41: Bath Accessories | V41: 422.8 | W41: 161.41 | X41: 133.49 | Y41: 471.07 | Z41: 484.58 | AA41: 161.41 | AB41: 133.49 | AC41: 452.2 | AD41: 161.41 | AE41: 189.33 | AF41: 229.91 | AG41: 202.41 | AH41: 405.06 | AI41: 133.91 | AJ41: 133.91 | AK41: 428.63 | AL41: 161.41 | AM41: 161.41 | AN41: 174.49 | AO41: 405.06 | AP41: 418.57 | AQ41: 174.49 | AR41: 161.41 | AS41: 174.49 | AT41: 161.41 | AU41: 161.41 | AV41: 198.9 | AW41: 473.39 | AX41: 203.75 | AY41: 161.41 | AZ41: 161.41 | BA41: 174.49 | BB41: 428.63 | BC41: 203.75 | BD41: 161.41 | BE41: 133.49 | BF41: 202.41 | BG41: 198.9 | BH41: 161.41
A42: Tulip | B42: Conifer - SC | C42: TH | D42: 1892 | E42: 4 | F42: 3.5 | G42: 2 | H42: =INDEX($V$58:$CA$58,MATCH(B42,$V$3:$CA$3,0)) -> 149921.85 | I42: 5900 | J42: 11100 | K42: 6500 | L42: =H42/D42 -> 79.239878 | M42: 150 | U42: Shower Door | V42: 1320 | W42: 690 | X42: 690 | Y42: 0 | Z42: 1260 | AA42: 630 | AB42: 630 | AC42: 630 | AD42: 630 | AE42: 630 | AF42: 630 | AG42: 630 | AH42: 690 | AI42: 630 | AJ42: 695.9 | AK42: 690 | AL42: 690 | AM42: 630 | AN42: 690 | AO42: 787.07 | AP42: 690 | AQ42: 630 | AR42: 690 | AS42: 690 | AT42: 690 | AU42: 690 | AV42: 1380 | AW42: 1232.97 | AX42: 690 | AY42: 690 | AZ42: 690 | BA42: 690 | BB42: 630 | BC42: 1380 | BD42: 690 | BE42: 690 | BF42: 630 | BG42: 1380 | BH42: 690
A43: White Oak | B43: Palmetto II - SC | C43: TH | D43: 1424 | E43: 3 | F43: 2.5 | G43: 0 | H43: =INDEX($V$58:$CA$58,MATCH(B43,$V$3:$CA$3,0)) -> 99333.17 | I43: 4100 | J43: 7700 | K43: 4600 | L43: =H43/D43 -> 69.75644 | M43: 150 | U43: Countertops | V43: 3773 | W43: 3690 | X43: 4110 | Y43: 3243 | Z43: 4239 | AA43: 2680 | AB43: 3588 | AC43: 3530 | AD43: 3354 | AE43: 2680 | AF43: 4632 | AG43: 3960 | AH43: 4169 | AI43: 3310 | AJ43: 2604 | AK43: 3808 | AL43: 3050 | AM43: 2950 | AN43: 3201 | AO43: 3536 | AP43: 2948 | AQ43: 3698 | AR43: 2966 | AS43: 3235 | AT43: 3446 | AU43: 2882 | AV43: 4453 | AW43: 3423 | AX43: 3147 | AY43: 2966 | AZ43: 3134 | BA43: 3607 | BB43: 3068 | BC43: 3588 | BD43: 3690 | BE43: 4110 | BF43: 3960 | BG43: 4453 | BH43: 2948
A44: Willow | B44: CUSTOM | L44: =H44/D44 -> #DIV/0! | M44: 150 | U44: Cabinet Labor & Material | V44: 5840.6 | W44: 5613.79 | X44: 5788.54 | Y44: 5080.17 | Z44: 5704.65 | AA44: 4976.59 | AB44: 5682.59 | AC44: 4720 | AD44: 5174.96 | AE44: 4315 | AF44: 5980 | AG44: 6030.27 | AH44: 5414 | AI44: 4885 | AJ44: 4175 | AK44: 5380 | AL44: 5425.19 | AM44: 4889.41 | AN44: 5200 | AO44: 3500.12 | AP44: 3628 | AQ44: 4386 | AR44: 4971.04 | AS44: 3833 | AT44: 4362 | AU44: 4563 | AV44: 4718 | AW44: 4188 | AX44: 3925 | AY44: 4633.41 | AZ44: 4644.09 | BA44: 5257.95 | BB44: 4008.42 | BC44: 5632.32 | BD44: 9113.79 | BE44: 5788.54 | BF44: 6030.27 | BG44: 4718 | BH44: 3628
U45: Tile Labor & Material | V45: 0 | W45: 0 | X45: 0 | Y45: 0 | Z45: 0 | AA45: 0 | AB45: 0 | AC45: 0 | AD45: 0 | AE45: 0 | AF45: 0 | AG45: 0 | AH45: 0 | AI45: 0 | AJ45: 0 | AK45: 0 | AL45: 0 | AM45: 0 | AN45: 0 | AO45: 0 | AP45: 0 | AQ45: 0 | AR45: 0 | AS45: 0 | AT45: 0 | AU45: 0 | AV45: 0 | AW45: 0 | AX45: 0 | AY45: 0 | AZ45: 0 | BA45: 0 | BB45: 0 | BC45: 0 | BD45: 0 | BE45: 0 | BF45: 0 | BG45: 0 | BH45: 0
U46: Light Fixtures | V46: 652.11 | W46: 731.35 | X46: 540.12 | Y46: 589.64 | Z46: 626.34 | AA46: 656.54 | AB46: 624.04 | AC46: 614.82 | AD46: 689.11 | AE46: 482.16 | AF46: 591.11 | AG46: 754.88 | AH46: 520.82 | AI46: 446.08 | AJ46: 411.73 | AK46: 652.31 | AL46: 633.08 | AM46: 574.99 | AN46: 726.81 | AO46: 494.92 | AP46: 502.19 | AQ46: 759.7 | AR46: 614.7 | AS46: 703.59 | AT46: 581.79 | AU46: 609.85 | AV46: 642.98 | AW46: 671.01 | AX46: 626.5 | AY46: 616.91 | AZ46: 672.34 | BA46: 774.42 | BB46: 617.68 | BC46: 635.85 | BD46: 731.35 | BE46: 538.01 | BF46: 753.39 | BG46: 665.64 | BH46: 502.34
U47: Appliances | V47: 1586.06 | W47: 1586.06 | X47: 1586.06 | Y47: 1586.06 | Z47: 1586.06 | AA47: 1586.06 | AB47: 1586.06 | AC47: 1586.06 | AD47: 1586.06 | AE47: 1586.06 | AF47: 1586.06 | AG47: 1586.06 | AH47: 1586.06 | AI47: 1586.06 | AJ47: 1586.06 | AK47: 1586.06 | AL47: 1586.06 | AM47: 1586.06 | AN47: 1586.06 | AO47: 1586.06 | AP47: 1586.06 | AQ47: 1586.06 | AR47: 1586.06 | AS47: 1586.06 | AT47: 1586.06 | AU47: 1586.06 | AV47: 1586.06 | AW47: 1586.06 | AX47: 1586.06 | AY47: 1586.06 | AZ47: 1586.06 | BA47: 1586.06 | BB47: 1586.06 | BC47: 1586.06 | BD47: 1586.06 | BE47: 1616.06 | BF47: 1616.06 | BG47: 1616.06 | BH47: 1616.06
N48: Atlas II - SC | U48: Carpet Labor & Material | V48: 1658.63 | W48: 1850.38 | X48: 1398 | Y48: 1535.62 | Z48: 2056.88 | AA48: 1707.75 | AB48: 1899.5 | AC48: 2194.5 | AD48: 1899.5 | AE48: 1412.75 | AF48: 1619.25 | AG48: 2681.25 | AH48: 1786.37 | AI48: 1411.13 | AJ48: 953.88 | AK48: 2110.87 | AL48: 1929 | AM48: 1579.87 | AN48: 1643.88 | AO48: 1422.63 | AP48: 1402.87 | AQ48: 2283 | AR48: 1486.5 | AS48: 1678.25 | AT48: 1706 | AU48: 1737.25 | AV48: 1683 | AW48: 1432.37 | AX48: 1750 | AY48: 1742.12 | AZ48: 1855.25 | BA48: 2145.38 | BB48: 1663.5 | BC48: 1637.25 | BD48: 1850.38 | BE48: 1616 | BF48: 2681.25 | BG48: 1683.12 | BH48: 1402.87
N49: Magnolia - SC | U49: Hardwood Labor & Material | V49: 0 | W49: 0 | X49: 0 | Y49: 0 | Z49: 0 | AA49: 0 | AB49: 0 | AC49: 0 | AD49: 0 | AE49: 0 | AF49: 0 | AG49: 0 | AH49: 0 | AI49: 0 | AJ49: 0 | AK49: 0 | AL49: 0 | AM49: 0 | AN49: 0 | AO49: 0 | AP49: 0 | AQ49: 0 | AR49: 0 | AS49: 0 | AT49: 0 | AU49: 0 | AV49: 0 | AW49: 0 | AX49: 0 | AY49: 0 | AZ49: 0 | BA49: 0 | BB49: 0 | BC49: 0 | BD49: 0 | BE49: 0 | BF49: 0 | BG49: 0 | BH49: 0
N50: Conifer - SC | U50: LVP Labor & Material | V50: 4991.12 | W50: 3225.03 | X50: 3225.03 | Y50: 3660.74 | Z50: 3589.62 | AA50: 2380.38 | AB50: 2610.74 | AC50: 3281.46 | AD50: 2610.74 | AE50: 2583.6 | AF50: 4112.54 | AG50: 5040.76 | AH50: 3972.54 | AI50: 3303.25 | AJ50: 2430.02 | AK50: 3301.82 | AL50: 3274.67 | AM50: 2687.53 | AN50: 2917.89 | AO50: 2443.6 | AP50: 2610.74 | AQ50: 3916.11 | AR50: 2457.17 | AS50: 2917.89 | AT50: 2841.1 | AU50: 2533.95 | AV50: 4805.75 | AW50: 4268.25 | AX50: 2764.31 | AY50: 3584.6 | AZ50: 2197.52 | BA50: 2917.89 | BB50: 2150.02 | BC50: 4722.18 | BD50: 3225.03 | BE50: 3237.29 | BF50: 5294.87 | BG50: 4909.58 | BH50: 2684.28
N51: Palmetto II - SC | U51: Interior Clean | V51: 602.48 | W51: 521.84 | X51: 479.72 | Y51: 452 | Z51: 598.52 | AA51: 477.38 | AB51: 328.34 | AC51: 560 | AD51: 508.16 | AE51: 448.94 | AF51: 612.74 | AG51: 698.78 | AH51: 560.18 | AI51: 478.1 | AJ51: 410.6 | AK51: 560.9 | AL51: 534.26 | AM51: 470 | AN51: 504.02 | AO51: 434.72 | AP51: 456.32 | AQ51: 593.88 | AR51: 470 | AS51: 504.02 | AT51: 523.28 | AU51: 478.64 | AV51: 540.56 | AW51: 514.64 | AX51: 531.38 | AY51: 500.42 | AZ51: 504.02 | BA51: 558.74 | BB51: 466.94 | BC51: 523.64 | BD51: 521.84 | BE51: 577.96 | BF51: 870.04 | BG51: 659.08 | BH51: 546.76
U52: Gutters | V52: 882 | W52: 522 | X52: 1034 | Y52: 936 | Z52: 957 | AA52: 1212 | AB52: 858 | AC52: 1396 | AD52: 652 | AE52: 501 | AF52: 659 | AG52: 934 | AH52: 1243 | AI52: 657 | AJ52: 896 | AK52: 866 | AL52: 788 | AM52: 793.5 | AN52: 580 | AO52: 691 | AP52: 366 | AQ52: 976 | AR52: 519.2 | AS52: 1160 | AT52: 622 | AU52: 791 | AV52: 630 | AW52: 543 | AX52: 530 | AY52: 550 | AZ52: 784 | BA52: 848 | BB52: 532.5 | BC52: 438 | BD52: 522 | BE52: 920 | BF52: 700 | BG52: 805 | BH52: 455
U53: QI Inspection | V53: 310 | W53: 310 | X53: 310 | Y53: 310 | Z53: 310 | AA53: 310 | AB53: 0 | AC53: 310 | AD53: 310 | AE53: 310 | AF53: 310 | AG53: 310 | AH53: 310 | AI53: 310 | AJ53: 310 | AK53: 310 | AL53: 310 | AM53: 310 | AN53: 310 | AO53: 310 | AP53: 310 | AQ53: 310 | AR53: 310 | AS53: 310 | AT53: 310 | AU53: 310 | AV53: 310 | AW53: 310 | AX53: 310 | AY53: 310 | AZ53: 310 | BA53: 310 | BB53: 310 | BC53: 310 | BD53: 310 | BE53: 310 | BF53: 310 | BG53: 310 | BH53: 310
U54: Deck | V54: 0 | W54: 0 | X54: 0 | Y54: 0 | Z54: 0 | AA54: 0 | AB54: 0 | AC54: 0 | AD54: 0 | AE54: 0 | AF54: 0 | AG54: 0 | AH54: 0 | AI54: 0 | AJ54: 90 | AK54: 0 | AL54: 0 | AM54: 0 | AN54: 0 | AO54: 0 | AP54: 0 | AQ54: 0 | AR54: 0 | AS54: 0 | AT54: 0 | AU54: 0 | AV54: 0 | AW54: 1234 | AX54: 0 | AY54: 0 | AZ54: 0 | BA54: 0 | BB54: 0 | BC54: 3146 | BD54: 0 | BE54: 0 | BF54: 0 | BG54: 0 | BH54: 0
C55: Origination | D55: Rate | E55: LTC | F55: Lot Advance | G55: LTV | H55: Interest Account | U55: Mailbox | V55: 90 | W55: 90 | X55: 90 | Y55: 90 | Z55: 90 | AA55: 90 | AB55: 90 | AC55: 90 | AD55: 90 | AE55: 90 | AF55: 90 | AG55: 90 | AH55: 90 | AI55: 90 | AJ55: 0 | AK55: 90 | AL55: 90 | AM55: 0 | AN55: 0 | AO55: 0 | AP55: 0 | AQ55: 0 | AR55: 0 | AS55: 0 | AT55: 0 | AU55: 0 | AV55: 5026 | AW55: 0 | AX55: 0 | AY55: 0 | AZ55: 0 | BA55: 0 | BB55: 0 | BC55: 0 | BD55: 90 | BE55: 90 | BF55: 90 | BG55: 5026 | BH55: 0
B56: Gorilla | C56: 0.01 | D56: 0.105 | E56: 1 | F56: 0.7 | G56: 1 | H56: No | U56: Pressure Wash | V56: 235 | W56: 235 | X56: 235 | Y56: 235 | Z56: 235 | AA56: 235 | AB56: 235 | AC56: 235 | AD56: 235 | AE56: 235 | AF56: 235 | AG56: 235 | AH56: 235 | AI56: 235 | AJ56: 235 | AK56: 235 | AL56: 235 | AM56: 235 | AN56: 235 | AO56: 235 | AP56: 235 | AQ56: 310 | AR56: 235 | AS56: 235 | AT56: 310 | AU56: 235 | AV56: 310 | AW56: 310 | AX56: 310 | AY56: 235 | AZ56: 235 | BA56: 310 | BB56: 235 | BC56: 310 | BD56: 235 | BE56: 270 | BF56: 270 | BG56: 270 | BH56: 270
B57: Gorilla-15% | C57: 0 | D57: 0.15 | E57: 1 | F57: 0.7 | G57: 1 | H57: No | U57: Foundation | V57: 17107.5 | W57: 11205 | X57: 8050 | Y57: 6688 | Z57: 12930 | AA57: 9662.5 | AB57: 9940 | AC57: 11065 | AD57: 9970 | AE57: 11702 | AF57: 9137.5 | AG57: 14792.5 | AH57: 10472.5 | AI57: 16863 | AJ57: 12802.5 | AK57: 12045 | AL57: 10577.5 | AM57: 8417.5 | AN57: 8615 | AO57: 6620 | AP57: 6890 | AQ57: 12024.5 | AR57: 8450 | AS57: 8615 | AT57: 9315.5 | AU57: 7692.5 | AV57: 6792.5 | AW57: 6702.5 | AX57: 6312.5 | AY57: 8980 | AZ57: 9680 | BA57: 11022.5 | BB57: 8240 | BC57: 6297.5 | BD57: 11205 | BE57: 5640 | BF57: 12158.75 | BG57: 5893.75 | BH57: 5990
B58: Gorilla-18% | C58: 0 | D58: 0.18 | E58: 1 | F58: 0.7 | G58: 1 | H58: No | U58: Sticks & Bricks Subtotal | V58: 162510.14 | W58: 137618.63 | X58: 115967.93 | Y58: 132231.45 | Z58: 154828.84 | AA58: 123366.66 | AB58: 129651.85 | AC58: 141925.87 | AD58: 130967.62 | AE58: 120703.39 | AF58: 158070.49 | AG58: 174241.94 | AH58: 145757.73 | AI58: 126615.36 | AJ58: 105321.66 | AK58: 141504.81 | AL58: 131392.95 | AM58: 124245.5 | AN58: 130052.04 | AO58: 109770.74 | AP58: 111483.39 | AQ58: 158682.42 | AR58: 123038.45 | AS58: 127244.34 | AT58: 131296.42 | AU58: 123507.16 | AV58: 159080.34 | AW58: 149923.33 | AX58: 141829.36 | AY58: 128788.11 | AZ58: 137916.71 | BA58: 144637.38 | BB58: 129532.09 | BC58: 151578.79 | BD58: 158618.63 | BE58: 106047.85 | BF58: 162911.8 | BG58: 149921.85 | BH58: 99333.17
U59: Survey | V59: 1185 | W59: 1185 | X59: 1185 | Y59: 1185 | Z59: 1185 | AA59: 1185 | AB59: 1185 | AC59: 1185 | AD59: 1185 | AE59: 1185 | AF59: 1185 | AG59: 1185 | AH59: 1185 | AI59: 1185 | AJ59: 1185 | AK59: 1185 | AL59: 1185 | AM59: 1185 | AN59: 1185 | AO59: 1185 | AP59: 1185 | AQ59: 1185 | AR59: 1185 | AS59: 1185 | AT59: 1185 | AU59: 1185 | AV59: 1185 | AW59: 1185 | AX59: 1185 | AY59: 1185 | AZ59: 1185 | BA59: 1185 | BB59: 1185 | BC59: 1185 | BD59: 1185 | BE59: 1100 | BF59: 1100 | BG59: 1100 | BH59: 1100
B60: Builders Capital | C60: 0.0125 | D60: 0.103 | E60: 0.9 | F60: 0.75 | G60: 0.75 | H60: Yes | U60: Stake House | V60: 0 | W60: 0 | X60: 0 | Y60: 0 | Z60: 0 | AA60: 0 | AB60: 0 | AC60: 0 | AD60: 0 | AE60: 0 | AF60: 0 | AG60: 0 | AH60: 0 | AI60: 0 | AJ60: 0 | AK60: 0 | AL60: 0 | AM60: 0 | AN60: 0 | AO60: 0 | AP60: 0 | AQ60: 0 | AR60: 0 | AS60: 0 | AT60: 0 | AU60: 0 | AV60: 0 | AW60: 0 | AX60: 0 | AY60: 0 | AZ60: 0 | BA60: 0 | BB60: 0 | BC60: 0 | BD60: 0 | BE60: 0 | BF60: 0 | BG60: 0 | BH60: 0
B61: Casa Lending | C61: 0.0125 | D61: 0.0975 | E61: 0.9 | F61: 0.7 | G61: 0.7 | H61: Yes | U61: Grading/Lot Clear/Hauling | V61: 1700 | W61: 1700 | X61: 1700 | Y61: 1700 | Z61: 1700 | AA61: 1700 | AB61: 1700 | AC61: 1700 | AD61: 1700 | AE61: 1700 | AF61: 1700 | AG61: 1700 | AH61: 1700 | AI61: 1700 | AJ61: 1700 | AK61: 1700 | AL61: 1700 | AM61: 1700 | AN61: 1700 | AO61: 1700 | AP61: 1700 | AQ61: 1700 | AR61: 1700 | AS61: 1700 | AT61: 1700 | AU61: 1700 | AV61: 1700 | AW61: 1700 | AX61: 1700 | AY61: 1700 | AZ61: 1700 | BA61: 1700 | BB61: 1700 | BC61: 1700 | BD61: 1700 | BE61: 1700 | BF61: 1700 | BG61: 1700 | BH61: 1700
B62: Renovo | C62: 0.01 | D62: 0.1025 | E62: 0.9 | F62: 0.7 | G62: 0.7 | H62: Yes | U62: Silt Fence | V62: 2000 | W62: 2000 | X62: 2000 | Y62: 2000 | Z62: 2000 | AA62: 2000 | AB62: 2000 | AC62: 2000 | AD62: 2000 | AE62: 2000 | AF62: 2000 | AG62: 2000 | AH62: 2000 | AI62: 2000 | AJ62: 2000 | AK62: 2000 | AL62: 2000 | AM62: 2000 | AN62: 2000 | AO62: 2000 | AP62: 2000 | AQ62: 2000 | AR62: 2000 | AS62: 2000 | AT62: 2000 | AU62: 2000 | AV62: 2000 | AW62: 2000 | AX62: 2000 | AY62: 2000 | AZ62: 2000 | BA62: 2000 | BB62: 2000 | BC62: 2000 | BD62: 2000 | BE62: 2000 | BF62: 2000 | BG62: 2000 | BH62: 2000
B63: IfundCities | C63: 0.015 | D63: 0.1125 | E63: 0.9 | F63: 0.7 | G63: 0.7 | H63: Yes | U63: Temp Drive | V63: 500 | W63: 500 | X63: 500 | Y63: 500 | Z63: 500 | AA63: 500 | AB63: 500 | AC63: 500 | AD63: 500 | AE63: 500 | AF63: 500 | AG63: 500 | AH63: 500 | AI63: 500 | AJ63: 500 | AK63: 500 | AL63: 500 | AM63: 500 | AN63: 500 | AO63: 500 | AP63: 500 | AQ63: 500 | AR63: 500 | AS63: 500 | AT63: 500 | AU63: 500 | AV63: 500 | AW63: 500 | AX63: 500 | AY63: 500 | AZ63: 500 | BA63: 500 | BB63: 500 | BC63: 500 | BD63: 500 | BE63: 500 | BF63: 500 | BG63: 500 | BH63: 500
B64: Arixa | C64: 0.015 | D64: 0.1099 | E64: 0.9 | F64: 0.7 | G64: 0.7 | H64: Yes | U64: Landscaping | V64: 2500 | W64: 2500 | X64: 2500 | Y64: 2500 | Z64: 2500 | AA64: 2500 | AB64: 2500 | AC64: 2500 | AD64: 2500 | AE64: 2500 | AF64: 2500 | AG64: 2500 | AH64: 2500 | AI64: 2500 | AJ64: 2500 | AK64: 2500 | AL64: 2500 | AM64: 2500 | AN64: 2500 | AO64: 2500 | AP64: 2500 | AQ64: 2500 | AR64: 2500 | AS64: 2500 | AT64: 2500 | AU64: 2500 | AV64: 2500 | AW64: 2500 | AX64: 2500 | AY64: 2500 | AZ64: 2500 | BA64: 2500 | BB64: 2500 | BC64: 2500 | BD64: 2500 | BE64: 2500 | BF64: 2500 | BG64: 2500 | BH64: 2500
B65: Arixa + Subordinate | C65: 0.015 | D65: 0.1099 | E65: 0.9 | F65: 0.65 | G65: 0.7 | H65: Yes | U65: Flatwork | V65: 2475 | W65: 2475 | X65: 2475 | Y65: 2475 | Z65: 2475 | AA65: 2475 | AB65: 2475 | AC65: 2475 | AD65: 2475 | AE65: 2475 | AF65: 2475 | AG65: 2475 | AH65: 2475 | AI65: 2475 | AJ65: 2475 | AK65: 2475 | AL65: 2475 | AM65: 2475 | AN65: 2475 | AO65: 2475 | AP65: 2475 | AQ65: 2475 | AR65: 2475 | AS65: 2475 | AT65: 2475 | AU65: 2475 | AV65: 2475 | AW65: 2475 | AX65: 2475 | AY65: 2475 | AZ65: 2475 | BA65: 2475 | BB65: 2475 | BC65: 2475 | BD65: 2475 | BE65: 2475 | BF65: 2475 | BG65: 2475 | BH65: 2475
B66: Lima One | C66: 0.02 | D66: 0.1115 | E66: 0.8 | F66: 0.7 | G66: 0.7 | H66: Yes | U66: Site Specific Subtotal | V66: 10360 | W66: 10360 | X66: 10360 | Y66: 10360 | Z66: 10360 | AA66: 10360 | AB66: 10360 | AC66: 10360 | AD66: 10360 | AE66: 10360 | AF66: 10360 | AG66: 10360 | AH66: 10360 | AI66: 10360 | AJ66: 10360 | AK66: 10360 | AL66: 10360 | AM66: 10360 | AN66: 10360 | AO66: 10360 | AP66: 10360 | AQ66: 10360 | AR66: 10360 | AS66: 10360 | AT66: 10360 | AU66: 10360 | AV66: 10360 | AW66: 10360 | AX66: 10360 | AY66: 10360 | AZ66: 10360 | BA66: 10360 | BB66: 10360 | BC66: 10360 | BD66: 10360 | BE66: 10275 | BF66: 10275 | BG66: 10275 | BH66: 10275
B67: Plymouth | C67: 0.02 | D67: 0.12 | E67: 0.9 | F67: 0.7 | G67: 0.7 | H67: Yes | U67: Building Permits | V67: 2050 | W67: 2050 | X67: 2050 | Y67: 2050 | Z67: 2050 | AA67: 2050 | AB67: 2050 | AC67: 2050 | AD67: 2050 | AE67: 2050 | AF67: 2050 | AG67: 2050 | AH67: 2050 | AI67: 2050 | AJ67: 2050 | AK67: 2050 | AL67: 2050 | AM67: 2050 | AN67: 2050 | AO67: 2050 | AP67: 2050 | AQ67: 2050 | AR67: 2050 | AS67: 2050 | AT67: 2050 | AU67: 2050 | AV67: 2050 | AW67: 2050 | AX67: 2050 | AY67: 2050 | AZ67: 2050 | BA67: 2050 | BB67: 2050 | BC67: 2050 | BD67: 2050 | BE67: 2100 | BF67: 2100 | BG67: 2100 | BH67: 2100
B68: Dominion | C68: 0.02 | D68: 0.1075 | E68: 0.95 | F68: 0.7 | G68: 0.7 | H68: Yes | U68: Sewer Septic Permit | V68: 0 | W68: 0 | X68: 0 | Y68: 0 | Z68: 0 | AA68: 0 | AB68: 0 | AC68: 0 | AD68: 0 | AE68: 0 | AF68: 0 | AG68: 0 | AH68: 0 | AI68: 0 | AJ68: 0 | AK68: 0 | AL68: 0 | AM68: 0 | AN68: 0 | AO68: 0 | AP68: 0 | AQ68: 0 | AR68: 0 | AS68: 0 | AT68: 0 | AU68: 0 | AV68: 0 | AW68: 0 | AX68: 0 | AY68: 0 | AZ68: 0 | BA68: 0 | BB68: 0 | BC68: 0 | BD68: 0 | BE68: 0 | BF68: 0 | BG68: 0 | BH68: 0
B69: OZK | C69: 0.01 | D69: 0.095 | E69: 0.75 | F69: 0.7 | G69: 0.75 | H69: Yes | U69: Water Meter | V69: 0 | W69: 0 | X69: 0 | Y69: 0 | Z69: 0 | AA69: 0 | AB69: 0 | AC69: 0 | AD69: 0 | AE69: 0 | AF69: 0 | AG69: 0 | AH69: 0 | AI69: 0 | AJ69: 0 | AK69: 0 | AL69: 0 | AM69: 0 | AN69: 0 | AO69: 0 | AP69: 0 | AQ69: 0 | AR69: 0 | AS69: 0 | AT69: 0 | AU69: 0 | AV69: 0 | AW69: 0 | AX69: 0 | AY69: 0 | AZ69: 0 | BA69: 0 | BB69: 0 | BC69: 0 | BD69: 0 | BE69: 0 | BF69: 0 | BG69: 0 | BH69: 0
B70: Builder First Lot by Lot | C70: 0.025 | D70: 0.09 | E70: 0.9 | F70: 0.7 | G70: 0.75 | H70: Yes | U70: Engineering | V70: 600 | W70: 600 | X70: 600 | Y70: 600 | Z70: 600 | AA70: 600 | AB70: 600 | AC70: 600 | AD70: 600 | AE70: 600 | AF70: 600 | AG70: 600 | AH70: 600 | AI70: 600 | AJ70: 600 | AK70: 600 | AL70: 600 | AM70: 600 | AN70: 600 | AO70: 600 | AP70: 600 | AQ70: 600 | AR70: 600 | AS70: 600 | AT70: 600 | AU70: 600 | AV70: 600 | AW70: 600 | AX70: 600 | AY70: 600 | AZ70: 600 | BA70: 600 | BB70: 600 | BC70: 600 | BD70: 600 | BE70: 600 | BF70: 600 | BG70: 600 | BH70: 600
B71: Brenance | C71: 0.0175 | D71: 0.105 | E71: 0.85 | F71: 0.7 | G71: 0.7 | H71: Yes | U71: Soft Costs Subtotal | V71: 2650 | W71: 2650 | X71: 2650 | Y71: 2650 | Z71: 2650 | AA71: 2650 | AB71: 2650 | AC71: 2650 | AD71: 2650 | AE71: 2650 | AF71: 2650 | AG71: 2650 | AH71: 2650 | AI71: 2650 | AJ71: 2650 | AK71: 2650 | AL71: 2650 | AM71: 2650 | AN71: 2650 | AO71: 2650 | AP71: 2650 | AQ71: 2650 | AR71: 2650 | AS71: 2650 | AT71: 2650 | AU71: 2650 | AV71: 2650 | AW71: 2650 | AX71: 2650 | AY71: 2650 | AZ71: 2650 | BA71: 2650 | BB71: 2650 | BC71: 2650 | BD71: 2650 | BE71: 2700 | BF71: 2700 | BG71: 2700 | BH71: 2700
B72: Builder First SBA | C72: 0.01 | D72: 0.0999 | E72: 1 | F72: 0.7 | G72: 0.77 | H72: Yes
B73: OMB | C73: 0.02 | D73: 0.115 | E73: 0.9 | F73: 0.7 | G73: 0.75 | H73: Yes
B74: Park National
B75: United
B76: TowneBank
B77: Flagstar
B80: Mezz Debt
C81: Origination | D81: Pref | E81: Prom
B82: Red Cedar SLFI | C82: 0 | D82: 0.12 | E82: 0.2
B83: Red Cedar SLFII | C83: 0 | D83: 0.16 | E83: 0
B84: Mukesh | C84: 0 | D84: 0.12 | E84: 0.3
B85: Ron Julian | C85: 0 | D85: 0.18 | E85: 0 | F85: Sadler Lots that he is doing is at 22%
B86: Mohammed | C86: 0 | D86: 0.12 | E86: 0.2
B87: Chen | C87: 0 | D87: 0.2 | E87: 0
B88: Franklyn | D88: 0 | E88: 0.5
B89: Other | D89: 0.2 | E89: 0
B90: RCH | D90: 0 | E90: 0
B99: Miscellaneous Cost
C100: Average
B101: Survey/Enginnering/LDIRL | C101: 5000
B102: Perc Test | C102: 1000
B103: Demolition | C103: 12000
B108: Yes | C108: Survey | D108: 5000
B109: No | C109: Survey | D109: 0
B110: Yes | C110: Slab | D110: 0
B111: No | C111: Crawl | D111: 20000
B113: County | C113: Water Meter Size | D113: Water Tap Fee | E113: Water System Dev. Fee | F113: Total Water Fees | G113: Meter Charge/Unit
B114: None | D114: 0 | E114: 0 | F114: =D114+E114 -> 0 | G114: 0
B115: Other | F115: =D115+E115 -> 0
...

Sheet Construction Bell-Shaped Curve
B4: Construction Bell-Shaped Curve
C6: Monthly Distribution/Allocation (x-axis)
A7: Check (must be 100%) | B7: Construction Schedule in months (y-axis) | C7: 1 | D7: =C7+1 -> 2 | E7: =D7+1 -> 3 | F7: =E7+1 -> 4 | G7: =F7+1 -> 5 | H7: =G7+1 -> 6 | I7: =H7+1 -> 7 | J7: =I7+1 -> 8 | K7: =J7+1 -> 9 | ... AL7: =AK7+1 -> 36
A8: =SUM(C8:AL8) -> 1 | B8: 4 | C8: 0.2 | D8: 0.3 | E8: 0.3 | F8: 0.2
A9: =SUM(C9:AL9) -> 1 | B9: =+B8+1 -> 5 | C9: 0.15 | D9: 0.2 | E9: 0.3 | F9: 0.2 | G9: 0.15
A10: =SUM(C10:AL10) -> 1 | B10: =+B9+1 -> 6 | C10: 0.1 | D10: 0.15 | E10: 0.25 | F10: 0.25 | G10: 0.15 | H10: 0.1
A11: =SUM(C11:AL11) -> 1 | B11: =+B10+1 -> 7 | C11: 0.075 | D11: 0.125 | E11: 0.175 | F11: 0.25 | G11: 0.175 | H11: 0.125 | I11: 0.075
A12: =SUM(C12:AL12) -> 1 | B12: =+B11+1 -> 8 | C12: 0.05 | D12: 0.1 | E12: 0.15 | F12: 0.2 | G12: 0.2 | H12: 0.15 | I12: 0.1 | J12: 0.05
A13: =SUM(C13:AL13) -> 1 | B13: =+B12+1 -> 9 | C13: 0.05 | D13: 0.075 | E13: 0.125 | F13: 0.15 | G13: 0.2 | H13: 0.15 | I13: 0.125 | J13: 0.075 | K13: 0.05
A14: =SUM(C14:AL14) -> 1 | B14: =+B13+1 -> 10 | C14: 0.04 | D14: 0.065 | E14: 0.1 | F14: 0.125 | G14: 0.17 | H14: 0.17 | I14: 0.125 | J14: 0.1 | K14: 0.065 | L14: 0.04
A15: =SUM(C15:AL15) -> 1 | B15: =+B14+1 -> 11 | C15: 0.035 | D15: 0.05 | E15: 0.09 | F15: 0.12 | G15: 0.13 | H15: 0.15 | I15: 0.13 | J15: 0.12 | K15: 0.09 | L15: 0.05 | M15: 0.035
A16: =SUM(C16:AL16) -> 1 | B16: =+B15+1 -> 12 | C16: 0.03 | D16: 0.05 | E16: 0.07 | F16: 0.1 | G16: 0.12 | H16: 0.13 | I16: 0.13 | J16: 0.12 | K16: 0.1 | L16: 0.07 | M16: 0.05 | N16: 0.03
A17: =SUM(C17:AL17) -> 1 | B17: =+B16+1 -> 13 | C17: 0.025 | D17: 0.04 | E17: 0.06 | F17: 0.09 | G17: 0.11 | H17: 0.11 | I17: 0.13 | J17: 0.11 | K17: 0.11 | L17: 0.09 | M17: 0.06 | N17: 0.04 | O17: 0.025
A18: =SUM(C18:AL18) -> 1 | B18: =+B17+1 -> 14 | C18: 0.02 | D18: 0.04 | E18: 0.06 | F18: 0.08 | G18: 0.08 | H18: 0.1 | I18: 0.12 | J18: 0.12 | K18: 0.1 | L18: 0.08 | M18: 0.08 | N18: 0.06 | O18: 0.04 | P18: 0.02
A19: =SUM(C19:AL19) -> 1 | B19: =+B18+1 -> 15 | C19: 0.02 | D19: 0.03 | E19: 0.05 | F19: 0.07 | G19: 0.08 | H19: 0.09 | I19: 0.1 | J19: 0.12 | K19: 0.1 | L19: 0.09 | M19: 0.08 | N19: 0.07 | O19: 0.05 | P19: 0.03 | Q19: 0.02
A20: =SUM(C20:AL20) -> 1 | B20: =+B19+1 -> 16 | C20: 0.02 | D20: 0.03 | E20: 0.05 | F20: 0.06 | G20: 0.07 | H20: 0.08 | I20: 0.09 | J20: 0.1 | K20: 0.1 | L20: 0.09 | M20: 0.08 | N20: 0.07 | O20: 0.06 | P20: 0.05 | Q20: 0.03 | R20: 0.02
A21: =SUM(C21:AL21) -> 1 | B21: =+B20+1 -> 17 | C21: 0.02 | D21: 0.03 | E21: 0.04 | F21: 0.05 | G21: 0.06 | H21: 0.07 | I21: 0.09 | J21: 0.09 | K21: 0.1 | L21: 0.09 | M21: 0.09 | N21: 0.07 | O21: 0.06 | P21: 0.05 | Q21: 0.04 | R21: 0.03 | S21: 0.02
A22: =SUM(C22:AL22) -> 1 | B22: =+B21+1 -> 18 | C22: 0.015 | D22: 0.025 | E22: 0.025 | F22: 0.025 | G22: 0.03 | H22: 0.04 | I22: 0.05 | J22: 0.08 | K22: 0.1 | L22: 0.1 | M22: 0.09 | N22: 0.09 | O22: 0.09 | P22: 0.08 | Q22: 0.07 | R22: 0.05 | S22: 0.02 | T22: 0.02
A23: =SUM(C23:AL23) -> 1 | B23: =+B22+1 -> 19 | C23: 0.015 | D23: 0.025 | E23: 0.025 | F23: 0.025 | G23: 0.025 | H23: 0.03 | I23: 0.05 | J23: 0.065 | K23: 0.08 | L23: 0.08 | M23: 0.08 | N23: 0.08 | O23: 0.08 | P23: 0.08 | Q23: 0.08 | R23: 0.08 | S23: 0.06 | T23: 0.03 | U23: 0.01
A24: =SUM(C24:AL24) -> 1 | B24: =+B23+1 -> 20 | C24: 0.015 | D24: 0.015 | E24: 0.025 | F24: 0.025 | G24: 0.03 | H24: 0.03 | I24: 0.04 | J24: 0.05 | K24: 0.07 | L24: 0.07 | M24: 0.08 | N24: 0.08 | O24: 0.08 | P24: 0.08 | Q24: 0.08 | R24: 0.08 | S24: 0.07 | T24: 0.05 | U24: 0.02 | V24: 0.01
A25: =SUM(C25:AL25) -> 1 | B25: =+B24+1 -> 21 | C25: 0.01 | D25: 0.01 | E25: 0.02 | F25: 0.02 | G25: 0.02 | H25: 0.03 | I25: 0.04 | J25: 0.05 | K25: 0.07 | L25: 0.07 | M25: 0.07 | N25: 0.08 | O25: 0.08 | P25: 0.08 | Q25: 0.08 | R25: 0.08 | S25: 0.08 | T25: 0.05 | U25: 0.03 | V25: 0.02 | W25: 0.01
A26: =SUM(C26:AL26) -> 1 | B26: =+B25+1 -> 22 | C26: 0.01 | D26: 0.01 | E26: 0.01 | F26: 0.02 | G26: 0.02 | H26: 0.02 | I26: 0.03 | J26: 0.04 | K26: 0.05 | L26: 0.07 | M26: 0.07 | N26: 0.08 | O26: 0.08 | P26: 0.08 | Q26: 0.08 | R26: 0.08 | S26: 0.08 | T26: 0.08 | U26: 0.05 | V26: 0.02 | W26: 0.01 | X26: 0.01
A27: =SUM(C27:AL27) -> 1 | B27: =+B26+1 -> 23 | C27: 0.01 | D27: 0.01 | E27: 0.01 | F27: 0.01 | G27: 0.02 | H27: 0.02 | I27: 0.02 | J27: 0.03 | K27: 0.04 | L27: 0.06 | M27: 0.07 | N27: 0.07 | O27: 0.08 | P27: 0.08 | Q27: 0.08 | R27: 0.08 | S27: 0.08 | T27: 0.08 | U27: 0.06 | V27: 0.03 | W27: 0.03 | X27: 0.02 | Y27: 0.01
A28: =SUM(C28:AL28) -> 1 | B28: =+B27+1 -> 24 | C28: 0.01 | D28: 0.01 | E28: 0.01 | F28: 0.01 | G28: 0.01 | H28: 0.02 | I28: 0.02 | J28: 0.02 | K28: 0.03 | L28: 0.05 | M28: 0.06 | N28: 0.07 | O28: 0.07 | P28: 0.08 | Q28: 0.08 | R28: 0.08 | S28: 0.08 | T28: 0.08 | U28: 0.08 | V28: 0.05 | W28: 0.03 | X28: 0.02 | Y28: 0.02 | Z28: 0.01
A29: =SUM(C29:AL29) -> 1 | B29: =+B28+1 -> 25 | C29: 0.0032051282 | D29: 0.0096153846 | E29: 0.016025641 | F29: 0.022435897 | G29: 0.028846154 | H29: 0.03525641 | I29: 0.041666667 | J29: 0.048076923 | K29: 0.054487179 | L29: 0.060897436 | M29: 0.067307692 | N29: 0.073717949 | O29: 0.076923077 | P29: 0.073717949 | Q29: 0.067307692 | R29: 0.060897436 | S29: 0.054487179 | T29: 0.048076923 | U29: 0.041666667 | V29: 0.03525641 | W29: 0.028846154 | X29: 0.022435897 | Y29: 0.016025641 | Z29: 0.0096153846 | AA29: 0.0032051282
A30: =SUM(C30:AL30) -> 1 | B30: =+B29+1 -> 26 | C30: 0.0054945055 | D30: 0.010989011 | E30: 0.016483516 | F30: 0.021978022 | G30: 0.027472527 | H30: 0.032967033 | I30: 0.038461538 | J30: 0.043956044 | K30: 0.049450549 | L30: 0.054945055 | M30: 0.06043956 | N30: 0.065934066 | O30: 0.071428571 | P30: 0.071428571 | Q30: 0.065934066 | R30: 0.06043956 | S30: 0.054945055 | T30: 0.049450549 | U30: 0.043956044 | V30: 0.038461538 | W30: 0.032967033 | X30: 0.027472527 | Y30: 0.021978022 | Z30: 0.016483516 | AA30: 0.010989011 | AB30: 0.0054945055
A31: =SUM(C31:AL31) -> 1 | B31: =+B30+1 -> 27 | C31: 0.0027472527 | D31: 0.0082417582 | E31: 0.013736264 | F31: 0.019230769 | G31: 0.024725275 | H31: 0.03021978 | I31: 0.035714286 | J31: 0.041208791 | K31: 0.046703297 | L31: 0.052197802 | M31: 0.057692308 | N31: 0.063186813 | O31: 0.068681319 | P31: 0.071428571 | Q31: 0.068681319 | R31: 0.063186813 | S31: 0.057692308 | T31: 0.052197802 | U31: 0.046703297 | V31: 0.041208791 | W31: 0.035714286 | X31: 0.03021978 | Y31: 0.024725275 | Z31: 0.019230769 | AA31: 0.013736264 | AB31: 0.0082417582 | AC31: 0.0027472527
A32: =SUM(C32:AL32) -> 1 | B32: =+B31+1 -> 28 | C32: 0.0047619048 | D32: 0.0095238095 | E32: 0.014285714 | F32: 0.019047619 | G32: 0.023809524 | H32: 0.028571429 | I32: 0.033333333 | J32: 0.038095238 | K32: 0.042857143 | L32: 0.047619048 | M32: 0.052380952 | N32: 0.057142857 | O32: 0.061904762 | P32: 0.066666667 | Q32: 0.066666667 | R32: 0.061904762 | S32: 0.057142857 | T32: 0.052380952 | U32: 0.047619048 | V32: 0.042857143 | W32: 0.038095238 | X32: 0.033333333 | Y32: 0.028571429 | Z32: 0.023809524 | AA32: 0.019047619 | AB32: 0.014285714 | AC32: 0.0095238095 | AD32: 0.0047619048
A33: =SUM(C33:AL33) -> 1 | B33: =+B32+1 -> 29 | C33: 0.0023809524 | D33: 0.0071428571 | E33: 0.011904762 | F33: 0.016666667 | G33: 0.021428571 | H33: 0.026190476 | I33: 0.030952381 | J33: 0.035714286 | K33: 0.04047619 | L33: 0.045238095 | M33: 0.05 | N33: 0.054761905 | O33: 0.05952381 | P33: 0.064285714 | Q33: 0.066666667 | R33: 0.064285714 | S33: 0.05952381 | T33: 0.054761905 | U33: 0.05 | V33: 0.045238095 | W33: 0.04047619 | X33: 0.035714286 | Y33: 0.030952381 | Z33: 0.026190476 | AA33: 0.021428571 | AB33: 0.016666667 | AC33: 0.011904762 | AD33: 0.0071428571 | AE33: 0.0023809524
A34: =SUM(C34:AL34) -> 1 | B34: =+B33+1 -> 30 | C34: 0.0041666667 | D34: 0.0083333333 | E34: 0.0125 | F34: 0.016666667 | G34: 0.020833333 | H34: 0.025 | I34: 0.029166667 | J34: 0.033333333 | K34: 0.0375 | L34: 0.041666667 | M34: 0.045833333 | N34: 0.05 | O34: 0.054166667 | P34: 0.058333333 | Q34: 0.0625 | R34: 0.0625 | S34: 0.058333333 | T34: 0.054166667 | U34: 0.05 | V34: 0.045833333 | W34: 0.041666667 | X34: 0.0375 | Y34: 0.033333333 | Z34: 0.029166667 | AA34: 0.025 | AB34: 0.020833333 | AC34: 0.016666667 | AD34: 0.0125 | AE34: 0.0083333333 | AF34: 0.0041666667
A35: =SUM(C35:AL35) -> 1 | B35: =+B34+1 -> 31 | C35: 0.0020833333 | D35: 0.00625 | E35: 0.010416667 | F35: 0.014583333 | G35: 0.01875 | H35: 0.022916667 | I35: 0.027083333 | J35: 0.03125 | K35: 0.035416667 | L35: 0.039583333 | M35: 0.04375 | N35: 0.047916667 | O35: 0.052083333 | P35: 0.05625 | Q35: 0.060416667 | R35: 0.0625 | S35: 0.060416667 | T35: 0.05625 | U35: 0.052083333 | V35: 0.047916667 | W35: 0.04375 | X35: 0.039583333 | Y35: 0.035416667 | Z35: 0.03125 | AA35: 0.027083333 | AB35: 0.022916667 | AC35: 0.01875 | AD35: 0.014583333 | AE35: 0.010416667 | AF35: 0.00625 | AG35: 0.0020833333
A36: =SUM(C36:AL36) -> 1 | B36: =+B35+1 -> 32 | C36: 0.0036764706 | D36: 0.0073529412 | E36: 0.011029412 | F36: 0.014705882 | G36: 0.018382353 | H36: 0.022058824 | I36: 0.025735294 | J36: 0.029411765 | K36: 0.033088235 | L36: 0.036764706 | M36: 0.040441176 | N36: 0.044117647 | O36: 0.047794118 | P36: 0.051470588 | Q36: 0.055147059 | R36: 0.058823529 | S36: 0.058823529 | T36: 0.055147059 | U36: 0.051470588 | V36: 0.047794118 | W36: 0.044117647 | X36: 0.040441176 | Y36: 0.036764706 | Z36: 0.033088235 | AA36: 0.029411765 | AB36: 0.025735294 | AC36: 0.022058824 | AD36: 0.018382353 | AE36: 0.014705882 | AF36: 0.011029412 | AG36: 0.0073529412 | AH36: 0.0036764706
A37: =SUM(C37:AL37) -> 1 | B37: =+B36+1 -> 33 | C37: 0.0018382353 | D37: 0.0055147059 | E37: 0.0091911765 | F37: 0.012867647 | G37: 0.016544118 | H37: 0.020220588 | I37: 0.023897059 | J37: 0.027573529 | K37: 0.03125 | L37: 0.034926471 | M37: 0.038602941 | N37: 0.042279412 | O37: 0.045955882 | P37: 0.049632353 | Q37: 0.053308824 | R37: 0.056985294 | S37: 0.058823529 | T37: 0.056985294 | U37: 0.053308824 | V37: 0.049632353 | W37: 0.045955882 | X37: 0.042279412 | Y37: 0.038602941 | Z37: 0.034926471 | AA37: 0.03125 | AB37: 0.027573529 | AC37: 0.023897059 | AD37: 0.020220588 | AE37: 0.016544118 | AF37: 0.012867647 | AG37: 0.0091911765 | AH37: 0.0055147059 | AI37: 0.0018382353
A38: =SUM(C38:AL38) -> 1 | B38: =+B37+1 -> 34 | C38: 0.0032679739 | D38: 0.0065359477 | E38: 0.0098039216 | F38: 0.013071895 | G38: 0.016339869 | H38: 0.019607843 | I38: 0.022875817 | J38: 0.026143791 | K38: 0.029411765 | L38: 0.032679739 | M38: 0.035947712 | N38: 0.039215686 | O38: 0.04248366 | P38: 0.045751634 | Q38: 0.049019608 | R38: 0.052287582 | S38: 0.055555556 | T38: 0.055555556 | U38: 0.052287582 | V38: 0.049019608 | W38: 0.045751634 | X38: 0.04248366 | Y38: 0.039215686 | Z38: 0.035947712 | AA38: 0.032679739 | AB38: 0.029411765 | AC38: 0.026143791 | AD38: 0.022875817 | AE38: 0.019607843 | AF38: 0.016339869 | AG38: 0.013071895 | AH38: 0.0098039216 | AI38: 0.0065359477 | AJ38: 0.0032679739
A39: =SUM(C39:AL39) -> 1 | B39: =+B38+1 -> 35 | C39: 0.0016339869 | D39: 0.0049019608 | E39: 0.0081699346 | F39: 0.011437908 | G39: 0.014705882 | H39: 0.017973856 | I39: 0.02124183 | J39: 0.024509804 | K39: 0.027777778 | L39: 0.031045752 | M39: 0.034313725 | N39: 0.037581699 | O39: 0.040849673 | P39: 0.044117647 | Q39: 0.047385621 | R39: 0.050653595 | S39: 0.053921569 | T39: 0.055555556 | U39: 0.053921569 | V39: 0.050653595 | W39: 0.047385621 | X39: 0.044117647 | Y39: 0.040849673 | Z39: 0.037581699 | AA39: 0.034313725 | AB39: 0.031045752 | AC39: 0.027777778 | AD39: 0.024509804 | AE39: 0.02124183 | AF39: 0.017973856 | AG39: 0.014705882 | AH39: 0.011437908 | AI39: 0.0081699346 | AJ39: 0.0049019608 | AK39: 0.0016339869
A40: =SUM(C40:AL40) -> 1 | B40: =+B39+1 -> 36 | C40: 0.0029239766 | D40: 0.0058479532 | E40: 0.0087719298 | F40: 0.011695906 | G40: 0.014619883 | H40: 0.01754386 | I40: 0.020467836 | J40: 0.023391813 | K40: 0.026315789 | L40: 0.029239766 | M40: 0.032163743 | N40: 0.035087719 | O40: 0.038011696 | P40: 0.040935673 | Q40: 0.043859649 | R40: 0.046783626 | S40: 0.049707602 | T40: 0.052631579 | U40: 0.052631579 | V40: 0.049707602 | W40: 0.046783626 | X40: 0.043859649 | Y40: 0.040935673 | Z40: 0.038011696 | AA40: 0.035087719 | AB40: 0.032163743 | AC40: 0.029239766 | AD40: 0.026315789 | AE40: 0.023391813 | AF40: 0.020467836 | AG40: 0.01754386 | AH40: 0.014619883 | AI40: 0.011695906 | AJ40: 0.0087719298 | AK40: 0.0058479532 | AL40: 0.0029239766

Sheet Process
Q1: Deal Sheet v11.2 - 2024-11-18
Q2: - Corrected Sales Commissions, Incentives, etc.
B3: 1 | C3: Create Deal Sheet | Q3: - Added per unit calcs to Dashboard
B4: 2 | C4: Pressure test - do we have all site costs included, how much time until we can start vertical? | Q4: - Removed calculated list price from loan calc
B5: 3 | C5: Ryan Cox Approval
B6: 4 | C6: Review with Sales - both model and pricing | Q6: Deal Sheet v11.3 - 2024-11-27
B7: 5 | C7: Review with precon/vertical team for vertical capacity | Q7: - Set template builder profit calc to AUTO w/ 15% floor
B8: 6 | C8: Jamie Robinson Review | Q8: - Edited monthly CF to fully fund equity at closing
B9: 7 | C9: Review with Damon - and then I determine if it needs to get escalated to Jon | Q9: - Changed formatting on Profit Analysis on Finance Dashboard
B10: 8 | C10: Send "under contract" email | Q10: - Added LDRL, LD Plat and Survey Costs to Inputs for #builds>1
B11: 9 | C11: Send lender package to Jake
Q12: Deal Sheet v11.4 - 2024-12-4
Q13: -Updated model costs
Q15: Deal Sheet v11.5 - 2024-12-17
Q16: -Updated LTC calc to exclude non-mortgageable costs
Q18: Deal Sheet v11.6 - 2025-2-24
Q19: -New Updated Reference sheet
Q20: - Added Fee Build Calculator
Q21: - Changed Build Durations to 150d from 120d
Q23: Deal Sheet v11.7 - 2025-3-11
Q24: -Added draw fee allowances
Q26: Deal Sheet v11.8 - 2025-3-14
Q27: -Schedule of Values (SOV) has directly been implemented
... Q49: -Added SC specified models for Greenville team

Sheet Internal Budget
E1: Builder Profit | F1: =Inputs!$O$23 -> 26743.702 | H1: =Inputs!F72 -> 26743.702 | J1: =Inputs!F73 -> 0 | L1: =Inputs!F74 -> 0 | N1: =Inputs!F75 -> 0
G2: Internal | P2: External | Z2: Check
Z3: =G5 -> Atlas II - SC | AA3: =IF(Z3="","",Inputs!C72) -> 1
F4: Margin Per Build | H4: =H1/AA3 -> 26743.702 | J4: =IFERROR(J1/AA4,0) -> 0 | L4: =IFERROR(L1/AA5,0) -> 0 | N4: =IFERROR(N1/AA6,0) -> 0 | V4: Model | Z4: =IF(I5=0,"",I5) | AA4: =IF(Z4="","",Inputs!C73)
F5: ACTIVITY | G5: =Inputs!B72 -> Atlas II - SC | H5: =SUM(H6:H88) -> 1 | I5: =Inputs!B73 -> 0 | J5: =SUM(J6:J88) -> 1 | K5: =Inputs!B74 -> 0 | L5: =SUM(L6:L88) -> 1 | M5: =Inputs!B75 -> 0 | N5: =SUM(N6:N88) -> 1 | P5: =IF(ISBLANK(G5),"--",G5) -> Atlas II - SC | Q5: Margin | R5: =I5 -> 0 | S5: Margin | T5: =K5 -> 0 | U5: Margin | V5: =M5 -> 0 | W5: Margin | Z5: =IF(K5=0,"",K5) | AA5: =IF(Z5="","",Inputs!C74)
E6: 1 | F6: Dumpster | G6: =INDEX('Reference Tab'!$V$4:$CA$74, MATCH('Internal Budget'!F6, 'Reference Tab'!$U$4:$U$71, 0), MATCH('Internal Budget'!$G$5, 'Reference Tab'!$V$3:$CA$3, 0)) -> 3000 | I6: =IFERROR(IF(Inputs!$B$73="",0,INDEX('Reference Tab'!$V$4:$CA$74,MATCH('Internal Budget'!F6,'Reference Tab'!$U$4:$U$71,0),MATCH('Internal Budget'!$I$5,'Reference Tab'!$V$3:$CA$3,0))),) -> 0 | K6: =IFERROR(IF(Inputs!$B$74="",0,INDEX('Reference Tab'!$V$4:$CA$74,MATCH('Internal Budget'!F6,'Reference Tab'!$U$4:$U$71,0),MATCH('Internal Budget'!$K$5,'Reference Tab'!$V$3:$CA$3,0))),) -> 0 | M6: =IFERROR(IF(Inputs!$B$75="",0,INDEX('Reference Tab'!$V$4:$CA$74,MATCH('Internal Budget'!F6,'Reference Tab'!$U$4:$U$71,0),MATCH('Internal Budget'!$M$5,'Reference Tab'!$V$3:$CA$3,0))),) -> 0 | P6: =G6+($H$4*$H6) -> 3000 | Q6: =P6-G6 -> 0 | R6: =IF(I6=0,0,I6+($J$4*$J6)) -> 0 | S6: =R6-I6 -> 0 | T6: =IF(K6=0,0,K6+($L$4*$L6)) -> 0 | U6: =T6-K6 -> 0 | V6: =IF(M6=0,0,M6+($N$4*$N6)) -> 0 | W6: =V6-M6 -> 0 | Z6: =IF(M5=0,"",M5) | AA6: =IF(Z6="","",Inputs!C75)
E7: 1 | F7: Utilities | G7: =INDEX('Reference Tab'!$V$4:$CA$74, MATCH('Internal Budget'!F7, 'Reference Tab'!$U$4:$U$71, 0), MATCH('Internal Budget'!$G$5, 'Reference Tab'!$V$3:$CA$3, 0)) -> 300 | I7: =IFERROR(IF(Inputs!$B$73="",0,INDEX('Reference Tab'!$V$4:$CA$74,MATCH('Internal Budget'!F7,'Reference Tab'!$U$4:$U$71,0),MATCH('Internal Budget'!$I$5,'Reference Tab'!$V$3:$CA$3,0))),) -> 0 | K7: =IFERROR(IF(Inputs!$B$74="",0,INDEX('Reference Tab'!$V$4:$CA$74,MATCH('Internal Budget'!F7,'Reference Tab'!$U$4:$U$71,0),MATCH('Internal Budget'!$K$5,'Reference Tab'!$V$3:$CA$3,0))),) -> 0 | M7: =IFERROR(IF(Inputs!$B$75="",0,INDEX('Reference Tab'!$V$4:$AY$71,MATCH('Internal Budget'!F7,'Reference Tab'!$U$4:$U$71,0),MATCH('Internal Budget'!$M$5,'Reference Tab'!$V$3:$AY$3,0))),) -> 0 | P7: =G7+($H$4*$H7) -> 300 | Q7: =P7-G7 -> 0 | R7: =IF(I7=0,0,I7+($J$4*$J7)) -> 0 | S7: =R7-I7 -> 0 | T7: =IF(K7=0,0,K7+($L$4*$L7)) -> 0 | U7: =T7-K7 -> 0 | V7: =IF(M7=0,0,M7+($N$4*$N7)) -> 0 | W7: =V7-M7 -> 0 | Z7: Check | AA7: =H1+J1+L1+N1 -> 26743.702
E8: 1 | F8: Portable toilet | G8: =INDEX('Reference Tab'!$V$4:$CA$74, MATCH('Internal Budget'!F8, 'Reference Tab'!$U$4:$U$71, 0), MATCH('Internal Budget'!$G$5, 'Reference Tab'!$V$3:$CA$3, 0)) -> 875 | I8: =IFERROR(IF(Inputs!$B$73="",0,INDEX('Reference Tab'!$V$4:$CA$74,MATCH('Internal Budget'!F8,'Reference Tab'!$U$4:$U$71,0),MATCH('Internal Budget'!$I$5,'Reference Tab'!$V$3:$CA$3,0))),) -> 0 | K8: =IFERROR(IF(Inputs!$B$74="",0,INDEX('Reference Tab'!$V$4:$CA$74,MATCH('Internal Budget'!F8,'Reference Tab'!$U$4:$U$71,0),MATCH('Internal Budget'!$K$5,'Reference Tab'!$V$3:$CA$3,0))),) -> 0 | M8: =IFERROR(IF(Inputs!$B$75="",0,INDEX('Reference Tab'!$V$4:$AY$71,MATCH('Internal Budget'!F8,'Reference Tab'!$U$4:$U$71,0),MATCH('Internal Budget'!$M$5,'Reference Tab'!$V$3:$AY$3,0))),) -> 0 | P8: =G8+($H$4*$H8) -> 875 | Q8: =P8-G8 -> 0 | R8: =IF(I8=0,0,I8+($J$4*$J8)) -> 0 | S8: =R8-I8 -> 0 | T8: =IF(K8=0,0,K8+($L$4*$L8)) -> 0 | U8: =T8-K8 -> 0 | V8: =IF(M8=0,0,M8+($N$4*$N8)) -> 0 | W8: =V8-M8 -> 0
E9: 1 | F9: Permit Box | G9: =INDEX('Reference Tab'!$V$4:$CA$74, MATCH('Internal Budget'!F9, 'Reference Tab'!$U$4:$U$71, 0), MATCH('Internal Budget'!$G$5, 'Reference Tab'!$V$3:$CA$3, 0)) -> 50 | I9: =IFERROR(IF(Inputs!$B$73="",0,INDEX('Reference Tab'!$V$4:$CA$74,MATCH('Internal Budget'!F9,'Reference Tab'!$U$4:$U$71,0),MATCH('Internal Budget'!$I$5,'Reference Tab'!$V$3:$CA$3,0))),) -> 0 | K9: =IFERROR(IF(Inputs!$B$74="",0,INDEX('Reference Tab'!$V$4:$CA$74,MATCH('Internal Budget'!F9,'Reference Tab'!$U$4:$U$71,0),MATCH('Internal Budget'!$K$5,'Reference Tab'!$V$3:$CA$3,0))),) -> 0 | M9: =IFERROR(IF(Inputs!$B$75="",0,INDEX('Reference Tab'!$V$4:$AY$71,MATCH('Internal Budget'!F9,'Reference Tab'!$U$4:$U$71,0),MATCH('Internal Budget'!$M$5,'Reference Tab'!$V$3:$AY$3,0))),) -> 0 | P9: =G9+($H$4*$H9) -> 50 | Q9: =P9-G9 -> 0 | R9: =IF(I9=0,0,I9+($J$4*$J9)) -> 0 | S9: =R9-I9 -> 0 | T9: =IF(K9=0,0,K9+($L$4*$L9)) -> 0 | U9: =T9-K9 -> 0 | V9: =IF(M9=0,0,M9+($N$4*$N9)) -> 0 | W9: =V9-M9 -> 0
E10: 1 | F10: Termite | G10: =INDEX('Reference Tab'!$V$4:$CA$74, MATCH('Internal Budget'!F10, 'Reference Tab'!$U$4:$U$71, 0), MATCH('Internal Budget'!$G$5, 'Reference Tab'!$V$3:$CA$3, 0)) -> 225 | I10: =IFERROR(IF(Inputs!$B$73="",0,INDEX('Reference Tab'!$V$4:$CA$74,MATCH('Internal Budget'!F10,'Reference Tab'!$U$4:$U$71,0),MATCH('Internal Budget'!$I$5,'Reference Tab'!$V$3:$CA$3,0))),) -> 0 | K10: =IFERROR(IF(Inputs!$B$74="",0,INDEX('Reference Tab'!$V$4:$CA$74,MATCH('Internal Budget'!F10,'Reference Tab'!$U$4:$U$71,0),MATCH('Internal Budget'!$K$5,'Reference Tab'!$V$3:$CA$3,0))),) -> 0 | M10: =IFERROR(IF(Inputs!$B$75="",0,INDEX('Reference Tab'!$V$4:$AY$71,MATCH('Internal Budget'!F10,'Reference Tab'!$U$4:$U$71,0),MATCH('Internal Budget'!$M$5,'Reference Tab'!$V$3:$AY$3,0))),) -> 0 | P10: =G10+($H$4*$H10) -> 225 | Q10: =P10-G10 -> 0 | R10: =IF(I10=0,0,I10+($J$4*$J10)) -> 0 | S10: =R10-I10 -> 0 | T10: =IF(K10=0,0,K10+($L$4*$L10)) -> 0 | U10: =T10-K10 -> 0 | V10: =IF(M10=0,0,M10+($N$4*$N10)) -> 0 | W10: =V10-M10 -> 0
E11: 2 | F11: Lumber All Floors | G11: =INDEX('Reference Tab'!$V$4:$CA$74, MATCH('Internal Budget'!F11, 'Reference Tab'!$U$4:$U$71, 0), MATCH('Internal Budget'!$G$5, 'Reference Tab'!$V$3:$CA$3, 0)) -> 6661.73 | I11: =IFERROR(IF(Inputs!$B$73="",0,INDEX('Reference Tab'!$V$4:$CA$74,MATCH('Internal Budget'!F11,'Reference Tab'!$U$4:$U$71,0),MATCH('Internal Budget'!$I$5,'Reference Tab'!$V$3:$CA$3,0))),) -> 0 | K11: =IFERROR(IF(Inputs!$B$74="",0,INDEX('Reference Tab'!$V$4:$CA$74,MATCH('Internal Budget'!F11,'Reference Tab'!$U$4:$U$71,0),MATCH('Internal Budget'!$K$5,'Reference Tab'!$V$3:$CA$3,0))),) -> 0 | M11: =IFERROR(IF(Inputs!$B$75="",0,INDEX('Reference Tab'!$V$4:$AY$71,MATCH('Internal Budget'!F11,'Reference Tab'!$U$4:$U$71,0),MATCH('Internal Budget'!$M$5,'Reference Tab'!$V$3:$AY$3,0))),) -> 0 | P11: =G11+($H$4*$H11) -> 6661.73 | Q11: =P11-G11 -> 0 | R11: =IF(I11=0,0,I11+($J$4*$J11)) -> 0 | S11: =R11-I11 -> 0 | T11: =IF(K11=0,0,K11+($L$4*$L11)) -> 0 | U11: =T11-K11 -> 0 | V11: =IF(M11=0,0,M11+($N$4*$N11)) -> 0 | W11: =V11-M11 -> 0
E12: 2 | F12: Framing Labor | G12: =INDEX('Reference Tab'!$V$4:$CA$74, MATCH('Internal Budget'!F12, 'Reference Tab'!$U$4:$U$71, 0), MATCH('Internal Budget'!$G$5, 'Reference Tab'!$V$3:$CA$3, 0)) -> 7399.8 | I12: =IFERROR(IF(Inputs!$B$73="",0,INDEX('Reference Tab'!$V$4:$CA$74,MATCH('Internal Budget'!F12,'Reference Tab'!$U$4:$U$71,0),MATCH('Internal Budget'!$I$5,'Reference Tab'!$V$3:$CA$3,0))),) -> 0 | K12: =IFERROR(IF(Inputs!$B$74="",0,INDEX('Reference Tab'!$V$4:$CA$74,MATCH('Internal Budget'!F12,'Reference Tab'!$U$4:$U$71,0),MATCH('Internal Budget'!$K$5,'Reference Tab'!$V$3:$CA$3,0))),) -> 0 | M12: =IFERROR(IF(Inputs!$B$75="",0,INDEX('Reference Tab'!$V$4:$AY$71,MATCH('Internal Budget'!F12,'Reference Tab'!$U$4:$U$71,0),MATCH('Internal Budget'!$M$5,'Reference Tab'!$V$3:$AY$3,0))),) -> 0 | P12: =G12+($H$4*$H12) -> 7399.8 | Q12: =P12-G12 -> 0 | R12: =IF(I12=0,0,I12+($J$4*$J12)) -> 0 | S12: =R12-I12 -> 0 | T12: =IF(K12=0,0,K12+($L$4*$L12)) -> 0 | U12: =T12-K12 -> 0 | V12: =IF(M12=0,0,M12+($N$4*$N12)) -> 0 | W12: =V12-M12 -> 0
E13: 2 | F13: Floor Trusses | G13: =INDEX('Reference Tab'!$V$4:$CA$74, MATCH('Internal Budget'!F13, 'Reference Tab'!$U$4:$U$71, 0), MATCH('Internal Budget'!$G$5, 'Reference Tab'!$V$3:$CA$3, 0)) -> 2616.73 | I13: =IFERROR(IF(Inputs!$B$73="",0,INDEX('Reference Tab'!$V$4:$CA$74,MATCH('Internal Budget'!F13,'Reference Tab'!$U$4:$U$71,0),MATCH('Internal Budget'!$I$5,'Reference Tab'!$V$3:$CA$3,0))),) -> 0 | K13: =IFERROR(IF(Inputs!$B$74="",0,INDEX('Reference Tab'!$V$4:$CA$74,MATCH('Internal Budget'!F13,'Reference Tab'!$U$4:$U$71,0),MATCH('Internal Budget'!$K$5,'Reference Tab'!$V$3:$CA$3,0))),) -> 0 | M13: =IFERROR(IF(Inputs!$B$75="",0,INDEX('Reference Tab'!$V$4:$AY$71,MATCH('Internal Budget'!F13,'Reference Tab'!$U$4:$U$71,0),MATCH('Internal Budget'!$M$5,'Reference Tab'!$V$3:$AY$3,0))),) -> 0 | P13: =G13+($H$4*$H13) -> 2616.73 | Q13: =P13-G13 -> 0 | R13: =IF(I13=0,0,I13+($J$4*$J13)) -> 0 | S13: =R13-I13 -> 0 | T13: =IF(K13=0,0,K13+($L$4*$L13)) -> 0 | U13: =T13-K13 -> 0 | V13: =IF(M13=0,0,M13+($N$4*$N13)) -> 0 | W13: =V13-M13 -> 0
E14: 2 | F14: Stairs | G14: =INDEX('Reference Tab'!$V$4:$CA$74, MATCH('Internal Budget'!F14, 'Reference Tab'!$U$4:$U$71, 0), MATCH('Internal Budget'!$G$5, 'Reference Tab'!$V$3:$CA$3, 0)) -> 573.82 | I14: =IFERROR(IF(Inputs!$B$73="",0,INDEX('Reference Tab'!$V$4:$CA$74,MATCH('Internal Budget'!F14,'Reference Tab'!$U$4:$U$71,0),MATCH('Internal Budget'!$I$5,'Reference Tab'!$V$3:$CA$3,0))),) -> 0 | K14: =IFERROR(IF(Inputs!$B$74="",0,INDEX('Reference Tab'!$V$4:$CA$74,MATCH('Internal Budget'!F14,'Reference Tab'!$U$4:$U$71,0),MATCH('Internal Budget'!$K$5,'Reference Tab'!$V$3:$CA$3,0))),) -> 0 | M14: =IFERROR(IF(Inputs!$B$75="",0,INDEX('Reference Tab'!$V$4:$AY$71,MATCH('Internal Budget'!F14,'Reference Tab'!$U$4:$U$71,0),MATCH('Internal Budget'!$M$5,'Reference Tab'!$V$3:$AY$3,0))),) -> 0 | P14: =G14+($H$4*$H14) -> 573.82 | Q14: =P14-G14 -> 0 | R14: =IF(I14=0,0,I14+($J$4*$J14)) -> 0 | S14: =R14-I14 -> 0 | T14: =IF(K14=0,0,K14+($L$4*$L14)) -> 0 | U14: =T14-K14 -> 0 | V14: =IF(M14=0,0,M14+($N$4*$N14)) -> 0 | W14: =V14-M14 -> 0
E15: 2 | F15: Roof Trusses | G15: =INDEX('Reference Tab'!$V$4:$CA$74, MATCH('Internal Budget'!F15, 'Reference Tab'!$U$4:$U$71, 0), MATCH('Internal Budget'!$G$5, 'Reference Tab'!$V$3:$CA$3, 0)) -> 2458.39 | I15: =IFERROR(IF(Inputs!$B$73="",0,INDEX('Reference Tab'!$V$4:$CA$74,MATCH('Internal Budget'!F15,'Reference Tab'!$U$4:$U$71,0),MATCH('Internal Budget'!$I$5,'Reference Tab'!$V$3:$CA$3,0))),) -> 0 | K15: =IFERROR(IF(Inputs!$B$74="",0,INDEX('Reference Tab'!$V$4:$CA$74,MATCH('Internal Budget'!F15,'Reference Tab'!$U$4:$U$71,0),MATCH('Internal Budget'!$K$5,'Reference Tab'!$V$3:$CA$3,0))),) -> 0 | M15: =IFERROR(IF(Inputs!$B$75="",0,INDEX('Reference Tab'!$V$4:$AY$71,MATCH('Internal Budget'!F15,'Reference Tab'!$U$4:$U$71,0),MATCH('Internal Budget'!$M$5,'Reference Tab'!$V$3:$AY$3,0))),) -> 0 | P15: =G15+($H$4*$H15) -> 2458.39 | Q15: =P15-G15 -> 0 | R15: =IF(I15=0,0,I15+($J$4*$J15)) -> 0 | S15: =R15-I15 -> 0 | T15: =IF(K15=0,0,K15+($L$4*$L15)) -> 0 | U15: =T15-K15 -> 0 | V15: =IF(M15=0,0,M15+($N$4*$N15)) -> 0 | W15: =V15-M15 -> 0
E16: 2 | F16: I-Joist/EWP | G16: =INDEX('Reference Tab'!$V$4:$CA$74, MATCH('Internal Budget'!F16, 'Reference Tab'!$U$4:$U$71, 0), MATCH('Internal Budget'!$G$5, 'Reference Tab'!$V$3:$CA$3, 0)) -> 0 | I16: =IFERROR(IF(Inputs!$B$73="",0,INDEX('Reference Tab'!$V$4:$CA$74,MATCH('Internal Budget'!F16,'Reference Tab'!$U$4:$U$71,0),MATCH('Internal Budget'!$I$5,'Reference Tab'!$V$3:$CA$3,0))),) -> 0 | K16: =IFERROR(IF(Inputs!$B$74="",0,INDEX('Reference Tab'!$V$4:$CA$74,MATCH('Internal Budget'!F16,'Reference Tab'!$U$4:$U$71,0),MATCH('Internal Budget'!$K$5,'Reference Tab'!$V$3:$CA$3,0))),) -> 0 | M16: =IFERROR(IF(Inputs!$B$75="",0,INDEX('Reference Tab'!$V$4:$AY$71,MATCH('Internal Budget'!F16,'Reference Tab'!$U$4:$U$71,0),MATCH('Internal Budget'!$M$5,'Reference Tab'!$V$3:$AY$3,0))),) -> 0 | P16: =G16+($H$4*$H16) -> 0 | Q16: =P16-G16 -> 0 | R16: =IF(I16=0,0,I16+($J$4*$J16)) -> 0 | S16: =R16-I16 -> 0 | T16: =IF(K16=0,0,K16+($L$4*$L16)) -> 0 | U16: =T16-K16 -> 0 | V16: =IF(M16=0,0,M16+($N$4*$N16)) -> 0 | W16: =V16-M16 -> 0
E17: 2 | F17: Roofing Shingle | G17: =INDEX('Reference Tab'!$V$4:$CA$74, MATCH('Internal Budget'!F17, 'Reference Tab'!$U$4:$U$71, 0), MATCH('Internal Budget'!$G$5, 'Reference Tab'!$V$3:$CA$3, 0)) -> 0 | I17: =IFERROR(IF(Inputs!$B$73="",0,INDEX('Reference Tab'!$V$4:$CA$74,MATCH('Internal Budget'!F17,'Reference Tab'!$U$4:$U$71,0),MATCH('Internal Budget'!$I$5,'Reference Tab'!$V$3:$CA$3,0))),) -> 0 | K17: =IFERROR(IF(Inputs!$B$74="",0,INDEX('Reference Tab'!$V$4:$CA$74,MATCH('Internal Budget'!F17,'Reference Tab'!$U$4:$U$71,0),MATCH('Internal Budget'!$K$5,'Reference Tab'!$V$3:$CA$3,0))),) -> 0 | M17: =IFERROR(IF(Inputs!$B$75="",0,INDEX('Reference Tab'!$V$4:$AY$71,MATCH('Internal Budget'!F17,'Reference Tab'!$U$4:$U$71,0),MATCH('Internal Budget'!$M$5,'Reference Tab'!$V$3:$AY$3,0))),) -> 0 | P17: =G17+($H$4*$H17) -> 0 | Q17: =P17-G17 -> 0 | R17: =IF(I17=0,0,I17+($J$4*$J17)) -> 0 | S17: =R17-I17 -> 0 | T17: =IF(K17=0,0,K17+($L$4*$L17)) -> 0 | U17: =T17-K17 -> 0 | V17: =IF(M17=0,0,M17+($N$4*$N17)) -> 0 | W17: =V17-M17 -> 0
E18: 2 | F18: Roofing Metal | G18: =INDEX('Reference Tab'!$V$4:$CA$74, MATCH('Internal Budget'!F18, 'Reference Tab'!$U$4:$U$71, 0), MATCH('Internal Budget'!$G$5, 'Reference Tab'!$V$3:$CA$3, 0)) -> 0 | I18: =IFERROR(IF(Inputs!$B$73="",0,INDEX('Reference Tab'!$V$4:$CA$74,MATCH('Internal Budget'!F18,'Reference Tab'!$U$4:$U$71,0),MATCH('Internal Budget'!$I$5,'Reference Tab'!$V$3:$CA$3,0))),) -> 0 | K18: =IFERROR(IF(Inputs!$B$74="",0,INDEX('Reference Tab'!$V$4:$CA$74,MATCH('Internal Budget'!F18,'Reference Tab'!$U$4:$U$71,0),MATCH('Internal Budget'!$K$5,'Reference Tab'!$V$3:$CA$3,0))),) -> 0 | M18: =IFERROR(IF(Inputs!$B$75="",0,INDEX('Reference Tab'!$V$4:$AY$71,MATCH('Internal Budget'!F18,'Reference Tab'!$U$4:$U$71,0),MATCH('Internal Budget'!$M$5,'Reference Tab'!$V$3:$AY$3,0))),) -> 0 | P18: =G18+($H$4*$H18) -> 0 | Q18: =P18-G18 -> 0 | R18: =IF(I18=0,0,I18+($J$4*$J18)) -> 0 | S18: =R18-I18 -> 0 | T18: =IF(K18=0,0,K18+($L$4*$L18)) -> 0 | U18: =T18-K18 -> 0 | V18: =IF(M18=0,0,M18+($N$4*$N18)) -> 0 | W18: =V18-M18 -> 0
E19: 2 | F19: Roofing Labor & Material | G19: =INDEX('Reference Tab'!$V$4:$CA$74, MATCH('Internal Budget'!F19, 'Reference Tab'!$U$4:$U$71, 0), MATCH('Internal Budget'!$G$5, 'Reference Tab'!$V$3:$CA$3, 0)) -> 3070.51 | I19: =IFERROR(IF(Inputs!$B$73="",0,INDEX('Reference Tab'!$V$4:$CA$74,MATCH('Internal Budget'!F19,'Reference Tab'!$U$4:$U$71,0),MATCH('Internal Budget'!$I$5,'Reference Tab'!$V$3:$CA$3,0))),) -> 0 | K19: =IFERROR(IF(Inputs!$B$74="",0,INDEX('Reference Tab'!$V$4:$CA$74,MATCH('Internal Budget'!F19,'Reference Tab'!$U$4:$U$71,0),MATCH('Internal Budget'!$K$5,'Reference Tab'!$V$3:$CA$3,0))),) -> 0 | M19: =IFERROR(IF(Inputs!$B$75="",0,INDEX('Reference Tab'!$V$4:$AY$71,MATCH('Internal Budget'!F19,'Reference Tab'!$U$4:$U$71,0),MATCH('Internal Budget'!$M$5,'Reference Tab'!$V$3:$AY$3,0))),) -> 0 | P19: =G19+($H$4*$H19) -> 3070.51 | Q19: =P19-G19 -> 0 | R19: =IF(I19=0,0,I19+($J$4*$J19)) -> 0 | S19: =R19-I19 -> 0 | T19: =IF(K19=0,0,K19+($L$4*$L19)) -> 0 | U19: =T19-K19 -> 0 | V19: =IF(M19=0,0,M19+($N$4*$N19)) -> 0 | W19: =V19-M19 -> 0
... E26: 2 | F26: Garage Door Labor & Material | G26: =INDEX('Reference Tab'!$V$4:$CA$74, MATCH('Internal Budget'!F26, 'Reference Tab'!$U$4:$U$71, 0), MATCH('Internal Budget'!$G$5, 'Reference Tab'!$V$3:$CA$3, 0)) -> 0 | I26: =IFERROR(IF(Inputs!$B$73="",0,INDEX('Reference Tab'!$V$4:$CA$74,MATCH('Internal Budget'!F26,'Reference Tab'!$U$4:$U$71,0),MATCH('Internal Budget'!$I$5,'Reference Tab'!$V$3:$CA$3,0))),) -> 0 | K26: =IFERROR(IF(Inputs!$B$74="",0,INDEX('Reference Tab'!$V$4:$CA$74,MATCH('Internal Budget'!F26,'Reference Tab'!$U$4:$U$71,0),MATCH('Internal Budget'!$K$5,'Reference Tab'!$V$3:$CA$3,0))),) -> 0 | M26: =IFERROR(IF(Inputs!$B$75="",0,INDEX('Reference Tab'!$V$4:$AY$71,MATCH('Internal Budget'!F26,'Reference Tab'!$U$4:$U$71,0),MATCH('Internal Budget'!$M$5,'Reference Tab'!$V$3:$AY$3,0))),) -> 0 | P26: =G26+($H$4*$H26) -> 0 | Q26: =P26-G26 -> 0 | R26: =IF(I26=0,0,I26+($J$4*$J26)) -> 0 | S26: =R26-I26 -> 0 | T26: =IF(K26=0,0,K26+($L$4*$L26)) -> 0 | U26: =T26-K26 -> 0 | V26: =IF(M26=0,0,M26+($N$4*$N26)) -> 0 | W26: =V26-M26 -> 0
A27: Plumbing Turnkey | B27: 0.3 | E27: 3 | F27: Rough Plumbing | G27: =INDEX('Reference Tab'!$V$4:$CA$74, MATCH(A27, 'Reference Tab'!$U$4:$U$71, 0), MATCH('Internal Budget'!$G$5, 'Reference Tab'!$V$3:$CA$3, 0))*B27 -> 3034.5 | I27: =IFERROR(IF(Inputs!$B$73="",0,INDEX('Reference Tab'!$V$4:$CA$74,MATCH('Internal Budget'!F27,'Reference Tab'!$U$4:$U$71,0),MATCH('Internal Budget'!$I$5,'Reference Tab'!$V$3:$CA$3,0))),) -> 0 | K27: =IFERROR(IF(Inputs!$B$74="",0,INDEX('Reference Tab'!$V$4:$CA$74,MATCH('Internal Budget'!F27,'Reference Tab'!$U$4:$U$71,0),MATCH('Internal Budget'!$K$5,'Reference Tab'!$V$3:$CA$3,0))),) -> 0 | M27: =IFERROR(IF(Inputs!$B$75="",0,INDEX('Reference Tab'!$V$4:$AY$71,MATCH('Internal Budget'!F27,'Reference Tab'!$U$4:$U$71,0),MATCH('Internal Budget'!$M$5,'Reference Tab'!$V$3:$AY$3,0))),) -> 0 | P27: =G27+($H$4*$H27) -> 3034.5 | Q27: =P27-G27 -> 0 | R27: =IF(I27=0,0,I27+($J$4*$J27)) -> 0 | S27: =R27-I27 -> 0 | T27: =IF(K27=0,0,K27+($L$4*$L27)) -> 0 | U27: =T27-K27 -> 0 | V27: =IF(M27=0,0,M27+($N$4*$N27)) -> 0 | W27: =V27-M27 -> 0
A28: Plumbing Turnkey | B28: 0.4 | E28: 3 | F28: Final Plumbing | G28: =INDEX('Reference Tab'!$V$4:$CA$74, MATCH(A28, 'Reference Tab'!$U$4:$U$71, 0), MATCH('Internal Budget'!$G$5, 'Reference Tab'!$V$3:$CA$3, 0))*B28 -> 4046 | I28: =IFERROR(IF(Inputs!$B$73="",0,INDEX('Reference Tab'!$V$4:$CA$74,MATCH('Internal Budget'!F28,'Reference Tab'!$U$4:$U$71,0),MATCH('Internal Budget'!$I$5,'Reference Tab'!$V$3:$CA$3,0))),) -> 0 | K28: =IFERROR(IF(Inputs!$B$74="",0,INDEX('Reference Tab'!$V$4:$CA$74,MATCH('Internal Budget'!F28,'Reference Tab'!$U$4:$U$71,0),MATCH('Internal Budget'!$K$5,'Reference Tab'!$V$3:$CA$3,0))),) -> 0 | M28: =IFERROR(IF(Inputs!$B$75="",0,INDEX('Reference Tab'!$V$4:$AY$71,MATCH('Internal Budget'!F28,'Reference Tab'!$U$4:$U$71,0),MATCH('Internal Budget'!$M$5,'Reference Tab'!$V$3:$AY$3,0))),) -> 0 | P28: =G28+($H$4*$H28) -> 4046 | Q28: =P28-G28 -> 0 | R28: =IF(I28=0,0,I28+($J$4*$J28)) -> 0 | S28: =R28-I28 -> 0 | T28: =IF(K28=0,0,K28+($L$4*$L28)) -> 0 | U28: =T28-K28 -> 0 | V28: =IF(M28=0,0,M28+($N$4*$N28)) -> 0 | W28: =V28-M28 -> 0
A29: HVAC | B29: 0.7 | E29: 3 | F29: Rough HVAC | G29: =INDEX('Reference Tab'!$V$4:$CA$74, MATCH(A29, 'Reference Tab'!$U$4:$U$71, 0), MATCH('Internal Budget'!$G$5, 'Reference Tab'!$V$3:$CA$3, 0))*B29 -> 5775 | I29: =IFERROR(IF(Inputs!$B$73="",0,INDEX('Reference Tab'!$V$4:$CA$74,MATCH('Internal Budget'!F29,'Reference Tab'!$U$4:$U$71,0),MATCH('Internal Budget'!$I$5,'Reference Tab'!$V$3:$CA$3,0))),) -> 0 | K29: =IFERROR(IF(Inputs!$B$74="",0,INDEX('Reference Tab'!$V$4:$CA$74,MATCH('Internal Budget'!F29,'Reference Tab'!$U$4:$U$71,0),MATCH('Internal Budget'!$K$5,'Reference Tab'!$V$3:$CA$3,0))),) -> 0 | M29: =IFERROR(IF(Inputs!$B$75="",0,INDEX('Reference Tab'!$V$4:$AY$71,MATCH('Internal Budget'!F29,'Reference Tab'!$U$4:$U$71,0),MATCH('Internal Budget'!$M$5,'Reference Tab'!$V$3:$AY$3,0))),) -> 0 | P29: =G29+($H$4*$H29) -> 5775 | Q29: =P29-G29 -> 0 | R29: =IF(I29=0,0,I29+($J$4*$J29)) -> 0 | S29: =R29-I29 -> 0 | T29: =IF(K29=0,0,K29+($L$4*$L29)) -> 0 | U29: =T29-K29 -> 0 | V29: =IF(M29=0,0,M29+($N$4*$N29)) -> 0 | W29: =V29-M29 -> 0
A30: HVAC | B30: 0.3 | E30: 3 | F30: Final HVAC | G30: =INDEX('Reference Tab'!$V$4:$CA$74, MATCH(A30, 'Reference Tab'!$U$4:$U$71, 0), MATCH('Internal Budget'!$G$5, 'Reference Tab'!$V$3:$CA$3, 0))*B30 -> 2475 | I30: =IFERROR(IF(Inputs!$B$73="",0,INDEX('Reference Tab'!$V$4:$CA$74,MATCH('Internal Budget'!F30,'Reference Tab'!$U$4:$U$71,0),MATCH('Internal Budget'!$I$5,'Reference Tab'!$V$3:$CA$3,0))),) -> 0 | K30: =IFERROR(IF(Inputs!$B$74="",0,INDEX('Reference Tab'!$V$4:$CA$74,MATCH('Internal Budget'!F30,'Reference Tab'!$U$4:$U$71,0),MATCH('Internal Budget'!$K$5,'Reference Tab'!$V$3:$CA$3,0))),) -> 0 | M30: =IFERROR(IF(Inputs!$B$75="",0,INDEX('Reference Tab'!$V$4:$AY$71,MATCH('Internal Budget'!F30,'Reference Tab'!$U$4:$U$71,0),MATCH('Internal Budget'!$M$5,'Reference Tab'!$V$3:$AY$3,0))),) -> 0 | P30: =G30+($H$4*$H30) -> 2475 | Q30: =P30-G30 -> 0 | R30: =IF(I30=0,0,I30+($J$4*$J30)) -> 0 | S30: =R30-I30 -> 0 | T30: =IF(K30=0,0,K30+($L$4*$L30)) -> 0 | U30: =T30-K30 -> 0 | V30: =IF(M30=0,0,M30+($N$4*$N30)) -> 0 | W30: =V30-M30 -> 0
A31: Electrical Rough & Trim | B31: 0.6 | E31: 3 | F31: Rough Electrical | G31: =INDEX('Reference Tab'!$V$4:$CA$74, MATCH(A31, 'Reference Tab'!$U$4:$U$71, 0), MATCH('Internal Budget'!$G$5, 'Reference Tab'!$V$3:$CA$3, 0))*B31 -> 3762 | I31: =IFERROR(IF(Inputs!$B$73="",0,INDEX('Reference Tab'!$V$4:$CA$74,MATCH('Internal Budget'!F31,'Reference Tab'!$U$4:$U$71,0),MATCH('Internal Budget'!$I$5,'Reference Tab'!$V$3:$CA$3,0))),) -> 0 | K31: =IFERROR(IF(Inputs!$B$74="",0,INDEX('Reference Tab'!$V$4:$CA$74,MATCH('Internal Budget'!F31,'Reference Tab'!$U$4:$U$71,0),MATCH('Internal Budget'!$K$5,'Reference Tab'!$V$3:$CA$3,0))),) -> 0 | M31: =IFERROR(IF(Inputs!$B$75="",0,INDEX('Reference Tab'!$V$4:$AY$71,MATCH('Internal Budget'!F31,'Reference Tab'!$U$4:$U$71,0),MATCH('Internal Budget'!$M$5,'Reference Tab'!$V$3:$AY$3,0))),) -> 0 | P31: =G31+($H$4*$H31) -> 3762 | Q31: =P31-G31 -> 0 | R31: =IF(I31=0,0,I31+($J$4*$J31)) -> 0 | S31: =R31-I31 -> 0 | T31: =IF(K31=0,0,K31+($L$4*$L31)) -> 0 | U31: =T31-K31 -> 0 | V31: =IF(M31=0,0,M31+($N$4*$N31)) -> 0 | W31: =V31-M31 -> 0
A32: Electrical Rough & Trim | B32: 0.4 | E32: 3 | F32: Final Electrical | G32: =INDEX('Reference Tab'!$V$4:$CA$74, MATCH(A32, 'Reference Tab'!$U$4:$U$71, 0), MATCH('Internal Budget'!$G$5, 'Reference Tab'!$V$3:$CA$3, 0))*B32 -> 2508 | I32: =IFERROR(IF(Inputs!$B$73="",0,INDEX('Reference Tab'!$V$4:$CA$74,MATCH('Internal Budget'!F32,'Reference Tab'!$U$4:$U$71,0),MATCH('Internal Budget'!$I$5,'Reference Tab'!$V$3:$CA$3,0))),) -> 0 | K32: =IFERROR(IF(Inputs!$B$74="",0,INDEX('Reference Tab'!$V$4:$CA$74,MATCH('Internal Budget'!F32,'Reference Tab'!$U$4:$U$71,0),MATCH('Internal Budget'!$K$5,'Reference Tab'!$V$3:$CA$3,0))),) -> 0 | M32: =IFERROR(IF(Inputs!$B$75="",0,INDEX('Reference Tab'!$V$4:$AY$71,MATCH('Internal Budget'!F32,'Reference Tab'!$U$4:$U$71,0),MATCH('Internal Budget'!$M$5,'Reference Tab'!$V$3:$AY$3,0))),) -> 0 | P32: =G32+($H$4*$H32) -> 2508 | Q32: =P32-G32 -> 0 | R32: =IF(I32=0,0,I32+($J$4*$J32)) -> 0 | S32: =R32-I32 -> 0 | T32: =IF(K32=0,0,K32+($L$4*$L32)) -> 0 | U32: =T32-K32 -> 0 | V32: =IF(M32=0,0,M32+($N$4*$N32)) -> 0 | W32: =V32-M32 -> 0
E33: 3 | F33: Blower Test | G33: =INDEX('Reference Tab'!$V$4:$CA$74, MATCH('Internal Budget'!F33, 'Reference Tab'!$U$4:$U$71, 0), MATCH('Internal Budget'!$G$5, 'Reference Tab'!$V$3:$CA$3, 0)) -> 275 | I33: =IFERROR(IF(Inputs!$B$73="",0,INDEX('Reference Tab'!$V$4:$CA$74,MATCH('Internal Budget'!F33,'Reference Tab'!$U$4:$U$71,0),MATCH('Internal Budget'!$I$5,'Reference Tab'!$V$3:$CA$3,0))),) -> 0 | K33: =IFERROR(IF(Inputs!$B$74="",0,INDEX('Reference Tab'!$V$4:$CA$74,MATCH('Internal Budget'!F33,'Reference Tab'!$U$4:$U$71,0),MATCH('Internal Budget'!$K$5,'Reference Tab'!$V$3:$CA$3,0))),) -> 0 | M33: =IFERROR(IF(Inputs!$B$75="",0,INDEX('Reference Tab'!$V$4:$AY$71,MATCH('Internal Budget'!F33,'Reference Tab'!$U$4:$U$71,0),MATCH('Internal Budget'!$M$5,'Reference Tab'!$V$3:$AY$3,0))),) -> 0 | P33: =G33+($H$4*$H33) -> 275 | Q33: =P33-G33 -> 0 | R33: =IF(I33=0,0,I33+($J$4*$J33)) -> 0 | S33: =R33-I33 -> 0 | T33: =IF(K33=0,0,K33+($L$4*$L33)) -> 0 | U33: =T33-K33 -> 0 | V33: =IF(M33=0,0,M33+($N$4*$N33)) -> 0 | W33: =V33-M33 -> 0
E34: 3 | F34: Low Voltage/AV | G34: =INDEX('Reference Tab'!$V$4:$CA$74, MATCH('Internal Budget'!F34, 'Reference Tab'!$U$4:$U$71, 0), MATCH('Internal Budget'!$G$5, 'Reference Tab'!$V$3:$CA$3, 0)) -> 0 | I34: =IFERROR(IF(Inputs!$B$73="",0,INDEX('Reference Tab'!$V$4:$CA$74,MATCH('Internal Budget'!F34,'Reference Tab'!$U$4:$U$71,0),MATCH('Internal Budget'!$I$5,'Reference Tab'!$V$3:$CA$3,0))),) -> 0 | K34: =IFERROR(IF(Inputs!$B$74="",0,INDEX('Reference Tab'!$V$4:$CA$74,MATCH('Internal Budget'!F34,'Reference Tab'!$U$4:$U$71,0),MATCH('Internal Budget'!$K$5,'Reference Tab'!$V$3:$CA$3,0))),) -> 0 | M34: =IFERROR(IF(Inputs!$B$75="",0,INDEX('Reference Tab'!$V$4:$AY$71,MATCH('Internal Budget'!F34,'Reference Tab'!$U$4:$U$71,0),MATCH('Internal Budget'!$M$5,'Reference Tab'!$V$3:$AY$3,0))),) -> 0 | P34: =G34+($H$4*$H34) -> 0 | Q34: =P34-G34 -> 0 | R34: =IF(I34=0,0,I34+($J$4*$J34)) -> 0 | S34: =R34-I34 -> 0 | T34: =IF(K34=0,0,K34+($L$4*$L34)) -> 0 | U34: =T34-K34 -> 0 | V34: =IF(M34=0,0,M34+($N$4*$N34)) -> 0 | W34: =V34-M34 -> 0
E35: 3 | F35: Insulation | G35: =INDEX('Reference Tab'!$V$4:$CA$74, MATCH('Internal Budget'!F35, 'Reference Tab'!$U$4:$U$71, 0), MATCH('Internal Budget'!$G$5, 'Reference Tab'!$V$3:$CA$3, 0)) -> 2800 | I35: =IFERROR(IF(Inputs!$B$73="",0,INDEX('Reference Tab'!$V$4:$CA$74,MATCH('Internal Budget'!F35,'Reference Tab'!$U$4:$U$71,0),MATCH('Internal Budget'!$I$5,'Reference Tab'!$V$3:$CA$3,0))),) -> 0 | K35: =IFERROR(IF(Inputs!$B$74="",0,INDEX('Reference Tab'!$V$4:$CA$74,MATCH('Internal Budget'!F35,'Reference Tab'!$U$4:$U$71,0),MATCH('Internal Budget'!$K$5,'Reference Tab'!$V$3:$CA$3,0))),) -> 0 | M35: =IFERROR(IF(Inputs!$B$75="",0,INDEX('Reference Tab'!$V$4:$AY$71,MATCH('Internal Budget'!F35,'Reference Tab'!$U$4:$U$71,0),MATCH('Internal Budget'!$M$5,'Reference Tab'!$V$3:$AY$3,0))),) -> 0 | P35: =G35+($H$4*$H35) -> 2800 | Q35: =P35-G35 -> 0 | R35: =IF(I35=0,0,I35+($J$4*$J35)) -> 0 | S35: =R35-I35 -> 0 | T35: =IF(K35=0,0,K35+($L$4*$L35)) -> 0 | U35: =T35-K35 -> 0 | V35: =IF(M35=0,0,M35+($N$4*$N35)) -> 0 | W35: =V35-M35 -> 0
E36: 3 | F36: Drywall Material | G36: =INDEX('Reference Tab'!$V$4:$CA$74, MATCH('Internal Budget'!F36, 'Reference Tab'!$U$4:$U$71, 0), MATCH('Internal Budget'!$G$5, 'Reference Tab'!$V$3:$CA$3, 0)) -> 3181.59 | I36: =IFERROR(IF(Inputs!$B$73="",0,INDEX('Reference Tab'!$V$4:$CA$74,MATCH('Internal Budget'!F36,'Reference Tab'!$U$4:$U$71,0),MATCH('Internal Budget'!$I$5,'Reference Tab'!$V$3:$CA$3,0))),) -> 0 | K36: =IFERROR(IF(Inputs!$B$74="",0,INDEX('Reference Tab'!$V$4:$CA$74,MATCH('Internal Budget'!F36,'Reference Tab'!$U$4:$U$71,0),MATCH('Internal Budget'!$K$5,'Reference Tab'!$V$3:$CA$3,0))),) -> 0 | M36: =IFERROR(IF(Inputs!$B$75="",0,INDEX('Reference Tab'!$V$4:$AY$71,MATCH('Internal Budget'!F36,'Reference Tab'!$U$4:$U$71,0),MATCH('Internal Budget'!$M$5,'Reference Tab'!$V$3:$AY$3,0))),) -> 0 | P36: =G36+($H$4*$H36) -> 3181.59 | Q36: =P36-G36 -> 0 | R36: =IF(I36=0,0,I36+($J$4*$J36)) -> 0 | S36: =R36-I36 -> 0 | T36: =IF(K36=0,0,K36+($L$4*$L36)) -> 0 | U36: =T36-K36 -> 0 | V36: =IF(M36=0,0,M36+($N$4*$N36)) -> 0 | W36: =V36-M36 -> 0
E37: 3 | F37: Drywall Labor | G37: =INDEX('Reference Tab'!$V$4:$CA$74, MATCH('Internal Budget'!F37, 'Reference Tab'!$U$4:$U$71, 0), MATCH('Internal Budget'!$G$5, 'Reference Tab'!$V$3:$CA$3, 0)) -> 3783.96 | I37: =IFERROR(IF(Inputs!$B$73="",0,INDEX('Reference Tab'!$V$4:$CA$74,MATCH('Internal Budget'!F37,'Reference Tab'!$U$4:$U$71,0),MATCH('Internal Budget'!$I$5,'Reference Tab'!$V$3:$CA$3,0))),) -> 0 | K37: =IFERROR(IF(Inputs!$B$74="",0,INDEX('Reference Tab'!$V$4:$CA$74,MATCH('Internal Budget'!F37,'Reference Tab'!$U$4:$U$71,0),MATCH('Internal Budget'!$K$5,'Reference Tab'!$V$3:$CA$3,0))),) -> 0 | M37: =IFERROR(IF(Inputs!$B$75="",0,INDEX('Reference Tab'!$V$4:$AY$71,MATCH('Internal Budget'!F37,'Reference Tab'!$U$4:$U$71,0),MATCH('Internal Budget'!$M$5,'Reference Tab'!$V$3:$AY$3,0))),) -> 0 | P37: =G37+($H$4*$H37) -> 3783.96 | Q37: =P37-G37 -> 0 | R37: =IF(I37=0,0,I37+($J$4*$J37)) -> 0 | S37: =R37-I37 -> 0 | T37: =IF(K37=0,0,K37+($L$4*$L37)) -> 0 | U37: =T37-K37 -> 0 | V37: =IF(M37=0,0,M37+($N$4*$N37)) -> 0 | W37: =V37-M37 -> 0
E38: 4 | F38: Exterior Paint Labor & Material | G38: =INDEX('Reference Tab'!$V$4:$CA$74, MATCH('Internal Budget'!F38, 'Reference Tab'!$U$4:$U$71, 0), MATCH('Internal Budget'!$G$5, 'Reference Tab'!$V$3:$CA$3, 0)) -> 45 | I38: =IFERROR(IF(Inputs!$B$73="",0,INDEX('Reference Tab'!$V$4:$CA$74,MATCH('Internal Budget'!F38,'Reference Tab'!$U$4:$U$71,0),MATCH('Internal Budget'!$I$5,'Reference Tab'!$V$3:$CA$3,0))),) -> 0 | K38: =IFERROR(IF(Inputs!$B$74="",0,INDEX('Reference Tab'!$V$4:$CA$74,MATCH('Internal Budget'!F38,'Reference Tab'!$U$4:$U$71,0),MATCH('Internal Budget'!$K$5,'Reference Tab'!$V$3:$CA$3,0))),) -> 0 | M38: =IFERROR(IF(Inputs!$B$75="",0,INDEX('Reference Tab'!$V$4:$AY$71,MATCH('Internal Budget'!F38,'Reference Tab'!$U$4:$U$71,0),MATCH('Internal Budget'!$M$5,'Reference Tab'!$V$3:$AY$3,0))),) -> 0 | P38: =G38+($H$4*$H38) -> 45 | Q38: =P38-G38 -> 0 | R38: =IF(I38=0,0,I38+($J$4*$J38)) -> 0 | S38: =R38-I38 -> 0 | T38: =IF(K38=0,0,K38+($L$4*$L38)) -> 0 | U38: =T38-K38 -> 0 | V38: =IF(M38=0,0,M38+($N$4*$N38)) -> 0 | W38: =V38-M38 -> 0
E39: 4 | F39: Interior Paint | G39: =INDEX('Reference Tab'!$V$4:$CA$74, MATCH('Internal Budget'!F39, 'Reference Tab'!$U$4:$U$71, 0), MATCH('Internal Budget'!$G$5, 'Reference Tab'!$V$3:$CA$3, 0)) -> 2786 | I39: =IFERROR(IF(Inputs!$B$73="",0,INDEX('Reference Tab'!$V$4:$CA$74,MATCH('Internal Budget'!F39,'Reference Tab'!$U$4:$U$71,0),MATCH('Internal Budget'!$I$5,'Reference Tab'!$V$3:$CA$3,0))),) -> 0 | K39: =IFERROR(IF(Inputs!$B$74="",0,INDEX('Reference Tab'!$V$4:$CA$74,MATCH('Internal Budget'!F39,'Reference Tab'!$U$4:$U$71,0),MATCH('Internal Budget'!$K$5,'Reference Tab'!$V$3:$CA$3,0))),) -> 0 | M39: =IFERROR(IF(Inputs!$B$75="",0,INDEX('Reference Tab'!$V$4:$AY$71,MATCH('Internal Budget'!F39,'Reference Tab'!$U$4:$U$71,0),MATCH('Internal Budget'!$M$5,'Reference Tab'!$V$3:$AY$3,0))),) -> 0 | P39: =G39+($H$4*$H39) -> 2786 | Q39: =P39-G39 -> 0 | R39: =IF(I39=0,0,I39+($J$4*$J39)) -> 0 | S39: =R39-I39 -> 0 | T39: =IF(K39=0,0,K39+($L$4*$L39)) -> 0 | U39: =T39-K39 -> 0 | V39: =IF(M39=0,0,M39+($N$4*$N39)) -> 0 | W39: =V39-M39 -> 0
E40: 4 | F40: Interior Trim Material | G40: =INDEX('Reference Tab'!$V$4:$CA$74, MATCH('Internal Budget'!F40, 'Reference Tab'!$U$4:$U$71, 0), MATCH('Internal Budget'!$G$5, 'Reference Tab'!$V$3:$CA$3, 0)) -> 0 | I40: =IFERROR(IF(Inputs!$B$73="",0,INDEX('Reference Tab'!$V$4:$CA$74,MATCH('Internal Budget'!F40,'Reference Tab'!$U$4:$U$71,0),MATCH('Internal Budget'!$I$5,'Reference Tab'!$V$3:$CA$3,0))),) -> 0 | K40: =IFERROR(IF(Inputs!$B$74="",0,INDEX('Reference Tab'!$V$4:$CA$74,MATCH('Internal Budget'!F40,'Reference Tab'!$U$4:$U$71,0),MATCH('Internal Budget'!$K$5,'Reference Tab'!$V$3:$CA$3,0))),) -> 0 | M40: =IFERROR(IF(Inputs!$B$75="",0,INDEX('Reference Tab'!$V$4:$AY$71,MATCH('Internal Budget'!F40,'Reference Tab'!$U$4:$U$71,0),MATCH('Internal Budget'!$M$5,'Reference Tab'!$V$3:$AY$3,0))),) -> 0 | P40: =G40+($H$4*$H40) -> 0 | Q40: =P40-G40 -> 0 | R40: =IF(I40=0,0,I40+($J$4*$J40)) -> 0 | S40: =R40-I40 -> 0 | T40: =IF(K40=0,0,K40+($L$4*$L40)) -> 0 | U40: =T40-K40 -> 0 | V40: =IF(M40=0,0,M40+($N$4*$N40)) -> 0 | W40: =V40-M40 -> 0
E41: 4 | F41: Interior Trim Turnkey | G41: =INDEX('Reference Tab'!$V$4:$CA$74, MATCH('Internal Budget'!F41, 'Reference Tab'!$U$4:$U$71, 0), MATCH('Internal Budget'!$G$5, 'Reference Tab'!$V$3:$CA$3, 0)) -> 4068 | I41: =IFERROR(IF(Inputs!$B$73="",0,INDEX('Reference Tab'!$V$4:$CA$74,MATCH('Internal Budget'!F41,'Reference Tab'!$U$4:$U$71,0),MATCH('Internal Budget'!$I$5,'Reference Tab'!$V$3:$CA$3,0))),) -> 0 | K41: =IFERROR(IF(Inputs!$B$74="",0,INDEX('Reference Tab'!$V$4:$CA$74,MATCH('Internal Budget'!F41,'Reference Tab'!$U$4:$U$71,0),MATCH('Internal Budget'!$K$5,'Reference Tab'!$V$3:$CA$3,0))),) -> 0 | M41: =IFERROR(IF(Inputs!$B$75="",0,INDEX('Reference Tab'!$V$4:$AY$71,MATCH('Internal Budget'!F41,'Reference Tab'!$U$4:$U$71,0),MATCH('Internal Budget'!$M$5,'Reference Tab'!$V$3:$AY$3,0))),) -> 0 | P41: =G41+($H$4*$H41) -> 4068 | Q41: =P41-G41 -> 0 | R41: =IF(I41=0,0,I41+($J$4*$J41)) -> 0 | S41: =R41-I41 -> 0 | T41: =IF(K41=0,0,K41+($L$4*$L41)) -> 0 | U41: =T41-K41 -> 0 | V41: =IF(M41=0,0,M41+($N$4*$N41)) -> 0 | W41: =V41-M41 -> 0
E42: 5 | F42: Door Hardware | G42: =INDEX('Reference Tab'!$V$4:$CA$74, MATCH('Internal Budget'!F42, 'Reference Tab'!$U$4:$U$71, 0), MATCH('Internal Budget'!$G$5, 'Reference Tab'!$V$3:$CA$3, 0)) -> 451.21 | I42: =IFERROR(IF(Inputs!$B$73="",0,INDEX('Reference Tab'!$V$4:$CA$74,MATCH('Internal Budget'!F42,'Reference Tab'!$U$4:$U$71,0),MATCH('Internal Budget'!$I$5,'Reference Tab'!$V$3:$CA$3,0))),) -> 0 | K42: =IFERROR(IF(Inputs!$B$74="",0,INDEX('Reference Tab'!$V$4:$CA$74,MATCH('Internal Budget'!F42,'Reference Tab'!$U$4:$U$71,0),MATCH('Internal Budget'!$K$5,'Reference Tab'!$V$3:$CA$3,0))),) -> 0 | M42: =IFERROR(IF(Inputs!$B$75="",0,INDEX('Reference Tab'!$V$4:$AY$71,MATCH('Internal Budget'!F42,'Reference Tab'!$U$4:$U$71,0),MATCH('Internal Budget'!$M$5,'Reference Tab'!$V$3:$AY$3,0))),) -> 0 | P42: =G42+($H$4*$H42) -> 451.21 | Q42: =P42-G42 -> 0 | R42: =IF(I42=0,0,I42+($J$4*$J42)) -> 0 | S42: =R42-I42 -> 0 | T42: =IF(K42=0,0,K42+($L$4*$L42)) -> 0 | U42: =T42-K42 -> 0 | V42: =IF(M42=0,0,M42+($N$4*$N42)) -> 0 | W42: =V42-M42 -> 0
E43: 5 | F43: Shelving | G43: =INDEX('Reference Tab'!$V$4:$CA$74, MATCH('Internal Budget'!F43, 'Reference Tab'!$U$4:$U$71, 0), MATCH('Internal Budget'!$G$5, 'Reference Tab'!$V$3:$CA$3, 0)) -> 259.2 | I43: =IFERROR(IF(Inputs!$B$73="",0,INDEX('Reference Tab'!$V$4:$CA$74,MATCH('Internal Budget'!F43,'Reference Tab'!$U$4:$U$71,0),MATCH('Internal Budget'!$I$5,'Reference Tab'!$V$3:$CA$3,0))),) -> 0 | K43: =IFERROR(IF(Inputs!$B$74="",0,INDEX('Reference Tab'!$V$4:$CA$74,MATCH('Internal Budget'!F43,'Reference Tab'!$U$4:$U$71,0),MATCH('Internal Budget'!$K$5,'Reference Tab'!$V$3:$CA$3,0))),) -> 0 | M43: =IFERROR(IF(Inputs!$B$75="",0,INDEX('Reference Tab'!$V$4:$AY$71,MATCH('Internal Budget'!F43,'Reference Tab'!$U$4:$U$71,0),MATCH('Internal Budget'!$M$5,'Reference Tab'!$V$3:$AY$3,0))),) -> 0 | P43: =G43+($H$4*$H43) -> 259.2 | Q43: =P43-G43 -> 0 | R43: =IF(I43=0,0,I43+($J$4*$J43)) -> 0 | S43: =R43-I43 -> 0 | T43: =IF(K43=0,0,K43+($L$4*$L43)) -> 0 | U43: =T43-K43 -> 0 | V43: =IF(M43=0,0,M43+($N$4*$N43)) -> 0 | W43: =V43-M43 -> 0
E44: 4 | F44: Interior Trim Labor | G44: =INDEX('Reference Tab'!$V$4:$CA$74, MATCH('Internal Budget'!F44, 'Reference Tab'!$U$4:$U$71, 0), MATCH('Internal Budget'!$G$5, 'Reference Tab'!$V$3:$CA$3, 0)) -> 0 | I44: =IFERROR(IF(Inputs!$B$73="",0,INDEX('Reference Tab'!$V$4:$CA$74,MATCH('Internal Budget'!F44,'Reference Tab'!$U$4:$U$71,0),MATCH('Internal Budget'!$I$5,'Reference Tab'!$V$3:$CA$3,0))),) -> 0 | K44: =IFERROR(IF(Inputs!$B$74="",0,INDEX('Reference Tab'!$V$4:$CA$74,MATCH('Internal Budget'!F44,'Reference Tab'!$U$4:$U$71,0),MATCH('Internal Budget'!$K$5,'Reference Tab'!$V$3:$CA$3,0))),) -> 0 | M44: =IFERROR(IF(Inputs!$B$75="",0,INDEX('Reference Tab'!$V$4:$AY$71,MATCH('Internal Budget'!F44,'Reference Tab'!$U$4:$U$71,0),MATCH('Internal Budget'!$M$5,'Reference Tab'!$V$3:$AY$3,0))),) -> 0 | P44: =G44+($H$4*$H44) -> 0 | Q44: =P44-G44 -> 0 | R44: =IF(I44=0,0,I44+($J$4*$J44)) -> 0 | S44: =R44-I44 -> 0 | T44: =IF(K44=0,0,K44+($L$4*$L44)) -> 0 | U44: =T44-K44 -> 0 | V44: =IF(M44=0,0,M44+($N$4*$N44)) -> 0 | W44: =V44-M44 -> 0
... E57: 1 | F57: Gutters | G57: =INDEX('Reference Tab'!$V$4:$CA$74, MATCH('Internal Budget'!F57, 'Reference Tab'!$U$4:$U$71, 0), MATCH('Internal Budget'!$G$5, 'Reference Tab'!$V$3:$CA$3, 0)) -> 920 | I57: =IFERROR(IF(Inputs!$B$73="",0,INDEX('Reference Tab'!$V$4:$CA$74,MATCH('Internal Budget'!F57,'Reference Tab'!$U$4:$U$71,0),MATCH('Internal Budget'!$I$5,'Reference Tab'!$V$3:$CA$3,0))),) -> 0 | K57: =IFERROR(IF(Inputs!$B$74="",0,INDEX('Reference Tab'!$V$4:$CA$74,MATCH('Internal Budget'!F57,'Reference Tab'!$U$4:$U$71,0),MATCH('Internal Budget'!$K$5,'Reference Tab'!$V$3:$CA$3,0))),) -> 0 | M57: =IFERROR(IF(Inputs!$B$75="",0,INDEX('Reference Tab'!$V$4:$AY$71,MATCH('Internal Budget'!F57,'Reference Tab'!$U$4:$U$71,0),MATCH('Internal Budget'!$M$5,'Reference Tab'!$V$3:$AY$3,0))),) -> 0 | P57: =G57+($H$4*$H57) -> 920 | Q57: =P57-G57 -> 0 | R57: =IF(I57=0,0,I57+($J$4*$J57)) -> 0 | S57: =R57-I57 -> 0 | T57: =IF(K57=0,0,K57+($L$4*$L57)) -> 0 | U57: =T57-K57 -> 0 | V57: =IF(M57=0,0,M57+($N$4*$N57)) -> 0 | W57: =V57-M57 -> 0
E58: 5 | F58: QI Inspection | G58: =INDEX('Reference Tab'!$V$4:$CA$74, MATCH('Internal Budget'!F58, 'Reference Tab'!$U$4:$U$71, 0), MATCH('Internal Budget'!$G$5, 'Reference Tab'!$V$3:$CA$3, 0)) -> 310 | I58: =IFERROR(IF(Inputs!$B$73="",0,INDEX('Reference Tab'!$V$4:$CA$74,MATCH('Internal Budget'!F58,'Reference Tab'!$U$4:$U$71,0),MATCH('Internal Budget'!$I$5,'Reference Tab'!$V$3:$CA$3,0))),) -> 0 | K58: =IFERROR(IF(Inputs!$B$74="",0,INDEX('Reference Tab'!$V$4:$CA$74,MATCH('Internal Budget'!F58,'Reference Tab'!$U$4:$U$71,0),MATCH('Internal Budget'!$K$5,'Reference Tab'!$V$3:$CA$3,0))),) -> 0 | M58: =IFERROR(IF(Inputs!$B$75="",0,INDEX('Reference Tab'!$V$4:$AY$71,MATCH('Internal Budget'!F58,'Reference Tab'!$U$4:$U$71,0),MATCH('Internal Budget'!$M$5,'Reference Tab'!$V$3:$AY$3,0))),) -> 0 | P58: =G58+($H$4*$H58) -> 310 | R58: =IF(I58=0,0,I58+($J$4*$J58)) -> 0 | T58: =IF(K58=0,0,K58+($L$4*$L58)) -> 0 | V58: =IF(M58=0,0,M58+($N$4*$N58)) -> 0
E59: 5 | F59: Deck | G59: =INDEX('Reference Tab'!$V$4:$CA$74, MATCH('Internal Budget'!F59, 'Reference Tab'!$U$4:$U$71, 0), MATCH('Internal Budget'!$G$5, 'Reference Tab'!$V$3:$CA$3, 0)) -> 0 | I59: =IFERROR(IF(Inputs!$B$73="",0,INDEX('Reference Tab'!$V$4:$CA$74,MATCH('Internal Budget'!F59,'Reference Tab'!$U$4:$U$71,0),MATCH('Internal Budget'!$I$5,'Reference Tab'!$V$3:$CA$3,0))),) -> 0 | K59: =IFERROR(IF(Inputs!$B$74="",0,INDEX('Reference Tab'!$V$4:$CA$74,MATCH('Internal Budget'!F59,'Reference Tab'!$U$4:$U$71,0),MATCH('Internal Budget'!$K$5,'Reference Tab'!$V$3:$CA$3,0))),) -> 0 | M59: =IFERROR(IF(Inputs!$B$75="",0,INDEX('Reference Tab'!$V$4:$AY$71,MATCH('Internal Budget'!F59,'Reference Tab'!$U$4:$U$71,0),MATCH('Internal Budget'!$M$5,'Reference Tab'!$V$3:$AY$3,0))),) -> 0 | P59: =G59+($H$4*$H59) -> 0 | R59: =IF(I59=0,0,I59+($J$4*$J59)) -> 0 | T59: =IF(K59=0,0,K59+($L$4*$L59)) -> 0 | V59: =IF(M59=0,0,M59+($N$4*$N59)) -> 0
E60: 5 | F60: Mailbox | G60: =INDEX('Reference Tab'!$V$4:$CA$74, MATCH('Internal Budget'!F60, 'Reference Tab'!$U$4:$U$71, 0), MATCH('Internal Budget'!$G$5, 'Reference Tab'!$V$3:$CA$3, 0)) -> 90 | I60: =IFERROR(IF(Inputs!$B$73="",0,INDEX('Reference Tab'!$V$4:$CA$74,MATCH('Internal Budget'!F60,'Reference Tab'!$U$4:$U$71,0),MATCH('Internal Budget'!$I$5,'Reference Tab'!$V$3:$CA$3,0))),) -> 0 | K60: =IFERROR(IF(Inputs!$B$74="",0,INDEX('Reference Tab'!$V$4:$CA$74,MATCH('Internal Budget'!F60,'Reference Tab'!$U$4:$U$71,0),MATCH('Internal Budget'!$K$5,'Reference Tab'!$V$3:$CA$3,0))),) -> 0 | M60: =IFERROR(IF(Inputs!$B$75="",0,INDEX('Reference Tab'!$V$4:$AY$71,MATCH('Internal Budget'!F60,'Reference Tab'!$U$4:$U$71,0),MATCH('Internal Budget'!$M$5,'Reference Tab'!$V$3:$AY$3,0))),) -> 0 | P60: =G60+($H$4*$H60) -> 90 | Q60: =P60-G60 -> 0 | R60: =IF(I60=0,0,I60+($J$4*$J60)) -> 0 | S60: =R60-I60 -> 0 | T60: =IF(K60=0,0,K60+($L$4*$L60)) -> 0 | U60: =T60-K60 -> 0 | V60: =IF(M60=0,0,M60+($N$4*$N60)) -> 0 | W60: =V60-M60 -> 0
E61: 5 | F61: Pressure Wash | G61: =INDEX('Reference Tab'!$V$4:$CA$74, MATCH('Internal Budget'!F61, 'Reference Tab'!$U$4:$U$71, 0), MATCH('Internal Budget'!$G$5, 'Reference Tab'!$V$3:$CA$3, 0)) -> 270 | I61: =IFERROR(IF(Inputs!$B$73="",0,INDEX('Reference Tab'!$V$4:$CA$74,MATCH('Internal Budget'!F61,'Reference Tab'!$U$4:$U$71,0),MATCH('Internal Budget'!$I$5,'Reference Tab'!$V$3:$CA$3,0))),) -> 0 | K61: =IFERROR(IF(Inputs!$B$74="",0,INDEX('Reference Tab'!$V$4:$CA$74,MATCH('Internal Budget'!F61,'Reference Tab'!$U$4:$U$71,0),MATCH('Internal Budget'!$K$5,'Reference Tab'!$V$3:$CA$3,0))),) -> 0 | M61: =IFERROR(IF(Inputs!$B$75="",0,INDEX('Reference Tab'!$V$4:$AY$71,MATCH('Internal Budget'!F61,'Reference Tab'!$U$4:$U$71,0),MATCH('Internal Budget'!$M$5,'Reference Tab'!$V$3:$AY$3,0))),) -> 0 | P61: =G61+($H$4*$H61) -> 270 | Q61: =P61-G61 -> 0 | R61: =IF(I61=0,0,I61+($J$4*$J61)) -> 0 | S61: =R61-I61 -> 0 | T61: =IF(K61=0,0,K61+($L$4*$L61)) -> 0 | U61: =T61-K61 -> 0 | V61: =IF(M61=0,0,M61+($N$4*$N61)) -> 0 | W61: =V61-M61 -> 0
A62: Plumbing Turnkey | B62: 0.3 | E62: 1 | F62: Foundation | G62: =INDEX('Reference Tab'!$V$4:$CA$74, MATCH('Internal Budget'!F62, 'Reference Tab'!$U$4:$U$71, 0), MATCH('Internal Budget'!$G$5, 'Reference Tab'!$V$3:$CA$3, 0))+INDEX('Reference Tab'!$V$4:$CA$74, MATCH(A62, 'Reference Tab'!$U$4:$U$71, 0), MATCH('Internal Budget'!$G$5, 'Reference Tab'!$V$3:$CA$3, 0))*B62 -> 8674.5 | H62: 1 | I62: =IFERROR(IF(Inputs!$B$73="",0,INDEX('Reference Tab'!$V$4:$CA$74,MATCH('Internal Budget'!F62,'Reference Tab'!$U$4:$U$71,0),MATCH('Internal Budget'!$I$5,'Reference Tab'!$V$3:$CA$3,0))),) -> 0 | J62: 1 | K62: =IFERROR(IF(Inputs!$B$74="",0,INDEX('Reference Tab'!$V$4:$CA$74,MATCH('Internal Budget'!F62,'Reference Tab'!$U$4:$U$71,0),MATCH('Internal Budget'!$K$5,'Reference Tab'!$V$3:$CA$3,0))),) -> 0 | L62: 1 | M62: =IFERROR(IF(Inputs!$B$75="",0,INDEX('Reference Tab'!$V$4:$AY$71,MATCH('Internal Budget'!F62,'Reference Tab'!$U$4:$U$71,0),MATCH('Internal Budget'!$M$5,'Reference Tab'!$V$3:$AY$3,0))),) -> 0 | N62: 1 | P62: =G62+($H$4*$H62) -> 35418.202 | Q62: =P62-G62 -> 26743.702 | R62: =IF(I62=0,0,I62+($J$4*$J62)) -> 0 | S62: =R62-I62 -> 0 | T62: =IF(K62=0,0,K62+($L$4*$L62)) -> 0 | U62: =T62-K62 -> 0 | V62: =IF(M62=0,0,M62+($N$4*$N62)) -> 0 | W62: =V62-M62 -> 0
F63: Sticks & Bricks Subtotal | G63: =SUBTOTAL(9,G6:G62) -> 106047.85 | I63: =SUBTOTAL(9,I6:I62) -> 0 | K63: =SUBTOTAL(9,K6:K62) -> 0 | M63: =SUBTOTAL(9,M6:M62) -> 0 | P63: =SUM(P6:P62) -> 132791.55 | R63: =SUM(R6:R62) -> 0 | T63: =SUM(T6:T62) -> 0 | V63: =SUM(V6:V62) -> 0
E64: 1 | F64: Flatwork | G64: =Inputs!$D$55 -> 0 | I64: =IF(ISBLANK(Inputs!$B$73),0,Inputs!$D$55) -> 0 | K64: =IF(ISBLANK(Inputs!$B$74),0,Inputs!$D$55) -> 0 | M64: =IF(ISBLANK(Inputs!$B$75),0,Inputs!$D$55) -> 0 | P64: =G64 -> 0 | R64: =IF(I64=0,0,I64) -> 0 | T64: =IF(K64=0,0,K64) -> 0 | V64: =IF(M64=0,0,M64) -> 0
E65: 1 | F65: Survey | G65: =Inputs!$D$49 -> 0 | I65: =IF(ISBLANK(Inputs!$B$73),0,Inputs!$D$49) -> 0 | K65: =IF(ISBLANK(Inputs!$B$74),0,Inputs!$D$49) -> 0 | M65: =IF(ISBLANK(Inputs!$B$75),0,Inputs!$D$49) -> 0 | P65: =G65 -> 0 | R65: =IF(I65=0,0,I65) -> 0 | T65: =IF(K65=0,0,K65) -> 0 | V65: =IF(M65=0,0,M65) -> 0
E66: 1 | F66: Stake House | G66: =Inputs!$D$50 -> 0 | I66: =IF(ISBLANK(Inputs!$B$73),0,Inputs!$D$50) -> 0 | K66: =IF(ISBLANK(Inputs!$B$74),0,Inputs!$D$50) -> 0 | M66: =IF(ISBLANK(Inputs!$B$75),0,Inputs!$D$50) -> 0 | P66: =G66 -> 0 | R66: =IF(I66=0,0,I66) -> 0 | T66: =IF(K66=0,0,K66) -> 0 | V66: =IF(M66=0,0,M66) -> 0
E67: 1 | F67: Grading/Lot Clear/Hauling | G67: =Inputs!$D$51 -> 1700 | I67: =IF(ISBLANK(Inputs!$B$73),0,Inputs!$D$51) -> 0 | K67: =IF(ISBLANK(Inputs!$B$74),0,Inputs!$D$51) -> 0 | M67: =IF(ISBLANK(Inputs!$B$75),0,Inputs!$D$51) -> 0 | P67: =G67 -> 1700 | R67: =IF(I67=0,0,I67) -> 0 | T67: =IF(K67=0,0,K67) -> 0 | V67: =IF(M67=0,0,M67) -> 0
E68: 1 | F68: Silt Fence | G68: =Inputs!$D$52 -> 0 | I68: =IF(ISBLANK(Inputs!$B$73),0,Inputs!$D$52) -> 0 | K68: =IF(ISBLANK(Inputs!$B$74),0,Inputs!$D$52) -> 0 | M68: =IF(ISBLANK(Inputs!$B$75),0,Inputs!$D$52) -> 0 | P68: =G68 -> 0 | R68: =IF(I68=0,0,I68) -> 0 | T68: =IF(K68=0,0,K68) -> 0 | V68: =IF(M68=0,0,M68) -> 0
E69: 1 | F69: Temp Drive | G69: =Inputs!$D$53 -> 0 | I69: =IF(ISBLANK(Inputs!$B$73),0,Inputs!$D$53) -> 0 | K69: =IF(ISBLANK(Inputs!$B$74),0,Inputs!$D$53) -> 0 | M69: =IF(ISBLANK(Inputs!$B$75),0,Inputs!$D$53) -> 0 | P69: =G69 -> 0 | R69: =IF(I69=0,0,I69) -> 0 | T69: =IF(K69=0,0,K69) -> 0 | V69: =IF(M69=0,0,M69) -> 0
E70: 1 | F70: Landscaping | G70: =Inputs!$D$54 -> 2500 | I70: =IF(ISBLANK(Inputs!$B$73),0,Inputs!$D$54) -> 0 | K70: =IF(ISBLANK(Inputs!$B$74),0,Inputs!$D$54) -> 0 | M70: =IF(ISBLANK(Inputs!$B$75),0,Inputs!$D$54) -> 0 | P70: =G70 -> 2500 | R70: =IF(I70=0,0,I70) -> 0 | T70: =IF(K70=0,0,K70) -> 0 | V70: =IF(M70=0,0,M70) -> 0
E71: 1 | F71: Privacy Fence | G71: =Inputs!$D$56 -> 8000 | I71: =IF(Inputs!$B$73="",0,Inputs!D56) -> 0 | K71: =IF(Inputs!$B$74="",0,Inputs!D56) -> 0 | M71: =IF(Inputs!$B$75="",0,Inputs!D56) -> 0 | P71: =G71 -> 8000 | R71: =I71 -> 0 | T71: =K71 -> 0 | V71: =M71 -> 0
E72: 1 | F72: Mscellaneous | G72: =Inputs!$D$57 -> 0 | I72: =IF(ISBLANK(Inputs!$B$73),0,Inputs!$D$57) -> 0 | K72: =IF(ISBLANK(Inputs!$B$74),0,Inputs!$D$57) -> 0 | M72: =IF(ISBLANK(Inputs!$B$75),0,Inputs!$D$57) -> 0 | P72: =G72 -> 0 | R72: =IF(I72=0,0,I72) -> 0 | T72: =IF(K72=0,0,K72) -> 0 | V72: =IF(M72=0,0,M72) -> 0
F73: Site Specific Subtotal | G73: =SUBTOTAL(9,G64:G72) -> 12200 | I73: =SUBTOTAL(9,I64:I72) -> 0 | K73: =SUBTOTAL(9,K64:K72) -> 0 | M73: =SUBTOTAL(9,M64:M72) -> 0 | P73: =G73 -> 12200 | R73: =I73 -> 0 | T73: =K73 -> 0 | V73: =M73 -> 0 | X73: =G73=Inputs!D58 -> TRUE | Y73: =R73*4 -> 0
E74: 1 | F74: Building Permits | G74: =Inputs!$D61 -> 2050 | I74: =IF(ISBLANK(Inputs!$B$73),0,Inputs!D61) -> 0 | K74: =IF(ISBLANK(Inputs!$B$74),0,Inputs!D61) -> 0 | M74: =IF(ISBLANK(Inputs!$B$75),0,Inputs!D61) -> 0 | P74: =G74 -> 2050 | R74: =IF(I74=0,0,I74) -> 0 | T74: =IF(K74=0,0,K74) -> 0 | V74: =M74 -> 0
E75: 1 | F75: Sewer Septic Permit | G75: =Inputs!$E65 -> 1500 | I75: =IF(ISBLANK(Inputs!$B$73),0,Inputs!E65) -> 0 | K75: =IF(ISBLANK(Inputs!$B$74),0,Inputs!E65) -> 0 | M75: =IF(ISBLANK(Inputs!$B$75),0,Inputs!E65) -> 0 | P75: =G75 -> 1500 | R75: =IF(I75=0,0,I75) -> 0 | T75: =IF(K75=0,0,K75) -> 0 | V75: =M75 -> 0
E76: 1 | F76: Water Meter | G76: =Inputs!$E64 -> 6000 | I76: =IF(ISBLANK(Inputs!$B$73),0,Inputs!E64) -> 0 | K76: =IF(ISBLANK(Inputs!$B$74),0,Inputs!E64) -> 0 | M76: =IF(ISBLANK(Inputs!$B$75),0,Inputs!E64) -> 0 | P76: =G76 -> 6000 | R76: =IF(I76=0,0,I76) -> 0 | T76: =IF(K76=0,0,K76) -> 0 | V76: =M76 -> 0
E77: 1 | F77: Engineering | G77: =Inputs!$D62 -> 1000 | I77: =IF(ISBLANK(Inputs!$B$73),0,Inputs!D62) -> 0 | K77: =IF(ISBLANK(Inputs!$B$74),0,Inputs!D62) -> 0 | M77: =IF(ISBLANK(Inputs!$B$75),0,Inputs!D62) -> 0 | P77: =G77 -> 1000 | R77: =IF(I77=0,0,I77) -> 0 | T77: =IF(K77=0,0,K77) -> 0 | V77: =M77 -> 0
F78: Soft Costs from Budget Subtotal | G78: =SUBTOTAL(9,G74:G77) -> 10550 | I78: =SUBTOTAL(9,I74:I77) -> 0 | K78: =SUBTOTAL(9,K74:K77) -> 0 | M78: =SUBTOTAL(9,M74:M77) -> 0 | P78: =G78 -> 10550 | R78: =I78 -> 0 | T78: =K78 -> 0 | V78: =M78 -> 0
E79: 1 | F79: Annual Insurance | G79: =Inputs!$E$66 -> 333.33333 | I79: =IF(ISBLANK(Inputs!$B$73),0,Inputs!$E$66) -> 0 | K79: =IF(ISBLANK(Inputs!$B$74),0,Inputs!$E$66) -> 0 | M79: =IF(ISBLANK(Inputs!$B$75),0,Inputs!$E$66) -> 0 | P79: =G79 -> 333.33333 | R79: =IF(I79=0,0,I79) -> 0 | T79: =IF(K79=0,0,K79) -> 0 | V79: =M79 -> 0
E80: 1 | F80: Annual Property Taxes | G80: =Inputs!$E$67 -> 333.33333 | I80: =IF(ISBLANK(Inputs!$B$73),0,Inputs!$E$66) -> 0 | K80: =IF(ISBLANK(Inputs!$B$74),0,Inputs!$E$66) -> 0 | M80: =IF(ISBLANK(Inputs!$B$75),0,Inputs!$E$66) -> 0 | P80: =G80 -> 333.33333 | R80: =IF(I80=0,0,I80) -> 0 | T80: =IF(K80=0,0,K80) -> 0 | V80: =M80 -> 0
E81: 1 | F81: Demolition | G81: =Inputs!$D48 -> 0 | I81: =IF(ISBLANK(Inputs!B73),0,Inputs!$D48) -> 0 | K81: =IF(ISBLANK(Inputs!B74),0,Inputs!$D48) -> 0 | M81: =IF(ISBLANK(Inputs!B75),0,Inputs!$D48) -> 0 | P81: =G81 -> 0 | R81: =IF(I81=0,0,I81) -> 0 | T81: =IF(K81=0,0,K81) -> 0 | V81: =M81 -> 0
E82: 1 | F82: Draw Fees | G82: =Inputs!$D63 -> 0 | I82: =IF(ISBLANK(Inputs!B74),0,Inputs!$D63) -> 0 | K82: =IF(ISBLANK(Inputs!D75),0,Inputs!$D63) -> 0 | M82: =IF(ISBLANK(Inputs!B75),0,Inputs!$D63) -> 0 | P82: =G82 -> 0 | R82: =IF(I82=0,0,I82) -> 0 | T82: =IF(K82=0,0,K82) -> 0 | V82: =M82 -> 0
F83: Soft Costs + Insurance & Tax Subtotal | G83: =SUM(G79:G82)+G78 -> 11216.667 | I83: =SUM(I79:I82)+I78 -> 0 | K83: =SUM(K79:K82)+K78 -> 0 | M83: =SUM(M79:M82)+M78 -> 0 | P83: =G83 -> 11216.667 | R83: =I83 -> 0 | T83: =K83 -> 0 | V83: =M83 -> 0 | X83: =G83=Inputs!O24/buildcount -> TRUE | Y83: =R83*4 -> 0
E84: 4 | F84: Upgrade | G84: =Inputs!G79 -> 0 | I84: =Inputs!G80 -> 0 | K84: =Inputs!G81 -> 0 | M84: =Inputs!G82 -> 0 | P84: =G84 -> 0 | R84: =IF(I84=0,0,I84) -> 0 | T84: =IF(K84=0,0,K84) -> 0 | V84: =M84 -> 0
E85: 1 | F85: Crawl Space | G85: =Inputs!H79 -> 0 | I85: =Inputs!H80 -> 0 | K85: =Inputs!H81 -> 0 | M85: =Inputs!H82 -> 0 | P85: =G85 -> 0 | R85: =IF(I85=0,0,I85) -> 0 | T85: =IF(K85=0,0,K85) -> 0 | V85: =M85 -> 0
E86: 1 | F86: Detached Garage | G86: =Inputs!I79 -> 0 | I86: =Inputs!I80 -> 0 | K86: =Inputs!I81 -> 0 | M86: =Inputs!I82 -> 0 | P86: =G86 -> 0 | R86: =IF(I86=0,0,I86) -> 0 | T86: =IF(K86=0,0,K86) -> 0 | V86: =M86 -> 0
F87: Miscellaneous Subtotal | G87: =SUM(G84:G86) -> 0 | I87: =SUM(I84:I86) -> 0 | K87: =SUM(K84:K86) -> 0 | M87: =SUM(M84:M86) -> 0 | P87: =G87 -> 0 | R87: =I87 -> 0 | T87: =K87 -> 0 | V87: =M87 -> 0
F88: Site Work | G88: =SUM(G79:G82)+G111 -> 7516.6667 | I88: =SUM(I79:I82)+I111 -> 0 | K88: =SUM(K79:K82)+K111 -> 0 | M88: =SUM(M79:M82)+M111 -> 0 | P88: =G88+($H$4*$H88) -> 7516.6667 | R88: =I88+($J$4*$J88) -> 0 | T88: =K88+($L$4*$L88) -> 0 | V88: =M88+($N$4*$N88) -> 0
F89: Total | G89: =G63+G73+G83+G87 -> 129464.52 | I89: =I63+I73+I83+I87 -> 0 | K89: =K63+K73+K83+K87 -> 0 | M89: =M63+M73+M83+M87 -> 0 | P89: =G89+($H$4*$H5) -> 156208.22 | Q89: =SUM(Q6:Q80) -> 26743.702 | R89: =I89+($J$4*$J5) -> 0 | S89: =SUM(S6:S80) -> 0 | T89: =K89+($L$4*$L5) -> 0 | U89: =SUM(U6:U80) -> 0 | V89: =M89+($N$4*$N5) -> 0 | W89: =SUM(W6:W80) -> 0
O90: Check | P90: =P63+P73+P83+P87 -> 156208.22 | R90: =R63+R73+R83+R87 -> 0 | T90: =T63+T73+T83+T87 -> 0 | V90: =V63+V73+V83+V87 -> 0
P91: =P90=P89 -> TRUE | R91: =R90=R89 -> TRUE | T91: =T90=T89 -> TRUE | V91: =V90=V89 -> TRUE
P92: =P90+P111 -> 163058.22 | R92: =R90+R111 -> 0 | T92: =T90+T111 -> 0 | V92: =V90+V111 -> 0
F93: Acquisitions Due Dilligence & Horizontal Costs | P93: ='SOV - External'!K11 -> 163058.22 | R93: ='SOV - External'!L11 -> 0 | T93: ='SOV - External'!M11 -> 0 | V93: ='SOV - External'!N11 -> 0
F94: Subdivision Costs? | G94: =Inputs!$D$28 -> 0 | I94: =IF(Inputs!$B$73="",0,Inputs!D28) -> 0 | K94: =IF(Inputs!$B$74="",0,Inputs!D28) -> 0 | M94: =IF(Inputs!$B$75="",0,Inputs!D28) -> 0 | P94: =G94 -> 0 | R94: =I94 -> 0 | T94: =K94 -> 0 | V94: =M94 -> 0
