Workbook

Sheet Summary
A1: Red Cedar Model Comparison
A3: County | B3: None
A5: Model | B5: SFR/TH | C5: Heated SF | D5: Bed | E5: Bath | F5: Garage | G5: Unheated SF | H5: Floors | I5: Total $/ Heated SF | J5: Soft Cost | K5: Site Specific | L5: Sticks & Bricks | M5: S&B $/ Heated SF | N5: Total | O5: Classic | P5: Elegance | Q5: Harmony | R5: Pad Size | S5: Floorplan | T5: Notes
A6: Acacia | B6: SFH | C6: 2236 | D6: 4 | E6: 3 | F6: 2 | G6: 413 | H6: 1.5 | I6: =N6/C6 -> 79.846668 | J6: =IFERROR(_xlfn.XLOOKUP(A6,'MODEL SUMMARY'!$B$3:$AL$3,'MODEL SUMMARY'!$B$71:$AL$71)+_xlfn.XLOOKUP($B$3,'Water & Sewer Data'!$C:$C,'Water & Sewer Data'!$K:$K),"") -> 2650 | K6: =IFERROR(_xlfn.XLOOKUP(A6,'MODEL SUMMARY'!$B$3:$AL$3,'MODEL SUMMARY'!$B$66:$AL$66),"") -> 10875 | L6: =IFERROR(_xlfn.XLOOKUP(A6,'MODEL SUMMARY'!$B$3:$AL$3,'MODEL SUMMARY'!$B$58:$AL$58),"") -> 165012.15 | M6: =L6/C6 -> 73.79792 | N6: =SUM(J6:L6) -> 178537.15 | O6: 4200 | P6: 10000 | Q6: TBD | R6: 39/54 | T6: Standard covered back porch | U6: =LEFT(FIND("/",R6)
A7: Aspen 2-Story | B7: SFH | C7: 1788 | D7: 3 | E7: 2.5 | F7: 2 | G7: 400 | H7: 2 | I7: =N7/C7 -> 85.534972 | J7: =IFERROR(_xlfn.XLOOKUP(A7,'MODEL SUMMARY'!$B$3:$AL$3,'MODEL SUMMARY'!$B$71:$AL$71)+_xlfn.XLOOKUP($B$3,'Water & Sewer Data'!$C:$C,'Water & Sewer Data'!$K:$K),"") -> 2650 | K7: =IFERROR(_xlfn.XLOOKUP(A7,'MODEL SUMMARY'!$B$3:$AL$3,'MODEL SUMMARY'!$B$66:$AL$66),"") -> 10875 | L7: =IFERROR(_xlfn.XLOOKUP(A7,'MODEL SUMMARY'!$B$3:$AL$3,'MODEL SUMMARY'!$B$58:$AL$58),"") -> 139411.53 | M7: =L7/C7 -> 77.970654 | N7: =SUM(J7:L7) -> 152936.53 | O7: 4750 | P7: 9600 | Q7: TBD | R7: 24-33 | AA7: Last Updated 12.14.2024
A8: Atlas | B8: SFH | C8: 1554 | D8: 3 | E8: 2.5 | F8: 0 | G8: 0 | H8: 2 | I8: =N8/C8 -> 81.918745 | J8: =IFERROR(_xlfn.XLOOKUP(A8,'MODEL SUMMARY'!$B$3:$AL$3,'MODEL SUMMARY'!$B$71:$AL$71)+_xlfn.XLOOKUP($B$3,'Water & Sewer Data'!$C:$C,'Water & Sewer Data'!$K:$K),"") -> 2650 | K8: =IFERROR(_xlfn.XLOOKUP(A8,'MODEL SUMMARY'!$B$3:$AL$3,'MODEL SUMMARY'!$B$66:$AL$66),"") -> 10875 | L8: =IFERROR(_xlfn.XLOOKUP(A8,'MODEL SUMMARY'!$B$3:$AL$3,'MODEL SUMMARY'!$B$58:$AL$58),"") -> 113776.73 | M8: =L8/C8 -> 73.215399 | N8: =SUM(J8:L8) -> 127301.73 | O8: 4200 | P8: 8800 | Q8: TBD | R8: 24/33 | AA8: Old Pricing numbers from old deal sheet
A9: Banyan | B9: SFH | C9: 1400 | D9: 3 | E9: 3 | F9: 2 | G9: 582 | H9: 3 | I9: =N9/C9 -> 105.4161 | J9: =IFERROR(_xlfn.XLOOKUP(A9,'MODEL SUMMARY'!$B$3:$AL$3,'MODEL SUMMARY'!$B$71:$AL$71)+_xlfn.XLOOKUP($B$3,'Water & Sewer Data'!$C:$C,'Water & Sewer Data'!$K:$K),"") -> 2650 | K9: =IFERROR(_xlfn.XLOOKUP(A9,'MODEL SUMMARY'!$B$3:$AL$3,'MODEL SUMMARY'!$B$66:$AL$66),"") -> 10875 | L9: =IFERROR(_xlfn.XLOOKUP(A9,'MODEL SUMMARY'!$B$3:$AL$3,'MODEL SUMMARY'!$B$58:$AL$58),"") -> 134057.54 | M9: =L9/C9 -> 95.755386 | N9: =SUM(J9:L9) -> 147582.54 | O9: 4600 | P9: 10300 | Q9: TBD | R9: 28/24 | AA9: Archived Models. No pricing updates
A10: Cherry | B10: SFH | C10: 2214 | D10: 4 | E10: 3 | F10: 2 | G10: 428 | H10: 2 | I10: =N10/C10 -> 76.981965 | J10: =IFERROR(_xlfn.XLOOKUP(A10,'MODEL SUMMARY'!$B$3:$AL$3,'MODEL SUMMARY'!$B$71:$AL$71)+_xlfn.XLOOKUP($B$3,'Water & Sewer Data'!$C:$C,'Water & Sewer Data'!$K:$K),"") -> 2650 | K10: =IFERROR(_xlfn.XLOOKUP(A10,'MODEL SUMMARY'!$B$3:$AL$3,'MODEL SUMMARY'!$B$66:$AL$66),"") -> 10875 | L10: =IFERROR(_xlfn.XLOOKUP(A10,'MODEL SUMMARY'!$B$3:$AL$3,'MODEL SUMMARY'!$B$58:$AL$58),"") -> 156913.07 | M10: =L10/C10 -> 70.873112 | N10: =SUM(J10:L10) -> 170438.07 | O10: 5000 | P10: 11000 | Q10: TBD | R10: 38/38 | AA10: One time models
A11: Dogwood | B11: SFH | C11: 1541 | D11: 3 | E11: 2.5 | F11: 2 | G11: 397 | H11: 2 | I11: =N11/C11 -> 89.264101 | J11: =IFERROR(_xlfn.XLOOKUP(A11,'MODEL SUMMARY'!$B$3:$AL$3,'MODEL SUMMARY'!$B$71:$AL$71)+_xlfn.XLOOKUP($B$3,'Water & Sewer Data'!$C:$C,'Water & Sewer Data'!$K:$K),"") -> 2650 | K11: =IFERROR(_xlfn.XLOOKUP(A11,'MODEL SUMMARY'!$B$3:$AL$3,'MODEL SUMMARY'!$B$66:$AL$66),"") -> 10875 | L11: =IFERROR(_xlfn.XLOOKUP(A11,'MODEL SUMMARY'!$B$3:$AL$3,'MODEL SUMMARY'!$B$58:$AL$58),"") -> 124030.98 | M11: =L11/C11 -> 80.487333 | N11: =SUM(J11:L11) -> 137555.98 | O11: 4000 | P11: 8300 | Q11: TBD | R11: 29/36 | AA11: Future Plans - No line-itemed budget. Still being bidded out
A12: Hazel | B12: SFH | C12: 1713 | D12: 4 | E12: 2.5 | F12: 2 | G12: 677 | H12: 2 | I12: =N12/C12 -> 86.237741 | J12: =IFERROR(_xlfn.XLOOKUP(A12,'MODEL SUMMARY'!$B$3:$AL$3,'MODEL SUMMARY'!$B$71:$AL$71)+_xlfn.XLOOKUP($B$3,'Water & Sewer Data'!$C:$C,'Water & Sewer Data'!$K:$K),"") -> 2650 | K12: =IFERROR(_xlfn.XLOOKUP(A12,'MODEL SUMMARY'!$B$3:$AL$3,'MODEL SUMMARY'!$B$66:$AL$66),"") -> 10875 | L12: =IFERROR(_xlfn.XLOOKUP(A12,'MODEL SUMMARY'!$B$3:$AL$3,'MODEL SUMMARY'!$B$58:$AL$58),"") -> 134200.25 | M12: =L12/C12 -> 78.342236 | N12: =SUM(J12:L12) -> 147725.25 | O12: 4450 | P12: 9100 | Q12: TBD | R12: 28/34
A13: Holly | B13: SFH | C13: 2000 | D13: 4 | E13: 2.5 | F13: 2 | G13: 404 | H13: 2 | I13: =N13/C13 -> 78.9401 | J13: =IFERROR(_xlfn.XLOOKUP(A13,'MODEL SUMMARY'!$B$3:$AL$3,'MODEL SUMMARY'!$B$71:$AL$71)+_xlfn.XLOOKUP($B$3,'Water & Sewer Data'!$C:$C,'Water & Sewer Data'!$K:$K),"") -> 2650 | K13: =IFERROR(_xlfn.XLOOKUP(A13,'MODEL SUMMARY'!$B$3:$AL$3,'MODEL SUMMARY'!$B$66:$AL$66),"") -> 10875 | L13: =IFERROR(_xlfn.XLOOKUP(A13,'MODEL SUMMARY'!$B$3:$AL$3,'MODEL SUMMARY'!$B$58:$AL$58),"") -> 144355.2 | M13: =L13/C13 -> 72.1776 | N13: =SUM(J13:L13) -> 157880.2 | O13: 4000 | P13: 8500 | Q13: TBD | R13: 29/48
A14: Elm | B14: SFH | C14: 1712 | D14: 4 | E14: 2.5 | F14: 2 | G14: 408 | H14: 2 | I14: =N14/C14 -> 86.4866 | J14: =IFERROR(_xlfn.XLOOKUP(A14,'MODEL SUMMARY'!$B$3:$AL$3,'MODEL SUMMARY'!$B$71:$AL$71)+_xlfn.XLOOKUP($B$3,'Water & Sewer Data'!$C:$C,'Water & Sewer Data'!$K:$K),"") -> 2650 | K14: =IFERROR(_xlfn.XLOOKUP(A14,'MODEL SUMMARY'!$B$3:$AL$3,'MODEL SUMMARY'!$B$66:$AL$66),"") -> 10875 | L14: =IFERROR(_xlfn.XLOOKUP(A14,'MODEL SUMMARY'!$B$3:$AL$3,'MODEL SUMMARY'!$B$58:$AL$58),"") -> 134540.06 | M14: =L14/C14 -> 78.586484 | N14: =SUM(J14:L14) -> 148065.06 | O14: 4300 | P14: 9000 | Q14: TBD | R14: 28/35
A15: Lilac | B15: SFH | C15: 1382 | D15: 3 | E15: 3 | F15: 1 | G15: 425 | H15: 1.5 | I15: =N15/C15 -> 98.447808 | J15: =IFERROR(_xlfn.XLOOKUP(A15,'MODEL SUMMARY'!$B$3:$AL$3,'MODEL SUMMARY'!$B$71:$AL$71)+_xlfn.XLOOKUP($B$3,'Water & Sewer Data'!$C:$C,'Water & Sewer Data'!$K:$K),"") -> 2650 | K15: =IFERROR(_xlfn.XLOOKUP(A15,'MODEL SUMMARY'!$B$3:$AL$3,'MODEL SUMMARY'!$B$66:$AL$66),"") -> 10875 | L15: =IFERROR(_xlfn.XLOOKUP(A15,'MODEL SUMMARY'!$B$3:$AL$3,'MODEL SUMMARY'!$B$58:$AL$58),"") -> 122529.87 | M15: =L15/C15 -> 88.661266 | N15: =SUM(J15:L15) -> 136054.87 | O15: 4000 | P15: 9000 | Q15: TBD | R15: 30/46
A16: Lily | B16: SFH | C16: 2293 | D16: 4 | E16: 3.5 | F16: 0 | G16: 0 | H16: 2.5 | I16: =N16/C16 -> 74.779773 | J16: =IFERROR(_xlfn.XLOOKUP(A16,'MODEL SUMMARY'!$B$3:$AL$3,'MODEL SUMMARY'!$B$71:$AL$71)+_xlfn.XLOOKUP($B$3,'Water & Sewer Data'!$C:$C,'Water & Sewer Data'!$K:$K),"") -> 2650 | K16: =IFERROR(_xlfn.XLOOKUP(A16,'MODEL SUMMARY'!$B$3:$AL$3,'MODEL SUMMARY'!$B$66:$AL$66),"") -> 10875 | L16: =IFERROR(_xlfn.XLOOKUP(A16,'MODEL SUMMARY'!$B$3:$AL$3,'MODEL SUMMARY'!$B$58:$AL$58),"") -> 157945.02 | M16: =L16/C16 -> 68.881387 | N16: =SUM(J16:L16) -> 171470.02 | O16: 5400 | P16: 10700 | Q16: TBD | R16: 34/30 | T16: Widest point of plan, 26 ft at marrowest depth
A17: Magnolia | B17: SFH | C17: 2771 | D17: 4 | E17: 3 | F17: 2 | G17: 423 | H17: 2 | I17: =N17/C17 -> 69.184168 | J17: =IFERROR(_xlfn.XLOOKUP(A17,'MODEL SUMMARY'!$B$3:$AL$3,'MODEL SUMMARY'!$B$71:$AL$71)+_xlfn.XLOOKUP($B$3,'Water & Sewer Data'!$C:$C,'Water & Sewer Data'!$K:$K),"") -> 2650 | K17: =IFERROR(_xlfn.XLOOKUP(A17,'MODEL SUMMARY'!$B$3:$AL$3,'MODEL SUMMARY'!$B$66:$AL$66),"") -> 10875 | L17: =IFERROR(_xlfn.XLOOKUP(A17,'MODEL SUMMARY'!$B$3:$AL$3,'MODEL SUMMARY'!$B$58:$AL$58),"") -> 178184.33 | M17: =L17/C17 -> 64.303259 | N17: =SUM(J17:L17) -> 191709.33 | O17: 4600 | P17: 11100 | Q17: TBD | R17: 38/40
A18: Spindle | B18: SFH | C18: 2001 | D18: 3 | E18: 2 | F18: 0 | G18: 0 | H18: 2 | I18: =N18/C18 -> 80.476032 | J18: =IFERROR(_xlfn.XLOOKUP(A18,'MODEL SUMMARY'!$B$3:$AL$3,'MODEL SUMMARY'!$B$71:$AL$71)+_xlfn.XLOOKUP($B$3,'Water & Sewer Data'!$C:$C,'Water & Sewer Data'!$K:$K),"") -> 2650 | K18: =IFERROR(_xlfn.XLOOKUP(A18,'MODEL SUMMARY'!$B$3:$AL$3,'MODEL SUMMARY'!$B$66:$AL$66),"") -> 10875 | L18: =IFERROR(_xlfn.XLOOKUP(A18,'MODEL SUMMARY'!$B$3:$AL$3,'MODEL SUMMARY'!$B$58:$AL$58),"") -> 147507.54 | M18: =L18/C18 -> 73.716912 | N18: =SUM(J18:L18) -> 161032.54 | O18: 4100 | P18: 8800 | Q18: TBD | R18: 24/51
A19: Spruce | B19: SFH | C19: 1545 | D19: 3 | E19: 2 | F19: 2 | G19: 425 | H19: 1 | I19: =N19/C19 -> 92.584311 | J19: =IFERROR(_xlfn.XLOOKUP(A19,'MODEL SUMMARY'!$B$3:$AL$3,'MODEL SUMMARY'!$B$71:$AL$71)+_xlfn.XLOOKUP($B$3,'Water & Sewer Data'!$C:$C,'Water & Sewer Data'!$K:$K),"") -> 2650 | K19: =IFERROR(_xlfn.XLOOKUP(A19,'MODEL SUMMARY'!$B$3:$AL$3,'MODEL SUMMARY'!$B$66:$AL$66),"") -> 10875 | L19: =IFERROR(_xlfn.XLOOKUP(A19,'MODEL SUMMARY'!$B$3:$AL$3,'MODEL SUMMARY'!$B$58:$AL$58),"") -> 129517.76 | M19: =L19/C19 -> 83.830265 | N19: =SUM(J19:L19) -> 143042.76 | O19: 2800 | P19: 7300 | Q19: TBD | R19: 39/54
A20: Tulip | B20: SFH | C20: 1170 | D20: 3 | E20: 2 | F20: 1 | G20: 246 | H20: 1 | I20: =N20/C20 -> 102.00524 | J20: =IFERROR(_xlfn.XLOOKUP(A20,'MODEL SUMMARY'!$B$3:$AL$3,'MODEL SUMMARY'!$B$71:$AL$71)+_xlfn.XLOOKUP($B$3,'Water & Sewer Data'!$C:$C,'Water & Sewer Data'!$K:$K),"") -> 2650 | K20: =IFERROR(_xlfn.XLOOKUP(A20,'MODEL SUMMARY'!$B$3:$AL$3,'MODEL SUMMARY'!$B$66:$AL$66),"") -> 10875 | L20: =IFERROR(_xlfn.XLOOKUP(A20,'MODEL SUMMARY'!$B$3:$AL$3,'MODEL SUMMARY'!$B$58:$AL$58),"") -> 105821.13 | M20: =L20/C20 -> 90.44541 | N20: =SUM(J20:L20) -> 119346.13 | O20: 3000 | P20: 6500 | Q20: TBD | R20: 30/50
A21: White Oak | B21: SFH | C21: 2005 | D21: 4 | E21: 2.5 | F21: 2 | G21: 442 | H21: 2 | I21: =N21/C21 -> 78.492544 | J21: =IFERROR(_xlfn.XLOOKUP(A21,'MODEL SUMMARY'!$B$3:$AL$3,'MODEL SUMMARY'!$B$71:$AL$71)+_xlfn.XLOOKUP($B$3,'Water & Sewer Data'!$C:$C,'Water & Sewer Data'!$K:$K),"") -> 2650 | K21: =IFERROR(_xlfn.XLOOKUP(A21,'MODEL SUMMARY'!$B$3:$AL$3,'MODEL SUMMARY'!$B$66:$AL$66),"") -> 10875 | L21: =IFERROR(_xlfn.XLOOKUP(A21,'MODEL SUMMARY'!$B$3:$AL$3,'MODEL SUMMARY'!$B$58:$AL$58),"") -> 143852.55 | M21: =L21/C21 -> 71.746908 | N21: =SUM(J21:L21) -> 157377.55 | O21: 4400 | P21: 6700 | Q21: TBD | R21: 38/35
A22: Willow | B22: SFH | C22: 1857 | D22: 4 | E22: 2.5 | F22: 1 | G22: 250 | H22: 2 | I22: =N22/C22 -> 79.383759 | J22: =IFERROR(_xlfn.XLOOKUP(A22,'MODEL SUMMARY'!$B$3:$AL$3,'MODEL SUMMARY'!$B$71:$AL$71)+_xlfn.XLOOKUP($B$3,'Water & Sewer Data'!$C:$C,'Water & Sewer Data'!$K:$K),"") -> 2650 | K22: =IFERROR(_xlfn.XLOOKUP(A22,'MODEL SUMMARY'!$B$3:$AL$3,'MODEL SUMMARY'!$B$66:$AL$66),"") -> 10875 | L22: =IFERROR(_xlfn.XLOOKUP(A22,'MODEL SUMMARY'!$B$3:$AL$3,'MODEL SUMMARY'!$B$58:$AL$58),"") -> 133890.64 | M22: =L22/C22 -> 72.100506 | N22: =SUM(J22:L22) -> 147415.64 | O22: 4100 | P22: 9000 | Q22: TBD | R22: 30/40
A23: Jasmine | B23: TH | C23: 1500 | D23: 3 | E23: 2.5 | F23: 1 | G23: 244 | H23: 2 | I23: =N23/C23 -> 93.777893 | J23: =IFERROR(_xlfn.XLOOKUP(A23,'MODEL SUMMARY'!$B$3:$AL$3,'MODEL SUMMARY'!$B$71:$AL$71)+_xlfn.XLOOKUP($B$3,'Water & Sewer Data'!$C:$C,'Water & Sewer Data'!$K:$K),"") -> 2650 | K23: =IFERROR(_xlfn.XLOOKUP(A23,'MODEL SUMMARY'!$B$3:$AL$3,'MODEL SUMMARY'!$B$66:$AL$66),"") -> 10875 | L23: =IFERROR(_xlfn.XLOOKUP(A23,'MODEL SUMMARY'!$B$3:$AL$3,'MODEL SUMMARY'!$B$58:$AL$58),"") -> 127141.84 | M23: =L23/C23 -> 84.761227 | N23: =SUM(J23:L23) -> 140666.84 | O23: 3800 | P23: 8000 | Q23: 4500 | R23: 20/49
A24: Palmetto | B24: TH | C24: 1304 | D24: 3 | E24: 2.5 | F24: 0 | G24: 0 | H24: 2 | I24: =N24/C24 -> 94.760874 | J24: =IFERROR(_xlfn.XLOOKUP(A24,'MODEL SUMMARY'!$B$3:$AL$3,'MODEL SUMMARY'!$B$71:$AL$71)+_xlfn.XLOOKUP($B$3,'Water & Sewer Data'!$C:$C,'Water & Sewer Data'!$K:$K),"") -> 2650 | K24: =IFERROR(_xlfn.XLOOKUP(A24,'MODEL SUMMARY'!$B$3:$AL$3,'MODEL SUMMARY'!$B$66:$AL$66),"") -> 10875 | L24: =IFERROR(_xlfn.XLOOKUP(A24,'MODEL SUMMARY'!$B$3:$AL$3,'MODEL SUMMARY'!$B$58:$AL$58),"") -> 110043.18 | M24: =L24/C24 -> 84.388942 | N24: =SUM(J24:L24) -> 123568.18 | O24: 3900 | P24: 8200 | Q24: TBD | R24: 20/42
A25: Palmetto II | B25: TH | C25: 1424 | D25: 3 | E25: 2.5 | F25: 0 | G25: 32 | H25: 2 | I25: =N25/C25 -> 87.485744 | J25: =IFERROR(_xlfn.XLOOKUP(A25,'MODEL SUMMARY'!$B$3:$AL$3,'MODEL SUMMARY'!$B$71:$AL$71)+_xlfn.XLOOKUP($B$3,'Water & Sewer Data'!$C:$C,'Water & Sewer Data'!$K:$K),"") -> 2650 | K25: =IFERROR(_xlfn.XLOOKUP(A25,'MODEL SUMMARY'!$B$3:$AL$3,'MODEL SUMMARY'!$B$66:$AL$66),"") -> 10875 | L25: =IFERROR(_xlfn.XLOOKUP(A25,'MODEL SUMMARY'!$B$3:$AL$3,'MODEL SUMMARY'!$B$58:$AL$58),"") -> 111054.7 | M25: =L25/C25 -> 77.987851 | N25: =SUM(J25:L25) -> 124579.7 | O25: 4100 | P25: 7200 | Q25: 5000 | R25: 20x37
A26: Palm II | B26: TH | C26: 1689 | D26: 3 | E26: 2.5 | F26: 1F | G26: 261 | H26: 2 | I26: =N26/C26 -> 86.398615 | J26: =IFERROR(_xlfn.XLOOKUP(A26,'MODEL SUMMARY'!$B$3:$AL$3,'MODEL SUMMARY'!$B$71:$AL$71)+_xlfn.XLOOKUP($B$3,'Water & Sewer Data'!$C:$C,'Water & Sewer Data'!$K:$K),"") -> 2650 | K26: =IFERROR(_xlfn.XLOOKUP(A26,'MODEL SUMMARY'!$B$3:$AL$3,'MODEL SUMMARY'!$B$66:$AL$66),"") -> 10875 | L26: =IFERROR(_xlfn.XLOOKUP(A26,'MODEL SUMMARY'!$B$3:$AL$3,'MODEL SUMMARY'!$B$58:$AL$58),"") -> 132402.26 | M26: =L26/C26 -> 78.390918 | N26: =SUM(J26:L26) -> 145927.26 | O26: 5000 | P26: 8500 | Q26: TBD | R26: 20/50
A27: Bayberry | B27: TH | C27: 1500 | D27: 3 | E27: 2.5 | F27: 1F | G27: 259 | H27: 2 | I27: =N27/C27 -> 92.517893 | J27: =IFERROR(_xlfn.XLOOKUP(A27,'MODEL SUMMARY'!$B$3:$AL$3,'MODEL SUMMARY'!$B$71:$AL$71)+_xlfn.XLOOKUP($B$3,'Water & Sewer Data'!$C:$C,'Water & Sewer Data'!$K:$K),"") -> 2650 | K27: =IFERROR(_xlfn.XLOOKUP(A27,'MODEL SUMMARY'!$B$3:$AL$3,'MODEL SUMMARY'!$B$66:$AL$66),"") -> 10875 | L27: =IFERROR(_xlfn.XLOOKUP(A27,'MODEL SUMMARY'!$B$3:$AL$3,'MODEL SUMMARY'!$B$58:$AL$58),"") -> 125251.84 | M27: =L27/C27 -> 83.501227 | N27: =SUM(J27:L27) -> 138776.84 | O27: 3600 | P27: 5500 | Q27: 6100 | R27: 20/50 | T27: Width is per unit
A28: Cottonwood | B28: TH | C28: 1729 | D28: 3 | E28: 2.5 | F28: 1F | G28: 270 | H28: 3 | I28: =N28/C28 -> 89.995899 | J28: =IFERROR(_xlfn.XLOOKUP(A28,'MODEL SUMMARY'!$B$3:$AL$3,'MODEL SUMMARY'!$B$71:$AL$71)+_xlfn.XLOOKUP($B$3,'Water & Sewer Data'!$C:$C,'Water & Sewer Data'!$K:$K),"") -> 2650 | K28: =IFERROR(_xlfn.XLOOKUP(A28,'MODEL SUMMARY'!$B$3:$AL$3,'MODEL SUMMARY'!$B$66:$AL$66),"") -> 10875 | L28: =IFERROR(_xlfn.XLOOKUP(A28,'MODEL SUMMARY'!$B$3:$AL$3,'MODEL SUMMARY'!$B$58:$AL$58),"") -> 142077.91 | M28: =L28/C28 -> 82.173459 | N28: =SUM(J28:L28) -> 155602.91 | O28: 6500 | P28: 7100 | Q28: TBD | R28: 18/40 | T28: Width is per unit
A29: Linville | B29: TH | C29: 2188 | D29: 4 | E29: 2.5 | F29: 2F | G29: =36+404+88 -> 528 | H29: 2 | I29: =N29/C29 -> 79.587669 | J29: =IFERROR(_xlfn.XLOOKUP(A29,'MODEL SUMMARY'!$B$3:$AL$3,'MODEL SUMMARY'!$B$71:$AL$71)+_xlfn.XLOOKUP($B$3,'Water & Sewer Data'!$C:$C,'Water & Sewer Data'!$K:$K),"") -> 2650 | K29: =IFERROR(_xlfn.XLOOKUP(A29,'MODEL SUMMARY'!$B$3:$AL$3,'MODEL SUMMARY'!$B$66:$AL$66),"") -> 10875 | L29: =IFERROR(_xlfn.XLOOKUP(A29,'MODEL SUMMARY'!$B$3:$AL$3,'MODEL SUMMARY'!$B$58:$AL$58),"") -> 160612.82 | M29: =L29/C29 -> 73.406225 | N29: =SUM(J29:L29) -> 174137.82 | O29: 4700 | P29: 8900 | Q29: 7300 | R29: 27/56
A30: Locust | B30: TH | C30: 1669 | D30: 3 | E30: 2.5 | F30: 1F | G30: 258 | H30: 2 | I30: =N30/C30 -> 88.359551 | J30: =IFERROR(_xlfn.XLOOKUP(A30,'MODEL SUMMARY'!$B$3:$AL$3,'MODEL SUMMARY'!$B$71:$AL$71)+_xlfn.XLOOKUP($B$3,'Water & Sewer Data'!$C:$C,'Water & Sewer Data'!$K:$K),"") -> 2650 | K30: =IFERROR(_xlfn.XLOOKUP(A30,'MODEL SUMMARY'!$B$3:$AL$3,'MODEL SUMMARY'!$B$66:$AL$66),"") -> 10875 | L30: =IFERROR(_xlfn.XLOOKUP(A30,'MODEL SUMMARY'!$B$3:$AL$3,'MODEL SUMMARY'!$B$58:$AL$58),"") -> 133947.09 | M30: =L30/C30 -> 80.255896 | N30: =SUM(J30:L30) -> 147472.09 | O30: 4600 | P30: 7200 | Q30: TBD | R30: 22/47 | T30: Width is per unit
A31: Fig | B31: TH | C31: 1798 | D31: 3 | E31: 3.5 | F31: 1R | G31: 324 | H31: 3 | I31: =N31/C31 -> 91.045445 | J31: =IFERROR(_xlfn.XLOOKUP(A31,'MODEL SUMMARY'!$B$3:$AL$3,'MODEL SUMMARY'!$B$71:$AL$71)+_xlfn.XLOOKUP($B$3,'Water & Sewer Data'!$C:$C,'Water & Sewer Data'!$K:$K),"") -> 2650 | K31: =IFERROR(_xlfn.XLOOKUP(A31,'MODEL SUMMARY'!$B$3:$AL$3,'MODEL SUMMARY'!$B$66:$AL$66),"") -> 10875 | L31: =IFERROR(_xlfn.XLOOKUP(A31,'MODEL SUMMARY'!$B$3:$AL$3,'MODEL SUMMARY'!$B$58:$AL$58),"") -> 150174.71 | M31: =L31/C31 -> 83.523198 | N31: =SUM(J31:L31) -> 163699.71 | O31: 3900 | P31: 8200 | Q31: 9000 | R31: 18/40 | T31: Width is per unit
A32: Poplar | B32: TH | C32: 1483 | D32: 3 | E32: 2.5 | F32: 2R | G32: 439 | H32: 2 | I32: =N32/C32 -> 97.328935 | J32: =IFERROR(_xlfn.XLOOKUP(A32,'MODEL SUMMARY'!$B$3:$AL$3,'MODEL SUMMARY'!$B$71:$AL$71)+_xlfn.XLOOKUP($B$3,'Water & Sewer Data'!$C:$C,'Water & Sewer Data'!$K:$K),"") -> 2650 | K32: =IFERROR(_xlfn.XLOOKUP(A32,'MODEL SUMMARY'!$B$3:$AL$3,'MODEL SUMMARY'!$B$66:$AL$66),"") -> 10875 | L32: =IFERROR(_xlfn.XLOOKUP(A32,'MODEL SUMMARY'!$B$3:$AL$3,'MODEL SUMMARY'!$B$58:$AL$58),"") -> 130813.81 | M32: =L32/C32 -> 88.208908 | N32: =SUM(J32:L32) -> 144338.81 | O32: 3900 | P32: 8200 | Q32: 3600 | R32: 20/50
A33: Fraser | B33: TH | C33: 1689 | D33: 3 | E33: 2.5 | F33: 2R | G33: 445 | H33: 2R | I33: =N33/C33 -> 87.085968 | J33: =IFERROR(_xlfn.XLOOKUP(A33,'MODEL SUMMARY'!$B$3:$AL$3,'MODEL SUMMARY'!$B$71:$AL$71)+_xlfn.XLOOKUP($B$3,'Water & Sewer Data'!$C:$C,'Water & Sewer Data'!$K:$K),"") -> 2650 | K33: =IFERROR(_xlfn.XLOOKUP(A33,'MODEL SUMMARY'!$B$3:$AL$3,'MODEL SUMMARY'!$B$66:$AL$66),"") -> 10875 | L33: =IFERROR(_xlfn.XLOOKUP(A33,'MODEL SUMMARY'!$B$3:$AL$3,'MODEL SUMMARY'!$B$58:$AL$58),"") -> 133563.2 | M33: =L33/C33 -> 79.078271 | N33: =SUM(J33:L33) -> 147088.2 | O33: 3300 | P33: 2700 | Q33: TBD | R33: 22/50
A34: Sycamore | B34: TH | C34: 1993 | D34: 3 | E34: 2.5 | F34: 2R | G34: 480 | H34: 2 | I34: =N34/C34 -> 80.474691 | J34: =IFERROR(_xlfn.XLOOKUP(A34,'MODEL SUMMARY'!$B$3:$AL$3,'MODEL SUMMARY'!$B$71:$AL$71)+_xlfn.XLOOKUP($B$3,'Water & Sewer Data'!$C:$C,'Water & Sewer Data'!$K:$K),"") -> 2650 | K34: =IFERROR(_xlfn.XLOOKUP(A34,'MODEL SUMMARY'!$B$3:$AL$3,'MODEL SUMMARY'!$B$66:$AL$66),"") -> 10875 | L34: =IFERROR(_xlfn.XLOOKUP(A34,'MODEL SUMMARY'!$B$3:$AL$3,'MODEL SUMMARY'!$B$58:$AL$58),"") -> 146861.06 | M34: =L34/C34 -> 73.68844 | N34: =SUM(J34:L34) -> 160386.06 | O34: 5500 | P34: 8600 | Q34: 4400
A35: Alder | B35: TH | C35: 1700 | D35: 3 | E35: 2.5 | F35: 1R | G35: 241 | H35: 2 | I35: =N35/C35 -> 84.541547 | J35: =IFERROR(_xlfn.XLOOKUP(A35,'MODEL SUMMARY'!$B$3:$AL$3,'MODEL SUMMARY'!$B$71:$AL$71)+_xlfn.XLOOKUP($B$3,'Water & Sewer Data'!$C:$C,'Water & Sewer Data'!$K:$K),"") -> 2650 | K35: =IFERROR(_xlfn.XLOOKUP(A35,'MODEL SUMMARY'!$B$3:$AL$3,'MODEL SUMMARY'!$B$66:$AL$66),"") -> 10875 | L35: =IFERROR(_xlfn.XLOOKUP(A35,'MODEL SUMMARY'!$B$3:$AL$3,'MODEL SUMMARY'!$B$58:$AL$58),"") -> 130195.63 | M35: =L35/C35 -> 76.585665 | N35: =SUM(J35:L35) -> 143720.63 | O35: 4600 | P35: 8800 | Q35: 5900 | R35: 20/49 | T35: Per Ryan, Alder is identical to Palm but with a flipped garages
A36: Boxelder | B36: TH | C36: 1796 | D36: 4 | E36: 2.5 | F36: 2 | G36: 354 | H36: 1R | I36: =N36/C36 -> 86.3126 | J36: =IFERROR(_xlfn.XLOOKUP(A36,'MODEL SUMMARY'!$B$3:$AL$3,'MODEL SUMMARY'!$B$71:$AL$71)+_xlfn.XLOOKUP($B$3,'Water & Sewer Data'!$C:$C,'Water & Sewer Data'!$K:$K),"") -> 2650 | K36: =IFERROR(_xlfn.XLOOKUP(A36,'MODEL SUMMARY'!$B$3:$AL$3,'MODEL SUMMARY'!$B$66:$AL$66),"") -> 10875 | L36: =IFERROR(_xlfn.XLOOKUP(A36,'MODEL SUMMARY'!$B$3:$AL$3,'MODEL SUMMARY'!$B$58:$AL$58),"") -> 141492.43 | M36: =L36/C36 -> 78.781977 | N36: =SUM(J36:L36) -> 155017.43 | O36: 6300 | P36: 9200 | Q36: 4800 | R36: 22/54
A37: Bur Oak | B37: TH | C37: 1548 | D37: 3 | E37: 2.5 | F37: 1 | I37: =N37/C37 -> 89.412791 | J37: =IFERROR(_xlfn.XLOOKUP(A37,'MODEL SUMMARY'!$B$3:$AL$3,'MODEL SUMMARY'!$B$71:$AL$71)+_xlfn.XLOOKUP($B$3,'Water & Sewer Data'!$C:$C,'Water & Sewer Data'!$K:$K),"") -> 2650 | K37: =IFERROR(_xlfn.XLOOKUP(A37,'MODEL SUMMARY'!$B$3:$AL$3,'MODEL SUMMARY'!$B$66:$AL$66),"") -> 10875 | L37: =IFERROR(_xlfn.XLOOKUP(A37,'MODEL SUMMARY'!$B$3:$AL$3,'MODEL SUMMARY'!$B$58:$AL$58),"") -> 124886 | M37: =L37/C37 -> 80.675711 | N37: =SUM(J37:L37) -> 138411 | O37: 5700 | P37: 8500 | Q37: 5200
A38: Conifer | B38: TH | C38: 1892 | F38: 2 | I38: =N38/C38 -> 93.315793 | J38: =IFERROR(_xlfn.XLOOKUP(A38,'MODEL SUMMARY'!$B$3:$AL$3,'MODEL SUMMARY'!$B$71:$AL$71)+_xlfn.XLOOKUP($B$3,'Water & Sewer Data'!$C:$C,'Water & Sewer Data'!$K:$K),"") -> 2650 | K38: =IFERROR(_xlfn.XLOOKUP(A38,'MODEL SUMMARY'!$B$3:$AL$3,'MODEL SUMMARY'!$B$66:$AL$66),"") -> 10875 | L38: =IFERROR(_xlfn.XLOOKUP(A38,'MODEL SUMMARY'!$B$3:$AL$3,'MODEL SUMMARY'!$B$58:$AL$58),"") -> 163028.48 | M38: =L38/C38 -> 86.167273 | N38: =SUM(J38:L38) -> 176553.48 | O38: 4700 | P38: 5900 | Q38: 7700
A39: Pinyon | B39: TH | C39: 1748 | D39: 3 | E39: 3.5 | F39: 2 | I39: =N39/C39 -> 94.490446 | J39: =IFERROR(_xlfn.XLOOKUP(A39,'MODEL SUMMARY'!$B$3:$AL$3,'MODEL SUMMARY'!$B$71:$AL$71)+_xlfn.XLOOKUP($B$3,'Water & Sewer Data'!$C:$C,'Water & Sewer Data'!$K:$K),"") -> 2650 | K39: =IFERROR(_xlfn.XLOOKUP(A39,'MODEL SUMMARY'!$B$3:$AL$3,'MODEL SUMMARY'!$B$66:$AL$66),"") -> 10875 | L39: =IFERROR(_xlfn.XLOOKUP(A39,'MODEL SUMMARY'!$B$3:$AL$3,'MODEL SUMMARY'!$B$58:$AL$58),"") -> 151644.3 | M39: =L39/C39 -> 86.753032 | N39: =SUM(J39:L39) -> 165169.3 | O39: 6600 | P39: 11200 | Q39: 6200
A40: Aspen 3-Story | B40: SFH | C40: 2168 | D40: 3 | E40: 2.5 | F40: 2 | G40: 400 | H40: 2 | I40: =N40/C40 -> 80.229027 | J40: =IFERROR(_xlfn.XLOOKUP(A40,'MODEL SUMMARY'!$B$3:$AL$3,'MODEL SUMMARY'!$B$71:$AL$71)+_xlfn.XLOOKUP($B$3,'Water & Sewer Data'!$C:$C,'Water & Sewer Data'!$K:$K),"") -> 2650 | K40: =IFERROR(_xlfn.XLOOKUP(A40,'MODEL SUMMARY'!$B$3:$AL$3,'MODEL SUMMARY'!$B$66:$AL$66),"") -> 10875 | L40: =IFERROR(_xlfn.XLOOKUP(A40,'MODEL SUMMARY'!$B$3:$AL$3,'MODEL SUMMARY'!$B$58:$AL$58),"") -> 160411.53 | M40: =L40/C40 -> 73.990558 | N40: =SUM(J40:L40) -> 173936.53 | O40: 5050 | P40: 10100 | Q40: TBD | R40: 24/33
A41: Arborbrook | B41: SFH | C41: 2219 | D41: 3 | E41: 3 | F41: 2 | G41: 496 | H41: 1.5 | I41: =N41/C41 -> 84.730509 | J41: 2650 | K41: 10875 | L41: 174492 | M41: =L41/C41 -> 78.635421 | N41: =SUM(J41:L41) -> 188017 | R41: 44/52 | T41: Widest point of plan, 47 ft at narrowest depth
A42: Ash | B42: SFH | C42: 1188 | D42: 3 | E42: 2 | F42: 2 | G42: 406 | H42: 1 | I42: =N42/C42 -> 145.25421 | J42: 19289 | K42: 12513 | L42: 140760 | M42: =L42/C42 -> 118.48485 | N42: =SUM(J42:L42) -> 172562 | R42: 30/62
A43: Hemlock | B43: SFH | C43: 2295 | D43: 4 | E43: 2.5 | F43: 2 | G43: 408 | H43: 2 | I43: =N43/C43 -> 93.831373 | J43: 19289 | K43: 12513 | L43: 183541 | M43: =L43/C43 -> 79.974292 | N43: =SUM(J43:L43) -> 215343 | R43: 38/39
A44: Hickory | B44: SFH | C44: 2295 | D44: 4 | E44: 2.5 | F44: 2 | G44: 408 | H44: 2 | I44: =N44/C44 -> 95.431373 | J44: 19289 | K44: 12513 | L44: 187213 | M44: =L44/C44 -> 81.574292 | N44: =SUM(J44:L44) -> 219015 | R44: 38/39
A45: Palm | B45: TH | C45: 1700 | D45: 3 | E45: 2.5 | F45: 1F | G45: 241 | H45: 2 | I45: =N45/C45 -> 86.818824 | J45: 2650 | K45: 10875 | L45: 134067 | M45: =L45/C45 -> 78.862941 | N45: =SUM(J45:L45) -> 147592 | R45: 20/50
A46: Red Oak | B46: SFH | C46: 2217 | D46: 4 | E46: 3 | F46: 2 | G46: 412 | H46: 2 | I46: =N46/C46 -> 77.363103 | J46: 2650 | K46: 10875 | L46: 157989 | M46: =L46/C46 -> 71.262517 | N46: =SUM(J46:L46) -> 171514 | R46: 38/40
A47: Walnut | B47: SFH | C47: 2781 | D47: 3 | E47: 2.5 | F47: 2 | G47: 403 | H47: 2 | I47: =N47/C47 -> 84.536857 | J47: 19289 | K47: 12513 | L47: 203295 | M47: =L47/C47 -> 73.101402 | N47: =SUM(J47:L47) -> 235097 | R47: 38/39
A48: Maple | B48: SFH | C48: 1596 | D48: 3 | E48: 2 | F48: 2 | G48: 391 | H48: 1 | I48: =N48/C48 -> 0 | M48: =L48/C48 -> 0 | N48: =SUM(J48:L48) -> 0 | R48: 39/54
A49: Boxelder | B49: TH | C49: 1960 | D49: 4 | E49: 2.5 | F49: 2F | G49: 362 | H49: 2 | I49: =N49/C49 -> 0 | M49: =L49/C49 -> 0 | N49: =SUM(J49:L49) -> 0 | R49: 22/54 | T49: Width is per unit
A50: Fraser | B50: TH | C50: 1689 | D50: 3 | E50: 2.5 | F50: 2R | G50: 445 | H50: 2 | I50: =N50/C50 -> 0 | M50: =L50/C50 -> 0 | N50: =SUM(J50:L50) -> 0 | R50: 22/50 | T50: Width is per unit
A51: Braxton Cottage | B51: SFH | C51: 802 | D51: 1 | E51: 1 | F51: 2F | G51: 542 | H51: 2 | I51: =N51/C51 -> 0 | M51: =L51/C51 -> 0 | N51: =SUM(J51:L51) -> 0 | R51: 28/24 | T51: Width is per unit
A52: Harrison Cottage | B52: SFH | C52: 1020 | D52: 3 | E52: 2.5 | F52: - | G52: 0 | H52: 2 | I52: =N52/C52 -> 0 | M52: =L52/C52 -> 0 | N52: =SUM(J52:L52) -> 0 | R52: 17/30 | T52: Width is per unit
A53: West End | B53: TH | C53: 1627 | D53: 3 | E53: 3.5 | F53: 1 | I53: =N53/C53 -> 103.50487 | J53: =IFERROR(_xlfn.XLOOKUP(A53,'MODEL SUMMARY'!$B$3:$AL$3,'MODEL SUMMARY'!$B$71:$AL$71)+_xlfn.XLOOKUP($B$3,'Water & Sewer Data'!$C:$C,'Water & Sewer Data'!$K:$K),"") -> 2200 | K53: =IFERROR(_xlfn.XLOOKUP(A53,'MODEL SUMMARY'!$B$3:$AL$3,'MODEL SUMMARY'!$B$66:$AL$66),"") -> 12549.99 | L53: =IFERROR(_xlfn.XLOOKUP(A53,'MODEL SUMMARY'!$B$3:$AL$3,'MODEL SUMMARY'!$B$58:$AL$58),"") -> 153652.44 | M53: =L53/C53 -> 94.439115 | N53: =SUM(J53:L53) -> 168402.43
A54: Long Farm | B54: TH | C54: 1718 | D54: 3 | E54: 2.5 | F54: 1 | I54: =N54/C54 -> 84.776423 | J54: =IFERROR(_xlfn.XLOOKUP(A54,'MODEL SUMMARY'!$B$3:$AL$3,'MODEL SUMMARY'!$B$71:$AL$71)+_xlfn.XLOOKUP($B$3,'Water & Sewer Data'!$C:$C,'Water & Sewer Data'!$K:$K),"") -> 1600 | K54: =IFERROR(_xlfn.XLOOKUP(A54,'MODEL SUMMARY'!$B$3:$AL$3,'MODEL SUMMARY'!$B$66:$AL$66),"") -> 9400 | L54: =IFERROR(_xlfn.XLOOKUP(A54,'MODEL SUMMARY'!$B$3:$AL$3,'MODEL SUMMARY'!$B$58:$AL$58),"") -> 134645.89 | M54: =L54/C54 -> 78.373629 | N54: =SUM(J54:L54) -> 145645.89
A55: Fir | B55: TH | C55: 2072 | D55: 4 | E55: 3.5 | F55: 2R | G55: 483 | H55: 3 | I55: =N55/C55 -> 92.35473 | J55: 2650 | K55: 8263 | L55: 180446 | M55: =L55/C55 -> 87.087838 | N55: =SUM(J55:L55) -> 191359 | R55: 24/37 | T55: Width is per unit

Sheet Trends
A1: Red Cedar Model Historical Trends
R2: Historical Data | X2: 45922 | Y2: 45883 | Z2: 45835 | AA2: 45813 | AB2: 45775 | AC2: 03.31.2025 | AD2: 02.27.2025 | AE2: 1.28.2025 | AF2: 1.10.2025 | AG2: 11.25.2024 | AH2: 10.29.2024 | AI2: 09.23.2024 | AJ2: 8.27.2024 | AK2: 7.22.2024 | AL2: 3.15.2024
A3: Current Month Variance to Historical Data | X3: September | Y3: August | Z3: June | AA3: May | AB3: April | AC3: March | AD3: February | AE3: January | AF3: December | AG3: November | AH3: October | AI3: September | AJ3: August | AK3: July | AL3: March
A4: Model | B4: September | C4: August | D4: June | E4: May | F4: April | G4: March | H4: February | I4: January | J4: December | K4: November | L4: October | M4: September | N4: August | O4: July | R4: Model | S4: SFR/TH | T4: SF | U4: Bed | V4: Bath | W4: Garage | X4: Sticks & Bricks | Y4: Sticks & Bricks | Z4: Sticks & Bricks | AA4: Sticks & Bricks | AB4: Sticks & Bricks | AC4: Sticks & Bricks | AD4: Sticks & Bricks | AE4: Sticks & Bricks | AF4: Sticks & Bricks | AG4: Sticks & Bricks | AH4: Sticks & Bricks | AI4: Sticks & Bricks | AJ4: Sticks & Bricks | AK4: Sticks & Bricks | AL4: Sticks & Bricks
A5: Acacia | B5: =IFERROR(X5/Y5-1,0) -> -0.0011998641 | C5: =IFERROR(Y5/Z5-1,0) -> -0.021133305 | D5: =IFERROR(Z5/AA5-1,0) -> 0.0051333042 | E5: =IFERROR(AA5/AB5-1,0) -> -0.018192947 | F5: =IFERROR(AB5/AC5-1,0) -> 0 | G5: =IFERROR(AC5/AD5-1,0) -> 0 | H5: =IFERROR(AD5/AE5-1,0) -> 0 | I5: =IFERROR(AE5/AF5-1,0) -> 0 | ... O5: =IFERROR(AK5/AL5-1,0) -> 0 | R5: Acacia | S5: =_xlfn.XLOOKUP(R5,Summary!A:A,Summary!B:B) -> SFH | T5: =_xlfn.XLOOKUP(R5,Summary!A:A,Summary!C:C) -> 2236 | U5: =_xlfn.XLOOKUP(R5,Summary!A:A,Summary!D:D) -> 4 | V5: =_xlfn.XLOOKUP(R5,Summary!A:A,Summary!E:E) -> 3 | W5: =_xlfn.XLOOKUP(R5,Summary!A:A,Summary!F:F) -> 2 | X5: =_xlfn.XLOOKUP(R5,Summary!A:A,Summary!L:L) -> 165012.15 | Y5: 165210.38 | Z5: 168777.2 | AA5: 167915.24 | AB5: 171026.72
A6: Aspen 2-Story | B6: =IFERROR(X6/Y6-1,0) -> -0.0015095011 | C6: =IFERROR(Y6/Z6-1,0) -> -0.023034239 | D6: =IFERROR(Z6/AA6-1,0) -> -0.03084456 | E6: =IFERROR(AA6/AB6-1,0) -> -0.0085214802 | F6: =IFERROR(AB6/AC6-1,0) -> 0.0057164824 | G6: =IFERROR(AC6/AD6-1,0) -> -0.014673166 | H6: =IFERROR(AD6/AE6-1,0) -> 0.019293909 | I6: =IFERROR(AE6/AF6-1,0) -> 0.007703446 | ... O6: =IFERROR(AK6/AL6-1,0) -> 0 | R6: Aspen 2-Story | S6: =_xlfn.XLOOKUP(R6,Summary!A:A,Summary!B:B) -> SFH | T6: =_xlfn.XLOOKUP(R6,Summary!A:A,Summary!C:C) -> 1788 | U6: =_xlfn.XLOOKUP(R6,Summary!A:A,Summary!D:D) -> 3 | V6: =_xlfn.XLOOKUP(R6,Summary!A:A,Summary!E:E) -> 2.5 | W6: =_xlfn.XLOOKUP(R6,Summary!A:A,Summary!F:F) -> 2 | X6: =_xlfn.XLOOKUP(R6,Summary!A:A,Summary!L:L) -> 139411.53 | Y6: 139622.29 | Z6: 142914.21 | AA6: 147462.63 | AB6: 148730.03 | AC6: 147884.65 | AD6: 150086.9 | AE6: 147245.95 | AF6: 146120.32 | AG6: 144275.17 | AH6: 141527.42 | AI6: 141527.42
A7: Atlas | B7: =IFERROR(X7/Y7-1,0) -> -0.00097578443 | C7: =IFERROR(Y7/Z7-1,0) -> -0.045152821 | D7: =IFERROR(Z7/AA7-1,0) -> -0.0015298502 | E7: =IFERROR(AA7/AB7-1,0) -> -0.0157654 | F7: =IFERROR(AB7/AC7-1,0) -> 0.0031560223 | G7: =IFERROR(AC7/AD7-1,0) -> 0.013243598 | H7: =IFERROR(AD7/AE7-1,0) -> 0.024901195 | I7: =IFERROR(AE7/AF7-1,0) -> 0.0059212852 | ... O7: =IFERROR(AK7/AL7-1,0) -> -0.025486934 | R7: Atlas | S7: =_xlfn.XLOOKUP(R7,Summary!A:A,Summary!B:B) -> SFH | T7: =_xlfn.XLOOKUP(R7,Summary!A:A,Summary!C:C) -> 1554 | U7: =_xlfn.XLOOKUP(R7,Summary!A:A,Summary!D:D) -> 3 | V7: =_xlfn.XLOOKUP(R7,Summary!A:A,Summary!E:E) -> 2.5 | W7: =_xlfn.XLOOKUP(R7,Summary!A:A,Summary!F:F) -> 0 | X7: =_xlfn.XLOOKUP(R7,Summary!A:A,Summary!L:L) -> 113776.73 | Y7: 113887.86 | Z7: 119273.39 | AA7: 119456.14 | AB7: 121369.58 | AC7: 120987.74 | AD7: 119406.37 | AE7: 116505.25 | AF7: 115819.45 | AG7: 117393 | AH7: 117268.41 | AI7: 120252.8 | AJ7: 120257.64 | AK7: 125936.46 | AL7: 129230.14
A8: Banyan | B8: =IFERROR(X8/Y8-1,0) -> -0.002807751 | C8: =IFERROR(Y8/Z8-1,0) -> -0.034428875 | D8: =IFERROR(Z8/AA8-1,0) -> 0.011011894 | E8: =IFERROR(AA8/AB8-1,0) -> -0.0077560483 | F8: =IFERROR(AB8/AC8-1,0) -> 0.0015862173 | G8: =IFERROR(AC8/AD8-1,0) -> 0.0047270556 | H8: =IFERROR(AD8/AE8-1,0) -> 0.019112735 | I8: =IFERROR(AE8/AF8-1,0) -> 0.051308309 | ... O8: =IFERROR(AK8/AL8-1,0) -> 0 | R8: Banyan | S8: =_xlfn.XLOOKUP(R8,Summary!A:A,Summary!B:B) -> SFH | T8: =_xlfn.XLOOKUP(R8,Summary!A:A,Summary!C:C) -> 1400 | U8: =_xlfn.XLOOKUP(R8,Summary!A:A,Summary!D:D) -> 3 | V8: =_xlfn.XLOOKUP(R8,Summary!A:A,Summary!E:E) -> 3 | W8: =_xlfn.XLOOKUP(R8,Summary!A:A,Summary!F:F) -> 2 | X8: =_xlfn.XLOOKUP(R8,Summary!A:A,Summary!L:L) -> 134057.54 | Y8: 134435 | Z8: 139228.48 | AA8: 137712.01 | AB8: 138788.46 | AC8: 138568.66 | AD8: 137916.72 | AE8: 135330.19 | AF8: 128725.5 | AG8: 127617.64 | AH8: 125378.71 | AI8: 125378.71
A9: Cherry | B9: =IFERROR(X9/Y9-1,0) -> -0.0055609798 | C9: =IFERROR(Y9/Z9-1,0) -> -0.0061237909 | D9: =IFERROR(Z9/AA9-1,0) -> 0.016814876 | E9: =IFERROR(AA9/AB9-1,0) -> -0.0029255636 | F9: =IFERROR(AB9/AC9-1,0) -> 0.0059418451 | G9: =IFERROR(AC9/AD9-1,0) -> 0.0053798986 | H9: =IFERROR(AD9/AE9-1,0) -> 0.01680861 | I9: =IFERROR(AE9/AF9-1,0) -> 0.016767479 | ... O9: =IFERROR(AK9/AL9-1,0) -> -0.056532855 | R9: Cherry | S9: =_xlfn.XLOOKUP(R9,Summary!A:A,Summary!B:B) -> SFH | T9: =_xlfn.XLOOKUP(R9,Summary!A:A,Summary!C:C) -> 2214 | U9: =_xlfn.XLOOKUP(R9,Summary!A:A,Summary!D:D) -> 4 | V9: =_xlfn.XLOOKUP(R9,Summary!A:A,Summary!E:E) -> 3 | W9: =_xlfn.XLOOKUP(R9,Summary!A:A,Summary!F:F) -> 2 | X9: =_xlfn.XLOOKUP(R9,Summary!A:A,Summary!L:L) -> 156913.07 | Y9: 157790.54 | Z9: 158762.77 | AA9: 156137.34 | AB9: 156595.47 | AC9: 155670.5 | AD9: 154837.49 | AE9: 152277.91 | AF9: 149766.7 | AG9: 151699.79 | AH9: 151515.73 | AI9: 155786.41 | AJ9: 155778.74 | AK9: 156950.76 | AL9: 166355.3
A10: Dogwood | B10: =IFERROR(X10/Y10-1,0) -> -0.0015276836 | C10: =IFERROR(Y10/Z10-1,0) -> -0.032542498 | D10: =IFERROR(Z10/AA10-1,0) -> 0.010693027 | E10: =IFERROR(AA10/AB10-1,0) -> -0.0030007903 | F10: =IFERROR(AB10/AC10-1,0) -> -0.0031234757 | G10: =IFERROR(AC10/AD10-1,0) -> 0.0054473447 | H10: =IFERROR(AD10/AE10-1,0) -> 0.016772164 | I10: =IFERROR(AE10/AF10-1,0) -> 0.035977873 | ... O10: =IFERROR(AK10/AL10-1,0) -> -0.066664213 | R10: Dogwood | S10: =_xlfn.XLOOKUP(R10,Summary!A:A,Summary!B:B) -> SFH | T10: =_xlfn.XLOOKUP(R10,Summary!A:A,Summary!C:C) -> 1541 | U10: =_xlfn.XLOOKUP(R10,Summary!A:A,Summary!D:D) -> 3 | V10: =_xlfn.XLOOKUP(R10,Summary!A:A,Summary!E:E) -> 2.5 | W10: =_xlfn.XLOOKUP(R10,Summary!A:A,Summary!F:F) -> 2 | X10: =_xlfn.XLOOKUP(R10,Summary!A:A,Summary!L:L) -> 124030.98 | Y10: 124220.75 | Z10: 128399.18 | AA10: 127040.73 | AB10: 127423.1 | AC10: 127822.35 | AD10: 127129.83 | AE10: 125032.76 | AF10: 120690.57 | AG10: 122061.15 | AH10: 122601.99 | AI10: 125295.09 | AJ10: 124464.88 | AK10: 125788.24 | AL10: 134772.76
A11: Hazel | B11: =IFERROR(X11/Y11-1,0) -> -0.0015925388 | C11: =IFERROR(Y11/Z11-1,0) -> -0.035070173 | D11: =IFERROR(Z11/AA11-1,0) -> 0.00893274 | E11: =IFERROR(AA11/AB11-1,0) -> 0.00017277299 | F11: =IFERROR(AB11/AC11-1,0) -> 0.0061235881 | G11: =IFERROR(AC11/AD11-1,0) -> 0.0085069702 | H11: =IFERROR(AD11/AE11-1,0) -> 0 | I11: =IFERROR(AE11/AF11-1,0) -> 0 | ... O11: =IFERROR(AK11/AL11-1,0) -> 0 | R11: Hazel | S11: =_xlfn.XLOOKUP(R11,Summary!A:A,Summary!B:B) -> SFH | T11: =_xlfn.XLOOKUP(R11,Summary!A:A,Summary!C:C) -> 1713 | U11: =_xlfn.XLOOKUP(R11,Summary!A:A,Summary!D:D) -> 4 | V11: =_xlfn.XLOOKUP(R11,Summary!A:A,Summary!E:E) -> 2.5 | W11: =_xlfn.XLOOKUP(R11,Summary!A:A,Summary!F:F) -> 2 | X11: =_xlfn.XLOOKUP(R11,Summary!A:A,Summary!L:L) -> 134200.25 | Y11: 134414.31 | Z11: 139299.57 | AA11: 138066.26 | AB11: 138042.41 | AC11: 137202.24 | AD11: 136044.91
A12: Holly | B12: =IFERROR(X12/Y12-1,0) -> -0.00097725611 | C12: =IFERROR(Y12/Z12-1,0) -> -0.017998863 | D12: =IFERROR(Z12/AA12-1,0) -> 0.0086222225 | E12: =IFERROR(AA12/AB12-1,0) -> -0.0067742138 | F12: =IFERROR(AB12/AC12-1,0) -> 0.0070257054 | G12: =IFERROR(AC12/AD12-1,0) -> 0.0062582916 | H12: =IFERROR(AD12/AE12-1,0) -> 0.020306011 | I12: =IFERROR(AE12/AF12-1,0) -> 0.015760936 | ... O12: =IFERROR(AK12/AL12-1,0) -> -0.057570298 | R12: Holly | S12: =_xlfn.XLOOKUP(R12,Summary!A:A,Summary!B:B) -> SFH | T12: =_xlfn.XLOOKUP(R12,Summary!A:A,Summary!C:C) -> 2000 | U12: =_xlfn.XLOOKUP(R12,Summary!A:A,Summary!D:D) -> 4 | V12: =_xlfn.XLOOKUP(R12,Summary!A:A,Summary!E:E) -> 2.5 | W12: =_xlfn.XLOOKUP(R12,Summary!A:A,Summary!F:F) -> 2 | X12: =_xlfn.XLOOKUP(R12,Summary!A:A,Summary!L:L) -> 144355.2 | Y12: 144496.41 | Z12: 147144.85 | AA12: 145886.98 | AB12: 146881.99 | AC12: 145857.24 | AD12: 144950.1 | AE12: 142065.32 | AF12: 139860.98 | AG12: 138711.9 | AH12: 137885.26 | AI12: 144934.63 | AJ12: 144903.38 | AK12: 147649.01 | AL12: 156668.46
A13: Elm | B13: =IFERROR(X13/Y13-1,0) -> -0.0013137906 | C13: =IFERROR(Y13/Z13-1,0) -> -0.0272222 | D13: =IFERROR(Z13/AA13-1,0) -> -0.012635111 | E13: =IFERROR(AA13/AB13-1,0) -> -0.0039013977 | F13: =IFERROR(AB13/AC13-1,0) -> 0.005491451 | G13: =IFERROR(AC13/AD13-1,0) -> -0.0010262274 | H13: =IFERROR(AD13/AE13-1,0) -> 0.024633447 | I13: =IFERROR(AE13/AF13-1,0) -> 0.027571259 | ... O13: =IFERROR(AK13/AL13-1,0) -> -0.052439154 | R13: Elm | S13: =_xlfn.XLOOKUP(R13,Summary!A:A,Summary!B:B) -> SFH | T13: =_xlfn.XLOOKUP(R13,Summary!A:A,Summary!C:C) -> 1712 | U13: =_xlfn.XLOOKUP(R13,Summary!A:A,Summary!D:D) -> 4 | V13: =_xlfn.XLOOKUP(R13,Summary!A:A,Summary!E:E) -> 2.5 | W13: =_xlfn.XLOOKUP(R13,Summary!A:A,Summary!F:F) -> 2 | X13: =_xlfn.XLOOKUP(R13,Summary!A:A,Summary!L:L) -> 134540.06 | Y13: 134717.05 | Z13: 138486.97 | AA13: 140259.16 | AB13: 140808.51 | AC13: 140039.49 | AD13: 140183.35 | AE13: 136813.17 | AF13: 133142.27 | AG13: 133555.91 | AH13: 136379.31 | AI13: 141504.52 | AJ13: 140535.5 | AK13: 141574.09 | AL13: 149408.97
A14: Lilac | B14: =IFERROR(X14/Y14-1,0) -> -0.0021993494 | C14: =IFERROR(Y14/Z14-1,0) -> -0.022188215 | D14: =IFERROR(Z14/AA14-1,0) -> -0.00024479124 | E14: =IFERROR(AA14/AB14-1,0) -> -0.0041715995 | F14: =IFERROR(AB14/AC14-1,0) -> 0.0019366219 | G14: =IFERROR(AC14/AD14-1,0) -> 0.015159626 | H14: =IFERROR(AD14/AE14-1,0) -> 0.032021491 | I14: =IFERROR(AE14/AF14-1,0) -> 0.010948172 | ... O14: =IFERROR(AK14/AL14-1,0) -> -0.023383773 | R14: Lilac | S14: =_xlfn.XLOOKUP(R14,Summary!A:A,Summary!B:B) -> SFH | T14: =_xlfn.XLOOKUP(R14,Summary!A:A,Summary!C:C) -> 1382 | U14: =_xlfn.XLOOKUP(R14,Summary!A:A,Summary!D:D) -> 3 | V14: =_xlfn.XLOOKUP(R14,Summary!A:A,Summary!E:E) -> 3 | W14: =_xlfn.XLOOKUP(R14,Summary!A:A,Summary!F:F) -> 1 | X14: =_xlfn.XLOOKUP(R14,Summary!A:A,Summary!L:L) -> 122529.87 | Y14: 122799.95 | Z14: 125586.49 | AA14: 125617.24 | AB14: 126143.46 | AC14: 125899.64 | AD14: 124019.55 | AE14: 120171.48 | AF14: 118870.07 | AG14: 120229.66 | AH14: 120885.54 | AI14: 123700.75 | AJ14: 123663.79 | AK14: 126480.21 | AL14: 129508.61
A15: Lily | B15: =IFERROR(X15/Y15-1,0) -> 0.0048645375 | C15: =IFERROR(Y15/Z15-1,0) -> -0.020035539 | D15: =IFERROR(Z15/AA15-1,0) -> -0.054948496 | E15: =IFERROR(AA15/AB15-1,0) -> -0.017850463 | F15: =IFERROR(AB15/AC15-1,0) -> 0.0035479844 | G15: =IFERROR(AC15/AD15-1,0) -> 0.0074092995 | H15: =IFERROR(AD15/AE15-1,0) -> -0.0088741284 | I15: =IFERROR(AE15/AF15-1,0) -> 0.058523199 | ... O15: =IFERROR(AK15/AL15-1,0) -> 0 | R15: Lily | S15: =_xlfn.XLOOKUP(R15,Summary!A:A,Summary!B:B) -> SFH | T15: =_xlfn.XLOOKUP(R15,Summary!A:A,Summary!C:C) -> 2293 | U15: =_xlfn.XLOOKUP(R15,Summary!A:A,Summary!D:D) -> 4 | V15: =_xlfn.XLOOKUP(R15,Summary!A:A,Summary!E:E) -> 3.5 | W15: =_xlfn.XLOOKUP(R15,Summary!A:A,Summary!F:F) -> 0 | X15: =_xlfn.XLOOKUP(R15,Summary!A:A,Summary!L:L) -> 157945.02 | Y15: 157180.41 | Z15: 160393.99 | AA15: 169719.84 | AB15: 172804.48 | AC15: 172193.54 | AD15: 170927.09 | AE15: 172457.5 | AF15: 162922.74 | AG15: 164965.33 | AH15: 164315.42 | AI15: 169487.86 | AJ15: 169172.9
A16: Magnolia | B16: =IFERROR(X16/Y16-1,0) -> -0.0012045456 | C16: =IFERROR(Y16/Z16-1,0) -> -0.016115807 | D16: =IFERROR(Z16/AA16-1,0) -> 0.0028516236 | E16: =IFERROR(AA16/AB16-1,0) -> 0.012138388 | F16: =IFERROR(AB16/AC16-1,0) -> -0.01384975 | G16: =IFERROR(AC16/AD16-1,0) -> 0.024055893 | H16: =IFERROR(AD16/AE16-1,0) -> 0.014545681 | I16: =IFERROR(AE16/AF16-1,0) -> 0.0074613045 | ... O16: =IFERROR(AK16/AL16-1,0) -> -0.066980979 | R16: Magnolia | S16: =_xlfn.XLOOKUP(R16,Summary!A:A,Summary!B:B) -> SFH | T16: =_xlfn.XLOOKUP(R16,Summary!A:A,Summary!C:C) -> 2771 | U16: =_xlfn.XLOOKUP(R16,Summary!A:A,Summary!D:D) -> 4 | V16: =_xlfn.XLOOKUP(R16,Summary!A:A,Summary!E:E) -> 3 | W16: =_xlfn.XLOOKUP(R16,Summary!A:A,Summary!F:F) -> 2 | X16: =_xlfn.XLOOKUP(R16,Summary!A:A,Summary!L:L) -> 178184.33 | Y16: 178399.22 | Z16: 181321.36 | AA16: 180805.77 | AB16: 178637.4 | AC16: 181146.23 | AD16: 176890.96 | AE16: 174354.85 | AF16: 173063.57 | AG16: 175115.46 | AH16: 173953.79 | AI16: 178920.09 | AJ16: 178913.31 | AK16: 179862.07 | AL16: 192774.28
A17: Spindle | B17: =IFERROR(X17/Y17-1,0) -> -0.0015564094 | C17: =IFERROR(Y17/Z17-1,0) -> -0.040861341 | D17: =IFERROR(Z17/AA17-1,0) -> 0.021973591 | E17: =IFERROR(AA17/AB17-1,0) -> -0.0071631752 | F17: =IFERROR(AB17/AC17-1,0) -> 0.00062618654 | G17: =IFERROR(AC17/AD17-1,0) -> 0.0071316149 | H17: =IFERROR(AD17/AE17-1,0) -> 0.012006067 | I17: =IFERROR(AE17/AF17-1,0) -> 0.019940461 | ... O17: =IFERROR(AK17/AL17-1,0) -> 0 | R17: Spindle | S17: =_xlfn.XLOOKUP(R17,Summary!A:A,Summary!B:B) -> SFH | T17: =_xlfn.XLOOKUP(R17,Summary!A:A,Summary!C:C) -> 2001 | U17: =_xlfn.XLOOKUP(R17,Summary!A:A,Summary!D:D) -> 3 | V17: =_xlfn.XLOOKUP(R17,Summary!A:A,Summary!E:E) -> 2 | W17: =_xlfn.XLOOKUP(R17,Summary!A:A,Summary!F:F) -> 0 | X17: =_xlfn.XLOOKUP(R17,Summary!A:A,Summary!L:L) -> 147507.54 | Y17: 147737.48 | Z17: 154031.41 | AA17: 150719.56 | AB17: 151806.98 | AC17: 151711.98 | AD17: 150637.69 | AE17: 148850.58 | AF17: 145940.46 | AG17: 147648.2 | AH17: 145479.36 | AI17: 149428.13 | AJ17: 149645.2
A18: Spruce | B18: =IFERROR(X18/Y18-1,0) -> -0.010555581 | C18: =IFERROR(Y18/Z18-1,0) -> 0.058148182 | D18: =IFERROR(Z18/AA18-1,0) -> -0.063721217 | E18: =IFERROR(AA18/AB18-1,0) -> -0.006503931 | F18: =IFERROR(AB18/AC18-1,0) -> 0.0030174162 | G18: =IFERROR(AC18/AD18-1,0) -> 0.011308958 | H18: =IFERROR(AD18/AE18-1,0) -> 0.021206373 | I18: =IFERROR(AE18/AF18-1,0) -> -0.007317559 | ... O18: =IFERROR(AK18/AL18-1,0) -> -0.027419458 | R18: Spruce | S18: =_xlfn.XLOOKUP(R18,Summary!A:A,Summary!B:B) -> SFH | T18: =_xlfn.XLOOKUP(R18,Summary!A:A,Summary!C:C) -> 1545 | U18: =_xlfn.XLOOKUP(R18,Summary!A:A,Summary!D:D) -> 3 | V18: =_xlfn.XLOOKUP(R18,Summary!A:A,Summary!E:E) -> 2 | W18: =_xlfn.XLOOKUP(R18,Summary!A:A,Summary!F:F) -> 2 | X18: =_xlfn.XLOOKUP(R18,Summary!A:A,Summary!L:L) -> 129517.76 | Y18: 130899.48 | Z18: 123706.19 | AA18: 132125.38 | AB18: 132990.34 | AC18: 132590.26 | AD18: 131107.57 | AE18: 128384.99 | AF18: 129331.38 | AG18: 130566.06 | AH18: 128971.36 | AI18: 132483.38 | AJ18: 132414.33 | AK18: 133718.99 | AL18: 137488.86
A19: Tulip | B19: =IFERROR(X19/Y19-1,0) -> -0.001589213 | C19: =IFERROR(Y19/Z19-1,0) -> -0.016204429 | D19: =IFERROR(Z19/AA19-1,0) -> -0.00071856012 | E19: =IFERROR(AA19/AB19-1,0) -> -0.0065245509 | F19: =IFERROR(AB19/AC19-1,0) -> -0.0020232499 | G19: =IFERROR(AC19/AD19-1,0) -> 0.010893182 | H19: =IFERROR(AD19/AE19-1,0) -> 0.027881551 | I19: =IFERROR(AE19/AF19-1,0) -> 0.0051888819 | ... O19: =IFERROR(AK19/AL19-1,0) -> -0.034063175 | R19: Tulip | S19: =_xlfn.XLOOKUP(R19,Summary!A:A,Summary!B:B) -> SFH | T19: =_xlfn.XLOOKUP(R19,Summary!A:A,Summary!C:C) -> 1170 | U19: =_xlfn.XLOOKUP(R19,Summary!A:A,Summary!D:D) -> 3 | V19: =_xlfn.XLOOKUP(R19,Summary!A:A,Summary!E:E) -> 2 | W19: =_xlfn.XLOOKUP(R19,Summary!A:A,Summary!F:F) -> 1 | X19: =_xlfn.XLOOKUP(R19,Summary!A:A,Summary!L:L) -> 105821.13 | Y19: 105989.57 | Z19: 107735.36 | AA19: 107812.83 | AB19: 108520.88 | AC19: 108740.89 | AD19: 107569.12 | AE19: 104651.28 | AF19: 104111.06 | AG19: 104069.33 | AH19: 104896.85 | AI19: 108136.37 | AJ19: 107741.02 | AK19: 109507.63 | AL19: 113369.35
A20: White Oak | B20: =IFERROR(X20/Y20-1,0) -> -0.0035472673 | C20: =IFERROR(Y20/Z20-1,0) -> -0.013117 | D20: =IFERROR(Z20/AA20-1,0) -> 0.005071755 | E20: =IFERROR(AA20/AB20-1,0) -> -0.011525289 | F20: =IFERROR(AB20/AC20-1,0) -> 0.0048349251 | G20: =IFERROR(AC20/AD20-1,0) -> 0.0055654297 | H20: =IFERROR(AD20/AE20-1,0) -> 0.015631235 | I20: =IFERROR(AE20/AF20-1,0) -> 0.0049491001 | ... O20: =IFERROR(AK20/AL20-1,0) -> -0.065552158 | R20: White Oak | S20: =_xlfn.XLOOKUP(R20,Summary!A:A,Summary!B:B) -> SFH | T20: =_xlfn.XLOOKUP(R20,Summary!A:A,Summary!C:C) -> 2005 | U20: =_xlfn.XLOOKUP(R20,Summary!A:A,Summary!D:D) -> 4 | V20: =_xlfn.XLOOKUP(R20,Summary!A:A,Summary!E:E) -> 2.5 | W20: =_xlfn.XLOOKUP(R20,Summary!A:A,Summary!F:F) -> 2 | X20: =_xlfn.XLOOKUP(R20,Summary!A:A,Summary!L:L) -> 143852.55 | Y20: 144364.65 | Z20: 146283.45 | AA20: 145545.28 | AB20: 147242.29 | AC20: 146533.81 | AD20: 145722.8 | AE20: 143480.03 | AF20: 142773.43 | AG20: 144645.94 | AH20: 144328.83 | AI20: 148424.43 | AJ20: 148365.62 | AK20: 149768.74 | AL20: 160275.12
A21: Willow | B21: =IFERROR(X21/Y21-1,0) -> -0.00051075306 | C21: =IFERROR(Y21/Z21-1,0) -> -0.019972266 | D21: =IFERROR(Z21/AA21-1,0) -> -0.0097718787 | E21: =IFERROR(AA21/AB21-1,0) -> -0.0077300307 | F21: =IFERROR(AB21/AC21-1,0) -> -0.00088812632 | G21: =IFERROR(AC21/AD21-1,0) -> 0.0075013607 | H21: =IFERROR(AD21/AE21-1,0) -> 0.021840128 | I21: =IFERROR(AE21/AF21-1,0) -> 0.0098417535 | ... O21: =IFERROR(AK21/AL21-1,0) -> -0.076824428 | R21: Willow | S21: =_xlfn.XLOOKUP(R21,Summary!A:A,Summary!B:B) -> SFH | T21: =_xlfn.XLOOKUP(R21,Summary!A:A,Summary!C:C) -> 1857 | U21: =_xlfn.XLOOKUP(R21,Summary!A:A,Summary!D:D) -> 4 | V21: =_xlfn.XLOOKUP(R21,Summary!A:A,Summary!E:E) -> 2.5 | W21: =_xlfn.XLOOKUP(R21,Summary!A:A,Summary!F:F) -> 1 | X21: =_xlfn.XLOOKUP(R21,Summary!A:A,Summary!L:L) -> 133890.64 | Y21: 133959.06 | Z21: 136689.05 | AA21: 138037.94 | AB21: 139113.29 | AC21: 139236.95 | AD21: 138200.26 | AE21: 135246.46 | AF21: 133928.37 | AG21: 135679.25 | AH21: 135999.59 | AI21: 139868.8 | AJ21: 139840.92 | AK21: 140530.9 | AL21: 152225.54
A22: Jasmine | B22: =IFERROR(X22/Y22-1,0) -> 0.0018729094 | C22: =IFERROR(Y22/Z22-1,0) -> -0.024778198 | D22: =IFERROR(Z22/AA22-1,0) -> -0.0082503722 | E22: =IFERROR(AA22/AB22-1,0) -> -0.0012665036 | F22: =IFERROR(AB22/AC22-1,0) -> -0.022053576 | G22: =IFERROR(AC22/AD22-1,0) -> 0.0070090284 | H22: =IFERROR(AD22/AE22-1,0) -> 0.029692611 | I22: =IFERROR(AE22/AF22-1,0) -> 0.0083674046 | ... O22: =IFERROR(AK22/AL22-1,0) -> 0.19855415 | R22: Jasmine | S22: =_xlfn.XLOOKUP(R22,Summary!A:A,Summary!B:B) -> TH | T22: =_xlfn.XLOOKUP(R22,Summary!A:A,Summary!C:C) -> 1500 | U22: =_xlfn.XLOOKUP(R22,Summary!A:A,Summary!D:D) -> 3 | V22: =_xlfn.XLOOKUP(R22,Summary!A:A,Summary!E:E) -> 2.5 | W22: =_xlfn.XLOOKUP(R22,Summary!A:A,Summary!F:F) -> 1 | X22: =_xlfn.XLOOKUP(R22,Summary!A:A,Summary!L:L) -> 127141.84 | Y22: 126904.16 | Z22: 130128.51 | AA22: 131211.05 | AB22: 131377.44 | AC22: 134340.12 | AD22: 133405.08 | AE22: 129558.16 | AF22: 128483.09 | AG22: 130698.67 | AH22: 130204.41 | AI22: 126796.97 | AJ22: 126530.55 | AK22: 169723.25 | AL22: 141606.66
A23: Palmetto | B23: =IFERROR(X23/Y23-1,0) -> -0.0016834085 | C23: =IFERROR(Y23/Z23-1,0) -> -0.026310241 | D23: =IFERROR(Z23/AA23-1,0) -> 0.0033806978 | E23: =IFERROR(AA23/AB23-1,0) -> -0.0064170068 | F23: =IFERROR(AB23/AC23-1,0) -> -0.026499427 | G23: =IFERROR(AC23/AD23-1,0) -> 0.011013404 | H23: =IFERROR(AD23/AE23-1,0) -> 0.041452426 | I23: =IFERROR(AE23/AF23-1,0) -> 0.02145097 | ... O23: =IFERROR(AK23/AL23-1,0) -> -0.075860161 | R23: Palmetto | S23: =_xlfn.XLOOKUP(R23,Summary!A:A,Summary!B:B) -> TH | T23: =_xlfn.XLOOKUP(R23,Summary!A:A,Summary!C:C) -> 1304 | U23: =_xlfn.XLOOKUP(R23,Summary!A:A,Summary!D:D) -> 3 | V23: =_xlfn.XLOOKUP(R23,Summary!A:A,Summary!E:E) -> 2.5 | W23: =_xlfn.XLOOKUP(R23,Summary!A:A,Summary!F:F) -> 0 | X23: =_xlfn.XLOOKUP(R23,Summary!A:A,Summary!L:L) -> 110043.18 | Y23: 110228.74 | Z23: 113207.25 | AA23: 112825.82 | AB23: 113554.5 | AC23: 116645.54 | AD23: 115374.87 | AE23: 110782.66 | AF23: 108456.17 | AG23: 110021.48 | AH23: 110042.23 | AI23: 112463.93 | AJ23: 112159.95 | AK23: 113126 | AL23: 122412.21
A24: Palmetto II | B24: =IFERROR(X24/Y24-1,0) -> -0.00024063428 | C24: =IFERROR(Y24/Z24-1,0) -> 0 | D24: =IFERROR(Z24/AA24-1,0) -> 0 | E24: =IFERROR(AA24/AB24-1,0) -> 0 | F24: =IFERROR(AB24/AC24-1,0) -> 0 | G24: =IFERROR(AC24/AD24-1,0) -> 0 | H24: =IFERROR(AD24/AE24-1,0) -> 0 | I24: =IFERROR(AE24/AF24-1,0) -> 0 | ... O24: =IFERROR(AK24/AL24-1,0) -> 0 | R24: Palmetto II | S24: TH | T24: 1424 | U24: 3 | V24: 2.5 | W24: 0 | X24: =_xlfn.XLOOKUP(R24,Summary!A:A,Summary!L:L) -> 111054.7 | Y24: 111081.43
A25: Palm II | B25: =IFERROR(X25/Y25-1,0) -> -0.0015174564 | C25: =IFERROR(Y25/Z25-1,0) -> 0 | D25: =IFERROR(Z25/AA25-1,0) -> 0 | E25: =IFERROR(AA25/AB25-1,0) -> 0 | F25: =IFERROR(AB25/AC25-1,0) -> 0 | G25: =IFERROR(AC25/AD25-1,0) -> 0 | H25: =IFERROR(AD25/AE25-1,0) -> 0 | I25: =IFERROR(AE25/AF25-1,0) -> 0 | ... O25: =IFERROR(AK25/AL25-1,0) -> 0 | R25: Palm II | S25: TH | T25: 1689 | U25: 3 | V25: 2.5 | W25: =_xlfn.XLOOKUP(R25,Summary!A:A,Summary!F:F) -> 1F | X25: =_xlfn.XLOOKUP(R25,Summary!A:A,Summary!L:L) -> 132402.26 | Y25: 132603.48
A26: Bayberry | B26: =IFERROR(X26/Y26-1,0) -> -0.0017035748 | C26: =IFERROR(Y26/Z26-1,0) -> -0.026674873 | D26: =IFERROR(Z26/AA26-1,0) -> 0.022250007 | E26: =IFERROR(AA26/AB26-1,0) -> -0.0088221458 | F26: =IFERROR(AB26/AC26-1,0) -> 0 | G26: =IFERROR(AC26/AD26-1,0) -> 0 | H26: =IFERROR(AD26/AE26-1,0) -> 0 | I26: =IFERROR(AE26/AF26-1,0) -> 0 | ... O26: =IFERROR(AK26/AL26-1,0) -> 0 | R26: Bayberry | S26: =_xlfn.XLOOKUP(R26,Summary!A:A,Summary!B:B) -> TH | T26: =_xlfn.XLOOKUP(R26,Summary!A:A,Summary!C:C) -> 1500 | U26: =_xlfn.XLOOKUP(R26,Summary!A:A,Summary!D:D) -> 3 | V26: =_xlfn.XLOOKUP(R26,Summary!A:A,Summary!E:E) -> 2.5 | W26: =_xlfn.XLOOKUP(R26,Summary!A:A,Summary!F:F) -> 1F | X26: =_xlfn.XLOOKUP(R26,Summary!A:A,Summary!L:L) -> 125251.84 | Y26: 125465.58 | Z26: 128904.08 | AA26: 126098.39 | AB26: 127220.75
A27: Cottonwood | B27: =IFERROR(X27/Y27-1,0) -> -0.00088647314 | C27: =IFERROR(Y27/Z27-1,0) -> -0.0053447587 | D27: =IFERROR(Z27/AA27-1,0) -> 0.0012093526 | E27: =IFERROR(AA27/AB27-1,0) -> -0.021927742 | F27: =IFERROR(AB27/AC27-1,0) -> 0 | G27: =IFERROR(AC27/AD27-1,0) -> 0 | H27: =IFERROR(AD27/AE27-1,0) -> 0 | I27: =IFERROR(AE27/AF27-1,0) -> 0 | ... O27: =IFERROR(AK27/AL27-1,0) -> 0 | R27: Cottonwood | S27: =_xlfn.XLOOKUP(R27,Summary!A:A,Summary!B:B) -> TH | T27: =_xlfn.XLOOKUP(R27,Summary!A:A,Summary!C:C) -> 1729 | U27: =_xlfn.XLOOKUP(R27,Summary!A:A,Summary!D:D) -> 3 | V27: =_xlfn.XLOOKUP(R27,Summary!A:A,Summary!E:E) -> 2.5 | W27: =_xlfn.XLOOKUP(R27,Summary!A:A,Summary!F:F) -> 1F | X27: =_xlfn.XLOOKUP(R27,Summary!A:A,Summary!L:L) -> 142077.91 | Y27: 142203.97 | Z27: 142968.1 | AA27: 142795.41 | AB27: 145996.79
A28: Linville | B28: =IFERROR(X28/Y28-1,0) -> -0.00039912383 | C28: =IFERROR(Y28/Z28-1,0) -> 0 | D28: =IFERROR(Z28/AA28-1,0) -> 0 | E28: =IFERROR(AA28/AB28-1,0) -> 0 | F28: =IFERROR(AB28/AC28-1,0) -> 0 | G28: =IFERROR(AC28/AD28-1,0) -> 0 | H28: =IFERROR(AD28/AE28-1,0) -> 0 | I28: =IFERROR(AE28/AF28-1,0) -> 0 | ... O28: =IFERROR(AK28/AL28-1,0) -> 0 | R28: Linville | S28: =_xlfn.XLOOKUP(R28,Summary!A:A,Summary!B:B) -> TH | T28: 2188 | U28: 4 | V28: 2.5 | W28: 2F | X28: =_xlfn.XLOOKUP(R28,Summary!A:A,Summary!L:L) -> 160612.82 | Y28: 160676.95
A29: Locust | B29: =IFERROR(X29/Y29-1,0) -> -0.0013079832 | C29: =IFERROR(Y29/Z29-1,0) -> -0.0188174 | D29: =IFERROR(Z29/AA29-1,0) -> 0.016328799 | E29: =IFERROR(AA29/AB29-1,0) -> -0.0097257021 | F29: =IFERROR(AB29/AC29-1,0) -> 0 | G29: =IFERROR(AC29/AD29-1,0) -> 0 | H29: =IFERROR(AD29/AE29-1,0) -> 0 | I29: =IFERROR(AE29/AF29-1,0) -> 0 | ... O29: =IFERROR(AK29/AL29-1,0) -> 0 | R29: Locust | S29: =_xlfn.XLOOKUP(R29,Summary!A:A,Summary!B:B) -> TH | T29: =_xlfn.XLOOKUP(R29,Summary!A:A,Summary!C:C) -> 1669 | U29: =_xlfn.XLOOKUP(R29,Summary!A:A,Summary!D:D) -> 3 | V29: =_xlfn.XLOOKUP(R29,Summary!A:A,Summary!E:E) -> 2.5 | W29: =_xlfn.XLOOKUP(R29,Summary!A:A,Summary!F:F) -> 1F | X29: =_xlfn.XLOOKUP(R29,Summary!A:A,Summary!L:L) -> 133947.09 | Y29: 134122.52 | Z29: 136694.76 | AA29: 134498.56 | AB29: 135819.5
A30: Fig | B30: =IFERROR(X30/Y30-1,0) -> 0.0047165403 | C30: =IFERROR(Y30/Z30-1,0) -> -0.01632041 | D30: =IFERROR(Z30/AA30-1,0) -> 0.0042832344 | E30: =IFERROR(AA30/AB30-1,0) -> -0.085437571 | F30: =IFERROR(AB30/AC30-1,0) -> 0 | G30: =IFERROR(AC30/AD30-1,0) -> 0 | H30: =IFERROR(AD30/AE30-1,0) -> 0 | I30: =IFERROR(AE30/AF30-1,0) -> 0 | ... O30: =IFERROR(AK30/AL30-1,0) -> 0 | R30: Fig | S30: =_xlfn.XLOOKUP(R30,Summary!A:A,Summary!B:B) -> TH | T30: =_xlfn.XLOOKUP(R30,Summary!A:A,Summary!C:C) -> 1798 | U30: =_xlfn.XLOOKUP(R30,Summary!A:A,Summary!D:D) -> 3 | V30: =_xlfn.XLOOKUP(R30,Summary!A:A,Summary!E:E) -> 3.5 | W30: =_xlfn.XLOOKUP(R30,Summary!A:A,Summary!F:F) -> 1R | X30: =_xlfn.XLOOKUP(R30,Summary!A:A,Summary!L:L) -> 150174.71 | Y30: 149469.73 | Z30: 151949.61 | AA30: 151301.55 | AB30: 165436 | AC30: 165436 | AD30: 165436 | AE30: 165436 | AF30: 165436
A31: Poplar | B31: =IFERROR(X31/Y31-1,0) -> -0.0015029306 | C31: =IFERROR(Y31/Z31-1,0) -> -0.0043543397 | D31: =IFERROR(Z31/AA31-1,0) -> 0 | E31: =IFERROR(AA31/AB31-1,0) -> 0 | F31: =IFERROR(AB31/AC31-1,0) -> 0 | G31: =IFERROR(AC31/AD31-1,0) -> 0 | H31: =IFERROR(AD31/AE31-1,0) -> 0 | I31: =IFERROR(AE31/AF31-1,0) -> 0 | ... O31: =IFERROR(AK31/AL31-1,0) -> 0 | R31: Poplar | S31: =_xlfn.XLOOKUP(R31,Summary!A:A,Summary!B:B) -> TH | T31: =_xlfn.XLOOKUP(R31,Summary!A:A,Summary!C:C) -> 1483 | U31: =_xlfn.XLOOKUP(R31,Summary!A:A,Summary!D:D) -> 3 | V31: =_xlfn.XLOOKUP(R31,Summary!A:A,Summary!E:E) -> 2.5 | W31: =_xlfn.XLOOKUP(R31,Summary!A:A,Summary!F:F) -> 2R | X31: =_xlfn.XLOOKUP(R31,Summary!A:A,Summary!L:L) -> 130813.81 | Y31: 131010.71 | Z31: 131583.67
A32: Fraser | B32: =IFERROR(X32/Y32-1,0) -> -0.0015324271 | C32: =IFERROR(Y32/Z32-1,0) -> -0.030648361 | D32: =IFERROR(Z32/AA32-1,0) -> 0 | E32: =IFERROR(AA32/AB32-1,0) -> 0 | F32: =IFERROR(AB32/AC32-1,0) -> 0 | G32: =IFERROR(AC32/AD32-1,0) -> 0 | H32: =IFERROR(AD32/AE32-1,0) -> 0 | I32: =IFERROR(AE32/AF32-1,0) -> 0 | ... O32: =IFERROR(AK32/AL32-1,0) -> 0 | R32: Fraser | S32: =_xlfn.XLOOKUP(R32,Summary!A:A,Summary!B:B) -> TH | T32: =_xlfn.XLOOKUP(R32,Summary!A:A,Summary!C:C) -> 1689 | U32: =_xlfn.XLOOKUP(R32,Summary!A:A,Summary!D:D) -> 3 | V32: =_xlfn.XLOOKUP(R32,Summary!A:A,Summary!E:E) -> 2.5 | W32: =_xlfn.XLOOKUP(R32,Summary!A:A,Summary!F:F) -> 2R | X32: =_xlfn.XLOOKUP(R32,Summary!A:A,Summary!L:L) -> 133563.2 | Y32: 133768.19 | Z32: 137997.59
A33: Sycamore | B33: =IFERROR(X33/Y33-1,0) -> 0.00042807059 | C33: =IFERROR(Y33/Z33-1,0) -> -0.027083784 | D33: =IFERROR(Z33/AA33-1,0) -> 0 | E33: =IFERROR(AA33/AB33-1,0) -> 0 | F33: =IFERROR(AB33/AC33-1,0) -> 0 | G33: =IFERROR(AC33/AD33-1,0) -> 0 | H33: =IFERROR(AD33/AE33-1,0) -> 0 | I33: =IFERROR(AE33/AF33-1,0) -> 0 | ... O33: =IFERROR(AK33/AL33-1,0) -> 0 | R33: Sycamore | S33: =_xlfn.XLOOKUP(R33,Summary!A:A,Summary!B:B) -> TH | T33: =_xlfn.XLOOKUP(R33,Summary!A:A,Summary!C:C) -> 1993 | U33: =_xlfn.XLOOKUP(R33,Summary!A:A,Summary!D:D) -> 3 | V33: =_xlfn.XLOOKUP(R33,Summary!A:A,Summary!E:E) -> 2.5 | W33: =_xlfn.XLOOKUP(R33,Summary!A:A,Summary!F:F) -> 2R | X33: =_xlfn.XLOOKUP(R33,Summary!A:A,Summary!L:L) -> 146861.06 | Y33: 146798.22 | Z33: 150884.75
A34: Alder | B34: =IFERROR(X34/Y34-1,0) -> 0 | C34: =IFERROR(Y34/Z34-1,0) -> 0 | D34: =IFERROR(Z34/AA34-1,0) -> 0 | E34: =IFERROR(AA34/AB34-1,0) -> 0 | F34: =IFERROR(AB34/AC34-1,0) -> 0 | G34: =IFERROR(AC34/AD34-1,0) -> 0 | H34: =IFERROR(AD34/AE34-1,0) -> 0 | I34: =IFERROR(AE34/AF34-1,0) -> 0 | R34: Alder | S34: =_xlfn.XLOOKUP(R34,Summary!A:A,Summary!B:B) -> TH | T34: =_xlfn.XLOOKUP(R34,Summary!A:A,Summary!C:C) -> 1700 | U34: =_xlfn.XLOOKUP(R34,Summary!A:A,Summary!D:D) -> 3 | V34: =_xlfn.XLOOKUP(R34,Summary!A:A,Summary!E:E) -> 2.5 | W34: =_xlfn.XLOOKUP(R34,Summary!A:A,Summary!F:F) -> 1R | X34: =_xlfn.XLOOKUP(R34,Summary!A:A,Summary!L:L) -> 130195.63
A35: Boxelder | B35: =IFERROR(X35/Y35-1,0) -> 0 | C35: =IFERROR(Y35/Z35-1,0) -> 0 | D35: =IFERROR(Z35/AA35-1,0) -> 0 | E35: =IFERROR(AA35/AB35-1,0) -> 0 | F35: =IFERROR(AB35/AC35-1,0) -> 0 | G35: =IFERROR(AC35/AD35-1,0) -> 0 | H35: =IFERROR(AD35/AE35-1,0) -> 0 | I35: =IFERROR(AE35/AF35-1,0) -> 0 | R35: Boxelder | S35: =_xlfn.XLOOKUP(R35,Summary!A:A,Summary!B:B) -> TH | T35: =_xlfn.XLOOKUP(R35,Summary!A:A,Summary!C:C) -> 1796 | U35: =_xlfn.XLOOKUP(R35,Summary!A:A,Summary!D:D) -> 4 | V35: =_xlfn.XLOOKUP(R35,Summary!A:A,Summary!E:E) -> 2.5 | W35: =_xlfn.XLOOKUP(R35,Summary!A:A,Summary!F:F) -> 2 | X35: =_xlfn.XLOOKUP(R35,Summary!A:A,Summary!L:L) -> 141492.43
A36: Bur Oak | B36: =IFERROR(X36/Y36-1,0) -> 0 | C36: =IFERROR(Y36/Z36-1,0) -> 0 | D36: =IFERROR(Z36/AA36-1,0) -> 0 | E36: =IFERROR(AA36/AB36-1,0) -> 0 | F36: =IFERROR(AB36/AC36-1,0) -> 0 | G36: =IFERROR(AC36/AD36-1,0) -> 0 | H36: =IFERROR(AD36/AE36-1,0) -> 0 | I36: =IFERROR(AE36/AF36-1,0) -> 0 | R36: Bur Oak | S36: =_xlfn.XLOOKUP(R36,Summary!A:A,Summary!B:B) -> TH | T36: =_xlfn.XLOOKUP(R36,Summary!A:A,Summary!C:C) -> 1548 | U36: =_xlfn.XLOOKUP(R36,Summary!A:A,Summary!D:D) -> 3 | V36: =_xlfn.XLOOKUP(R36,Summary!A:A,Summary!E:E) -> 2.5 | W36: =_xlfn.XLOOKUP(R36,Summary!A:A,Summary!F:F) -> 1 | X36: =_xlfn.XLOOKUP(R36,Summary!A:A,Summary!L:L) -> 124886
A37: Conifer | B37: =IFERROR(X37/Y37-1,0) -> 0 | C37: =IFERROR(Y37/Z37-1,0) -> 0 | D37: =IFERROR(Z37/AA37-1,0) -> 0 | E37: =IFERROR(AA37/AB37-1,0) -> 0 | F37: =IFERROR(AB37/AC37-1,0) -> 0 | G37: =IFERROR(AC37/AD37-1,0) -> 0 | H37: =IFERROR(AD37/AE37-1,0) -> 0 | I37: =IFERROR(AE37/AF37-1,0) -> 0 | R37: Conifer | S37: =_xlfn.XLOOKUP(R37,Summary!A:A,Summary!B:B) -> TH | T37: =_xlfn.XLOOKUP(R37,Summary!A:A,Summary!C:C) -> 1892 | U37: =_xlfn.XLOOKUP(R37,Summary!A:A,Summary!D:D) -> 0 | V37: =_xlfn.XLOOKUP(R37,Summary!A:A,Summary!E:E) -> 0 | W37: =_xlfn.XLOOKUP(R37,Summary!A:A,Summary!F:F) -> 2 | X37: =_xlfn.XLOOKUP(R37,Summary!A:A,Summary!L:L) -> 163028.48
A38: Pinyon | B38: =IFERROR(X38/Y38-1,0) -> 0 | C38: =IFERROR(Y38/Z38-1,0) -> 0 | D38: =IFERROR(Z38/AA38-1,0) -> 0 | E38: =IFERROR(AA38/AB38-1,0) -> 0 | F38: =IFERROR(AB38/AC38-1,0) -> 0 | G38: =IFERROR(AC38/AD38-1,0) -> 0 | H38: =IFERROR(AD38/AE38-1,0) -> 0 | I38: =IFERROR(AE38/AF38-1,0) -> 0 | R38: Pinyon | S38: =_xlfn.XLOOKUP(R38,Summary!A:A,Summary!B:B) -> TH | T38: =_xlfn.XLOOKUP(R38,Summary!A:A,Summary!C:C) -> 1748 | U38: =_xlfn.XLOOKUP(R38,Summary!A:A,Summary!D:D) -> 3 | V38: =_xlfn.XLOOKUP(R38,Summary!A:A,Summary!E:E) -> 3.5 | W38: =_xlfn.XLOOKUP(R38,Summary!A:A,Summary!F:F) -> 2 | X38: =_xlfn.XLOOKUP(R38,Summary!A:A,Summary!L:L) -> 151644.3
A40: Retired
A41: Arborbrook | D41: =IFERROR(Z41/AA41-1,0) -> -0.015338364 | E41: =IFERROR(AA41/AB41-1,0) -> -0.017791546 | F41: =IFERROR(AB41/AC41-1,0) -> 0.002137465 | G41: =IFERROR(AC41/AD41-1,0) -> 0.0031937584 | H41: =IFERROR(AD41/AE41-1,0) -> 0.01705282 | I41: =IFERROR(AE41/AF41-1,0) -> 0.01661383 | J41: =IFERROR(AF41/AG41-1,0) -> 4.4408921e-16 | K41: =IFERROR(AG41/AH41-1,0) -> 0.00030031511 | ... O41: =IFERROR(AK41/AL41-1,0) -> 0 | R41: Arborbrook | S41: =_xlfn.XLOOKUP(R41,Summary!A:A,Summary!B:B) -> SFH | T41: =_xlfn.XLOOKUP(R41,Summary!A:A,Summary!C:C) -> 2219 | U41: =_xlfn.XLOOKUP(R41,Summary!A:A,Summary!D:D) -> 3 | V41: =_xlfn.XLOOKUP(R41,Summary!A:A,Summary!E:E) -> 3 | W41: =_xlfn.XLOOKUP(R41,Summary!A:A,Summary!F:F) -> 2 | Z41: 174492.44 | AA41: 177210.56 | AB41: 180420.52 | AC41: 180035.7 | AD41: 179462.54 | AE41: 176453.51 | AF41: 173569.85 | AG41: 173569.85 | AH41: 173517.74 | AI41: 177694.73 | AJ41: 177503.33 | AK41: 174809.89
A42: Red Oak | D42: =IFERROR(Z42/AA42-1,0) -> 0.014378871 | E42: =IFERROR(AA42/AB42-1,0) -> -0.0033390678 | F42: =IFERROR(AB42/AC42-1,0) -> 0.002630482 | G42: =IFERROR(AC42/AD42-1,0) -> 0.009033978 | H42: =IFERROR(AD42/AE42-1,0) -> 0.019887262 | I42: =IFERROR(AE42/AF42-1,0) -> 0.028594617 | J42: =IFERROR(AF42/AG42-1,0) -> -0.012852205 | K42: =IFERROR(AG42/AH42-1,0) -> 0.0089320958 | ... O42: =IFERROR(AK42/AL42-1,0) -> -0.061185415 | R42: Red Oak | S42: =_xlfn.XLOOKUP(R42,Summary!A:A,Summary!B:B) -> SFH | T42: =_xlfn.XLOOKUP(R42,Summary!A:A,Summary!C:C) -> 2217 | U42: =_xlfn.XLOOKUP(R42,Summary!A:A,Summary!D:D) -> 4 | V42: =_xlfn.XLOOKUP(R42,Summary!A:A,Summary!E:E) -> 3 | W42: =_xlfn.XLOOKUP(R42,Summary!A:A,Summary!F:F) -> 2 | Z42: 157988.86 | AA42: 155749.36 | AB42: 156271.16 | AC42: 155861.17 | AD42: 154465.73 | AE42: 151453.73 | AF42: 147243.36 | AG42: 149160.4 | AH42: 147839.88 | AI42: 152017.35 | AJ42: 153780.72 | AK42: 154643.97 | AL42: 164722.59
A43: Palm | D43: =IFERROR(Z43/AA43-1,0) -> -0.014760446 | E43: =IFERROR(AA43/AB43-1,0) -> -0.0091076343 | F43: =IFERROR(AB43/AC43-1,0) -> -0.0095337566 | G43: =IFERROR(AC43/AD43-1,0) -> 0.0055803285 | H43: =IFERROR(AD43/AE43-1,0) -> 0.029379106 | I43: =IFERROR(AE43/AF43-1,0) -> -0.014324123 | J43: =IFERROR(AF43/AG43-1,0) -> -0.012122173 | K43: =IFERROR(AG43/AH43-1,0) -> -0.0023303741 | ... O43: =IFERROR(AK43/AL43-1,0) -> -0.034000537 | R43: Palm | S43: =_xlfn.XLOOKUP(R43,Summary!A:A,Summary!B:B) -> TH | T43: =_xlfn.XLOOKUP(R43,Summary!A:A,Summary!C:C) -> 1700 | U43: =_xlfn.XLOOKUP(R43,Summary!A:A,Summary!D:D) -> 3 | V43: =_xlfn.XLOOKUP(R43,Summary!A:A,Summary!E:E) -> 2.5 | W43: =_xlfn.XLOOKUP(R43,Summary!A:A,Summary!F:F) -> 1F | Z43: 134067.29 | AA43: 136075.83 | AB43: 137326.55 | AC43: 138648.39 | AD43: 137878.98 | AE43: 133943.83 | AF43: 135890.34 | AG43: 137557.84 | AH43: 137879.15 | AI43: 141949.58 | AJ43: 141278.69 | AK43: 143222.5 | AL43: 148263.54

Sheet MODEL SUMMARY
A1: County | B1: =Summary!B3 -> None | AI1: 21000 | AJ1: =C58+21000 -> 160411.53 | AM1: =AI1/6 -> 3500
A2: MODEL | AK2: Do not copy models to deal sheet
A3: ACTIVITY | B3: Acacia | C3: Aspen 2-Story | D3: Atlas | E3: Banyan | F3: Cherry | G3: Dogwood | H3: Hazel | I3: Holly | J3: Elm | K3: Lilac | L3: Lily | M3: Magnolia | N3: Spindle | O3: Spruce | P3: Tulip | Q3: White Oak | R3: Willow | S3: Jasmine | T3: Palm II | U3: Palmetto | V3: Palmetto II | W3: Linville | X3: Bayberry | Y3: Alder | Z3: Boxelder | AA3: Bur Oak | AB3: Conifer | AC3: Pinyon | AD3: Cottonwood | AE3: Locust | AF3: Fraser | AG3: Sycamore | AH3: Poplar | AI3: Fig | AJ3: Aspen 3-Story | AK3: West End | AL3: Long Farm | AM3: Fir
A4: Dumpster | B4: {=IFERROR(_xlfn.XLOOKUP($A4, INDIRECT("'" & B$3 & "'!A:A"), INDIRECT("'" & B$3 & "'!B:B")),0)} -> 3000 | C4: {=IFERROR(_xlfn.XLOOKUP($A4, INDIRECT("'" & C$3 & "'!A:A"), INDIRECT("'" & C$3 & "'!B:B")),0)} -> 3000 | D4: {=IFERROR(_xlfn.XLOOKUP($A4, INDIRECT("'" & D$3 & "'!A:A"), INDIRECT("'" & D$3 & "'!B:B")),0)} -> 3000 | E4: {=IFERROR(_xlfn.XLOOKUP($A4, INDIRECT("'" & E$3 & "'!A:A"), INDIRECT("'" & E$3 & "'!B:B")),0)} -> 3000 | F4: {=IFERROR(_xlfn.XLOOKUP($A4, INDIRECT("'" & F$3 & "'!A:A"), INDIRECT("'" & F$3 & "'!B:B")),0)} -> 3000 | G4: {=IFERROR(_xlfn.XLOOKUP($A4, INDIRECT("'" & G$3 & "'!A:A"), INDIRECT("'" & G$3 & "'!B:B")),0)} -> 3000 | H4: {=IFERROR(_xlfn.XLOOKUP($A4, INDIRECT("'" & H$3 & "'!A:A"), INDIRECT("'" & H$3 & "'!B:B")),0)} -> 3000 | I4: {=IFERROR(_xlfn.XLOOKUP($A4, INDIRECT("'" & I$3 & "'!A:A"), INDIRECT("'" & I$3 & "'!B:B")),0)} -> 3000 | ... AI4: {=IFERROR(_xlfn.XLOOKUP($A4, INDIRECT("'" & AI$3 & "'!A:A"), INDIRECT("'" & AI$3 & "'!B:B")),0)} -> 1500 | AJ4: =C4 -> 3000 | AK4: {=IFERROR(_xlfn.XLOOKUP($A4, INDIRECT("'" & AK$3 & "'!A:A"), INDIRECT("'" & AK$3 & "'!B:B")),0)} -> 1750 | AL4: {=IFERROR(_xlfn.XLOOKUP($A4, INDIRECT("'" & AL$3 & "'!A:A"), INDIRECT("'" & AL$3 & "'!B:B")),0)} -> 1750 | AM4: {=IFERROR(_xlfn.XLOOKUP($A4, INDIRECT("'" & AM$3 & "'!A:A"), INDIRECT("'" & AM$3 & "'!B:B")),0)} -> 1750
A5: Utilities | B5: {=IFERROR(_xlfn.XLOOKUP($A5, INDIRECT("'" & B$3 & "'!A:A"), INDIRECT("'" & B$3 & "'!B:B")),0)} -> 300 | C5: {=IFERROR(_xlfn.XLOOKUP($A5, INDIRECT("'" & C$3 & "'!A:A"), INDIRECT("'" & C$3 & "'!B:B")),0)} -> 300 | D5: {=IFERROR(_xlfn.XLOOKUP($A5, INDIRECT("'" & D$3 & "'!A:A"), INDIRECT("'" & D$3 & "'!B:B")),0)} -> 300 | E5: {=IFERROR(_xlfn.XLOOKUP($A5, INDIRECT("'" & E$3 & "'!A:A"), INDIRECT("'" & E$3 & "'!B:B")),0)} -> 300 | F5: {=IFERROR(_xlfn.XLOOKUP($A5, INDIRECT("'" & F$3 & "'!A:A"), INDIRECT("'" & F$3 & "'!B:B")),0)} -> 300 | G5: {=IFERROR(_xlfn.XLOOKUP($A5, INDIRECT("'" & G$3 & "'!A:A"), INDIRECT("'" & G$3 & "'!B:B")),0)} -> 300 | H5: {=IFERROR(_xlfn.XLOOKUP($A5, INDIRECT("'" & H$3 & "'!A:A"), INDIRECT("'" & H$3 & "'!B:B")),0)} -> 300 | I5: {=IFERROR(_xlfn.XLOOKUP($A5, INDIRECT("'" & I$3 & "'!A:A"), INDIRECT("'" & I$3 & "'!B:B")),0)} -> 300 | ... AI5: {=IFERROR(_xlfn.XLOOKUP($A5, INDIRECT("'" & AI$3 & "'!A:A"), INDIRECT("'" & AI$3 & "'!B:B")),0)} -> 300 | AJ5: =C5 -> 300 | AK5: {=IFERROR(_xlfn.XLOOKUP($A5, INDIRECT("'" & AK$3 & "'!A:A"), INDIRECT("'" & AK$3 & "'!B:B")),0)} -> 200 | AL5: {=IFERROR(_xlfn.XLOOKUP($A5, INDIRECT("'" & AL$3 & "'!A:A"), INDIRECT("'" & AL$3 & "'!B:B")),0)} -> 200 | AM5: {=IFERROR(_xlfn.XLOOKUP($A5, INDIRECT("'" & AM$3 & "'!A:A"), INDIRECT("'" & AM$3 & "'!B:B")),0)} -> 200
A6: Portable toilet | B6: {=IFERROR(_xlfn.XLOOKUP($A6, INDIRECT("'" & B$3 & "'!A:A"), INDIRECT("'" & B$3 & "'!B:B")),0)} -> 875 | C6: {=IFERROR(_xlfn.XLOOKUP($A6, INDIRECT("'" & C$3 & "'!A:A"), INDIRECT("'" & C$3 & "'!B:B")),0)} -> 875 | D6: {=IFERROR(_xlfn.XLOOKUP($A6, INDIRECT("'" & D$3 & "'!A:A"), INDIRECT("'" & D$3 & "'!B:B")),0)} -> 875 | E6: {=IFERROR(_xlfn.XLOOKUP($A6, INDIRECT("'" & E$3 & "'!A:A"), INDIRECT("'" & E$3 & "'!B:B")),0)} -> 875 | F6: {=IFERROR(_xlfn.XLOOKUP($A6, INDIRECT("'" & F$3 & "'!A:A"), INDIRECT("'" & F$3 & "'!B:B")),0)} -> 875 | G6: {=IFERROR(_xlfn.XLOOKUP($A6, INDIRECT("'" & G$3 & "'!A:A"), INDIRECT("'" & G$3 & "'!B:B")),0)} -> 875 | H6: {=IFERROR(_xlfn.XLOOKUP($A6, INDIRECT("'" & H$3 & "'!A:A"), INDIRECT("'" & H$3 & "'!B:B")),0)} -> 875 | I6: {=IFERROR(_xlfn.XLOOKUP($A6, INDIRECT("'" & I$3 & "'!A:A"), INDIRECT("'" & I$3 & "'!B:B")),0)} -> 875 | ... AI6: {=IFERROR(_xlfn.XLOOKUP($A6, INDIRECT("'" & AI$3 & "'!A:A"), INDIRECT("'" & AI$3 & "'!B:B")),0)} -> 437.5 | AJ6: =C6 -> 875 | AK6: {=IFERROR(_xlfn.XLOOKUP($A6, INDIRECT("'" & AK$3 & "'!A:A"), INDIRECT("'" & AK$3 & "'!B:B")),0)} -> 350 | AL6: {=IFERROR(_xlfn.XLOOKUP($A6, INDIRECT("'" & AL$3 & "'!A:A"), INDIRECT("'" & AL$3 & "'!B:B")),0)} -> 350 | AM6: {=IFERROR(_xlfn.XLOOKUP($A6, INDIRECT("'" & AM$3 & "'!A:A"), INDIRECT("'" & AM$3 & "'!B:B")),0)} -> 350
A7: Permit Box | B7: {=IFERROR(_xlfn.XLOOKUP($A7, INDIRECT("'" & B$3 & "'!A:A"), INDIRECT("'" & B$3 & "'!B:B")),0)} -> 50 | C7: {=IFERROR(_xlfn.XLOOKUP($A7, INDIRECT("'" & C$3 & "'!A:A"), INDIRECT("'" & C$3 & "'!B:B")),0)} -> 50 | D7: {=IFERROR(_xlfn.XLOOKUP($A7, INDIRECT("'" & D$3 & "'!A:A"), INDIRECT("'" & D$3 & "'!B:B")),0)} -> 50 | E7: {=IFERROR(_xlfn.XLOOKUP($A7, INDIRECT("'" & E$3 & "'!A:A"), INDIRECT("'" & E$3 & "'!B:B")),0)} -> 50 | F7: {=IFERROR(_xlfn.XLOOKUP($A7, INDIRECT("'" & F$3 & "'!A:A"), INDIRECT("'" & F$3 & "'!B:B")),0)} -> 50 | G7: {=IFERROR(_xlfn.XLOOKUP($A7, INDIRECT("'" & G$3 & "'!A:A"), INDIRECT("'" & G$3 & "'!B:B")),0)} -> 50 | H7: {=IFERROR(_xlfn.XLOOKUP($A7, INDIRECT("'" & H$3 & "'!A:A"), INDIRECT("'" & H$3 & "'!B:B")),0)} -> 50 | I7: {=IFERROR(_xlfn.XLOOKUP($A7, INDIRECT("'" & I$3 & "'!A:A"), INDIRECT("'" & I$3 & "'!B:B")),0)} -> 50 | ... AI7: {=IFERROR(_xlfn.XLOOKUP($A7, INDIRECT("'" & AI$3 & "'!A:A"), INDIRECT("'" & AI$3 & "'!B:B")),0)} -> 50 | AJ7: =C7 -> 50 | AK7: {=IFERROR(_xlfn.XLOOKUP($A7, INDIRECT("'" & AK$3 & "'!A:A"), INDIRECT("'" & AK$3 & "'!B:B")),0)} -> 50 | AL7: {=IFERROR(_xlfn.XLOOKUP($A7, INDIRECT("'" & AL$3 & "'!A:A"), INDIRECT("'" & AL$3 & "'!B:B")),0)} -> 50 | AM7: {=IFERROR(_xlfn.XLOOKUP($A7, INDIRECT("'" & AM$3 & "'!A:A"), INDIRECT("'" & AM$3 & "'!B:B")),0)} -> 50
A8: Termite | B8: {=IFERROR(_xlfn.XLOOKUP($A8, INDIRECT("'" & B$3 & "'!A:A"), INDIRECT("'" & B$3 & "'!B:B")),0)} -> 225 | C8: {=IFERROR(_xlfn.XLOOKUP($A8, INDIRECT("'" & C$3 & "'!A:A"), INDIRECT("'" & C$3 & "'!B:B")),0)} -> 225 | D8: {=IFERROR(_xlfn.XLOOKUP($A8, INDIRECT("'" & D$3 & "'!A:A"), INDIRECT("'" & D$3 & "'!B:B")),0)} -> 225 | E8: {=IFERROR(_xlfn.XLOOKUP($A8, INDIRECT("'" & E$3 & "'!A:A"), INDIRECT("'" & E$3 & "'!B:B")),0)} -> 225 | F8: {=IFERROR(_xlfn.XLOOKUP($A8, INDIRECT("'" & F$3 & "'!A:A"), INDIRECT("'" & F$3 & "'!B:B")),0)} -> 225 | G8: {=IFERROR(_xlfn.XLOOKUP($A8, INDIRECT("'" & G$3 & "'!A:A"), INDIRECT("'" & G$3 & "'!B:B")),0)} -> 225 | H8: {=IFERROR(_xlfn.XLOOKUP($A8, INDIRECT("'" & H$3 & "'!A:A"), INDIRECT("'" & H$3 & "'!B:B")),0)} -> 225 | I8: {=IFERROR(_xlfn.XLOOKUP($A8, INDIRECT("'" & I$3 & "'!A:A"), INDIRECT("'" & I$3 & "'!B:B")),0)} -> 225 | ... AI8: {=IFERROR(_xlfn.XLOOKUP($A8, INDIRECT("'" & AI$3 & "'!A:A"), INDIRECT("'" & AI$3 & "'!B:B")),0)} -> 100 | AJ8: =C8 -> 225 | AK8: {=IFERROR(_xlfn.XLOOKUP($A8, INDIRECT("'" & AK$3 & "'!A:A"), INDIRECT("'" & AK$3 & "'!B:B")),0)} -> 250 | AL8: {=IFERROR(_xlfn.XLOOKUP($A8, INDIRECT("'" & AL$3 & "'!A:A"), INDIRECT("'" & AL$3 & "'!B:B")),0)} -> 250 | AM8: {=IFERROR(_xlfn.XLOOKUP($A8, INDIRECT("'" & AM$3 & "'!A:A"), INDIRECT("'" & AM$3 & "'!B:B")),0)} -> 250
A9: Lumber All Floors | B9: {=IFERROR(_xlfn.XLOOKUP($A9, INDIRECT("'" & B$3 & "'!A:A"), INDIRECT("'" & B$3 & "'!B:B")),0)} -> 12160.21 | C9: {=IFERROR(_xlfn.XLOOKUP($A9, INDIRECT("'" & C$3 & "'!A:A"), INDIRECT("'" & C$3 & "'!B:B")),0)} -> 10337.34 | D9: {=IFERROR(_xlfn.XLOOKUP($A9, INDIRECT("'" & D$3 & "'!A:A"), INDIRECT("'" & D$3 & "'!B:B")),0)} -> 6740.29 | E9: {=IFERROR(_xlfn.XLOOKUP($A9, INDIRECT("'" & E$3 & "'!A:A"), INDIRECT("'" & E$3 & "'!B:B")),0)} -> 13360.22 | F9: {=IFERROR(_xlfn.XLOOKUP($A9, INDIRECT("'" & F$3 & "'!A:A"), INDIRECT("'" & F$3 & "'!B:B")),0)} -> 11967.7 | G9: {=IFERROR(_xlfn.XLOOKUP($A9, INDIRECT("'" & G$3 & "'!A:A"), INDIRECT("'" & G$3 & "'!B:B")),0)} -> 8834.11 | H9: {=IFERROR(_xlfn.XLOOKUP($A9, INDIRECT("'" & H$3 & "'!A:A"), INDIRECT("'" & H$3 & "'!B:B")),0)} -> 9421.12 | I9: {=IFERROR(_xlfn.XLOOKUP($A9, INDIRECT("'" & I$3 & "'!A:A"), INDIRECT("'" & I$3 & "'!B:B")),0)} -> 11034.64 | ... AI9: {=IFERROR(_xlfn.XLOOKUP($A9, INDIRECT("'" & AI$3 & "'!A:A"), INDIRECT("'" & AI$3 & "'!B:B")),0)} -> 17437.45 | AJ9: =C9+AM1 -> 13837.34 | AK9: {=IFERROR(_xlfn.XLOOKUP($A9, INDIRECT("'" & AK$3 & "'!A:A"), INDIRECT("'" & AK$3 & "'!B:B")),0)} -> 17978.67 | AL9: {=IFERROR(_xlfn.XLOOKUP($A9, INDIRECT("'" & AL$3 & "'!A:A"), INDIRECT("'" & AL$3 & "'!B:B")),0)} -> 13058.379 | AM9: {=IFERROR(_xlfn.XLOOKUP($A9, INDIRECT("'" & AM$3 & "'!A:A"), INDIRECT("'" & AM$3 & "'!B:B")),0)} -> 20960.029
A10: Framing Labor | B10: {=IFERROR(_xlfn.XLOOKUP($A10, INDIRECT("'" & B$3 & "'!A:A"), INDIRECT("'" & B$3 & "'!B:B")),0)} -> 11814 | C10: {=IFERROR(_xlfn.XLOOKUP($A10, INDIRECT("'" & C$3 & "'!A:A"), INDIRECT("'" & C$3 & "'!B:B")),0)} -> 9953.4 | D10: {=IFERROR(_xlfn.XLOOKUP($A10, INDIRECT("'" & D$3 & "'!A:A"), INDIRECT("'" & D$3 & "'!B:B")),0)} -> 7399.8 | E10: {=IFERROR(_xlfn.XLOOKUP($A10, INDIRECT("'" & E$3 & "'!A:A"), INDIRECT("'" & E$3 & "'!B:B")),0)} -> 9775 | F10: {=IFERROR(_xlfn.XLOOKUP($A10, INDIRECT("'" & F$3 & "'!A:A"), INDIRECT("'" & F$3 & "'!B:B")),0)} -> 11965.2 | G10: {=IFERROR(_xlfn.XLOOKUP($A10, INDIRECT("'" & G$3 & "'!A:A"), INDIRECT("'" & G$3 & "'!B:B")),0)} -> 8890.8 | H10: {=IFERROR(_xlfn.XLOOKUP($A10, INDIRECT("'" & H$3 & "'!A:A"), INDIRECT("'" & H$3 & "'!B:B")),0)} -> 9630 | I10: {=IFERROR(_xlfn.XLOOKUP($A10, INDIRECT("'" & I$3 & "'!A:A"), INDIRECT("'" & I$3 & "'!B:B")),0)} -> 10848 | ... AI10: {=IFERROR(_xlfn.XLOOKUP($A10, INDIRECT("'" & AI$3 & "'!A:A"), INDIRECT("'" & AI$3 & "'!B:B")),0)} -> 14443.8 | AJ10: =C10 -> 9953.4 | AK10: {=IFERROR(_xlfn.XLOOKUP($A10, INDIRECT("'" & AK$3 & "'!A:A"), INDIRECT("'" & AK$3 & "'!B:B")),0)} -> 13664 | AL10: {=IFERROR(_xlfn.XLOOKUP($A10, INDIRECT("'" & AL$3 & "'!A:A"), INDIRECT("'" & AL$3 & "'!B:B")),0)} -> 11896.044 | AM10: {=IFERROR(_xlfn.XLOOKUP($A10, INDIRECT("'" & AM$3 & "'!A:A"), INDIRECT("'" & AM$3 & "'!B:B")),0)} -> 19456
A11: Floor Trusses | B11: {=IFERROR(_xlfn.XLOOKUP($A11, INDIRECT("'" & B$3 & "'!A:A"), INDIRECT("'" & B$3 & "'!B:B")),0)} -> 3949.41 | C11: {=IFERROR(_xlfn.XLOOKUP($A11, INDIRECT("'" & C$3 & "'!A:A"), INDIRECT("'" & C$3 & "'!B:B")),0)} -> 5510.51 | D11: {=IFERROR(_xlfn.XLOOKUP($A11, INDIRECT("'" & D$3 & "'!A:A"), INDIRECT("'" & D$3 & "'!B:B")),0)} -> 2647.58 | E11: {=IFERROR(_xlfn.XLOOKUP($A11, INDIRECT("'" & E$3 & "'!A:A"), INDIRECT("'" & E$3 & "'!B:B")),0)} -> 6182.05 | F11: {=IFERROR(_xlfn.XLOOKUP($A11, INDIRECT("'" & F$3 & "'!A:A"), INDIRECT("'" & F$3 & "'!B:B")),0)} -> 4975.33 | G11: {=IFERROR(_xlfn.XLOOKUP($A11, INDIRECT("'" & G$3 & "'!A:A"), INDIRECT("'" & G$3 & "'!B:B")),0)} -> 3970.4 | H11: {=IFERROR(_xlfn.XLOOKUP($A11, INDIRECT("'" & H$3 & "'!A:A"), INDIRECT("'" & H$3 & "'!B:B")),0)} -> 5271.22 | I11: {=IFERROR(_xlfn.XLOOKUP($A11, INDIRECT("'" & I$3 & "'!A:A"), INDIRECT("'" & I$3 & "'!B:B")),0)} -> 5587.26 | ... AI11: {=IFERROR(_xlfn.XLOOKUP($A11, INDIRECT("'" & AI$3 & "'!A:A"), INDIRECT("'" & AI$3 & "'!B:B")),0)} -> 5590.86 | AJ11: =C11 -> 5510.51 | AK11: {=IFERROR(_xlfn.XLOOKUP($A11, INDIRECT("'" & AK$3 & "'!A:A"), INDIRECT("'" & AK$3 & "'!B:B")),0)} -> 0 | AL11: {=IFERROR(_xlfn.XLOOKUP($A11, INDIRECT("'" & AL$3 & "'!A:A"), INDIRECT("'" & AL$3 & "'!B:B")),0)} -> 0 | AM11: {=IFERROR(_xlfn.XLOOKUP($A11, INDIRECT("'" & AM$3 & "'!A:A"), INDIRECT("'" & AM$3 & "'!B:B")),0)} -> 0
A12: Stairs | B12: {=IFERROR(_xlfn.XLOOKUP($A12, INDIRECT("'" & B$3 & "'!A:A"), INDIRECT("'" & B$3 & "'!B:B")),0)} -> 580.59 | C12: {=IFERROR(_xlfn.XLOOKUP($A12, INDIRECT("'" & C$3 & "'!A:A"), INDIRECT("'" & C$3 & "'!B:B")),0)} -> 580.59 | D12: {=IFERROR(_xlfn.XLOOKUP($A12, INDIRECT("'" & D$3 & "'!A:A"), INDIRECT("'" & D$3 & "'!B:B")),0)} -> 580.59 | E12: {=IFERROR(_xlfn.XLOOKUP($A12, INDIRECT("'" & E$3 & "'!A:A"), INDIRECT("'" & E$3 & "'!B:B")),0)} -> 1161.17 | F12: {=IFERROR(_xlfn.XLOOKUP($A12, INDIRECT("'" & F$3 & "'!A:A"), INDIRECT("'" & F$3 & "'!B:B")),0)} -> 580.59 | G12: {=IFERROR(_xlfn.XLOOKUP($A12, INDIRECT("'" & G$3 & "'!A:A"), INDIRECT("'" & G$3 & "'!B:B")),0)} -> 580.59 | H12: {=IFERROR(_xlfn.XLOOKUP($A12, INDIRECT("'" & H$3 & "'!A:A"), INDIRECT("'" & H$3 & "'!B:B")),0)} -> 580.59 | I12: {=IFERROR(_xlfn.XLOOKUP($A12, INDIRECT("'" & I$3 & "'!A:A"), INDIRECT("'" & I$3 & "'!B:B")),0)} -> 580.59 | ... AI12: {=IFERROR(_xlfn.XLOOKUP($A12, INDIRECT("'" & AI$3 & "'!A:A"), INDIRECT("'" & AI$3 & "'!B:B")),0)} -> 1161.17 | AJ12: =C12 -> 580.59 | AK12: {=IFERROR(_xlfn.XLOOKUP($A12, INDIRECT("'" & AK$3 & "'!A:A"), INDIRECT("'" & AK$3 & "'!B:B")),0)} -> 541.34 | AL12: {=IFERROR(_xlfn.XLOOKUP($A12, INDIRECT("'" & AL$3 & "'!A:A"), INDIRECT("'" & AL$3 & "'!B:B")),0)} -> 604.57825 | AM12: {=IFERROR(_xlfn.XLOOKUP($A12, INDIRECT("'" & AM$3 & "'!A:A"), INDIRECT("'" & AM$3 & "'!B:B")),0)} -> 1082.68
A13: Roof Trusses | B13: {=IFERROR(_xlfn.XLOOKUP($A13, INDIRECT("'" & B$3 & "'!A:A"), INDIRECT("'" & B$3 & "'!B:B")),0)} -> 7573.68 | C13: {=IFERROR(_xlfn.XLOOKUP($A13, INDIRECT("'" & C$3 & "'!A:A"), INDIRECT("'" & C$3 & "'!B:B")),0)} -> 5111.54 | D13: {=IFERROR(_xlfn.XLOOKUP($A13, INDIRECT("'" & D$3 & "'!A:A"), INDIRECT("'" & D$3 & "'!B:B")),0)} -> 2487.38 | E13: {=IFERROR(_xlfn.XLOOKUP($A13, INDIRECT("'" & E$3 & "'!A:A"), INDIRECT("'" & E$3 & "'!B:B")),0)} -> 2268.08 | F13: {=IFERROR(_xlfn.XLOOKUP($A13, INDIRECT("'" & F$3 & "'!A:A"), INDIRECT("'" & F$3 & "'!B:B")),0)} -> 5402.18 | G13: {=IFERROR(_xlfn.XLOOKUP($A13, INDIRECT("'" & G$3 & "'!A:A"), INDIRECT("'" & G$3 & "'!B:B")),0)} -> 3618.35 | H13: {=IFERROR(_xlfn.XLOOKUP($A13, INDIRECT("'" & H$3 & "'!A:A"), INDIRECT("'" & H$3 & "'!B:B")),0)} -> 4454.89 | I13: {=IFERROR(_xlfn.XLOOKUP($A13, INDIRECT("'" & I$3 & "'!A:A"), INDIRECT("'" & I$3 & "'!B:B")),0)} -> 5406 | ... AI13: {=IFERROR(_xlfn.XLOOKUP($A13, INDIRECT("'" & AI$3 & "'!A:A"), INDIRECT("'" & AI$3 & "'!B:B")),0)} -> 3288.78 | AJ13: =C13 -> 5111.54 | AK13: {=IFERROR(_xlfn.XLOOKUP($A13, INDIRECT("'" & AK$3 & "'!A:A"), INDIRECT("'" & AK$3 & "'!B:B")),0)} -> 2350.87 | AL13: {=IFERROR(_xlfn.XLOOKUP($A13, INDIRECT("'" & AL$3 & "'!A:A"), INDIRECT("'" & AL$3 & "'!B:B")),0)} -> 4412.0162 | AM13: {=IFERROR(_xlfn.XLOOKUP($A13, INDIRECT("'" & AM$3 & "'!A:A"), INDIRECT("'" & AM$3 & "'!B:B")),0)} -> 2958.25
A14: I-Joist/EWP | B14: {=IFERROR(_xlfn.XLOOKUP($A14, INDIRECT("'" & B$3 & "'!A:A"), INDIRECT("'" & B$3 & "'!B:B")),0)} -> 0 | C14: {=IFERROR(_xlfn.XLOOKUP($A14, INDIRECT("'" & C$3 & "'!A:A"), INDIRECT("'" & C$3 & "'!B:B")),0)} -> 0 | D14: {=IFERROR(_xlfn.XLOOKUP($A14, INDIRECT("'" & D$3 & "'!A:A"), INDIRECT("'" & D$3 & "'!B:B")),0)} -> 0 | E14: {=IFERROR(_xlfn.XLOOKUP($A14, INDIRECT("'" & E$3 & "'!A:A"), INDIRECT("'" & E$3 & "'!B:B")),0)} -> 0 | F14: {=IFERROR(_xlfn.XLOOKUP($A14, INDIRECT("'" & F$3 & "'!A:A"), INDIRECT("'" & F$3 & "'!B:B")),0)} -> 0 | G14: {=IFERROR(_xlfn.XLOOKUP($A14, INDIRECT("'" & G$3 & "'!A:A"), INDIRECT("'" & G$3 & "'!B:B")),0)} -> 0 | H14: {=IFERROR(_xlfn.XLOOKUP($A14, INDIRECT("'" & H$3 & "'!A:A"), INDIRECT("'" & H$3 & "'!B:B")),0)} -> 0 | I14: {=IFERROR(_xlfn.XLOOKUP($A14, INDIRECT("'" & I$3 & "'!A:A"), INDIRECT("'" & I$3 & "'!B:B")),0)} -> 0 | ... AI14: {=IFERROR(_xlfn.XLOOKUP($A14, INDIRECT("'" & AI$3 & "'!A:A"), INDIRECT("'" & AI$3 & "'!B:B")),0)} -> 0 | AJ14: =C14 -> 0 | AK14: {=IFERROR(_xlfn.XLOOKUP($A14, INDIRECT("'" & AK$3 & "'!A:A"), INDIRECT("'" & AK$3 & "'!B:B")),0)} -> 3871.91 | AL14: {=IFERROR(_xlfn.XLOOKUP($A14, INDIRECT("'" & AL$3 & "'!A:A"), INDIRECT("'" & AL$3 & "'!B:B")),0)} -> 4990.8868 | AM14: {=IFERROR(_xlfn.XLOOKUP($A14, INDIRECT("'" & AM$3 & "'!A:A"), INDIRECT("'" & AM$3 & "'!B:B")),0)} -> 9288.65
A15: Roofing Shingle | B15: {=IFERROR(_xlfn.XLOOKUP($A15, INDIRECT("'" & B$3 & "'!A:A"), INDIRECT("'" & B$3 & "'!B:B")),0)} -> 0 | C15: {=IFERROR(_xlfn.XLOOKUP($A15, INDIRECT("'" & C$3 & "'!A:A"), INDIRECT("'" & C$3 & "'!B:B")),0)} -> 0 | D15: {=IFERROR(_xlfn.XLOOKUP($A15, INDIRECT("'" & D$3 & "'!A:A"), INDIRECT("'" & D$3 & "'!B:B")),0)} -> 0 | E15: {=IFERROR(_xlfn.XLOOKUP($A15, INDIRECT("'" & E$3 & "'!A:A"), INDIRECT("'" & E$3 & "'!B:B")),0)} -> 0 | F15: {=IFERROR(_xlfn.XLOOKUP($A15, INDIRECT("'" & F$3 & "'!A:A"), INDIRECT("'" & F$3 & "'!B:B")),0)} -> 0 | G15: {=IFERROR(_xlfn.XLOOKUP($A15, INDIRECT("'" & G$3 & "'!A:A"), INDIRECT("'" & G$3 & "'!B:B")),0)} -> 0 | H15: {=IFERROR(_xlfn.XLOOKUP($A15, INDIRECT("'" & H$3 & "'!A:A"), INDIRECT("'" & H$3 & "'!B:B")),0)} -> 0 | I15: {=IFERROR(_xlfn.XLOOKUP($A15, INDIRECT("'" & I$3 & "'!A:A"), INDIRECT("'" & I$3 & "'!B:B")),0)} -> 0 | ... AI15: {=IFERROR(_xlfn.XLOOKUP($A15, INDIRECT("'" & AI$3 & "'!A:A"), INDIRECT("'" & AI$3 & "'!B:B")),0)} -> 0 | AJ15: =C15 -> 0 | AK15: {=IFERROR(_xlfn.XLOOKUP($A15, INDIRECT("'" & AK$3 & "'!A:A"), INDIRECT("'" & AK$3 & "'!B:B")),0)} -> 1822.25 | AL15: {=IFERROR(_xlfn.XLOOKUP($A15, INDIRECT("'" & AL$3 & "'!A:A"), INDIRECT("'" & AL$3 & "'!B:B")),0)} -> 3624.3295 | AM15: {=IFERROR(_xlfn.XLOOKUP($A15, INDIRECT("'" & AM$3 & "'!A:A"), INDIRECT("'" & AM$3 & "'!B:B")),0)} -> 3215.39
A16: Roofing Metal | B16: {=IFERROR(_xlfn.XLOOKUP($A16, INDIRECT("'" & B$3 & "'!A:A"), INDIRECT("'" & B$3 & "'!B:B")),0)} -> 0 | C16: {=IFERROR(_xlfn.XLOOKUP($A16, INDIRECT("'" & C$3 & "'!A:A"), INDIRECT("'" & C$3 & "'!B:B")),0)} -> 0 | D16: {=IFERROR(_xlfn.XLOOKUP($A16, INDIRECT("'" & D$3 & "'!A:A"), INDIRECT("'" & D$3 & "'!B:B")),0)} -> 0 | E16: {=IFERROR(_xlfn.XLOOKUP($A16, INDIRECT("'" & E$3 & "'!A:A"), INDIRECT("'" & E$3 & "'!B:B")),0)} -> 0 | F16: {=IFERROR(_xlfn.XLOOKUP($A16, INDIRECT("'" & F$3 & "'!A:A"), INDIRECT("'" & F$3 & "'!B:B")),0)} -> 0 | G16: {=IFERROR(_xlfn.XLOOKUP($A16, INDIRECT("'" & G$3 & "'!A:A"), INDIRECT("'" & G$3 & "'!B:B")),0)} -> 0 | H16: {=IFERROR(_xlfn.XLOOKUP($A16, INDIRECT("'" & H$3 & "'!A:A"), INDIRECT("'" & H$3 & "'!B:B")),0)} -> 0 | I16: {=IFERROR(_xlfn.XLOOKUP($A16, INDIRECT("'" & I$3 & "'!A:A"), INDIRECT("'" & I$3 & "'!B:B")),0)} -> 0 | ... AI16: {=IFERROR(_xlfn.XLOOKUP($A16, INDIRECT("'" & AI$3 & "'!A:A"), INDIRECT("'" & AI$3 & "'!B:B")),0)} -> 0 | AJ16: =C16 -> 0 | AK16: {=IFERROR(_xlfn.XLOOKUP($A16, INDIRECT("'" & AK$3 & "'!A:A"), INDIRECT("'" & AK$3 & "'!B:B")),0)} -> 0 | AL16: {=IFERROR(_xlfn.XLOOKUP($A16, INDIRECT("'" & AL$3 & "'!A:A"), INDIRECT("'" & AL$3 & "'!B:B")),0)} -> 0 | AM16: {=IFERROR(_xlfn.XLOOKUP($A16, INDIRECT("'" & AM$3 & "'!A:A"), INDIRECT("'" & AM$3 & "'!B:B")),0)} -> 0
A17: Roofing Labor & Material | B17: {=IFERROR(_xlfn.XLOOKUP($A17, INDIRECT("'" & B$3 & "'!A:A"), INDIRECT("'" & B$3 & "'!B:B")),0)} -> 6424.32 | C17: {=IFERROR(_xlfn.XLOOKUP($A17, INDIRECT("'" & C$3 & "'!A:A"), INDIRECT("'" & C$3 & "'!B:B")),0)} -> 4236.58 | D17: {=IFERROR(_xlfn.XLOOKUP($A17, INDIRECT("'" & D$3 & "'!A:A"), INDIRECT("'" & D$3 & "'!B:B")),0)} -> 2920.44 | E17: {=IFERROR(_xlfn.XLOOKUP($A17, INDIRECT("'" & E$3 & "'!A:A"), INDIRECT("'" & E$3 & "'!B:B")),0)} -> 2998.27 | F17: {=IFERROR(_xlfn.XLOOKUP($A17, INDIRECT("'" & F$3 & "'!A:A"), INDIRECT("'" & F$3 & "'!B:B")),0)} -> 4800.84 | G17: {=IFERROR(_xlfn.XLOOKUP($A17, INDIRECT("'" & G$3 & "'!A:A"), INDIRECT("'" & G$3 & "'!B:B")),0)} -> 3690.25 | H17: {=IFERROR(_xlfn.XLOOKUP($A17, INDIRECT("'" & H$3 & "'!A:A"), INDIRECT("'" & H$3 & "'!B:B")),0)} -> 3672.91 | I17: {=IFERROR(_xlfn.XLOOKUP($A17, INDIRECT("'" & I$3 & "'!A:A"), INDIRECT("'" & I$3 & "'!B:B")),0)} -> 4800.96 | ... AI17: {=IFERROR(_xlfn.XLOOKUP($A17, INDIRECT("'" & AI$3 & "'!A:A"), INDIRECT("'" & AI$3 & "'!B:B")),0)} -> 2523.36 | AJ17: =C17 -> 4236.58 | AK17: {=IFERROR(_xlfn.XLOOKUP($A17, INDIRECT("'" & AK$3 & "'!A:A"), INDIRECT("'" & AK$3 & "'!B:B")),0)} -> 0 | AL17: {=IFERROR(_xlfn.XLOOKUP($A17, INDIRECT("'" & AL$3 & "'!A:A"), INDIRECT("'" & AL$3 & "'!B:B")),0)} -> 0 | AM17: {=IFERROR(_xlfn.XLOOKUP($A17, INDIRECT("'" & AM$3 & "'!A:A"), INDIRECT("'" & AM$3 & "'!B:B")),0)} -> 0
A18: Siding Material | B18: {=IFERROR(_xlfn.XLOOKUP($A18, INDIRECT("'" & B$3 & "'!A:A"), INDIRECT("'" & B$3 & "'!B:B")),0)} -> 5209.64 | C18: {=IFERROR(_xlfn.XLOOKUP($A18, INDIRECT("'" & C$3 & "'!A:A"), INDIRECT("'" & C$3 & "'!B:B")),0)} -> 5257.76 | D18: {=IFERROR(_xlfn.XLOOKUP($A18, INDIRECT("'" & D$3 & "'!A:A"), INDIRECT("'" & D$3 & "'!B:B")),0)} -> 3929.56 | E18: {=IFERROR(_xlfn.XLOOKUP($A18, INDIRECT("'" & E$3 & "'!A:A"), INDIRECT("'" & E$3 & "'!B:B")),0)} -> 6327.34 | F18: {=IFERROR(_xlfn.XLOOKUP($A18, INDIRECT("'" & F$3 & "'!A:A"), INDIRECT("'" & F$3 & "'!B:B")),0)} -> 5756.82 | G18: {=IFERROR(_xlfn.XLOOKUP($A18, INDIRECT("'" & G$3 & "'!A:A"), INDIRECT("'" & G$3 & "'!B:B")),0)} -> 4091.57 | H18: {=IFERROR(_xlfn.XLOOKUP($A18, INDIRECT("'" & H$3 & "'!A:A"), INDIRECT("'" & H$3 & "'!B:B")),0)} -> 5034.13 | I18: {=IFERROR(_xlfn.XLOOKUP($A18, INDIRECT("'" & I$3 & "'!A:A"), INDIRECT("'" & I$3 & "'!B:B")),0)} -> 4829.82 | ... AI18: {=IFERROR(_xlfn.XLOOKUP($A18, INDIRECT("'" & AI$3 & "'!A:A"), INDIRECT("'" & AI$3 & "'!B:B")),0)} -> 4755.98 | AJ18: =C18 -> 5257.76 | AK18: {=IFERROR(_xlfn.XLOOKUP($A18, INDIRECT("'" & AK$3 & "'!A:A"), INDIRECT("'" & AK$3 & "'!B:B")),0)} -> 5904.75 | AL18: {=IFERROR(_xlfn.XLOOKUP($A18, INDIRECT("'" & AL$3 & "'!A:A"), INDIRECT("'" & AL$3 & "'!B:B")),0)} -> 0 | AM18: {=IFERROR(_xlfn.XLOOKUP($A18, INDIRECT("'" & AM$3 & "'!A:A"), INDIRECT("'" & AM$3 & "'!B:B")),0)} -> 8926
A19: Siding Labor | B19: {=IFERROR(_xlfn.XLOOKUP($A19, INDIRECT("'" & B$3 & "'!A:A"), INDIRECT("'" & B$3 & "'!B:B")),0)} -> 3485 | C19: {=IFERROR(_xlfn.XLOOKUP($A19, INDIRECT("'" & C$3 & "'!A:A"), INDIRECT("'" & C$3 & "'!B:B")),0)} -> 3550 | D19: {=IFERROR(_xlfn.XLOOKUP($A19, INDIRECT("'" & D$3 & "'!A:A"), INDIRECT("'" & D$3 & "'!B:B")),0)} -> 2340 | E19: {=IFERROR(_xlfn.XLOOKUP($A19, INDIRECT("'" & E$3 & "'!A:A"), INDIRECT("'" & E$3 & "'!B:B")),0)} -> 4805 | F19: {=IFERROR(_xlfn.XLOOKUP($A19, INDIRECT("'" & F$3 & "'!A:A"), INDIRECT("'" & F$3 & "'!B:B")),0)} -> 3855 | G19: {=IFERROR(_xlfn.XLOOKUP($A19, INDIRECT("'" & G$3 & "'!A:A"), INDIRECT("'" & G$3 & "'!B:B")),0)} -> 2845 | H19: {=IFERROR(_xlfn.XLOOKUP($A19, INDIRECT("'" & H$3 & "'!A:A"), INDIRECT("'" & H$3 & "'!B:B")),0)} -> 3140 | I19: {=IFERROR(_xlfn.XLOOKUP($A19, INDIRECT("'" & I$3 & "'!A:A"), INDIRECT("'" & I$3 & "'!B:B")),0)} -> 3350 | ... AI19: {=IFERROR(_xlfn.XLOOKUP($A19, INDIRECT("'" & AI$3 & "'!A:A"), INDIRECT("'" & AI$3 & "'!B:B")),0)} -> 3885 | AJ19: =C19 -> 3550 | AK19: {=IFERROR(_xlfn.XLOOKUP($A19, INDIRECT("'" & AK$3 & "'!A:A"), INDIRECT("'" & AK$3 & "'!B:B")),0)} -> 3685 | AL19: {=IFERROR(_xlfn.XLOOKUP($A19, INDIRECT("'" & AL$3 & "'!A:A"), INDIRECT("'" & AL$3 & "'!B:B")),0)} -> 0 | AM19: {=IFERROR(_xlfn.XLOOKUP($A19, INDIRECT("'" & AM$3 & "'!A:A"), INDIRECT("'" & AM$3 & "'!B:B")),0)} -> 5915
A20: Window Material | B20: {=IFERROR(_xlfn.XLOOKUP($A20, INDIRECT("'" & B$3 & "'!A:A"), INDIRECT("'" & B$3 & "'!B:B")),0)} -> 3411.27 | C20: {=IFERROR(_xlfn.XLOOKUP($A20, INDIRECT("'" & C$3 & "'!A:A"), INDIRECT("'" & C$3 & "'!B:B")),0)} -> 2477.66 | D20: {=IFERROR(_xlfn.XLOOKUP($A20, INDIRECT("'" & D$3 & "'!A:A"), INDIRECT("'" & D$3 & "'!B:B")),0)} -> 2761.95 | E20: {=IFERROR(_xlfn.XLOOKUP($A20, INDIRECT("'" & E$3 & "'!A:A"), INDIRECT("'" & E$3 & "'!B:B")),0)} -> 3205.85 | F20: {=IFERROR(_xlfn.XLOOKUP($A20, INDIRECT("'" & F$3 & "'!A:A"), INDIRECT("'" & F$3 & "'!B:B")),0)} -> 3121.99 | G20: {=IFERROR(_xlfn.XLOOKUP($A20, INDIRECT("'" & G$3 & "'!A:A"), INDIRECT("'" & G$3 & "'!B:B")),0)} -> 2123.41 | H20: {=IFERROR(_xlfn.XLOOKUP($A20, INDIRECT("'" & H$3 & "'!A:A"), INDIRECT("'" & H$3 & "'!B:B")),0)} -> 2506.13 | I20: {=IFERROR(_xlfn.XLOOKUP($A20, INDIRECT("'" & I$3 & "'!A:A"), INDIRECT("'" & I$3 & "'!B:B")),0)} -> 3898.44 | ... AI20: {=IFERROR(_xlfn.XLOOKUP($A20, INDIRECT("'" & AI$3 & "'!A:A"), INDIRECT("'" & AI$3 & "'!B:B")),0)} -> 2132.97 | AJ20: =C20+AM1 -> 5977.66 | AK20: {=IFERROR(_xlfn.XLOOKUP($A20, INDIRECT("'" & AK$3 & "'!A:A"), INDIRECT("'" & AK$3 & "'!B:B")),0)} -> 2076.02 | AL20: {=IFERROR(_xlfn.XLOOKUP($A20, INDIRECT("'" & AL$3 & "'!A:A"), INDIRECT("'" & AL$3 & "'!B:B")),0)} -> 2953.768 | AM20: {=IFERROR(_xlfn.XLOOKUP($A20, INDIRECT("'" & AM$3 & "'!A:A"), INDIRECT("'" & AM$3 & "'!B:B")),0)} -> 3307.18
A21: Exterior Door Material | B21: {=IFERROR(_xlfn.XLOOKUP($A21, INDIRECT("'" & B$3 & "'!A:A"), INDIRECT("'" & B$3 & "'!B:B")),0)} -> 1832.73 | C21: {=IFERROR(_xlfn.XLOOKUP($A21, INDIRECT("'" & C$3 & "'!A:A"), INDIRECT("'" & C$3 & "'!B:B")),0)} -> 1832.73 | D21: {=IFERROR(_xlfn.XLOOKUP($A21, INDIRECT("'" & D$3 & "'!A:A"), INDIRECT("'" & D$3 & "'!B:B")),0)} -> 1275.51 | E21: {=IFERROR(_xlfn.XLOOKUP($A21, INDIRECT("'" & E$3 & "'!A:A"), INDIRECT("'" & E$3 & "'!B:B")),0)} -> 2185.11 | F21: {=IFERROR(_xlfn.XLOOKUP($A21, INDIRECT("'" & F$3 & "'!A:A"), INDIRECT("'" & F$3 & "'!B:B")),0)} -> 1794.95 | G21: {=IFERROR(_xlfn.XLOOKUP($A21, INDIRECT("'" & G$3 & "'!A:A"), INDIRECT("'" & G$3 & "'!B:B")),0)} -> 1794.95 | H21: {=IFERROR(_xlfn.XLOOKUP($A21, INDIRECT("'" & H$3 & "'!A:A"), INDIRECT("'" & H$3 & "'!B:B")),0)} -> 1832.73 | I21: {=IFERROR(_xlfn.XLOOKUP($A21, INDIRECT("'" & I$3 & "'!A:A"), INDIRECT("'" & I$3 & "'!B:B")),0)} -> 1473.29 | ... AI21: {=IFERROR(_xlfn.XLOOKUP($A21, INDIRECT("'" & AI$3 & "'!A:A"), INDIRECT("'" & AI$3 & "'!B:B")),0)} -> 1855.76 | AJ21: =C21 -> 1832.73 | AK21: {=IFERROR(_xlfn.XLOOKUP($A21, INDIRECT("'" & AK$3 & "'!A:A"), INDIRECT("'" & AK$3 & "'!B:B")),0)} -> 2456.22 | AL21: {=IFERROR(_xlfn.XLOOKUP($A21, INDIRECT("'" & AL$3 & "'!A:A"), INDIRECT("'" & AL$3 & "'!B:B")),0)} -> 3656.8444 | AM21: {=IFERROR(_xlfn.XLOOKUP($A21, INDIRECT("'" & AM$3 & "'!A:A"), INDIRECT("'" & AM$3 & "'!B:B")),0)} -> 1548.34
A22: Exterior Door Labor | B22: {=IFERROR(_xlfn.XLOOKUP($A22, INDIRECT("'" & B$3 & "'!A:A"), INDIRECT("'" & B$3 & "'!B:B")),0)} -> 210 | C22: {=IFERROR(_xlfn.XLOOKUP($A22, INDIRECT("'" & C$3 & "'!A:A"), INDIRECT("'" & C$3 & "'!B:B")),0)} -> 173 | D22: {=IFERROR(_xlfn.XLOOKUP($A22, INDIRECT("'" & D$3 & "'!A:A"), INDIRECT("'" & D$3 & "'!B:B")),0)} -> 120 | E22: {=IFERROR(_xlfn.XLOOKUP($A22, INDIRECT("'" & E$3 & "'!A:A"), INDIRECT("'" & E$3 & "'!B:B")),0)} -> 240 | F22: {=IFERROR(_xlfn.XLOOKUP($A22, INDIRECT("'" & F$3 & "'!A:A"), INDIRECT("'" & F$3 & "'!B:B")),0)} -> 173 | G22: {=IFERROR(_xlfn.XLOOKUP($A22, INDIRECT("'" & G$3 & "'!A:A"), INDIRECT("'" & G$3 & "'!B:B")),0)} -> 173 | H22: {=IFERROR(_xlfn.XLOOKUP($A22, INDIRECT("'" & H$3 & "'!A:A"), INDIRECT("'" & H$3 & "'!B:B")),0)} -> 173 | I22: {=IFERROR(_xlfn.XLOOKUP($A22, INDIRECT("'" & I$3 & "'!A:A"), INDIRECT("'" & I$3 & "'!B:B")),0)} -> 180 | ... AI22: {=IFERROR(_xlfn.XLOOKUP($A22, INDIRECT("'" & AI$3 & "'!A:A"), INDIRECT("'" & AI$3 & "'!B:B")),0)} -> 173 | AJ22: =C22 -> 173 | AK22: {=IFERROR(_xlfn.XLOOKUP($A22, INDIRECT("'" & AK$3 & "'!A:A"), INDIRECT("'" & AK$3 & "'!B:B")),0)} -> 0 | AL22: {=IFERROR(_xlfn.XLOOKUP($A22, INDIRECT("'" & AL$3 & "'!A:A"), INDIRECT("'" & AL$3 & "'!B:B")),0)} -> 0 | AM22: {=IFERROR(_xlfn.XLOOKUP($A22, INDIRECT("'" & AM$3 & "'!A:A"), INDIRECT("'" & AM$3 & "'!B:B")),0)} -> 0
A23: Windows Labor | B23: {=IFERROR(_xlfn.XLOOKUP($A23, INDIRECT("'" & B$3 & "'!A:A"), INDIRECT("'" & B$3 & "'!B:B")),0)} -> 321 | C23: {=IFERROR(_xlfn.XLOOKUP($A23, INDIRECT("'" & C$3 & "'!A:A"), INDIRECT("'" & C$3 & "'!B:B")),0)} -> 308 | D23: {=IFERROR(_xlfn.XLOOKUP($A23, INDIRECT("'" & D$3 & "'!A:A"), INDIRECT("'" & D$3 & "'!B:B")),0)} -> 330 | E23: {=IFERROR(_xlfn.XLOOKUP($A23, INDIRECT("'" & E$3 & "'!A:A"), INDIRECT("'" & E$3 & "'!B:B")),0)} -> 330 | F23: {=IFERROR(_xlfn.XLOOKUP($A23, INDIRECT("'" & F$3 & "'!A:A"), INDIRECT("'" & F$3 & "'!B:B")),0)} -> 304 | G23: {=IFERROR(_xlfn.XLOOKUP($A23, INDIRECT("'" & G$3 & "'!A:A"), INDIRECT("'" & G$3 & "'!B:B")),0)} -> 242 | H23: {=IFERROR(_xlfn.XLOOKUP($A23, INDIRECT("'" & H$3 & "'!A:A"), INDIRECT("'" & H$3 & "'!B:B")),0)} -> 286 | I23: {=IFERROR(_xlfn.XLOOKUP($A23, INDIRECT("'" & I$3 & "'!A:A"), INDIRECT("'" & I$3 & "'!B:B")),0)} -> 370 | ... AI23: {=IFERROR(_xlfn.XLOOKUP($A23, INDIRECT("'" & AI$3 & "'!A:A"), INDIRECT("'" & AI$3 & "'!B:B")),0)} -> 182 | AJ23: =C23 -> 308 | AK23: {=IFERROR(_xlfn.XLOOKUP($A23, INDIRECT("'" & AK$3 & "'!A:A"), INDIRECT("'" & AK$3 & "'!B:B")),0)} -> 0 | AL23: {=IFERROR(_xlfn.XLOOKUP($A23, INDIRECT("'" & AL$3 & "'!A:A"), INDIRECT("'" & AL$3 & "'!B:B")),0)} -> 0 | AM23: {=IFERROR(_xlfn.XLOOKUP($A23, INDIRECT("'" & AM$3 & "'!A:A"), INDIRECT("'" & AM$3 & "'!B:B")),0)} -> 0
A24: Garage Door Labor & Material | B24: {=IFERROR(_xlfn.XLOOKUP($A24, INDIRECT("'" & B$3 & "'!A:A"), INDIRECT("'" & B$3 & "'!B:B")),0)} -> 1600 | C24: {=IFERROR(_xlfn.XLOOKUP($A24, INDIRECT("'" & C$3 & "'!A:A"), INDIRECT("'" & C$3 & "'!B:B")),0)} -> 1600 | D24: {=IFERROR(_xlfn.XLOOKUP($A24, INDIRECT("'" & D$3 & "'!A:A"), INDIRECT("'" & D$3 & "'!B:B")),0)} -> 0 | E24: {=IFERROR(_xlfn.XLOOKUP($A24, INDIRECT("'" & E$3 & "'!A:A"), INDIRECT("'" & E$3 & "'!B:B")),0)} -> 1600 | F24: {=IFERROR(_xlfn.XLOOKUP($A24, INDIRECT("'" & F$3 & "'!A:A"), INDIRECT("'" & F$3 & "'!B:B")),0)} -> 1600 | G24: {=IFERROR(_xlfn.XLOOKUP($A24, INDIRECT("'" & G$3 & "'!A:A"), INDIRECT("'" & G$3 & "'!B:B")),0)} -> 1600 | H24: {=IFERROR(_xlfn.XLOOKUP($A24, INDIRECT("'" & H$3 & "'!A:A"), INDIRECT("'" & H$3 & "'!B:B")),0)} -> 1600 | I24: {=IFERROR(_xlfn.XLOOKUP($A24, INDIRECT("'" & I$3 & "'!A:A"), INDIRECT("'" & I$3 & "'!B:B")),0)} -> 1600 | ... AI24: {=IFERROR(_xlfn.XLOOKUP($A24, INDIRECT("'" & AI$3 & "'!A:A"), INDIRECT("'" & AI$3 & "'!B:B")),0)} -> 1100 | AJ24: =C24 -> 1600 | AK24: {=IFERROR(_xlfn.XLOOKUP($A24, INDIRECT("'" & AK$3 & "'!A:A"), INDIRECT("'" & AK$3 & "'!B:B")),0)} -> 1200 | AL24: {=IFERROR(_xlfn.XLOOKUP($A24, INDIRECT("'" & AL$3 & "'!A:A"), INDIRECT("'" & AL$3 & "'!B:B")),0)} -> 1900 | AM24: {=IFERROR(_xlfn.XLOOKUP($A24, INDIRECT("'" & AM$3 & "'!A:A"), INDIRECT("'" & AM$3 & "'!B:B")),0)} -> 1800
A25: Plumbing Turnkey | B25: {=IFERROR(_xlfn.XLOOKUP($A25, INDIRECT("'" & B$3 & "'!A:A"), INDIRECT("'" & B$3 & "'!B:B")),0)} -> 13635 | C25: {=IFERROR(_xlfn.XLOOKUP($A25, INDIRECT("'" & C$3 & "'!A:A"), INDIRECT("'" & C$3 & "'!B:B")),0)} -> 12373 | D25: {=IFERROR(_xlfn.XLOOKUP($A25, INDIRECT("'" & D$3 & "'!A:A"), INDIRECT("'" & D$3 & "'!B:B")),0)} -> 11996 | E25: {=IFERROR(_xlfn.XLOOKUP($A25, INDIRECT("'" & E$3 & "'!A:A"), INDIRECT("'" & E$3 & "'!B:B")),0)} -> 13451 | F25: {=IFERROR(_xlfn.XLOOKUP($A25, INDIRECT("'" & F$3 & "'!A:A"), INDIRECT("'" & F$3 & "'!B:B")),0)} -> 15022 | G25: {=IFERROR(_xlfn.XLOOKUP($A25, INDIRECT("'" & G$3 & "'!A:A"), INDIRECT("'" & G$3 & "'!B:B")),0)} -> 12111 | H25: {=IFERROR(_xlfn.XLOOKUP($A25, INDIRECT("'" & H$3 & "'!A:A"), INDIRECT("'" & H$3 & "'!B:B")),0)} -> 12337 | I25: {=IFERROR(_xlfn.XLOOKUP($A25, INDIRECT("'" & I$3 & "'!A:A"), INDIRECT("'" & I$3 & "'!B:B")),0)} -> 12111 | ... AI25: {=IFERROR(_xlfn.XLOOKUP($A25, INDIRECT("'" & AI$3 & "'!A:A"), INDIRECT("'" & AI$3 & "'!B:B")),0)} -> 14692 | AJ25: =C25+AM1 -> 15873 | AK25: {=IFERROR(_xlfn.XLOOKUP($A25, INDIRECT("'" & AK$3 & "'!A:A"), INDIRECT("'" & AK$3 & "'!B:B")),0)} -> 15464.77 | AL25: {=IFERROR(_xlfn.XLOOKUP($A25, INDIRECT("'" & AL$3 & "'!A:A"), INDIRECT("'" & AL$3 & "'!B:B")),0)} -> 12812.389 | AM25: {=IFERROR(_xlfn.XLOOKUP($A25, INDIRECT("'" & AM$3 & "'!A:A"), INDIRECT("'" & AM$3 & "'!B:B")),0)} -> 13629.41
A26: HVAC | B26: {=IFERROR(_xlfn.XLOOKUP($A26, INDIRECT("'" & B$3 & "'!A:A"), INDIRECT("'" & B$3 & "'!B:B")),0)} -> 10900 | C26: {=IFERROR(_xlfn.XLOOKUP($A26, INDIRECT("'" & C$3 & "'!A:A"), INDIRECT("'" & C$3 & "'!B:B")),0)} -> 10300 | D26: {=IFERROR(_xlfn.XLOOKUP($A26, INDIRECT("'" & D$3 & "'!A:A"), INDIRECT("'" & D$3 & "'!B:B")),0)} -> 10100 | E26: {=IFERROR(_xlfn.XLOOKUP($A26, INDIRECT("'" & E$3 & "'!A:A"), INDIRECT("'" & E$3 & "'!B:B")),0)} -> 9600 | F26: {=IFERROR(_xlfn.XLOOKUP($A26, INDIRECT("'" & F$3 & "'!A:A"), INDIRECT("'" & F$3 & "'!B:B")),0)} -> 10900 | G26: {=IFERROR(_xlfn.XLOOKUP($A26, INDIRECT("'" & G$3 & "'!A:A"), INDIRECT("'" & G$3 & "'!B:B")),0)} -> 10200 | H26: {=IFERROR(_xlfn.XLOOKUP($A26, INDIRECT("'" & H$3 & "'!A:A"), INDIRECT("'" & H$3 & "'!B:B")),0)} -> 10400 | I26: {=IFERROR(_xlfn.XLOOKUP($A26, INDIRECT("'" & I$3 & "'!A:A"), INDIRECT("'" & I$3 & "'!B:B")),0)} -> 10400 | ... AI26: {=IFERROR(_xlfn.XLOOKUP($A26, INDIRECT("'" & AI$3 & "'!A:A"), INDIRECT("'" & AI$3 & "'!B:B")),0)} -> 13540 | AJ26: =C26+AM1 -> 13800 | AK26: {=IFERROR(_xlfn.XLOOKUP($A26, INDIRECT("'" & AK$3 & "'!A:A"), INDIRECT("'" & AK$3 & "'!B:B")),0)} -> 9900 | AL26: {=IFERROR(_xlfn.XLOOKUP($A26, INDIRECT("'" & AL$3 & "'!A:A"), INDIRECT("'" & AL$3 & "'!B:B")),0)} -> 9556.8 | AM26: {=IFERROR(_xlfn.XLOOKUP($A26, INDIRECT("'" & AM$3 & "'!A:A"), INDIRECT("'" & AM$3 & "'!B:B")),0)} -> 13990
A27: Electrical Rough & Trim | B27: {=IFERROR(_xlfn.XLOOKUP($A27, INDIRECT("'" & B$3 & "'!A:A"), INDIRECT("'" & B$3 & "'!B:B")),0)} -> 9475.97 | C27: {=IFERROR(_xlfn.XLOOKUP($A27, INDIRECT("'" & C$3 & "'!A:A"), INDIRECT("'" & C$3 & "'!B:B")),0)} -> 8397.78 | D27: {=IFERROR(_xlfn.XLOOKUP($A27, INDIRECT("'" & D$3 & "'!A:A"), INDIRECT("'" & D$3 & "'!B:B")),0)} -> 7191 | E27: {=IFERROR(_xlfn.XLOOKUP($A27, INDIRECT("'" & E$3 & "'!A:A"), INDIRECT("'" & E$3 & "'!B:B")),0)} -> 6622.98 | F27: {=IFERROR(_xlfn.XLOOKUP($A27, INDIRECT("'" & F$3 & "'!A:A"), INDIRECT("'" & F$3 & "'!B:B")),0)} -> 8947.9 | G27: {=IFERROR(_xlfn.XLOOKUP($A27, INDIRECT("'" & G$3 & "'!A:A"), INDIRECT("'" & G$3 & "'!B:B")),0)} -> 6948.88 | H27: {=IFERROR(_xlfn.XLOOKUP($A27, INDIRECT("'" & H$3 & "'!A:A"), INDIRECT("'" & H$3 & "'!B:B")),0)} -> 7859.77 | I27: {=IFERROR(_xlfn.XLOOKUP($A27, INDIRECT("'" & I$3 & "'!A:A"), INDIRECT("'" & I$3 & "'!B:B")),0)} -> 8989.73 | ... AI27: {=IFERROR(_xlfn.XLOOKUP($A27, INDIRECT("'" & AI$3 & "'!A:A"), INDIRECT("'" & AI$3 & "'!B:B")),0)} -> 7050.01 | AJ27: =C27+AM1 -> 11897.78 | AK27: {=IFERROR(_xlfn.XLOOKUP($A27, INDIRECT("'" & AK$3 & "'!A:A"), INDIRECT("'" & AK$3 & "'!B:B")),0)} -> 9228 | AL27: {=IFERROR(_xlfn.XLOOKUP($A27, INDIRECT("'" & AL$3 & "'!A:A"), INDIRECT("'" & AL$3 & "'!B:B")),0)} -> 9051.81 | AM27: {=IFERROR(_xlfn.XLOOKUP($A27, INDIRECT("'" & AM$3 & "'!A:A"), INDIRECT("'" & AM$3 & "'!B:B")),0)} -> 12580
A28: Blower Test | B28: {=IFERROR(_xlfn.XLOOKUP($A28, INDIRECT("'" & B$3 & "'!A:A"), INDIRECT("'" & B$3 & "'!B:B")),0)} -> 300.11 | C28: {=IFERROR(_xlfn.XLOOKUP($A28, INDIRECT("'" & C$3 & "'!A:A"), INDIRECT("'" & C$3 & "'!B:B")),0)} -> 300.11 | D28: {=IFERROR(_xlfn.XLOOKUP($A28, INDIRECT("'" & D$3 & "'!A:A"), INDIRECT("'" & D$3 & "'!B:B")),0)} -> 300.11 | E28: {=IFERROR(_xlfn.XLOOKUP($A28, INDIRECT("'" & E$3 & "'!A:A"), INDIRECT("'" & E$3 & "'!B:B")),0)} -> 300.11 | F28: {=IFERROR(_xlfn.XLOOKUP($A28, INDIRECT("'" & F$3 & "'!A:A"), INDIRECT("'" & F$3 & "'!B:B")),0)} -> 300.11 | G28: {=IFERROR(_xlfn.XLOOKUP($A28, INDIRECT("'" & G$3 & "'!A:A"), INDIRECT("'" & G$3 & "'!B:B")),0)} -> 300.11 | H28: {=IFERROR(_xlfn.XLOOKUP($A28, INDIRECT("'" & H$3 & "'!A:A"), INDIRECT("'" & H$3 & "'!B:B")),0)} -> 300.11 | I28: {=IFERROR(_xlfn.XLOOKUP($A28, INDIRECT("'" & I$3 & "'!A:A"), INDIRECT("'" & I$3 & "'!B:B")),0)} -> 300.11 | ... AI28: {=IFERROR(_xlfn.XLOOKUP($A28, INDIRECT("'" & AI$3 & "'!A:A"), INDIRECT("'" & AI$3 & "'!B:B")),0)} -> 300.11 | AJ28: =C28 -> 300.11 | AK28: {=IFERROR(_xlfn.XLOOKUP($A28, INDIRECT("'" & AK$3 & "'!A:A"), INDIRECT("'" & AK$3 & "'!B:B")),0)} -> 300.11 | AL28: {=IFERROR(_xlfn.XLOOKUP($A28, INDIRECT("'" & AL$3 & "'!A:A"), INDIRECT("'" & AL$3 & "'!B:B")),0)} -> 300.11 | AM28: {=IFERROR(_xlfn.XLOOKUP($A28, INDIRECT("'" & AM$3 & "'!A:A"), INDIRECT("'" & AM$3 & "'!B:B")),0)} -> 300.11
A29: Low Voltage/AV | B29: {=IFERROR(_xlfn.XLOOKUP($A29, INDIRECT("'" & B$3 & "'!A:A"), INDIRECT("'" & B$3 & "'!B:B")),0)} -> 0 | C29: {=IFERROR(_xlfn.XLOOKUP($A29, INDIRECT("'" & C$3 & "'!A:A"), INDIRECT("'" & C$3 & "'!B:B")),0)} -> 0 | D29: {=IFERROR(_xlfn.XLOOKUP($A29, INDIRECT("'" & D$3 & "'!A:A"), INDIRECT("'" & D$3 & "'!B:B")),0)} -> 0 | E29: {=IFERROR(_xlfn.XLOOKUP($A29, INDIRECT("'" & E$3 & "'!A:A"), INDIRECT("'" & E$3 & "'!B:B")),0)} -> 0 | F29: {=IFERROR(_xlfn.XLOOKUP($A29, INDIRECT("'" & F$3 & "'!A:A"), INDIRECT("'" & F$3 & "'!B:B")),0)} -> 0 | G29: {=IFERROR(_xlfn.XLOOKUP($A29, INDIRECT("'" & G$3 & "'!A:A"), INDIRECT("'" & G$3 & "'!B:B")),0)} -> 0 | H29: {=IFERROR(_xlfn.XLOOKUP($A29, INDIRECT("'" & H$3 & "'!A:A"), INDIRECT("'" & H$3 & "'!B:B")),0)} -> 0 | I29: {=IFERROR(_xlfn.XLOOKUP($A29, INDIRECT("'" & I$3 & "'!A:A"), INDIRECT("'" & I$3 & "'!B:B")),0)} -> 0 | ... AI29: {=IFERROR(_xlfn.XLOOKUP($A29, INDIRECT("'" & AI$3 & "'!A:A"), INDIRECT("'" & AI$3 & "'!B:B")),0)} -> 0 | AJ29: =C29 -> 0 | AK29: {=IFERROR(_xlfn.XLOOKUP($A29, INDIRECT("'" & AK$3 & "'!A:A"), INDIRECT("'" & AK$3 & "'!B:B")),0)} -> 0 | AL29: {=IFERROR(_xlfn.XLOOKUP($A29, INDIRECT("'" & AL$3 & "'!A:A"), INDIRECT("'" & AL$3 & "'!B:B")),0)} -> 0 | AM29: {=IFERROR(_xlfn.XLOOKUP($A29, INDIRECT("'" & AM$3 & "'!A:A"), INDIRECT("'" & AM$3 & "'!B:B")),0)} -> 0
A30: Insulation | B30: {=IFERROR(_xlfn.XLOOKUP($A30, INDIRECT("'" & B$3 & "'!A:A"), INDIRECT("'" & B$3 & "'!B:B")),0)} -> 4067 | C30: {=IFERROR(_xlfn.XLOOKUP($A30, INDIRECT("'" & C$3 & "'!A:A"), INDIRECT("'" & C$3 & "'!B:B")),0)} -> 3356 | D30: {=IFERROR(_xlfn.XLOOKUP($A30, INDIRECT("'" & D$3 & "'!A:A"), INDIRECT("'" & D$3 & "'!B:B")),0)} -> 2890 | E30: {=IFERROR(_xlfn.XLOOKUP($A30, INDIRECT("'" & E$3 & "'!A:A"), INDIRECT("'" & E$3 & "'!B:B")),0)} -> 2949 | F30: {=IFERROR(_xlfn.XLOOKUP($A30, INDIRECT("'" & F$3 & "'!A:A"), INDIRECT("'" & F$3 & "'!B:B")),0)} -> 4139 | G30: {=IFERROR(_xlfn.XLOOKUP($A30, INDIRECT("'" & G$3 & "'!A:A"), INDIRECT("'" & G$3 & "'!B:B")),0)} -> 3642 | H30: {=IFERROR(_xlfn.XLOOKUP($A30, INDIRECT("'" & H$3 & "'!A:A"), INDIRECT("'" & H$3 & "'!B:B")),0)} -> 3671 | I30: {=IFERROR(_xlfn.XLOOKUP($A30, INDIRECT("'" & I$3 & "'!A:A"), INDIRECT("'" & I$3 & "'!B:B")),0)} -> 3382 | ... AI30: {=IFERROR(_xlfn.XLOOKUP($A30, INDIRECT("'" & AI$3 & "'!A:A"), INDIRECT("'" & AI$3 & "'!B:B")),0)} -> 4939 | AJ30: =C30 -> 3356 | AK30: {=IFERROR(_xlfn.XLOOKUP($A30, INDIRECT("'" & AK$3 & "'!A:A"), INDIRECT("'" & AK$3 & "'!B:B")),0)} -> 5444 | AL30: {=IFERROR(_xlfn.XLOOKUP($A30, INDIRECT("'" & AL$3 & "'!A:A"), INDIRECT("'" & AL$3 & "'!B:B")),0)} -> 3366.6 | AM30: {=IFERROR(_xlfn.XLOOKUP($A30, INDIRECT("'" & AM$3 & "'!A:A"), INDIRECT("'" & AM$3 & "'!B:B")),0)} -> 4765
A31: Drywall Material | B31: {=IFERROR(_xlfn.XLOOKUP($A31, INDIRECT("'" & B$3 & "'!A:A"), INDIRECT("'" & B$3 & "'!B:B")),0)} -> 5765.79 | C31: {=IFERROR(_xlfn.XLOOKUP($A31, INDIRECT("'" & C$3 & "'!A:A"), INDIRECT("'" & C$3 & "'!B:B")),0)} -> 4501.41 | D31: {=IFERROR(_xlfn.XLOOKUP($A31, INDIRECT("'" & D$3 & "'!A:A"), INDIRECT("'" & D$3 & "'!B:B")),0)} -> 3724.58 | E31: {=IFERROR(_xlfn.XLOOKUP($A31, INDIRECT("'" & E$3 & "'!A:A"), INDIRECT("'" & E$3 & "'!B:B")),0)} -> 3908.31 | F31: {=IFERROR(_xlfn.XLOOKUP($A31, INDIRECT("'" & F$3 & "'!A:A"), INDIRECT("'" & F$3 & "'!B:B")),0)} -> 5393.62 | G31: {=IFERROR(_xlfn.XLOOKUP($A31, INDIRECT("'" & G$3 & "'!A:A"), INDIRECT("'" & G$3 & "'!B:B")),0)} -> 4177.97 | H31: {=IFERROR(_xlfn.XLOOKUP($A31, INDIRECT("'" & H$3 & "'!A:A"), INDIRECT("'" & H$3 & "'!B:B")),0)} -> 4637.4 | I31: {=IFERROR(_xlfn.XLOOKUP($A31, INDIRECT("'" & I$3 & "'!A:A"), INDIRECT("'" & I$3 & "'!B:B")),0)} -> 4800.14 | ... AI31: {=IFERROR(_xlfn.XLOOKUP($A31, INDIRECT("'" & AI$3 & "'!A:A"), INDIRECT("'" & AI$3 & "'!B:B")),0)} -> 4724.69 | AJ31: =C31 -> 4501.41 | AK31: {=IFERROR(_xlfn.XLOOKUP($A31, INDIRECT("'" & AK$3 & "'!A:A"), INDIRECT("'" & AK$3 & "'!B:B")),0)} -> 4102.83 | AL31: {=IFERROR(_xlfn.XLOOKUP($A31, INDIRECT("'" & AL$3 & "'!A:A"), INDIRECT("'" & AL$3 & "'!B:B")),0)} -> 4800.9562 | AM31: {=IFERROR(_xlfn.XLOOKUP($A31, INDIRECT("'" & AM$3 & "'!A:A"), INDIRECT("'" & AM$3 & "'!B:B")),0)} -> 4635.72
A32: Drywall Labor | B32: {=IFERROR(_xlfn.XLOOKUP($A32, INDIRECT("'" & B$3 & "'!A:A"), INDIRECT("'" & B$3 & "'!B:B")),0)} -> 5700.78 | C32: {=IFERROR(_xlfn.XLOOKUP($A32, INDIRECT("'" & C$3 & "'!A:A"), INDIRECT("'" & C$3 & "'!B:B")),0)} -> 4709.34 | D32: {=IFERROR(_xlfn.XLOOKUP($A32, INDIRECT("'" & D$3 & "'!A:A"), INDIRECT("'" & D$3 & "'!B:B")),0)} -> 4195.26 | E32: {=IFERROR(_xlfn.XLOOKUP($A32, INDIRECT("'" & E$3 & "'!A:A"), INDIRECT("'" & E$3 & "'!B:B")),0)} -> 4305.42 | F32: {=IFERROR(_xlfn.XLOOKUP($A32, INDIRECT("'" & F$3 & "'!A:A"), INDIRECT("'" & F$3 & "'!B:B")),0)} -> 5777.28 | G32: {=IFERROR(_xlfn.XLOOKUP($A32, INDIRECT("'" & G$3 & "'!A:A"), INDIRECT("'" & G$3 & "'!B:B")),0)} -> 4244.22 | H32: {=IFERROR(_xlfn.XLOOKUP($A32, INDIRECT("'" & H$3 & "'!A:A"), INDIRECT("'" & H$3 & "'!B:B")),0)} -> 4684.86 | I32: {=IFERROR(_xlfn.XLOOKUP($A32, INDIRECT("'" & I$3 & "'!A:A"), INDIRECT("'" & I$3 & "'!B:B")),0)} -> 4779.72 | ... AI32: {=IFERROR(_xlfn.XLOOKUP($A32, INDIRECT("'" & AI$3 & "'!A:A"), INDIRECT("'" & AI$3 & "'!B:B")),0)} -> 4571.64 | AJ32: =C32 -> 4709.34 | AK32: {=IFERROR(_xlfn.XLOOKUP($A32, INDIRECT("'" & AK$3 & "'!A:A"), INDIRECT("'" & AK$3 & "'!B:B")),0)} -> 4709.34 | AL32: {=IFERROR(_xlfn.XLOOKUP($A32, INDIRECT("'" & AL$3 & "'!A:A"), INDIRECT("'" & AL$3 & "'!B:B")),0)} -> 4044.3183 | AM32: {=IFERROR(_xlfn.XLOOKUP($A32, INDIRECT("'" & AM$3 & "'!A:A"), INDIRECT("'" & AM$3 & "'!B:B")),0)} -> 4469.78
A33: Exterior Paint Labor & Material | B33: {=IFERROR(_xlfn.XLOOKUP($A33, INDIRECT("'" & B$3 & "'!A:A"), INDIRECT("'" & B$3 & "'!B:B")),0)} -> 25 | C33: {=IFERROR(_xlfn.XLOOKUP($A33, INDIRECT("'" & C$3 & "'!A:A"), INDIRECT("'" & C$3 & "'!B:B")),0)} -> 50 | D33: {=IFERROR(_xlfn.XLOOKUP($A33, INDIRECT("'" & D$3 & "'!A:A"), INDIRECT("'" & D$3 & "'!B:B")),0)} -> 50 | E33: {=IFERROR(_xlfn.XLOOKUP($A33, INDIRECT("'" & E$3 & "'!A:A"), INDIRECT("'" & E$3 & "'!B:B")),0)} -> 400 | F33: {=IFERROR(_xlfn.XLOOKUP($A33, INDIRECT("'" & F$3 & "'!A:A"), INDIRECT("'" & F$3 & "'!B:B")),0)} -> 275 | G33: {=IFERROR(_xlfn.XLOOKUP($A33, INDIRECT("'" & G$3 & "'!A:A"), INDIRECT("'" & G$3 & "'!B:B")),0)} -> 100 | H33: {=IFERROR(_xlfn.XLOOKUP($A33, INDIRECT("'" & H$3 & "'!A:A"), INDIRECT("'" & H$3 & "'!B:B")),0)} -> 75 | I33: {=IFERROR(_xlfn.XLOOKUP($A33, INDIRECT("'" & I$3 & "'!A:A"), INDIRECT("'" & I$3 & "'!B:B")),0)} -> 100 | ... AI33: {=IFERROR(_xlfn.XLOOKUP($A33, INDIRECT("'" & AI$3 & "'!A:A"), INDIRECT("'" & AI$3 & "'!B:B")),0)} -> 100 | AJ33: =C33 -> 50 | AK33: {=IFERROR(_xlfn.XLOOKUP($A33, INDIRECT("'" & AK$3 & "'!A:A"), INDIRECT("'" & AK$3 & "'!B:B")),0)} -> 0 | AL33: {=IFERROR(_xlfn.XLOOKUP($A33, INDIRECT("'" & AL$3 & "'!A:A"), INDIRECT("'" & AL$3 & "'!B:B")),0)} -> 217.2 | AM33: {=IFERROR(_xlfn.XLOOKUP($A33, INDIRECT("'" & AM$3 & "'!A:A"), INDIRECT("'" & AM$3 & "'!B:B")),0)} -> 0
A34: Interior Paint | B34: {=IFERROR(_xlfn.XLOOKUP($A34, INDIRECT("'" & B$3 & "'!A:A"), INDIRECT("'" & B$3 & "'!B:B")),0)} -> 4114.24 | C34: {=IFERROR(_xlfn.XLOOKUP($A34, INDIRECT("'" & C$3 & "'!A:A"), INDIRECT("'" & C$3 & "'!B:B")),0)} -> 3289.92 | D34: {=IFERROR(_xlfn.XLOOKUP($A34, INDIRECT("'" & D$3 & "'!A:A"), INDIRECT("'" & D$3 & "'!B:B")),0)} -> 2923.28 | E34: {=IFERROR(_xlfn.XLOOKUP($A34, INDIRECT("'" & E$3 & "'!A:A"), INDIRECT("'" & E$3 & "'!B:B")),0)} -> 2576 | F34: {=IFERROR(_xlfn.XLOOKUP($A34, INDIRECT("'" & F$3 & "'!A:A"), INDIRECT("'" & F$3 & "'!B:B")),0)} -> 4073.76 | G34: {=IFERROR(_xlfn.XLOOKUP($A34, INDIRECT("'" & G$3 & "'!A:A"), INDIRECT("'" & G$3 & "'!B:B")),0)} -> 2835.44 | H34: {=IFERROR(_xlfn.XLOOKUP($A34, INDIRECT("'" & H$3 & "'!A:A"), INDIRECT("'" & H$3 & "'!B:B")),0)} -> 3151.92 | I34: {=IFERROR(_xlfn.XLOOKUP($A34, INDIRECT("'" & I$3 & "'!A:A"), INDIRECT("'" & I$3 & "'!B:B")),0)} -> 3680 | ... AI34: {=IFERROR(_xlfn.XLOOKUP($A34, INDIRECT("'" & AI$3 & "'!A:A"), INDIRECT("'" & AI$3 & "'!B:B")),0)} -> 3236.4 | AJ34: =C34 -> 3289.92 | AK34: {=IFERROR(_xlfn.XLOOKUP($A34, INDIRECT("'" & AK$3 & "'!A:A"), INDIRECT("'" & AK$3 & "'!B:B")),0)} -> 4230.2 | AL34: {=IFERROR(_xlfn.XLOOKUP($A34, INDIRECT("'" & AL$3 & "'!A:A"), INDIRECT("'" & AL$3 & "'!B:B")),0)} -> 2932.2 | AM34: {=IFERROR(_xlfn.XLOOKUP($A34, INDIRECT("'" & AM$3 & "'!A:A"), INDIRECT("'" & AM$3 & "'!B:B")),0)} -> 3729.6
A35: Interior Trim Material | B35: {=IFERROR(_xlfn.XLOOKUP($A35, INDIRECT("'" & B$3 & "'!A:A"), INDIRECT("'" & B$3 & "'!B:B")),0)} -> 0 | C35: {=IFERROR(_xlfn.XLOOKUP($A35, INDIRECT("'" & C$3 & "'!A:A"), INDIRECT("'" & C$3 & "'!B:B")),0)} -> 0 | D35: {=IFERROR(_xlfn.XLOOKUP($A35, INDIRECT("'" & D$3 & "'!A:A"), INDIRECT("'" & D$3 & "'!B:B")),0)} -> 0 | E35: {=IFERROR(_xlfn.XLOOKUP($A35, INDIRECT("'" & E$3 & "'!A:A"), INDIRECT("'" & E$3 & "'!B:B")),0)} -> 0 | F35: {=IFERROR(_xlfn.XLOOKUP($A35, INDIRECT("'" & F$3 & "'!A:A"), INDIRECT("'" & F$3 & "'!B:B")),0)} -> 0 | G35: {=IFERROR(_xlfn.XLOOKUP($A35, INDIRECT("'" & G$3 & "'!A:A"), INDIRECT("'" & G$3 & "'!B:B")),0)} -> 0 | H35: {=IFERROR(_xlfn.XLOOKUP($A35, INDIRECT("'" & H$3 & "'!A:A"), INDIRECT("'" & H$3 & "'!B:B")),0)} -> 0 | I35: {=IFERROR(_xlfn.XLOOKUP($A35, INDIRECT("'" & I$3 & "'!A:A"), INDIRECT("'" & I$3 & "'!B:B")),0)} -> 0 | ... AI35: {=IFERROR(_xlfn.XLOOKUP($A35, INDIRECT("'" & AI$3 & "'!A:A"), INDIRECT("'" & AI$3 & "'!B:B")),0)} -> 0 | AJ35: =C35 -> 0 | AK35: {=IFERROR(_xlfn.XLOOKUP($A35, INDIRECT("'" & AK$3 & "'!A:A"), INDIRECT("'" & AK$3 & "'!B:B")),0)} -> 0 | AL35: {=IFERROR(_xlfn.XLOOKUP($A35, INDIRECT("'" & AL$3 & "'!A:A"), INDIRECT("'" & AL$3 & "'!B:B")),0)} -> 3942.2126 | AM35: {=IFERROR(_xlfn.XLOOKUP($A35, INDIRECT("'" & AM$3 & "'!A:A"), INDIRECT("'" & AM$3 & "'!B:B")),0)} -> 0
A36: Interior Trim Turnkey | B36: {=IFERROR(_xlfn.XLOOKUP($A36, INDIRECT("'" & B$3 & "'!A:A"), INDIRECT("'" & B$3 & "'!B:B")),0)} -> 6581.37 | C36: {=IFERROR(_xlfn.XLOOKUP($A36, INDIRECT("'" & C$3 & "'!A:A"), INDIRECT("'" & C$3 & "'!B:B")),0)} -> 4352 | D36: {=IFERROR(_xlfn.XLOOKUP($A36, INDIRECT("'" & D$3 & "'!A:A"), INDIRECT("'" & D$3 & "'!B:B")),0)} -> 4068 | E36: {=IFERROR(_xlfn.XLOOKUP($A36, INDIRECT("'" & E$3 & "'!A:A"), INDIRECT("'" & E$3 & "'!B:B")),0)} -> 4455 | F36: {=IFERROR(_xlfn.XLOOKUP($A36, INDIRECT("'" & F$3 & "'!A:A"), INDIRECT("'" & F$3 & "'!B:B")),0)} -> 5005 | G36: {=IFERROR(_xlfn.XLOOKUP($A36, INDIRECT("'" & G$3 & "'!A:A"), INDIRECT("'" & G$3 & "'!B:B")),0)} -> 3740 | H36: {=IFERROR(_xlfn.XLOOKUP($A36, INDIRECT("'" & H$3 & "'!A:A"), INDIRECT("'" & H$3 & "'!B:B")),0)} -> 4384 | I36: {=IFERROR(_xlfn.XLOOKUP($A36, INDIRECT("'" & I$3 & "'!A:A"), INDIRECT("'" & I$3 & "'!B:B")),0)} -> 4645 | ... AI36: {=IFERROR(_xlfn.XLOOKUP($A36, INDIRECT("'" & AI$3 & "'!A:A"), INDIRECT("'" & AI$3 & "'!B:B")),0)} -> 4250 | AJ36: =C36 -> 4352 | AK36: {=IFERROR(_xlfn.XLOOKUP($A36, INDIRECT("'" & AK$3 & "'!A:A"), INDIRECT("'" & AK$3 & "'!B:B")),0)} -> 6410.41 | AL36: {=IFERROR(_xlfn.XLOOKUP($A36, INDIRECT("'" & AL$3 & "'!A:A"), INDIRECT("'" & AL$3 & "'!B:B")),0)} -> 0 | AM36: {=IFERROR(_xlfn.XLOOKUP($A36, INDIRECT("'" & AM$3 & "'!A:A"), INDIRECT("'" & AM$3 & "'!B:B")),0)} -> 5863.97
A37: Door Hardware | B37: {=IFERROR(_xlfn.XLOOKUP($A37, INDIRECT("'" & B$3 & "'!A:A"), INDIRECT("'" & B$3 & "'!B:B")),0)} -> 546.91 | C37: {=IFERROR(_xlfn.XLOOKUP($A37, INDIRECT("'" & C$3 & "'!A:A"), INDIRECT("'" & C$3 & "'!B:B")),0)} -> 454.35 | D37: {=IFERROR(_xlfn.XLOOKUP($A37, INDIRECT("'" & D$3 & "'!A:A"), INDIRECT("'" & D$3 & "'!B:B")),0)} -> 451.21 | E37: {=IFERROR(_xlfn.XLOOKUP($A37, INDIRECT("'" & E$3 & "'!A:A"), INDIRECT("'" & E$3 & "'!B:B")),0)} -> 570.95 | F37: {=IFERROR(_xlfn.XLOOKUP($A37, INDIRECT("'" & F$3 & "'!A:A"), INDIRECT("'" & F$3 & "'!B:B")),0)} -> 528.23 | G37: {=IFERROR(_xlfn.XLOOKUP($A37, INDIRECT("'" & G$3 & "'!A:A"), INDIRECT("'" & G$3 & "'!B:B")),0)} -> 449.17 | H37: {=IFERROR(_xlfn.XLOOKUP($A37, INDIRECT("'" & H$3 & "'!A:A"), INDIRECT("'" & H$3 & "'!B:B")),0)} -> 506.7 | I37: {=IFERROR(_xlfn.XLOOKUP($A37, INDIRECT("'" & I$3 & "'!A:A"), INDIRECT("'" & I$3 & "'!B:B")),0)} -> 567.04 | ... AI37: {=IFERROR(_xlfn.XLOOKUP($A37, INDIRECT("'" & AI$3 & "'!A:A"), INDIRECT("'" & AI$3 & "'!B:B")),0)} -> 471.12 | AJ37: =C37 -> 454.35 | AK37: {=IFERROR(_xlfn.XLOOKUP($A37, INDIRECT("'" & AK$3 & "'!A:A"), INDIRECT("'" & AK$3 & "'!B:B")),0)} -> 1073.05 | AL37: {=IFERROR(_xlfn.XLOOKUP($A37, INDIRECT("'" & AL$3 & "'!A:A"), INDIRECT("'" & AL$3 & "'!B:B")),0)} -> 982.84086 | AM37: {=IFERROR(_xlfn.XLOOKUP($A37, INDIRECT("'" & AM$3 & "'!A:A"), INDIRECT("'" & AM$3 & "'!B:B")),0)} -> 650.88
A38: Shelving | B38: {=IFERROR(_xlfn.XLOOKUP($A38, INDIRECT("'" & B$3 & "'!A:A"), INDIRECT("'" & B$3 & "'!B:B")),0)} -> 703.6 | C38: {=IFERROR(_xlfn.XLOOKUP($A38, INDIRECT("'" & C$3 & "'!A:A"), INDIRECT("'" & C$3 & "'!B:B")),0)} -> 488.2 | D38: {=IFERROR(_xlfn.XLOOKUP($A38, INDIRECT("'" & D$3 & "'!A:A"), INDIRECT("'" & D$3 & "'!B:B")),0)} -> 464.2 | E38: {=IFERROR(_xlfn.XLOOKUP($A38, INDIRECT("'" & E$3 & "'!A:A"), INDIRECT("'" & E$3 & "'!B:B")),0)} -> 396.65 | F38: {=IFERROR(_xlfn.XLOOKUP($A38, INDIRECT("'" & F$3 & "'!A:A"), INDIRECT("'" & F$3 & "'!B:B")),0)} -> 583.6 | G38: {=IFERROR(_xlfn.XLOOKUP($A38, INDIRECT("'" & G$3 & "'!A:A"), INDIRECT("'" & G$3 & "'!B:B")),0)} -> 535.6 | H38: {=IFERROR(_xlfn.XLOOKUP($A38, INDIRECT("'" & H$3 & "'!A:A"), INDIRECT("'" & H$3 & "'!B:B")),0)} -> 511.6 | I38: {=IFERROR(_xlfn.XLOOKUP($A38, INDIRECT("'" & I$3 & "'!A:A"), INDIRECT("'" & I$3 & "'!B:B")),0)} -> 607.3 | ... AI38: {=IFERROR(_xlfn.XLOOKUP($A38, INDIRECT("'" & AI$3 & "'!A:A"), INDIRECT("'" & AI$3 & "'!B:B")),0)} -> 543.35 | AJ38: =C38 -> 488.2 | AK38: {=IFERROR(_xlfn.XLOOKUP($A38, INDIRECT("'" & AK$3 & "'!A:A"), INDIRECT("'" & AK$3 & "'!B:B")),0)} -> 690.5 | AL38: {=IFERROR(_xlfn.XLOOKUP($A38, INDIRECT("'" & AL$3 & "'!A:A"), INDIRECT("'" & AL$3 & "'!B:B")),0)} -> 827.7492 | AM38: {=IFERROR(_xlfn.XLOOKUP($A38, INDIRECT("'" & AM$3 & "'!A:A"), INDIRECT("'" & AM$3 & "'!B:B")),0)} -> 551.85
A39: Interior Trim Labor | B39: {=IFERROR(_xlfn.XLOOKUP($A39, INDIRECT("'" & B$3 & "'!A:A"), INDIRECT("'" & B$3 & "'!B:B")),0)} -> 0 | C39: {=IFERROR(_xlfn.XLOOKUP($A39, INDIRECT("'" & C$3 & "'!A:A"), INDIRECT("'" & C$3 & "'!B:B")),0)} -> 0 | D39: {=IFERROR(_xlfn.XLOOKUP($A39, INDIRECT("'" & D$3 & "'!A:A"), INDIRECT("'" & D$3 & "'!B:B")),0)} -> 0 | E39: {=IFERROR(_xlfn.XLOOKUP($A39, INDIRECT("'" & E$3 & "'!A:A"), INDIRECT("'" & E$3 & "'!B:B")),0)} -> 0 | F39: {=IFERROR(_xlfn.XLOOKUP($A39, INDIRECT("'" & F$3 & "'!A:A"), INDIRECT("'" & F$3 & "'!B:B")),0)} -> 0 | G39: {=IFERROR(_xlfn.XLOOKUP($A39, INDIRECT("'" & G$3 & "'!A:A"), INDIRECT("'" & G$3 & "'!B:B")),0)} -> 0 | H39: {=IFERROR(_xlfn.XLOOKUP($A39, INDIRECT("'" & H$3 & "'!A:A"), INDIRECT("'" & H$3 & "'!B:B")),0)} -> 0 | I39: {=IFERROR(_xlfn.XLOOKUP($A39, INDIRECT("'" & I$3 & "'!A:A"), INDIRECT("'" & I$3 & "'!B:B")),0)} -> 0 | ... AI39: {=IFERROR(_xlfn.XLOOKUP($A39, INDIRECT("'" & AI$3 & "'!A:A"), INDIRECT("'" & AI$3 & "'!B:B")),0)} -> 0 | AJ39: =C39 -> 0 | AK39: {=IFERROR(_xlfn.XLOOKUP($A39, INDIRECT("'" & AK$3 & "'!A:A"), INDIRECT("'" & AK$3 & "'!B:B")),0)} -> 0 | AL39: {=IFERROR(_xlfn.XLOOKUP($A39, INDIRECT("'" & AL$3 & "'!A:A"), INDIRECT("'" & AL$3 & "'!B:B")),0)} -> 1677.87 | AM39: {=IFERROR(_xlfn.XLOOKUP($A39, INDIRECT("'" & AM$3 & "'!A:A"), INDIRECT("'" & AM$3 & "'!B:B")),0)} -> 0
... A43: Countertops | B43: {=IFERROR(_xlfn.XLOOKUP($A43, INDIRECT("'" & B$3 & "'!A:A"), INDIRECT("'" & B$3 & "'!B:B")),0)} -> 3773 | C43: {=IFERROR(_xlfn.XLOOKUP($A43, INDIRECT("'" & C$3 & "'!A:A"), INDIRECT("'" & C$3 & "'!B:B")),0)} -> 3690 | D43: {=IFERROR(_xlfn.XLOOKUP($A43, INDIRECT("'" & D$3 & "'!A:A"), INDIRECT("'" & D$3 & "'!B:B")),0)} -> 4110 | E43: {=IFERROR(_xlfn.XLOOKUP($A43, INDIRECT("'" & E$3 & "'!A:A"), INDIRECT("'" & E$3 & "'!B:B")),0)} -> 3243 | F43: {=IFERROR(_xlfn.XLOOKUP($A43, INDIRECT("'" & F$3 & "'!A:A"), INDIRECT("'" & F$3 & "'!B:B")),0)} -> 4239 | G43: {=IFERROR(_xlfn.XLOOKUP($A43, INDIRECT("'" & G$3 & "'!A:A"), INDIRECT("'" & G$3 & "'!B:B")),0)} -> 2680 | H43: {=IFERROR(_xlfn.XLOOKUP($A43, INDIRECT("'" & H$3 & "'!A:A"), INDIRECT("'" & H$3 & "'!B:B")),0)} -> 3588 | I43: {=IFERROR(_xlfn.XLOOKUP($A43, INDIRECT("'" & I$3 & "'!A:A"), INDIRECT("'" & I$3 & "'!B:B")),0)} -> 3530 | ... AI43: {=IFERROR(_xlfn.XLOOKUP($A43, INDIRECT("'" & AI$3 & "'!A:A"), INDIRECT("'" & AI$3 & "'!B:B")),0)} -> 3588 | AJ43: =C43 -> 3690 | AK43: {=IFERROR(_xlfn.XLOOKUP($A43, INDIRECT("'" & AK$3 & "'!A:A"), INDIRECT("'" & AK$3 & "'!B:B")),0)} -> 3178 | AL43: {=IFERROR(_xlfn.XLOOKUP($A43, INDIRECT("'" & AL$3 & "'!A:A"), INDIRECT("'" & AL$3 & "'!B:B")),0)} -> 3585.972 | AM43: {=IFERROR(_xlfn.XLOOKUP($A43, INDIRECT("'" & AM$3 & "'!A:A"), INDIRECT("'" & AM$3 & "'!B:B")),0)} -> 4555
A44: Cabinet Labor & Material | B44: {=IFERROR(_xlfn.XLOOKUP($A44, INDIRECT("'" & B$3 & "'!A:A"), INDIRECT("'" & B$3 & "'!B:B")),0)} -> 5840.6 | C44: {=IFERROR(_xlfn.XLOOKUP($A44, INDIRECT("'" & C$3 & "'!A:A"), INDIRECT("'" & C$3 & "'!B:B")),0)} -> 5613.79 | D44: {=IFERROR(_xlfn.XLOOKUP($A44, INDIRECT("'" & D$3 & "'!A:A"), INDIRECT("'" & D$3 & "'!B:B")),0)} -> 5788.54 | E44: {=IFERROR(_xlfn.XLOOKUP($A44, INDIRECT("'" & E$3 & "'!A:A"), INDIRECT("'" & E$3 & "'!B:B")),0)} -> 5080.17 | F44: {=IFERROR(_xlfn.XLOOKUP($A44, INDIRECT("'" & F$3 & "'!A:A"), INDIRECT("'" & F$3 & "'!B:B")),0)} -> 5704.65 | G44: {=IFERROR(_xlfn.XLOOKUP($A44, INDIRECT("'" & G$3 & "'!A:A"), INDIRECT("'" & G$3 & "'!B:B")),0)} -> 4976.59 | H44: {=IFERROR(_xlfn.XLOOKUP($A44, INDIRECT("'" & H$3 & "'!A:A"), INDIRECT("'" & H$3 & "'!B:B")),0)} -> 5682.59 | I44: {=IFERROR(_xlfn.XLOOKUP($A44, INDIRECT("'" & I$3 & "'!A:A"), INDIRECT("'" & I$3 & "'!B:B")),0)} -> 4720 | ... AI44: {=IFERROR(_xlfn.XLOOKUP($A44, INDIRECT("'" & AI$3 & "'!A:A"), INDIRECT("'" & AI$3 & "'!B:B")),0)} -> 5632.32 | AJ44: =C44+AM1 -> 9113.79 | AK44: {=IFERROR(_xlfn.XLOOKUP($A44, INDIRECT("'" & AK$3 & "'!A:A"), INDIRECT("'" & AK$3 & "'!B:B")),0)} -> 4776 | AL44: {=IFERROR(_xlfn.XLOOKUP($A44, INDIRECT("'" & AL$3 & "'!A:A"), INDIRECT("'" & AL$3 & "'!B:B")),0)} -> 6516.1303 | AM44: {=IFERROR(_xlfn.XLOOKUP($A44, INDIRECT("'" & AM$3 & "'!A:A"), INDIRECT("'" & AM$3 & "'!B:B")),0)} -> 6305.54
A45: Tile Labor & Material | B45: {=IFERROR(_xlfn.XLOOKUP($A45, INDIRECT("'" & B$3 & "'!A:A"), INDIRECT("'" & B$3 & "'!B:B")),0)} -> 0 | C45: {=IFERROR(_xlfn.XLOOKUP($A45, INDIRECT("'" & C$3 & "'!A:A"), INDIRECT("'" & C$3 & "'!B:B")),0)} -> 0 | D45: {=IFERROR(_xlfn.XLOOKUP($A45, INDIRECT("'" & D$3 & "'!A:A"), INDIRECT("'" & D$3 & "'!B:B")),0)} -> 0 | E45: {=IFERROR(_xlfn.XLOOKUP($A45, INDIRECT("'" & E$3 & "'!A:A"), INDIRECT("'" & E$3 & "'!B:B")),0)} -> 0 | F45: {=IFERROR(_xlfn.XLOOKUP($A45, INDIRECT("'" & F$3 & "'!A:A"), INDIRECT("'" & F$3 & "'!B:B")),0)} -> 0 | G45: {=IFERROR(_xlfn.XLOOKUP($A45, INDIRECT("'" & G$3 & "'!A:A"), INDIRECT("'" & G$3 & "'!B:B")),0)} -> 0 | H45: {=IFERROR(_xlfn.XLOOKUP($A45, INDIRECT("'" & H$3 & "'!A:A"), INDIRECT("'" & H$3 & "'!B:B")),0)} -> 0 | I45: {=IFERROR(_xlfn.XLOOKUP($A45, INDIRECT("'" & I$3 & "'!A:A"), INDIRECT("'" & I$3 & "'!B:B")),0)} -> 0 | ... AI45: {=IFERROR(_xlfn.XLOOKUP($A45, INDIRECT("'" & AI$3 & "'!A:A"), INDIRECT("'" & AI$3 & "'!B:B")),0)} -> 0 | AJ45: =C45 -> 0 | AK45: {=IFERROR(_xlfn.XLOOKUP($A45, INDIRECT("'" & AK$3 & "'!A:A"), INDIRECT("'" & AK$3 & "'!B:B")),0)} -> 2630 | AL45: {=IFERROR(_xlfn.XLOOKUP($A45, INDIRECT("'" & AL$3 & "'!A:A"), INDIRECT("'" & AL$3 & "'!B:B")),0)} -> 453.00334 | AM45: {=IFERROR(_xlfn.XLOOKUP($A45, INDIRECT("'" & AM$3 & "'!A:A"), INDIRECT("'" & AM$3 & "'!B:B")),0)} -> 1956.5
A46: Light Fixtures | B46: {=IFERROR(_xlfn.XLOOKUP($A46, INDIRECT("'" & B$3 & "'!A:A"), INDIRECT("'" & B$3 & "'!B:B")),0)} -> 652.11 | C46: {=IFERROR(_xlfn.XLOOKUP($A46, INDIRECT("'" & C$3 & "'!A:A"), INDIRECT("'" & C$3 & "'!B:B")),0)} -> 731.35 | D46: {=IFERROR(_xlfn.XLOOKUP($A46, INDIRECT("'" & D$3 & "'!A:A"), INDIRECT("'" & D$3 & "'!B:B")),0)} -> 540.12 | E46: {=IFERROR(_xlfn.XLOOKUP($A46, INDIRECT("'" & E$3 & "'!A:A"), INDIRECT("'" & E$3 & "'!B:B")),0)} -> 589.64 | F46: {=IFERROR(_xlfn.XLOOKUP($A46, INDIRECT("'" & F$3 & "'!A:A"), INDIRECT("'" & F$3 & "'!B:B")),0)} -> 626.34 | G46: {=IFERROR(_xlfn.XLOOKUP($A46, INDIRECT("'" & G$3 & "'!A:A"), INDIRECT("'" & G$3 & "'!B:B")),0)} -> 656.54 | H46: {=IFERROR(_xlfn.XLOOKUP($A46, INDIRECT("'" & H$3 & "'!A:A"), INDIRECT("'" & H$3 & "'!B:B")),0)} -> 624.04 | I46: {=IFERROR(_xlfn.XLOOKUP($A46, INDIRECT("'" & I$3 & "'!A:A"), INDIRECT("'" & I$3 & "'!B:B")),0)} -> 614.82 | ... AI46: {=IFERROR(_xlfn.XLOOKUP($A46, INDIRECT("'" & AI$3 & "'!A:A"), INDIRECT("'" & AI$3 & "'!B:B")),0)} -> 635.85 | AJ46: =C46 -> 731.35 | AK46: {=IFERROR(_xlfn.XLOOKUP($A46, INDIRECT("'" & AK$3 & "'!A:A"), INDIRECT("'" & AK$3 & "'!B:B")),0)} -> 1483.32 | AL46: {=IFERROR(_xlfn.XLOOKUP($A46, INDIRECT("'" & AL$3 & "'!A:A"), INDIRECT("'" & AL$3 & "'!B:B")),0)} -> 1424.2347 | AM46: {=IFERROR(_xlfn.XLOOKUP($A46, INDIRECT("'" & AM$3 & "'!A:A"), INDIRECT("'" & AM$3 & "'!B:B")),0)} -> 981.25
A47: Appliances | B47: {=IFERROR(_xlfn.XLOOKUP($A47, INDIRECT("'" & B$3 & "'!A:A"), INDIRECT("'" & B$3 & "'!B:B")),0)} -> 1616.06 | C47: {=IFERROR(_xlfn.XLOOKUP($A47, INDIRECT("'" & C$3 & "'!A:A"), INDIRECT("'" & C$3 & "'!B:B")),0)} -> 1616.06 | D47: {=IFERROR(_xlfn.XLOOKUP($A47, INDIRECT("'" & D$3 & "'!A:A"), INDIRECT("'" & D$3 & "'!B:B")),0)} -> 1616.06 | E47: {=IFERROR(_xlfn.XLOOKUP($A47, INDIRECT("'" & E$3 & "'!A:A"), INDIRECT("'" & E$3 & "'!B:B")),0)} -> 1616.06 | F47: {=IFERROR(_xlfn.XLOOKUP($A47, INDIRECT("'" & F$3 & "'!A:A"), INDIRECT("'" & F$3 & "'!B:B")),0)} -> 1616.06 | G47: {=IFERROR(_xlfn.XLOOKUP($A47, INDIRECT("'" & G$3 & "'!A:A"), INDIRECT("'" & G$3 & "'!B:B")),0)} -> 1616.06 | H47: {=IFERROR(_xlfn.XLOOKUP($A47, INDIRECT("'" & H$3 & "'!A:A"), INDIRECT("'" & H$3 & "'!B:B")),0)} -> 1616.06 | I47: {=IFERROR(_xlfn.XLOOKUP($A47, INDIRECT("'" & I$3 & "'!A:A"), INDIRECT("'" & I$3 & "'!B:B")),0)} -> 1616.06 | ... AI47: {=IFERROR(_xlfn.XLOOKUP($A47, INDIRECT("'" & AI$3 & "'!A:A"), INDIRECT("'" & AI$3 & "'!B:B")),0)} -> 1616.06 | AJ47: =C47 -> 1616.06 | AK47: {=IFERROR(_xlfn.XLOOKUP($A47, INDIRECT("'" & AK$3 & "'!A:A"), INDIRECT("'" & AK$3 & "'!B:B")),0)} -> 3583.88 | AL47: {=IFERROR(_xlfn.XLOOKUP($A47, INDIRECT("'" & AL$3 & "'!A:A"), INDIRECT("'" & AL$3 & "'!B:B")),0)} -> 1805.6379 | AM47: {=IFERROR(_xlfn.XLOOKUP($A47, INDIRECT("'" & AM$3 & "'!A:A"), INDIRECT("'" & AM$3 & "'!B:B")),0)} -> 156.8
A48: Carpet Labor & Material | B48: {=IFERROR(_xlfn.XLOOKUP($A48, INDIRECT("'" & B$3 & "'!A:A"), INDIRECT("'" & B$3 & "'!B:B")),0)} -> 1658.63 | C48: {=IFERROR(_xlfn.XLOOKUP($A48, INDIRECT("'" & C$3 & "'!A:A"), INDIRECT("'" & C$3 & "'!B:B")),0)} -> 1850.38 | D48: {=IFERROR(_xlfn.XLOOKUP($A48, INDIRECT("'" & D$3 & "'!A:A"), INDIRECT("'" & D$3 & "'!B:B")),0)} -> 1398 | E48: {=IFERROR(_xlfn.XLOOKUP($A48, INDIRECT("'" & E$3 & "'!A:A"), INDIRECT("'" & E$3 & "'!B:B")),0)} -> 1535.62 | F48: {=IFERROR(_xlfn.XLOOKUP($A48, INDIRECT("'" & F$3 & "'!A:A"), INDIRECT("'" & F$3 & "'!B:B")),0)} -> 1956.88 | G48: {=IFERROR(_xlfn.XLOOKUP($A48, INDIRECT("'" & G$3 & "'!A:A"), INDIRECT("'" & G$3 & "'!B:B")),0)} -> 1707.75 | H48: {=IFERROR(_xlfn.XLOOKUP($A48, INDIRECT("'" & H$3 & "'!A:A"), INDIRECT("'" & H$3 & "'!B:B")),0)} -> 1899.5 | I48: {=IFERROR(_xlfn.XLOOKUP($A48, INDIRECT("'" & I$3 & "'!A:A"), INDIRECT("'" & I$3 & "'!B:B")),0)} -> 2194.5 | ... AI48: {=IFERROR(_xlfn.XLOOKUP($A48, INDIRECT("'" & AI$3 & "'!A:A"), INDIRECT("'" & AI$3 & "'!B:B")),0)} -> 1637.25 | AJ48: =C48 -> 1850.38 | AK48: {=IFERROR(_xlfn.XLOOKUP($A48, INDIRECT("'" & AK$3 & "'!A:A"), INDIRECT("'" & AK$3 & "'!B:B")),0)} -> 0 | AL48: {=IFERROR(_xlfn.XLOOKUP($A48, INDIRECT("'" & AL$3 & "'!A:A"), INDIRECT("'" & AL$3 & "'!B:B")),0)} -> 0 | AM48: {=IFERROR(_xlfn.XLOOKUP($A48, INDIRECT("'" & AM$3 & "'!A:A"), INDIRECT("'" & AM$3 & "'!B:B")),0)} -> 1730.62
A49: Hardwood Labor & Material | B49: {=IFERROR(_xlfn.XLOOKUP($A49, INDIRECT("'" & B$3 & "'!A:A"), INDIRECT("'" & B$3 & "'!B:B")),0)} -> 0 | C49: {=IFERROR(_xlfn.XLOOKUP($A49, INDIRECT("'" & C$3 & "'!A:A"), INDIRECT("'" & C$3 & "'!B:B")),0)} -> 0 | D49: {=IFERROR(_xlfn.XLOOKUP($A49, INDIRECT("'" & D$3 & "'!A:A"), INDIRECT("'" & D$3 & "'!B:B")),0)} -> 0 | E49: {=IFERROR(_xlfn.XLOOKUP($A49, INDIRECT("'" & E$3 & "'!A:A"), INDIRECT("'" & E$3 & "'!B:B")),0)} -> 0 | F49: {=IFERROR(_xlfn.XLOOKUP($A49, INDIRECT("'" & F$3 & "'!A:A"), INDIRECT("'" & F$3 & "'!B:B")),0)} -> 0 | G49: {=IFERROR(_xlfn.XLOOKUP($A49, INDIRECT("'" & G$3 & "'!A:A"), INDIRECT("'" & G$3 & "'!B:B")),0)} -> 0 | H49: {=IFERROR(_xlfn.XLOOKUP($A49, INDIRECT("'" & H$3 & "'!A:A"), INDIRECT("'" & H$3 & "'!B:B")),0)} -> 0 | I49: {=IFERROR(_xlfn.XLOOKUP($A49, INDIRECT("'" & I$3 & "'!A:A"), INDIRECT("'" & I$3 & "'!B:B")),0)} -> 0 | ... AI49: {=IFERROR(_xlfn.XLOOKUP($A49, INDIRECT("'" & AI$3 & "'!A:A"), INDIRECT("'" & AI$3 & "'!B:B")),0)} -> 0 | AJ49: =C49 -> 0 | AK49: {=IFERROR(_xlfn.XLOOKUP($A49, INDIRECT("'" & AK$3 & "'!A:A"), INDIRECT("'" & AK$3 & "'!B:B")),0)} -> 0 | AL49: {=IFERROR(_xlfn.XLOOKUP($A49, INDIRECT("'" & AL$3 & "'!A:A"), INDIRECT("'" & AL$3 & "'!B:B")),0)} -> 0 | AM49: {=IFERROR(_xlfn.XLOOKUP($A49, INDIRECT("'" & AM$3 & "'!A:A"), INDIRECT("'" & AM$3 & "'!B:B")),0)} -> 0
A50: LVP Labor & Material | B50: {=IFERROR(_xlfn.XLOOKUP($A50, INDIRECT("'" & B$3 & "'!A:A"), INDIRECT("'" & B$3 & "'!B:B")),0)} -> 5061.42 | C50: {=IFERROR(_xlfn.XLOOKUP($A50, INDIRECT("'" & C$3 & "'!A:A"), INDIRECT("'" & C$3 & "'!B:B")),0)} -> 3270.46 | D50: {=IFERROR(_xlfn.XLOOKUP($A50, INDIRECT("'" & D$3 & "'!A:A"), INDIRECT("'" & D$3 & "'!B:B")),0)} -> 3192.95 | E50: {=IFERROR(_xlfn.XLOOKUP($A50, INDIRECT("'" & E$3 & "'!A:A"), INDIRECT("'" & E$3 & "'!B:B")),0)} -> 3697.51 | F50: {=IFERROR(_xlfn.XLOOKUP($A50, INDIRECT("'" & F$3 & "'!A:A"), INDIRECT("'" & F$3 & "'!B:B")),0)} -> 3640.18 | G50: {=IFERROR(_xlfn.XLOOKUP($A50, INDIRECT("'" & G$3 & "'!A:A"), INDIRECT("'" & G$3 & "'!B:B")),0)} -> 2413.91 | H50: {=IFERROR(_xlfn.XLOOKUP($A50, INDIRECT("'" & H$3 & "'!A:A"), INDIRECT("'" & H$3 & "'!B:B")),0)} -> 2647.51 | I50: {=IFERROR(_xlfn.XLOOKUP($A50, INDIRECT("'" & I$3 & "'!A:A"), INDIRECT("'" & I$3 & "'!B:B")),0)} -> 3414.72 | ... AI50: {=IFERROR(_xlfn.XLOOKUP($A50, INDIRECT("'" & AI$3 & "'!A:A"), INDIRECT("'" & AI$3 & "'!B:B")),0)} -> 4771.93 | AJ50: =C50 -> 3270.46 | AK50: {=IFERROR(_xlfn.XLOOKUP($A50, INDIRECT("'" & AK$3 & "'!A:A"), INDIRECT("'" & AK$3 & "'!B:B")),0)} -> 8525.64 | AL50: {=IFERROR(_xlfn.XLOOKUP($A50, INDIRECT("'" & AL$3 & "'!A:A"), INDIRECT("'" & AL$3 & "'!B:B")),0)} -> 6888.2808 | AM50: {=IFERROR(_xlfn.XLOOKUP($A50, INDIRECT("'" & AM$3 & "'!A:A"), INDIRECT("'" & AM$3 & "'!B:B")),0)} -> 8174
A51: Interior Clean | B51: {=IFERROR(_xlfn.XLOOKUP($A51, INDIRECT("'" & B$3 & "'!A:A"), INDIRECT("'" & B$3 & "'!B:B")),0)} -> 602.48 | C51: {=IFERROR(_xlfn.XLOOKUP($A51, INDIRECT("'" & C$3 & "'!A:A"), INDIRECT("'" & C$3 & "'!B:B")),0)} -> 521.84 | D51: {=IFERROR(_xlfn.XLOOKUP($A51, INDIRECT("'" & D$3 & "'!A:A"), INDIRECT("'" & D$3 & "'!B:B")),0)} -> 479.72 | E51: {=IFERROR(_xlfn.XLOOKUP($A51, INDIRECT("'" & E$3 & "'!A:A"), INDIRECT("'" & E$3 & "'!B:B")),0)} -> 452 | F51: {=IFERROR(_xlfn.XLOOKUP($A51, INDIRECT("'" & F$3 & "'!A:A"), INDIRECT("'" & F$3 & "'!B:B")),0)} -> 598.52 | G51: {=IFERROR(_xlfn.XLOOKUP($A51, INDIRECT("'" & G$3 & "'!A:A"), INDIRECT("'" & G$3 & "'!B:B")),0)} -> 477.38 | H51: {=IFERROR(_xlfn.XLOOKUP($A51, INDIRECT("'" & H$3 & "'!A:A"), INDIRECT("'" & H$3 & "'!B:B")),0)} -> 328.34 | I51: {=IFERROR(_xlfn.XLOOKUP($A51, INDIRECT("'" & I$3 & "'!A:A"), INDIRECT("'" & I$3 & "'!B:B")),0)} -> 560 | ... AI51: {=IFERROR(_xlfn.XLOOKUP($A51, INDIRECT("'" & AI$3 & "'!A:A"), INDIRECT("'" & AI$3 & "'!B:B")),0)} -> 523.64 | AJ51: =C51 -> 521.84 | AK51: {=IFERROR(_xlfn.XLOOKUP($A51, INDIRECT("'" & AK$3 & "'!A:A"), INDIRECT("'" & AK$3 & "'!B:B")),0)} -> 492.86 | AL51: {=IFERROR(_xlfn.XLOOKUP($A51, INDIRECT("'" & AL$3 & "'!A:A"), INDIRECT("'" & AL$3 & "'!B:B")),0)} -> 418.22 | AM51: {=IFERROR(_xlfn.XLOOKUP($A51, INDIRECT("'" & AM$3 & "'!A:A"), INDIRECT("'" & AM$3 & "'!B:B")),0)} -> 472.96
A52: Gutters | B52: {=IFERROR(_xlfn.XLOOKUP($A52, INDIRECT("'" & B$3 & "'!A:A"), INDIRECT("'" & B$3 & "'!B:B")),0)} -> 882 | C52: {=IFERROR(_xlfn.XLOOKUP($A52, INDIRECT("'" & C$3 & "'!A:A"), INDIRECT("'" & C$3 & "'!B:B")),0)} -> 522 | D52: {=IFERROR(_xlfn.XLOOKUP($A52, INDIRECT("'" & D$3 & "'!A:A"), INDIRECT("'" & D$3 & "'!B:B")),0)} -> 1034 | E52: {=IFERROR(_xlfn.XLOOKUP($A52, INDIRECT("'" & E$3 & "'!A:A"), INDIRECT("'" & E$3 & "'!B:B")),0)} -> 936 | F52: {=IFERROR(_xlfn.XLOOKUP($A52, INDIRECT("'" & F$3 & "'!A:A"), INDIRECT("'" & F$3 & "'!B:B")),0)} -> 957 | G52: {=IFERROR(_xlfn.XLOOKUP($A52, INDIRECT("'" & G$3 & "'!A:A"), INDIRECT("'" & G$3 & "'!B:B")),0)} -> 1212 | H52: {=IFERROR(_xlfn.XLOOKUP($A52, INDIRECT("'" & H$3 & "'!A:A"), INDIRECT("'" & H$3 & "'!B:B")),0)} -> 858 | I52: {=IFERROR(_xlfn.XLOOKUP($A52, INDIRECT("'" & I$3 & "'!A:A"), INDIRECT("'" & I$3 & "'!B:B")),0)} -> 1396 | ... AI52: {=IFERROR(_xlfn.XLOOKUP($A52, INDIRECT("'" & AI$3 & "'!A:A"), INDIRECT("'" & AI$3 & "'!B:B")),0)} -> 438 | AJ52: =C52 -> 522 | AK52: {=IFERROR(_xlfn.XLOOKUP($A52, INDIRECT("'" & AK$3 & "'!A:A"), INDIRECT("'" & AK$3 & "'!B:B")),0)} -> 490.67 | AL52: {=IFERROR(_xlfn.XLOOKUP($A52, INDIRECT("'" & AL$3 & "'!A:A"), INDIRECT("'" & AL$3 & "'!B:B")),0)} -> 651.6 | AM52: {=IFERROR(_xlfn.XLOOKUP($A52, INDIRECT("'" & AM$3 & "'!A:A"), INDIRECT("'" & AM$3 & "'!B:B")),0)} -> 500
A53: QI Inspection | B53: {=IFERROR(_xlfn.XLOOKUP($A53, INDIRECT("'" & B$3 & "'!A:A"), INDIRECT("'" & B$3 & "'!B:B")),0)} -> 310 | C53: {=IFERROR(_xlfn.XLOOKUP($A53, INDIRECT("'" & C$3 & "'!A:A"), INDIRECT("'" & C$3 & "'!B:B")),0)} -> 310 | D53: {=IFERROR(_xlfn.XLOOKUP($A53, INDIRECT("'" & D$3 & "'!A:A"), INDIRECT("'" & D$3 & "'!B:B")),0)} -> 310 | E53: {=IFERROR(_xlfn.XLOOKUP($A53, INDIRECT("'" & E$3 & "'!A:A"), INDIRECT("'" & E$3 & "'!B:B")),0)} -> 310 | F53: {=IFERROR(_xlfn.XLOOKUP($A53, INDIRECT("'" & F$3 & "'!A:A"), INDIRECT("'" & F$3 & "'!B:B")),0)} -> 310 | G53: {=IFERROR(_xlfn.XLOOKUP($A53, INDIRECT("'" & G$3 & "'!A:A"), INDIRECT("'" & G$3 & "'!B:B")),0)} -> 310 | H53: {=IFERROR(_xlfn.XLOOKUP($A53, INDIRECT("'" & H$3 & "'!A:A"), INDIRECT("'" & H$3 & "'!B:B")),0)} -> 310 | I53: {=IFERROR(_xlfn.XLOOKUP($A53, INDIRECT("'" & I$3 & "'!A:A"), INDIRECT("'" & I$3 & "'!B:B")),0)} -> 310 | ... AI53: {=IFERROR(_xlfn.XLOOKUP($A53, INDIRECT("'" & AI$3 & "'!A:A"), INDIRECT("'" & AI$3 & "'!B:B")),0)} -> 310 | AJ53: =C53 -> 310 | AK53: {=IFERROR(_xlfn.XLOOKUP($A53, INDIRECT("'" & AK$3 & "'!A:A"), INDIRECT("'" & AK$3 & "'!B:B")),0)} -> 0 | AL53: {=IFERROR(_xlfn.XLOOKUP($A53, INDIRECT("'" & AL$3 & "'!A:A"), INDIRECT("'" & AL$3 & "'!B:B")),0)} -> 0 | AM53: {=IFERROR(_xlfn.XLOOKUP($A53, INDIRECT("'" & AM$3 & "'!A:A"), INDIRECT("'" & AM$3 & "'!B:B")),0)} -> 0
A54: Deck | B54: {=IFERROR(_xlfn.XLOOKUP($A54, INDIRECT("'" & B$3 & "'!A:A"), INDIRECT("'" & B$3 & "'!B:B")),0)} -> 0 | C54: {=IFERROR(_xlfn.XLOOKUP($A54, INDIRECT("'" & C$3 & "'!A:A"), INDIRECT("'" & C$3 & "'!B:B")),0)} -> 0 | D54: {=IFERROR(_xlfn.XLOOKUP($A54, INDIRECT("'" & D$3 & "'!A:A"), INDIRECT("'" & D$3 & "'!B:B")),0)} -> 0 | E54: {=IFERROR(_xlfn.XLOOKUP($A54, INDIRECT("'" & E$3 & "'!A:A"), INDIRECT("'" & E$3 & "'!B:B")),0)} -> 0 | F54: {=IFERROR(_xlfn.XLOOKUP($A54, INDIRECT("'" & F$3 & "'!A:A"), INDIRECT("'" & F$3 & "'!B:B")),0)} -> 0 | G54: {=IFERROR(_xlfn.XLOOKUP($A54, INDIRECT("'" & G$3 & "'!A:A"), INDIRECT("'" & G$3 & "'!B:B")),0)} -> 0 | H54: {=IFERROR(_xlfn.XLOOKUP($A54, INDIRECT("'" & H$3 & "'!A:A"), INDIRECT("'" & H$3 & "'!B:B")),0)} -> 0 | I54: {=IFERROR(_xlfn.XLOOKUP($A54, INDIRECT("'" & I$3 & "'!A:A"), INDIRECT("'" & I$3 & "'!B:B")),0)} -> 0 | ... AI54: {=IFERROR(_xlfn.XLOOKUP($A54, INDIRECT("'" & AI$3 & "'!A:A"), INDIRECT("'" & AI$3 & "'!B:B")),0)} -> 3146 | AJ54: =C54 -> 0 | AK54: {=IFERROR(_xlfn.XLOOKUP($A54, INDIRECT("'" & AK$3 & "'!A:A"), INDIRECT("'" & AK$3 & "'!B:B")),0)} -> 0 | AL54: {=IFERROR(_xlfn.XLOOKUP($A54, INDIRECT("'" & AL$3 & "'!A:A"), INDIRECT("'" & AL$3 & "'!B:B")),0)} -> 0 | AM54: {=IFERROR(_xlfn.XLOOKUP($A54, INDIRECT("'" & AM$3 & "'!A:A"), INDIRECT("'" & AM$3 & "'!B:B")),0)} -> 0
A55: Mailbox | B55: {=IFERROR(_xlfn.XLOOKUP($A55, INDIRECT("'" & B$3 & "'!A:A"), INDIRECT("'" & B$3 & "'!B:B")),0)} -> 90 | C55: {=IFERROR(_xlfn.XLOOKUP($A55, INDIRECT("'" & C$3 & "'!A:A"), INDIRECT("'" & C$3 & "'!B:B")),0)} -> 90 | D55: {=IFERROR(_xlfn.XLOOKUP($A55, INDIRECT("'" & D$3 & "'!A:A"), INDIRECT("'" & D$3 & "'!B:B")),0)} -> 90 | E55: {=IFERROR(_xlfn.XLOOKUP($A55, INDIRECT("'" & E$3 & "'!A:A"), INDIRECT("'" & E$3 & "'!B:B")),0)} -> 90 | F55: {=IFERROR(_xlfn.XLOOKUP($A55, INDIRECT("'" & F$3 & "'!A:A"), INDIRECT("'" & F$3 & "'!B:B")),0)} -> 90 | G55: {=IFERROR(_xlfn.XLOOKUP($A55, INDIRECT("'" & G$3 & "'!A:A"), INDIRECT("'" & G$3 & "'!B:B")),0)} -> 90 | H55: {=IFERROR(_xlfn.XLOOKUP($A55, INDIRECT("'" & H$3 & "'!A:A"), INDIRECT("'" & H$3 & "'!B:B")),0)} -> 90 | I55: {=IFERROR(_xlfn.XLOOKUP($A55, INDIRECT("'" & I$3 & "'!A:A"), INDIRECT("'" & I$3 & "'!B:B")),0)} -> 90 | ... AI55: {=IFERROR(_xlfn.XLOOKUP($A55, INDIRECT("'" & AI$3 & "'!A:A"), INDIRECT("'" & AI$3 & "'!B:B")),0)} -> 0 | AJ55: =C55 -> 90 | AK55: {=IFERROR(_xlfn.XLOOKUP($A55, INDIRECT("'" & AK$3 & "'!A:A"), INDIRECT("'" & AK$3 & "'!B:B")),0)} -> 0 | AL55: {=IFERROR(_xlfn.XLOOKUP($A55, INDIRECT("'" & AL$3 & "'!A:A"), INDIRECT("'" & AL$3 & "'!B:B")),0)} -> 0 | AM55: {=IFERROR(_xlfn.XLOOKUP($A55, INDIRECT("'" & AM$3 & "'!A:A"), INDIRECT("'" & AM$3 & "'!B:B")),0)} -> 0
A56: Pressure Wash | B56: {=IFERROR(_xlfn.XLOOKUP($A56, INDIRECT("'" & B$3 & "'!A:A"), INDIRECT("'" & B$3 & "'!B:B")),0)} -> 235 | C56: {=IFERROR(_xlfn.XLOOKUP($A56, INDIRECT("'" & C$3 & "'!A:A"), INDIRECT("'" & C$3 & "'!B:B")),0)} -> 235 | D56: {=IFERROR(_xlfn.XLOOKUP($A56, INDIRECT("'" & D$3 & "'!A:A"), INDIRECT("'" & D$3 & "'!B:B")),0)} -> 235 | E56: {=IFERROR(_xlfn.XLOOKUP($A56, INDIRECT("'" & E$3 & "'!A:A"), INDIRECT("'" & E$3 & "'!B:B")),0)} -> 235 | F56: {=IFERROR(_xlfn.XLOOKUP($A56, INDIRECT("'" & F$3 & "'!A:A"), INDIRECT("'" & F$3 & "'!B:B")),0)} -> 235 | G56: {=IFERROR(_xlfn.XLOOKUP($A56, INDIRECT("'" & G$3 & "'!A:A"), INDIRECT("'" & G$3 & "'!B:B")),0)} -> 235 | H56: {=IFERROR(_xlfn.XLOOKUP($A56, INDIRECT("'" & H$3 & "'!A:A"), INDIRECT("'" & H$3 & "'!B:B")),0)} -> 235 | I56: {=IFERROR(_xlfn.XLOOKUP($A56, INDIRECT("'" & I$3 & "'!A:A"), INDIRECT("'" & I$3 & "'!B:B")),0)} -> 235 | ... AI56: {=IFERROR(_xlfn.XLOOKUP($A56, INDIRECT("'" & AI$3 & "'!A:A"), INDIRECT("'" & AI$3 & "'!B:B")),0)} -> 310 | AJ56: =C56 -> 235 | AK56: {=IFERROR(_xlfn.XLOOKUP($A56, INDIRECT("'" & AK$3 & "'!A:A"), INDIRECT("'" & AK$3 & "'!B:B")),0)} -> 250 | AL56: {=IFERROR(_xlfn.XLOOKUP($A56, INDIRECT("'" & AL$3 & "'!A:A"), INDIRECT("'" & AL$3 & "'!B:B")),0)} -> 165 | AM56: {=IFERROR(_xlfn.XLOOKUP($A56, INDIRECT("'" & AM$3 & "'!A:A"), INDIRECT("'" & AM$3 & "'!B:B")),0)} -> 300
A57: Foundation | B57: {=IFERROR(_xlfn.XLOOKUP($A57, INDIRECT("'" & B$3 & "'!A:A"), INDIRECT("'" & B$3 & "'!B:B")),0)} -> 17107.5 | C57: {=IFERROR(_xlfn.XLOOKUP($A57, INDIRECT("'" & C$3 & "'!A:A"), INDIRECT("'" & C$3 & "'!B:B")),0)} -> 11205 | D57: {=IFERROR(_xlfn.XLOOKUP($A57, INDIRECT("'" & D$3 & "'!A:A"), INDIRECT("'" & D$3 & "'!B:B")),0)} -> 6750 | E57: {=IFERROR(_xlfn.XLOOKUP($A57, INDIRECT("'" & E$3 & "'!A:A"), INDIRECT("'" & E$3 & "'!B:B")),0)} -> 6688 | F57: {=IFERROR(_xlfn.XLOOKUP($A57, INDIRECT("'" & F$3 & "'!A:A"), INDIRECT("'" & F$3 & "'!B:B")),0)} -> 12930 | G57: {=IFERROR(_xlfn.XLOOKUP($A57, INDIRECT("'" & G$3 & "'!A:A"), INDIRECT("'" & G$3 & "'!B:B")),0)} -> 9662.5 | H57: {=IFERROR(_xlfn.XLOOKUP($A57, INDIRECT("'" & H$3 & "'!A:A"), INDIRECT("'" & H$3 & "'!B:B")),0)} -> 9940 | I57: {=IFERROR(_xlfn.XLOOKUP($A57, INDIRECT("'" & I$3 & "'!A:A"), INDIRECT("'" & I$3 & "'!B:B")),0)} -> 11065 | ... AI57: {=IFERROR(_xlfn.XLOOKUP($A57, INDIRECT("'" & AI$3 & "'!A:A"), INDIRECT("'" & AI$3 & "'!B:B")),0)} -> 6297.5 | AJ57: =C57 -> 11205 | AK57: {=IFERROR(_xlfn.XLOOKUP($A57, INDIRECT("'" & AK$3 & "'!A:A"), INDIRECT("'" & AK$3 & "'!B:B")),0)} -> 5778 | AL57: {=IFERROR(_xlfn.XLOOKUP($A57, INDIRECT("'" & AL$3 & "'!A:A"), INDIRECT("'" & AL$3 & "'!B:B")),0)} -> 6285.8766 | AM57: {=IFERROR(_xlfn.XLOOKUP($A57, INDIRECT("'" & AM$3 & "'!A:A"), INDIRECT("'" & AM$3 & "'!B:B")),0)} -> 7000
A58: Sticks & Bricks Subtotal | B58: =SUM(B4:B57) -> 165012.15 | C58: =SUM(C4:C57) -> 139411.53 | D58: =SUM(D4:D57) -> 113776.73 | E58: =SUM(E4:E57) -> 134057.54 | F58: =SUM(F4:F57) -> 156913.07 | G58: =SUM(G4:G57) -> 124030.98 | H58: =SUM(H4:H57) -> 134200.25 | I58: =SUM(I4:I57) -> 144355.2 | ... AM58: =SUM(AM4:AM57) -> 180445.85
A59: Survey | B59: {=IFERROR(_xlfn.XLOOKUP($A59, INDIRECT("'" & B$3 & "'!A:A"), INDIRECT("'" & B$3 & "'!B:B")),0)} -> 1700 | C59: {=IFERROR(_xlfn.XLOOKUP($A59, INDIRECT("'" & C$3 & "'!A:A"), INDIRECT("'" & C$3 & "'!B:B")),0)} -> 1700 | D59: {=IFERROR(_xlfn.XLOOKUP($A59, INDIRECT("'" & D$3 & "'!A:A"), INDIRECT("'" & D$3 & "'!B:B")),0)} -> 1700 | E59: {=IFERROR(_xlfn.XLOOKUP($A59, INDIRECT("'" & E$3 & "'!A:A"), INDIRECT("'" & E$3 & "'!B:B")),0)} -> 1700 | F59: {=IFERROR(_xlfn.XLOOKUP($A59, INDIRECT("'" & F$3 & "'!A:A"), INDIRECT("'" & F$3 & "'!B:B")),0)} -> 1700 | G59: {=IFERROR(_xlfn.XLOOKUP($A59, INDIRECT("'" & G$3 & "'!A:A"), INDIRECT("'" & G$3 & "'!B:B")),0)} -> 1700 | H59: {=IFERROR(_xlfn.XLOOKUP($A59, INDIRECT("'" & H$3 & "'!A:A"), INDIRECT("'" & H$3 & "'!B:B")),0)} -> 1700 | I59: {=IFERROR(_xlfn.XLOOKUP($A59, INDIRECT("'" & I$3 & "'!A:A"), INDIRECT("'" & I$3 & "'!B:B")),0)} -> 1700 | ... AI59: {=IFERROR(_xlfn.XLOOKUP($A59, INDIRECT("'" & AI$3 & "'!A:A"), INDIRECT("'" & AI$3 & "'!B:B")),0)} -> 1700 | AJ59: =C59 -> 1700 | AK59: {=IFERROR(_xlfn.XLOOKUP($A59, INDIRECT("'" & AK$3 & "'!A:A"), INDIRECT("'" & AK$3 & "'!B:B")),0)} -> 0 | AL59: {=IFERROR(_xlfn.XLOOKUP($A59, INDIRECT("'" & AL$3 & "'!A:A"), INDIRECT("'" & AL$3 & "'!B:B")),0)} -> 0 | AM59: {=IFERROR(_xlfn.XLOOKUP($A59, INDIRECT("'" & AM$3 & "'!A:A"), INDIRECT("'" & AM$3 & "'!B:B")),0)} -> 0
A60: Stake House | B60: {=IFERROR(_xlfn.XLOOKUP($A60, INDIRECT("'" & B$3 & "'!A:A"), INDIRECT("'" & B$3 & "'!B:B")),0)} -> 0 | C60: {=IFERROR(_xlfn.XLOOKUP($A60, INDIRECT("'" & C$3 & "'!A:A"), INDIRECT("'" & C$3 & "'!B:B")),0)} -> 0 | D60: {=IFERROR(_xlfn.XLOOKUP($A60, INDIRECT("'" & D$3 & "'!A:A"), INDIRECT("'" & D$3 & "'!B:B")),0)} -> 0 | E60: {=IFERROR(_xlfn.XLOOKUP($A60, INDIRECT("'" & E$3 & "'!A:A"), INDIRECT("'" & E$3 & "'!B:B")),0)} -> 0 | F60: {=IFERROR(_xlfn.XLOOKUP($A60, INDIRECT("'" & F$3 & "'!A:A"), INDIRECT("'" & F$3 & "'!B:B")),0)} -> 0 | G60: {=IFERROR(_xlfn.XLOOKUP($A60, INDIRECT("'" & G$3 & "'!A:A"), INDIRECT("'" & G$3 & "'!B:B")),0)} -> 0 | H60: {=IFERROR(_xlfn.XLOOKUP($A60, INDIRECT("'" & H$3 & "'!A:A"), INDIRECT("'" & H$3 & "'!B:B")),0)} -> 0 | I60: {=IFERROR(_xlfn.XLOOKUP($A60, INDIRECT("'" & I$3 & "'!A:A"), INDIRECT("'" & I$3 & "'!B:B")),0)} -> 0 | ... AI60: {=IFERROR(_xlfn.XLOOKUP($A60, INDIRECT("'" & AI$3 & "'!A:A"), INDIRECT("'" & AI$3 & "'!B:B")),0)} -> 0 | AJ60: =C60 -> 0 | AK60: {=IFERROR(_xlfn.XLOOKUP($A60, INDIRECT("'" & AK$3 & "'!A:A"), INDIRECT("'" & AK$3 & "'!B:B")),0)} -> 600 | AL60: {=IFERROR(_xlfn.XLOOKUP($A60, INDIRECT("'" & AL$3 & "'!A:A"), INDIRECT("'" & AL$3 & "'!B:B")),0)} -> 600 | AM60: {=IFERROR(_xlfn.XLOOKUP($A60, INDIRECT("'" & AM$3 & "'!A:A"), INDIRECT("'" & AM$3 & "'!B:B")),0)} -> 0
A61: Grading/Lot Clear/Hauling | B61: {=IFERROR(_xlfn.XLOOKUP($A61, INDIRECT("'" & B$3 & "'!A:A"), INDIRECT("'" & B$3 & "'!B:B")),0)} -> 1700 | C61: {=IFERROR(_xlfn.XLOOKUP($A61, INDIRECT("'" & C$3 & "'!A:A"), INDIRECT("'" & C$3 & "'!B:B")),0)} -> 1700 | D61: {=IFERROR(_xlfn.XLOOKUP($A61, INDIRECT("'" & D$3 & "'!A:A"), INDIRECT("'" & D$3 & "'!B:B")),0)} -> 1700 | E61: {=IFERROR(_xlfn.XLOOKUP($A61, INDIRECT("'" & E$3 & "'!A:A"), INDIRECT("'" & E$3 & "'!B:B")),0)} -> 1700 | F61: {=IFERROR(_xlfn.XLOOKUP($A61, INDIRECT("'" & F$3 & "'!A:A"), INDIRECT("'" & F$3 & "'!B:B")),0)} -> 1700 | G61: {=IFERROR(_xlfn.XLOOKUP($A61, INDIRECT("'" & G$3 & "'!A:A"), INDIRECT("'" & G$3 & "'!B:B")),0)} -> 1700 | H61: {=IFERROR(_xlfn.XLOOKUP($A61, INDIRECT("'" & H$3 & "'!A:A"), INDIRECT("'" & H$3 & "'!B:B")),0)} -> 1700 | I61: {=IFERROR(_xlfn.XLOOKUP($A61, INDIRECT("'" & I$3 & "'!A:A"), INDIRECT("'" & I$3 & "'!B:B")),0)} -> 1700 | ... AI61: {=IFERROR(_xlfn.XLOOKUP($A61, INDIRECT("'" & AI$3 & "'!A:A"), INDIRECT("'" & AI$3 & "'!B:B")),0)} -> 1700 | AJ61: =C61 -> 1700 | AK61: {=IFERROR(_xlfn.XLOOKUP($A61, INDIRECT("'" & AK$3 & "'!A:A"), INDIRECT("'" & AK$3 & "'!B:B")),0)} -> 2400 | AL61: {=IFERROR(_xlfn.XLOOKUP($A61, INDIRECT("'" & AL$3 & "'!A:A"), INDIRECT("'" & AL$3 & "'!B:B")),0)} -> 1800 | AM61: {=IFERROR(_xlfn.XLOOKUP($A61, INDIRECT("'" & AM$3 & "'!A:A"), INDIRECT("'" & AM$3 & "'!B:B")),0)} -> 1500
A62: Silt Fence | B62: {=IFERROR(_xlfn.XLOOKUP($A62, INDIRECT("'" & B$3 & "'!A:A"), INDIRECT("'" & B$3 & "'!B:B")),0)} -> 2000 | C62: {=IFERROR(_xlfn.XLOOKUP($A62, INDIRECT("'" & C$3 & "'!A:A"), INDIRECT("'" & C$3 & "'!B:B")),0)} -> 2000 | D62: {=IFERROR(_xlfn.XLOOKUP($A62, INDIRECT("'" & D$3 & "'!A:A"), INDIRECT("'" & D$3 & "'!B:B")),0)} -> 2000 | E62: {=IFERROR(_xlfn.XLOOKUP($A62, INDIRECT("'" & E$3 & "'!A:A"), INDIRECT("'" & E$3 & "'!B:B")),0)} -> 2000 | F62: {=IFERROR(_xlfn.XLOOKUP($A62, INDIRECT("'" & F$3 & "'!A:A"), INDIRECT("'" & F$3 & "'!B:B")),0)} -> 2000 | G62: {=IFERROR(_xlfn.XLOOKUP($A62, INDIRECT("'" & G$3 & "'!A:A"), INDIRECT("'" & G$3 & "'!B:B")),0)} -> 2000 | H62: {=IFERROR(_xlfn.XLOOKUP($A62, INDIRECT("'" & H$3 & "'!A:A"), INDIRECT("'" & H$3 & "'!B:B")),0)} -> 2000 | I62: {=IFERROR(_xlfn.XLOOKUP($A62, INDIRECT("'" & I$3 & "'!A:A"), INDIRECT("'" & I$3 & "'!B:B")),0)} -> 2000 | ... AI62: {=IFERROR(_xlfn.XLOOKUP($A62, INDIRECT("'" & AI$3 & "'!A:A"), INDIRECT("'" & AI$3 & "'!B:B")),0)} -> 2000 | AJ62: =C62 -> 2000 | AK62: {=IFERROR(_xlfn.XLOOKUP($A62, INDIRECT("'" & AK$3 & "'!A:A"), INDIRECT("'" & AK$3 & "'!B:B")),0)} -> 2000 | AL62: {=IFERROR(_xlfn.XLOOKUP($A62, INDIRECT("'" & AL$3 & "'!A:A"), INDIRECT("'" & AL$3 & "'!B:B")),0)} -> 2000 | AM62: {=IFERROR(_xlfn.XLOOKUP($A62, INDIRECT("'" & AM$3 & "'!A:A"), INDIRECT("'" & AM$3 & "'!B:B")),0)} -> 1000
A63: Temp Drive | B63: {=IFERROR(_xlfn.XLOOKUP($A63, INDIRECT("'" & B$3 & "'!A:A"), INDIRECT("'" & B$3 & "'!B:B")),0)} -> 500 | C63: {=IFERROR(_xlfn.XLOOKUP($A63, INDIRECT("'" & C$3 & "'!A:A"), INDIRECT("'" & C$3 & "'!B:B")),0)} -> 500 | D63: {=IFERROR(_xlfn.XLOOKUP($A63, INDIRECT("'" & D$3 & "'!A:A"), INDIRECT("'" & D$3 & "'!B:B")),0)} -> 500 | E63: {=IFERROR(_xlfn.XLOOKUP($A63, INDIRECT("'" & E$3 & "'!A:A"), INDIRECT("'" & E$3 & "'!B:B")),0)} -> 500 | F63: {=IFERROR(_xlfn.XLOOKUP($A63, INDIRECT("'" & F$3 & "'!A:A"), INDIRECT("'" & F$3 & "'!B:B")),0)} -> 500 | G63: {=IFERROR(_xlfn.XLOOKUP($A63, INDIRECT("'" & G$3 & "'!A:A"), INDIRECT("'" & G$3 & "'!B:B")),0)} -> 500 | H63: {=IFERROR(_xlfn.XLOOKUP($A63, INDIRECT("'" & H$3 & "'!A:A"), INDIRECT("'" & H$3 & "'!B:B")),0)} -> 500 | I63: {=IFERROR(_xlfn.XLOOKUP($A63, INDIRECT("'" & I$3 & "'!A:A"), INDIRECT("'" & I$3 & "'!B:B")),0)} -> 500 | ... AI63: {=IFERROR(_xlfn.XLOOKUP($A63, INDIRECT("'" & AI$3 & "'!A:A"), INDIRECT("'" & AI$3 & "'!B:B")),0)} -> 500 | AJ63: =C63 -> 500 | AK63: {=IFERROR(_xlfn.XLOOKUP($A63, INDIRECT("'" & AK$3 & "'!A:A"), INDIRECT("'" & AK$3 & "'!B:B")),0)} -> 500 | AL63: {=IFERROR(_xlfn.XLOOKUP($A63, INDIRECT("'" & AL$3 & "'!A:A"), INDIRECT("'" & AL$3 & "'!B:B")),0)} -> 500 | AM63: {=IFERROR(_xlfn.XLOOKUP($A63, INDIRECT("'" & AM$3 & "'!A:A"), INDIRECT("'" & AM$3 & "'!B:B")),0)} -> 500
A64: Landscaping | B64: {=IFERROR(_xlfn.XLOOKUP($A64, INDIRECT("'" & B$3 & "'!A:A"), INDIRECT("'" & B$3 & "'!B:B")),0)} -> 2500 | C64: {=IFERROR(_xlfn.XLOOKUP($A64, INDIRECT("'" & C$3 & "'!A:A"), INDIRECT("'" & C$3 & "'!B:B")),0)} -> 2500 | D64: {=IFERROR(_xlfn.XLOOKUP($A64, INDIRECT("'" & D$3 & "'!A:A"), INDIRECT("'" & D$3 & "'!B:B")),0)} -> 2500 | E64: {=IFERROR(_xlfn.XLOOKUP($A64, INDIRECT("'" & E$3 & "'!A:A"), INDIRECT("'" & E$3 & "'!B:B")),0)} -> 2500 | F64: {=IFERROR(_xlfn.XLOOKUP($A64, INDIRECT("'" & F$3 & "'!A:A"), INDIRECT("'" & F$3 & "'!B:B")),0)} -> 2500 | G64: {=IFERROR(_xlfn.XLOOKUP($A64, INDIRECT("'" & G$3 & "'!A:A"), INDIRECT("'" & G$3 & "'!B:B")),0)} -> 2500 | H64: {=IFERROR(_xlfn.XLOOKUP($A64, INDIRECT("'" & H$3 & "'!A:A"), INDIRECT("'" & H$3 & "'!B:B")),0)} -> 2500 | I64: {=IFERROR(_xlfn.XLOOKUP($A64, INDIRECT("'" & I$3 & "'!A:A"), INDIRECT("'" & I$3 & "'!B:B")),0)} -> 2500 | ... AI64: {=IFERROR(_xlfn.XLOOKUP($A64, INDIRECT("'" & AI$3 & "'!A:A"), INDIRECT("'" & AI$3 & "'!B:B")),0)} -> 2500 | AJ64: =C64 -> 2500 | AK64: {=IFERROR(_xlfn.XLOOKUP($A64, INDIRECT("'" & AK$3 & "'!A:A"), INDIRECT("'" & AK$3 & "'!B:B")),0)} -> 1500 | AL64: {=IFERROR(_xlfn.XLOOKUP($A64, INDIRECT("'" & AL$3 & "'!A:A"), INDIRECT("'" & AL$3 & "'!B:B")),0)} -> 3000 | AM64: {=IFERROR(_xlfn.XLOOKUP($A64, INDIRECT("'" & AM$3 & "'!A:A"), INDIRECT("'" & AM$3 & "'!B:B")),0)} -> 2500
A65: Flatwork | B65: {=IFERROR(_xlfn.XLOOKUP($A65, INDIRECT("'" & B$3 & "'!A:A"), INDIRECT("'" & B$3 & "'!B:B")),0)} -> 2475 | C65: {=IFERROR(_xlfn.XLOOKUP($A65, INDIRECT("'" & C$3 & "'!A:A"), INDIRECT("'" & C$3 & "'!B:B")),0)} -> 2475 | D65: {=IFERROR(_xlfn.XLOOKUP($A65, INDIRECT("'" & D$3 & "'!A:A"), INDIRECT("'" & D$3 & "'!B:B")),0)} -> 2475 | E65: {=IFERROR(_xlfn.XLOOKUP($A65, INDIRECT("'" & E$3 & "'!A:A"), INDIRECT("'" & E$3 & "'!B:B")),0)} -> 2475 | F65: {=IFERROR(_xlfn.XLOOKUP($A65, INDIRECT("'" & F$3 & "'!A:A"), INDIRECT("'" & F$3 & "'!B:B")),0)} -> 2475 | G65: {=IFERROR(_xlfn.XLOOKUP($A65, INDIRECT("'" & G$3 & "'!A:A"), INDIRECT("'" & G$3 & "'!B:B")),0)} -> 2475 | H65: {=IFERROR(_xlfn.XLOOKUP($A65, INDIRECT("'" & H$3 & "'!A:A"), INDIRECT("'" & H$3 & "'!B:B")),0)} -> 2475 | I65: {=IFERROR(_xlfn.XLOOKUP($A65, INDIRECT("'" & I$3 & "'!A:A"), INDIRECT("'" & I$3 & "'!B:B")),0)} -> 2475 | ... AI65: {=IFERROR(_xlfn.XLOOKUP($A65, INDIRECT("'" & AI$3 & "'!A:A"), INDIRECT("'" & AI$3 & "'!B:B")),0)} -> 2475 | AJ65: =C65 -> 2475 | AK65: {=IFERROR(_xlfn.XLOOKUP($A65, INDIRECT("'" & AK$3 & "'!A:A"), INDIRECT("'" & AK$3 & "'!B:B")),0)} -> 5549.99 | AL65: {=IFERROR(_xlfn.XLOOKUP($A65, INDIRECT("'" & AL$3 & "'!A:A"), INDIRECT("'" & AL$3 & "'!B:B")),0)} -> 1500 | AM65: {=IFERROR(_xlfn.XLOOKUP($A65, INDIRECT("'" & AM$3 & "'!A:A"), INDIRECT("'" & AM$3 & "'!B:B")),0)} -> 2763
A66: Site Specific Subtotal | B66: =SUM(B59:B65) -> 10875 | C66: =SUM(C59:C65) -> 10875 | D66: =SUM(D59:D65) -> 10875 | E66: =SUM(E59:E65) -> 10875 | F66: =SUM(F59:F65) -> 10875 | G66: =SUM(G59:G65) -> 10875 | H66: =SUM(H59:H65) -> 10875 | I66: =SUM(I59:I65) -> 10875 | ... AM66: =SUM(AM59:AM65) -> 8263
A67: Building Permits | B67: {=IFERROR(_xlfn.XLOOKUP($A67, INDIRECT("'" & B$3 & "'!A:A"), INDIRECT("'" & B$3 & "'!B:B")),0)} -> 2050 | C67: {=IFERROR(_xlfn.XLOOKUP($A67, INDIRECT("'" & C$3 & "'!A:A"), INDIRECT("'" & C$3 & "'!B:B")),0)} -> 2050 | D67: {=IFERROR(_xlfn.XLOOKUP($A67, INDIRECT("'" & D$3 & "'!A:A"), INDIRECT("'" & D$3 & "'!B:B")),0)} -> 2050 | E67: {=IFERROR(_xlfn.XLOOKUP($A67, INDIRECT("'" & E$3 & "'!A:A"), INDIRECT("'" & E$3 & "'!B:B")),0)} -> 2050 | F67: {=IFERROR(_xlfn.XLOOKUP($A67, INDIRECT("'" & F$3 & "'!A:A"), INDIRECT("'" & F$3 & "'!B:B")),0)} -> 2050 | G67: {=IFERROR(_xlfn.XLOOKUP($A67, INDIRECT("'" & G$3 & "'!A:A"), INDIRECT("'" & G$3 & "'!B:B")),0)} -> 2050 | H67: {=IFERROR(_xlfn.XLOOKUP($A67, INDIRECT("'" & H$3 & "'!A:A"), INDIRECT("'" & H$3 & "'!B:B")),0)} -> 2050 | I67: {=IFERROR(_xlfn.XLOOKUP($A67, INDIRECT("'" & I$3 & "'!A:A"), INDIRECT("'" & I$3 & "'!B:B")),0)} -> 2050 | ... AI67: {=IFERROR(_xlfn.XLOOKUP($A67, INDIRECT("'" & AI$3 & "'!A:A"), INDIRECT("'" & AI$3 & "'!B:B")),0)} -> 2050 | AJ67: =C67 -> 2050 | AK67: {=IFERROR(_xlfn.XLOOKUP($A67, INDIRECT("'" & AK$3 & "'!A:A"), INDIRECT("'" & AK$3 & "'!B:B")),0)} -> 1600 | AL67: {=IFERROR(_xlfn.XLOOKUP($A67, INDIRECT("'" & AL$3 & "'!A:A"), INDIRECT("'" & AL$3 & "'!B:B")),0)} -> 1600 | AM67: {=IFERROR(_xlfn.XLOOKUP($A67, INDIRECT("'" & AM$3 & "'!A:A"), INDIRECT("'" & AM$3 & "'!B:B")),0)} -> 2050
A68: Sewer Septic Permit | B68: =_xlfn.XLOOKUP(Summary!$B$3,'Water & Sewer Data'!$C:$C,'Water & Sewer Data'!$J:$J) -> 0 | C68: =_xlfn.XLOOKUP(Summary!$B$3,'Water & Sewer Data'!$C:$C,'Water & Sewer Data'!$J:$J) -> 0 | D68: =_xlfn.XLOOKUP(Summary!$B$3,'Water & Sewer Data'!$C:$C,'Water & Sewer Data'!$J:$J) -> 0 | E68: =_xlfn.XLOOKUP(Summary!$B$3,'Water & Sewer Data'!$C:$C,'Water & Sewer Data'!$J:$J) -> 0 | F68: =_xlfn.XLOOKUP(Summary!$B$3,'Water & Sewer Data'!$C:$C,'Water & Sewer Data'!$J:$J) -> 0 | G68: =_xlfn.XLOOKUP(Summary!$B$3,'Water & Sewer Data'!$C:$C,'Water & Sewer Data'!$J:$J) -> 0 | H68: =_xlfn.XLOOKUP(Summary!$B$3,'Water & Sewer Data'!$C:$C,'Water & Sewer Data'!$J:$J) -> 0 | I68: =_xlfn.XLOOKUP(Summary!$B$3,'Water & Sewer Data'!$C:$C,'Water & Sewer Data'!$J:$J) -> 0 | ... AE68: =_xlfn.XLOOKUP(Summary!$B$3,'Water & Sewer Data'!$C:$C,'Water & Sewer Data'!$J:$J) -> 0 | AF68: {=IFERROR(_xlfn.XLOOKUP($A68, INDIRECT("'" & AF$3 & "'!A:A"), INDIRECT("'" & AF$3 & "'!B:B")),0)} -> 0 | AG68: {=IFERROR(_xlfn.XLOOKUP($A68, INDIRECT("'" & AG$3 & "'!A:A"), INDIRECT("'" & AG$3 & "'!B:B")),0)} -> 0 | AH68: {=IFERROR(_xlfn.XLOOKUP($A68, INDIRECT("'" & AH$3 & "'!A:A"), INDIRECT("'" & AH$3 & "'!B:B")),0)} -> 0 | AI68: =_xlfn.XLOOKUP(Summary!$B$3,'Water & Sewer Data'!$C:$C,'Water & Sewer Data'!$J:$J) -> 0 | AJ68: =C68 -> 0 | AK68: =_xlfn.XLOOKUP(Summary!$B$3,'Water & Sewer Data'!$C:$C,'Water & Sewer Data'!$J:$J) -> 0 | AL68: =_xlfn.XLOOKUP(Summary!$B$3,'Water & Sewer Data'!$C:$C,'Water & Sewer Data'!$J:$J) -> 0 | AM68: =_xlfn.XLOOKUP(Summary!$B$3,'Water & Sewer Data'!$C:$C,'Water & Sewer Data'!$J:$J) -> 0
A69: Water Meter | B69: =_xlfn.XLOOKUP(Summary!$B$3,'Water & Sewer Data'!$C:$C,'Water & Sewer Data'!$G:$G) -> 0 | C69: =_xlfn.XLOOKUP(Summary!$B$3,'Water & Sewer Data'!$C:$C,'Water & Sewer Data'!$G:$G) -> 0 | D69: =_xlfn.XLOOKUP(Summary!$B$3,'Water & Sewer Data'!$C:$C,'Water & Sewer Data'!$G:$G) -> 0 | E69: =_xlfn.XLOOKUP(Summary!$B$3,'Water & Sewer Data'!$C:$C,'Water & Sewer Data'!$G:$G) -> 0 | F69: =_xlfn.XLOOKUP(Summary!$B$3,'Water & Sewer Data'!$C:$C,'Water & Sewer Data'!$G:$G) -> 0 | G69: =_xlfn.XLOOKUP(Summary!$B$3,'Water & Sewer Data'!$C:$C,'Water & Sewer Data'!$G:$G) -> 0 | H69: =_xlfn.XLOOKUP(Summary!$B$3,'Water & Sewer Data'!$C:$C,'Water & Sewer Data'!$G:$G) -> 0 | I69: =_xlfn.XLOOKUP(Summary!$B$3,'Water & Sewer Data'!$C:$C,'Water & Sewer Data'!$G:$G) -> 0 | ... AM69: =_xlfn.XLOOKUP(Summary!$B$3,'Water & Sewer Data'!$C:$C,'Water & Sewer Data'!$G:$G) -> 0
A70: Engineering | B70: {=IFERROR(_xlfn.XLOOKUP($A70, INDIRECT("'" & B$3 & "'!A:A"), INDIRECT("'" & B$3 & "'!B:B")),0)} -> 600 | C70: {=IFERROR(_xlfn.XLOOKUP($A70, INDIRECT("'" & C$3 & "'!A:A"), INDIRECT("'" & C$3 & "'!B:B")),0)} -> 600 | D70: {=IFERROR(_xlfn.XLOOKUP($A70, INDIRECT("'" & D$3 & "'!A:A"), INDIRECT("'" & D$3 & "'!B:B")),0)} -> 600 | E70: {=IFERROR(_xlfn.XLOOKUP($A70, INDIRECT("'" & E$3 & "'!A:A"), INDIRECT("'" & E$3 & "'!B:B")),0)} -> 600 | F70: {=IFERROR(_xlfn.XLOOKUP($A70, INDIRECT("'" & F$3 & "'!A:A"), INDIRECT("'" & F$3 & "'!B:B")),0)} -> 600 | G70: {=IFERROR(_xlfn.XLOOKUP($A70, INDIRECT("'" & G$3 & "'!A:A"), INDIRECT("'" & G$3 & "'!B:B")),0)} -> 600 | H70: {=IFERROR(_xlfn.XLOOKUP($A70, INDIRECT("'" & H$3 & "'!A:A"), INDIRECT("'" & H$3 & "'!B:B")),0)} -> 600 | I70: {=IFERROR(_xlfn.XLOOKUP($A70, INDIRECT("'" & I$3 & "'!A:A"), INDIRECT("'" & I$3 & "'!B:B")),0)} -> 600 | ... AI70: {=IFERROR(_xlfn.XLOOKUP($A70, INDIRECT("'" & AI$3 & "'!A:A"), INDIRECT("'" & AI$3 & "'!B:B")),0)} -> 600 | AJ70: =C70 -> 600 | AK70: {=IFERROR(_xlfn.XLOOKUP($A70, INDIRECT("'" & AK$3 & "'!A:A"), INDIRECT("'" & AK$3 & "'!B:B")),0)} -> 600 | AL70: {=IFERROR(_xlfn.XLOOKUP($A70, INDIRECT("'" & AL$3 & "'!A:A"), INDIRECT("'" & AL$3 & "'!B:B")),0)} -> 0 | AM70: {=IFERROR(_xlfn.XLOOKUP($A70, INDIRECT("'" & AM$3 & "'!A:A"), INDIRECT("'" & AM$3 & "'!B:B")),0)} -> 600
A71: Soft Costs Subtotal | B71: =SUM(B67:B70) -> 2650 | C71: =SUM(C67:C70) -> 2650 | D71: =SUM(D67:D70) -> 2650 | E71: =SUM(E67:E70) -> 2650 | F71: =SUM(F67:F70) -> 2650 | G71: =SUM(G67:G70) -> 2650 | H71: =SUM(H67:H70) -> 2650 | I71: =SUM(I67:I70) -> 2650 | ... AM71: =SUM(AM67:AM70) -> 2650

Sheet Acacia
A1: ACACIA BASE HOUSE COSTS
A3: ACTIVITY | B3: COSTS
A4: Dumpster | B4: 3000
A5: Utilities | B5: 300
A6: Portable toilet | B6: 875
A7: Permit Box | B7: 50
A8: Termite | B8: 225
A9: Lumber All Floors | B9: 12160.21
A10: Roof Trusses | B10: 7573.68
A11: Floor Trusses | B11: 3949.41
A12: Stairs | B12: 580.59
A13: Framing Labor | B13: 11814
A14: Windows Labor | B14: 321
A15: Window Material | B15: 3411.27
... A51: Foundation | B51: 17107.5
A52: Sticks & Bricks Subtotal | B52: =SUBTOTAL(109,B4:B51) -> 165012.15
A53: Survey | B53: 1700
A54: Grading/Lot Clear/Hauling | B54: 1700
A55: Silt Fence | B55: 2000
A56: Temp Drive | B56: 500
A57: Landscaping | B57: 2500
A58: Flatwork | B58: 2475
A59: Site Specific Subtotal | B59: =SUM(B53:B58) -> 10875
A60: Building Permits | B60: 2050
A61: Water Meter | B61: 10000
A62: Engineering | B62: 600
A63: Soft Costs Subtotal | B63: =SUM(B60:B62) -> 12650
A64: TOTAL | B64: =B63+B59+B52 -> 188537.15
A66: Classic Package | B66: 4200
A67: Elegance Package | B67: 10000
A68: BTR Harmony Package | B68: TBD

Sheet Aspen 2-Story
A1: ASPEN BASE HOUSE COSTS
A3: ACTIVITY | B3: COSTS
A4: Dumpster | B4: 3000
A5: Utilities | B5: 300
A6: Portable toilet | B6: 875
A7: Permit Box | B7: 50
A8: Termite | B8: 225
A9: Lumber All Floors | B9: 10337.34
A10: Roof Trusses | B10: 5111.54
A11: Floor Trusses | B11: 5510.51
A12: Stairs | B12: 580.59
A13: Framing Labor | B13: 9953.4
A14: Windows Labor | B14: 308
A15: Window Material | B15: 2477.66
... A51: Foundation | B51: 11205
A52: Sticks & Bricks Subtotal | B52: =SUBTOTAL(109,B4:B51) -> 139411.53
A53: Survey | B53: 1700
A54: Grading/Lot Clear/Hauling | B54: 1700
A55: Silt Fence | B55: 2000
A56: Temp Drive | B56: 500
A57: Landscaping | B57: 2500
A58: Flatwork | B58: 2475
A59: Site Specific Subtotal | B59: =SUM(B53:B58) -> 10875
A60: Building Permits | B60: 2050
A61: Water Meter | B61: 10000
A62: Engineering | B62: 600
A63: Soft Costs Subtotal | B63: =SUM(B60:B62) -> 12650
A64: TOTAL | B64: =B63+B59+B52 -> 162936.53
A66: Classic Package | B66: 4750
A67: Elegance Package | B67: 9600
A68: BTR Harmony Package | B68: TBD

Sheet Atlas
A1: ATLAS BASE HOUSE COSTS
A3: ACTIVITY | B3: COSTS
A4: Dumpster | B4: 3000
A5: Utilities | B5: 300
A6: Portable toilet | B6: 875
A7: Permit Box | B7: 50
A8: Termite | B8: 225
A9: Lumber All Floors | B9: 6740.29
A10: Roof Trusses | B10: 2487.38
A11: Floor Trusses | B11: 2647.58
A12: Stairs | B12: 580.59
A13: Framing Labor | B13: 7399.8
A14: Windows Labor | B14: 330
A15: Window Material | B15: 2761.95
... A51: Foundation | B51: 6750
A52: Sticks & Bricks Subtotal | B52: =SUBTOTAL(109,B4:B51) -> 113776.73
A53: Survey | B53: 1700
A54: Grading/Lot Clear/Hauling | B54: 1700
A55: Silt Fence | B55: 2000
A56: Temp Drive | B56: 500
A57: Landscaping | B57: 2500
A58: Flatwork | B58: 2475
A59: Site Specific Subtotal | B59: =SUM(B53:B58) -> 10875
A60: Building Permits | B60: 2050
A61: Water Meter | B61: 10000
A62: Engineering | B62: 600
A63: Soft Costs Subtotal | B63: =SUM(B60:B62) -> 12650
A64: TOTAL | B64: =B63+B59+B52 -> 137301.73
A66: Classic Package | B66: 4200
A67: Elegance Package | B67: 8800
A68: BTR Harmony Package | B68: TBD

Sheet Banyan
A1: BANYAN BASE HOUSE COSTS
A3: ACTIVITY | B3: COSTS
A4: Dumpster | B4: 3000
A5: Utilities | B5: 300
A6: Portable toilet | B6: 875
A7: Permit Box | B7: 50
A8: Termite | B8: 225
A9: Lumber All Floors | B9: 13360.22
A10: Roof Trusses | B10: 2268.08
A11: Floor Trusses | B11: 6182.05
A12: Stairs | B12: 1161.17
A13: Framing Labor | B13: 9775
A14: Windows Labor | B14: 330
A15: Window Material | B15: 3205.85
... A51: Foundation | B51: 6688
A52: Sticks & Bricks Subtotal | B52: =SUBTOTAL(109,B4:B51) -> 134057.54
A53: Survey | B53: 1700
A54: Grading/Lot Clear/Hauling | B54: 1700
A55: Silt Fence | B55: 2000
A56: Temp Drive | B56: 500
A57: Landscaping | B57: 2500
A58: Flatwork | B58: 2475
A59: Site Specific Subtotal | B59: =SUM(B53:B58) -> 10875
A60: Building Permits | B60: 2050
A61: Water Meter | B61: 10000
A62: Engineering | B62: 600
A63: Soft Costs Subtotal | B63: =SUM(B60:B62) -> 12650
A64: TOTAL | B64: =B63+B59+B52 -> 157582.54
A66: Classic Package | B66: 4600
A67: Elegance Package | B67: 10300
A68: BTR Harmony Package | B68: TBD

Sheet Cherry
A1: CHERRY BASE HOUSE COSTS
A3: ACTIVITY | B3: COSTS
A4: Dumpster | B4: 3000
A5: Utilities | B5: 300
A6: Portable toilet | B6: 875
A7: Permit Box | B7: 50
A8: Termite | B8: 225
A9: Lumber All Floors | B9: 11967.7
A10: Roof Trusses | B10: 5402.18
A11: Floor Trusses | B11: 4975.33
A12: Stairs | B12: 580.59
A13: Framing Labor | B13: 11965.2
A14: Windows Labor | B14: 304
A15: Window Material | B15: 3121.99
... A51: Foundation | B51: 12930
A52: Sticks & Bricks Subtotal | B52: =SUBTOTAL(109,B4:B51) -> 156913.07
A53: Survey | B53: 1700
A54: Grading/Lot Clear/Hauling | B54: 1700
A55: Silt Fence | B55: 2000
A56: Temp Drive | B56: 500
A57: Landscaping | B57: 2500
A58: Flatwork | B58: 2475
A59: Site Specific Subtotal | B59: =SUM(B53:B58) -> 10875
A60: Building Permits | B60: 2050
A61: Water Meter | B61: 10000
A62: Engineering | B62: 600
A63: Soft Costs Subtotal | B63: =SUM(B60:B62) -> 12650
A64: TOTAL | B64: =B63+B59+B52 -> 180438.07
A66: Classic Package | B66: 5000
A67: Elegance Package | B67: 11000
A68: BTR Harmony Package | B68: TBD

Sheet Dogwood
A1: DOGWOOD BASE HOUSE COSTS
A3: ACTIVITY | B3: COSTS
A4: Dumpster | B4: 3000
A5: Utilities | B5: 300
A6: Portable toilet | B6: 875
A7: Permit Box | B7: 50
A8: Termite | B8: 225
A9: Lumber All Floors | B9: 8834.11
A10: Roof Trusses | B10: 3618.35
A11: Floor Trusses | B11: 3970.4
A12: Stairs | B12: 580.59
A13: Framing Labor | B13: 8890.8
A14: Windows Labor | B14: 242
A15: Window Material | B15: 2123.41
... A51: Foundation | B51: 9662.5
A52: Sticks & Bricks Subtotal | B52: =SUBTOTAL(109,B4:B51) -> 124030.98
A53: Survey | B53: 1700
A54: Grading/Lot Clear/Hauling | B54: 1700
A55: Silt Fence | B55: 2000
A56: Temp Drive | B56: 500
A57: Landscaping | B57: 2500
A58: Flatwork | B58: 2475
A59: Site Specific Subtotal | B59: =SUM(B53:B58) -> 10875
A60: Building Permits | B60: 2050
A61: Water Meter | B61: 10000
A62: Engineering | B62: 600
A63: Soft Costs Subtotal | B63: =SUM(B60:B62) -> 12650
A64: TOTAL | B64: =B63+B59+B52 -> 147555.98
A66: Classic Package | B66: 4000
A67: Elegance Package | B67: 8300
A68: BTR Harmony Package | B68: TBD

Sheet Hazel
A1: HAZEL BASE HOUSE COSTS
A3: ACTIVITY | B3: COSTS
A4: Dumpster | B4: 3000
A5: Utilities | B5: 300
A6: Portable toilet | B6: 875
A7: Permit Box | B7: 50
A8: Termite | B8: 225
A9: Lumber All Floors | B9: 9421.12
A10: Roof Trusses | B10: 4454.89
A11: Floor Trusses | B11: 5271.22
A12: Stairs | B12: 580.59
A13: Framing Labor | B13: 9630
A14: Windows Labor | B14: 286 | C14: =D14=A14 -> FALSE | D14: ='MODEL SUMMARY'!A14 -> I-Joist/EWP | E14: ='MODEL SUMMARY'!H14 -> 0
A15: Window Material | B15: 2506.13 | C15: =D15=A15 -> FALSE | D15: ='MODEL SUMMARY'!A15 -> Roofing Shingle | E15: ='MODEL SUMMARY'!H15 -> 0
A16: Roofing Labor & Material | B16: 3672.91 | C16: =D16=A16 -> FALSE | D16: ='MODEL SUMMARY'!A16 -> Roofing Metal | E16: ='MODEL SUMMARY'!H16 -> 0
A17: Exterior Door Labor | B17: 173 | C17: =D17=A17 -> FALSE | D17: ='MODEL SUMMARY'!A17 -> Roofing Labor & Material | E17: ='MODEL SUMMARY'!H17 -> 3672.91
A18: Exterior Door Material | B18: 1832.73 | C18: =D18=A18 -> FALSE | D18: ='MODEL SUMMARY'!A18 -> Siding Material | E18: ='MODEL SUMMARY'!H18 -> 5034.13
A19: Garage Door Labor & Material | B19: 1600 | C19: =D19=A19 -> FALSE | D19: ='MODEL SUMMARY'!A19 -> Siding Labor | E19: ='MODEL SUMMARY'!H19 -> 3140
A20: Siding Material | B20: 5034.13 | C20: =D20=A20 -> FALSE | D20: ='MODEL SUMMARY'!A20 -> Window Material | E20: ='MODEL SUMMARY'!H20 -> 2506.13
A21: Siding Labor | B21: 3140 | C21: =D21=A21 -> FALSE | D21: ='MODEL SUMMARY'!A21 -> Exterior Door Material | E21: ='MODEL SUMMARY'!H21 -> 1832.73
A22: HVAC | B22: 10400 | C22: =D22=A22 -> FALSE | D22: ='MODEL SUMMARY'!A22 -> Exterior Door Labor | E22: ='MODEL SUMMARY'!H22 -> 173
A23: Blower Test | B23: 300.11 | C23: =D23=A23 -> FALSE | D23: ='MODEL SUMMARY'!A23 -> Windows Labor | E23: ='MODEL SUMMARY'!H23 -> 286
A24: Electrical Rough & Trim | B24: 7859.77 | C24: =D24=A24 -> FALSE | D24: ='MODEL SUMMARY'!A24 -> Garage Door Labor & Material | E24: ='MODEL SUMMARY'!H24 -> 1600
A25: Light Fixtures | B25: 624.04 | C25: =D25=A25 -> FALSE | D25: ='MODEL SUMMARY'!A25 -> Plumbing Turnkey | E25: ='MODEL SUMMARY'!H25 -> 12337
... A45: Interior Clean | B45: 328.34 | C45: =D45=A45 -> FALSE | D45: ='MODEL SUMMARY'!A45 -> Tile Labor & Material | E45: ='MODEL SUMMARY'!H45 -> 0
A46: Pressure Wash | B46: 235 | D46: ='MODEL SUMMARY'!A46 -> Light Fixtures | E46: ='MODEL SUMMARY'!H46 -> 624.04
A47: Gutters | B47: 858 | D47: ='MODEL SUMMARY'!A47 -> Appliances | E47: ='MODEL SUMMARY'!H47 -> 1616.06
A48: QI Inspection | B48: 310 | D48: ='MODEL SUMMARY'!A48 -> Carpet Labor & Material | E48: ='MODEL SUMMARY'!H48 -> 1899.5
A49: Deck | B49: 0 | D49: ='MODEL SUMMARY'!A49 -> Hardwood Labor & Material | E49: ='MODEL SUMMARY'!H49 -> 0
A50: Mailbox | B50: 90 | D50: ='MODEL SUMMARY'!A50 -> LVP Labor & Material | E50: ='MODEL SUMMARY'!H50 -> 2647.51
A51: Foundation | B51: 9940 | D51: ='MODEL SUMMARY'!A51 -> Interior Clean | E51: ='MODEL SUMMARY'!H51 -> 328.34
A52: Sticks & Bricks Subtotal | B52: =SUBTOTAL(109,B4:B51) -> 134200.25 | D52: ='MODEL SUMMARY'!A52 -> Gutters | E52: ='MODEL SUMMARY'!H52 -> 858
A53: Survey | B53: 1700 | D53: ='MODEL SUMMARY'!A53 -> QI Inspection | E53: ='MODEL SUMMARY'!H53 -> 310
A54: Grading/Lot Clear/Hauling | B54: 1700 | D54: ='MODEL SUMMARY'!A54 -> Deck | E54: ='MODEL SUMMARY'!H54 -> 0
A55: Silt Fence | B55: 2000 | D55: ='MODEL SUMMARY'!A55 -> Mailbox | E55: ='MODEL SUMMARY'!H55 -> 90
A56: Temp Drive | B56: 500 | D56: ='MODEL SUMMARY'!A56 -> Pressure Wash | E56: ='MODEL SUMMARY'!H56 -> 235
A57: Landscaping | B57: 2500 | D57: ='MODEL SUMMARY'!A57 -> Foundation | E57: ='MODEL SUMMARY'!H57 -> 9940
A58: Flatwork | B58: 2475 | D58: ='MODEL SUMMARY'!A58 -> Sticks & Bricks Subtotal | E58: ='MODEL SUMMARY'!H58 -> 134200.25
A59: Site Specific Subtotal | B59: =SUM(B53:B58) -> 10875
A60: Building Permits | B60: 2050
A61: Water Meter | B61: 10000
A62: Engineering | B62: 600
A63: Soft Costs Subtotal | B63: =SUM(B60:B62) -> 12650
A64: TOTAL | B64: =B63+B59+B52 -> 157725.25
A66: Classic Package | B66: 4450
A67: Elegance Package | B67: 9100
A68: BTR Harmony Package | B68: TBD

Sheet Holly
A1: HOLLY BASE HOUSE COSTS
A3: ACTIVITY | B3: COSTS
A4: Dumpster | B4: 3000
A5: Utilities | B5: 300
A6: Portable toilet | B6: 875
A7: Permit Box | B7: 50
A8: Termite | B8: 225
A9: Lumber All Floors | B9: 11034.64
A10: Roof Trusses | B10: 5406
A11: Floor Trusses | B11: 5587.26
A12: Stairs | B12: 580.59
A13: Framing Labor | B13: 10848
A14: Windows Labor | B14: 370
A15: Window Material | B15: 3898.44
... A51: Foundation | B51: 11065
A52: Sticks & Bricks Subtotal | B52: =SUBTOTAL(109,B4:B51) -> 144355.2
A53: Survey | B53: 1700
A54: Grading/Lot Clear/Hauling | B54: 1700
A55: Silt Fence | B55: 2000
A56: Temp Drive | B56: 500
A57: Landscaping | B57: 2500
A58: Flatwork | B58: 2475
A59: Site Specific Subtotal | B59: =SUM(B53:B58) -> 10875
A60: Building Permits | B60: 2050
A61: Water Meter | B61: 10000
A62: Engineering | B62: 600
A63: Soft Costs Subtotal | B63: =SUM(B60:B62) -> 12650
A64: TOTAL | B64: =B63+B59+B52 -> 167880.2
A66: Classic Package | B66: 4000
A67: Elegance Package | B67: 8500
A68: BTR Harmony Package | B68: TBD

Sheet Elm
A1: ELM BASE HOUSE COSTS
A3: ACTIVITY | B3: COSTS
A4: Dumpster | B4: 3000
A5: Utilities | B5: 300
A6: Portable toilet | B6: 875
A7: Permit Box | B7: 50
A8: Termite | B8: 225
A9: Lumber All Floors | B9: 9923.15
A10: Roof Trusses | B10: 3980.26
A11: Floor Trusses | B11: 5738.21
A12: Stairs | B12: 580.59
A13: Framing Labor | B13: 9714
A14: Windows Labor | B14: 286
A15: Window Material | B15: 2547.19
... A51: Foundation | B51: 9970
A52: Sticks & Bricks Subtotal | B52: =SUBTOTAL(109,B4:B51) -> 134540.06
A53: Survey | B53: 1700
A54: Grading/Lot Clear/Hauling | B54: 1700
A55: Silt Fence | B55: 2000
A56: Temp Drive | B56: 500
A57: Landscaping | B57: 2500
A58: Flatwork | B58: 2475
A59: Site Specific Subtotal | B59: =SUM(B53:B58) -> 10875
A60: Building Permits | B60: 2050
A61: Water Meter | B61: 10000
A62: Engineering | B62: 600
A63: Soft Costs Subtotal | B63: =SUM(B60:B62) -> 12650
A64: TOTAL | B64: =B63+B59+B52 -> 158065.06
A66: Classic Package | B66: 4300
A67: Elegance Package | B67: 9000
A68: BTR Harmony Package | B68: TBD

Sheet Lilac
A1: LILAC BASE HOUSE COSTS
A3: ACTIVITY | B3: COSTS
A4: Dumpster | B4: 3000
A5: Utilities | B5: 300
A6: Portable toilet | B6: 875
A7: Permit Box | B7: 50
A8: Termite | B8: 225
A9: Lumber All Floors | B9: 6531.13
A10: Roof Trusses | B10: 4722.22
A11: Floor Trusses | B11: 3556.41
A12: Stairs | B12: 580.59
A13: Framing Labor | B13: 8378.4
A14: Windows Labor | B14: 204
A15: Window Material | B15: 2225.4
... A51: Foundation | B51: 11702
A52: Sticks & Bricks Subtotal | B52: =SUBTOTAL(109,B4:B51) -> 122529.87
A53: Survey | B53: 1700
A54: Grading/Lot Clear/Hauling | B54: 1700
A55: Silt Fence | B55: 2000
A56: Temp Drive | B56: 500
A57: Landscaping | B57: 2500
A58: Flatwork | B58: 2475
A59: Site Specific Subtotal | B59: =SUM(B53:B58) -> 10875
A60: Building Permits | B60: 2050
A61: Water Meter | B61: 10000
A62: Engineering | B62: 600
A63: Soft Costs Subtotal | B63: =SUM(B60:B62) -> 12650
A64: TOTAL | B64: =B63+B59+B52 -> 146054.87
A66: Classic Package | B66: 4000
A67: Elegance Package | B67: 9000
A68: BTR Harmony Package | B68: TBD

Sheet Lily
A1: LILY BASE HOUSE COSTS
A3: ACTIVITY | B3: COSTS
A4: Dumpster | B4: 3000
A5: Utilities | B5: 300
A6: Portable toilet | B6: 875
A7: Permit Box | B7: 50
A8: Termite | B8: 225
A9: Lumber All Floors | B9: 9983.46
A10: Roof Trusses | B10: 3966.85
A11: Floor Trusses | B11: 5616
A12: Stairs | B12: 1161.17
A13: Framing Labor | B13: 8722.8
A14: Windows Labor | B14: 525
A15: Window Material | B15: 5281.01
... A51: Foundation | B51: 9137.5
A52: Sticks & Bricks Subtotal | B52: =SUBTOTAL(109,B4:B51) -> 157945.02
A53: Survey | B53: 1700
A54: Grading/Lot Clear/Hauling | B54: 1700
A55: Silt Fence | B55: 2000
A56: Temp Drive | B56: 500
A57: Landscaping | B57: 2500
A58: Flatwork | B58: 2475
A59: Site Specific Subtotal | B59: =SUM(B53:B58) -> 10875
A60: Building Permits | B60: 2050
A61: Water Meter | B61: 10000
A62: Engineering | B62: 600
A63: Soft Costs Subtotal | B63: =SUM(B60:B62) -> 12650
A64: TOTAL | B64: =B63+B59+B52 -> 181470.02
A66: Classic Package | B66: 5400
A67: Elegance Package | B67: 10700
A68: BTR Harmony Package | B68: TBD

Sheet Magnolia
A1: MAGNOLIA BASE HOUSE COSTS
A3: ACTIVITY | B3: COSTS
A4: Dumpster | B4: 3000
A5: Utilities | B5: 300
A6: Portable toilet | B6: 875
A7: Permit Box | B7: 50
A8: Termite | B8: 225
A9: Lumber All Floors | B9: 14417.8
A10: Roof Trusses | B10: 6566.68
A11: Floor Trusses | B11: 5532.68
A12: Stairs | B12: 580.59
A13: Framing Labor | B13: 14014.8
A14: Windows Labor | B14: 440
A15: Window Material | B15: 3823.99
... A51: Foundation | B51: 14792.5
A52: Sticks & Bricks Subtotal | B52: =SUBTOTAL(109,B4:B51) -> 178184.33
A53: Survey | B53: 1700
A54: Grading/Lot Clear/Hauling | B54: 1700
A55: Silt Fence | B55: 2000
A56: Temp Drive | B56: 500
A57: Landscaping | B57: 2500
A58: Flatwork | B58: 2475
A59: Site Specific Subtotal | B59: =SUM(B53:B58) -> 10875
A60: Building Permits | B60: 2050
A61: Water Meter | B61: 10000
A62: Engineering | B62: 600
A63: Soft Costs Subtotal | B63: =SUM(B60:B62) -> 12650
A64: TOTAL | B64: =B63+B59+B52 -> 201709.33
A66: Classic Package | B66: 4600
A67: Elegance Package | B67: 11100
A68: BTR Harmony Package | B68: TBD

Sheet Spindle
A1: SPINDLE BASE HOUSE COSTS
A3: ACTIVITY | B3: COSTS
A4: Dumpster | B4: 3000
A5: Utilities | B5: 300
A6: Portable toilet | B6: 875
A7: Permit Box | B7: 50
A8: Termite | B8: 225
A9: Lumber All Floors | B9: 14299.08
A10: Roof Trusses | B10: 3670.5
A11: Floor Trusses | B11: 5428
A12: Stairs | B12: 580.59
A13: Framing Labor | B13: 9646.8
A14: Windows Labor | B14: 370
A15: Window Material | B15: 3725.69
... A51: Foundation | B51: 10472.5
A52: Sticks & Bricks Subtotal | B52: =SUBTOTAL(109,B4:B51) -> 147507.54
A53: Survey | B53: 1700
A54: Grading/Lot Clear/Hauling | B54: 1700
A55: Silt Fence | B55: 2000
A56: Temp Drive | B56: 500
A57: Landscaping | B57: 2500
A58: Flatwork | B58: 2475
A59: Site Specific Subtotal | B59: =SUM(B53:B58) -> 10875
A60: Building Permits | B60: 2050
A61: Water Meter | B61: 10000
A62: Engineering | B62: 600
A63: Soft Costs Subtotal | B63: =SUM(B60:B62) -> 12650
A64: TOTAL | B64: =B63+B59+B52 -> 171032.54
A66: Classic Package | B66: 4100
A67: Elegance Package | B67: 8800
A68: BTR Harmony Package | B68: TBD

Sheet Spruce
A1: SPRUCE BASE HOUSE COSTS
A3: ACTIVITY | B3: COSTS
A4: Dumpster | B4: 3000
A5: Utilities | B5: 300
A6: Portable toilet | B6: 875
A7: Permit Box | B7: 50
A8: Termite | B8: 225
A9: Lumber All Floors | B9: 7621.57
A10: Roof Trusses | B10: 8954.3
A11: Floor Trusses | B11: 0
A12: Stairs | B12: 0
A13: Framing Labor | B13: 9272
A14: Windows Labor | B14: 226
A15: Window Material | B15: 2445.22
... A51: Foundation | B51: 16863
A52: Sticks & Bricks Subtotal | B52: =SUBTOTAL(109,B4:B51) -> 129517.76
A53: Survey | B53: 1700
A54: Grading/Lot Clear/Hauling | B54: 1700
A55: Silt Fence | B55: 2000
A56: Temp Drive | B56: 500
A57: Landscaping | B57: 2500
A58: Flatwork | B58: 2475
A59: Site Specific Subtotal | B59: =SUM(B53:B58) -> 10875
A60: Building Permits | B60: 2050
A61: Water Meter | B61: 10000
A62: Engineering | B62: 600
A63: Soft Costs Subtotal | B63: =SUM(B60:B62) -> 12650
A64: TOTAL | B64: =B63+B59+B52 -> 153042.76
A66: Classic Package | B66: 2800
A67: Elegance Package | B67: 7300
A68: BTR Harmony Package | B68: TBD

Sheet Tulip
A1: TULIP BASE HOUSE COSTS
A3: ACTIVITY | B3: COSTS
A4: Dumpster | B4: 3000
A5: Utilities | B5: 300
A6: Portable toilet | B6: 875
A7: Permit Box | B7: 50
A8: Termite | B8: 225
A9: Lumber All Floors | B9: 6015.42
A10: Roof Trusses | B10: 4959.1
A11: Floor Trusses | B11: 0
A12: Stairs | B12: 0
A13: Framing Labor | B13: 6936
A14: Windows Labor | B14: 240
A15: Window Material | B15: 1274.11
... A51: Foundation | B51: 12802.5
A52: Sticks & Bricks Subtotal | B52: =SUBTOTAL(109,B4:B51) -> 105821.13
A53: Survey | B53: 1700
A54: Grading/Lot Clear/Hauling | B54: 1700
A55: Silt Fence | B55: 2000
A56: Temp Drive | B56: 500
A57: Landscaping | B57: 2500
A58: Flatwork | B58: 2475
A59: Site Specific Subtotal | B59: =SUM(B53:B58) -> 10875
A60: Building Permits | B60: 2050
A61: Water Meter | B61: 10000
A62: Engineering | B62: 600
A63: Soft Costs Subtotal | B63: =SUM(B60:B62) -> 12650
A64: TOTAL | B64: =B63+B59+B52 -> 129346.13
A66: Classic Package | B66: 3000
A67: Elegance Package | B67: 6500
A68: BTR Harmony Package | B68: TBD

Sheet White Oak
A1: WHITE OAK BASE HOUSE COSTS
A3: ACTIVITY | B3: COSTS
A4: Dumpster | B4: 3000
A5: Utilities | B5: 300
A6: Portable toilet | B6: 875
A7: Permit Box | B7: 50
A8: Termite | B8: 225
A9: Lumber All Floors | B9: 10234.67
A10: Roof Trusses | B10: 4487.34
A11: Floor Trusses | B11: 5465.46
A12: Stairs | B12: 580.59
A13: Framing Labor | B13: 10877.4
A14: Windows Labor | B14: 352
A15: Window Material | B15: 2936.09
... A51: Foundation | B51: 12045
A52: Sticks & Bricks Subtotal | B52: =SUBTOTAL(109,B4:B51) -> 143852.55
A53: Survey | B53: 1700
A54: Grading/Lot Clear/Hauling | B54: 1700
A55: Silt Fence | B55: 2000
A56: Temp Drive | B56: 500
A57: Landscaping | B57: 2500
A58: Flatwork | B58: 2475
A59: Site Specific Subtotal | B59: =SUM(B53:B58) -> 10875
A60: Building Permits | B60: 2050
A61: Water Meter | B61: 10000
A62: Engineering | B62: 600
A63: Soft Costs Subtotal | B63: =SUM(B60:B62) -> 12650
A64: TOTAL | B64: =B63+B59+B52 -> 167377.55
A66: Classic Package | B66: 4400
A67: Elegance Package | B67: 6700
A68: BTR Harmony Package | B68: TBD

Sheet Willow
A1: WILLOW BASE HOUSE COSTS
A3: ACTIVITY | B3: COSTS
A4: Dumpster | B4: 3000
A5: Utilities | B5: 300
A6: Portable toilet | B6: 875
A7: Permit Box | B7: 50
A8: Termite | B8: 225
A9: Lumber All Floors | B9: 9344.9
A10: Roof Trusses | B10: 4489.66
A11: Floor Trusses | B11: 3213.92
A12: Stairs | B12: 580.59
A13: Framing Labor | B13: 10244.8
A14: Windows Labor | B14: 308
A15: Window Material | B15: 2741.53
... A51: Foundation | B51: 10577.5
A52: Sticks & Bricks Subtotal | B52: =SUBTOTAL(109,B4:B51) -> 133890.64
A53: Survey | B53: 1700
A54: Grading/Lot Clear/Hauling | B54: 1700
A55: Silt Fence | B55: 2000
A56: Temp Drive | B56: 500
A57: Landscaping | B57: 2500
A58: Flatwork | B58: 2475
A59: Site Specific Subtotal | B59: =SUM(B53:B58) -> 10875
A60: Building Permits | B60: 2050
A61: Water Meter | B61: 10000
A62: Engineering | B62: 600
A63: Soft Costs Subtotal | B63: =SUM(B60:B62) -> 12650
A64: TOTAL | B64: =B63+B59+B52 -> 157415.64
A66: Classic Package | B66: 4100
A67: Elegance Package | B67: 9000
A68: BTR Harmony Package | B68: TBD

Sheet Alder
A1: ALDER TH BASE HOUSE COSTS
A3: ACTIVITY | B3: COSTS
A4: Dumpster | B4: 1500
A5: Utilities | B5: 300
A6: Portable toilet | B6: 437.5
A7: Permit Box | B7: 50
A8: Termite | B8: 100
A9: Lumber All Floors | B9: 12257.66
A10: Roof Trusses | B10: 3893.18
A11: Floor Trusses | B11: 3919.99
A12: Stairs | B12: 580.59
A13: Framing Labor | B13: 12164
A14: Windows Labor | B14: 242
A15: Window Material | B15: 1951.74
... A51: Foundation | B51: 8615
A52: Sticks & Bricks Subtotal | B52: =SUBTOTAL(109,B4:B51) -> 130195.63
A53: Survey | B53: 1700
A54: Grading/Lot Clear/Hauling | B54: 1700
A55: Silt Fence | B55: 2000
A56: Temp Drive | B56: 500
A57: Landscaping | B57: 2500
A58: Flatwork | B58: 2475
A59: Site Specific Subtotal | B59: =SUM(B53:B58) -> 10875
A60: Building Permits | B60: 2050
A61: Water Meter | B61: 10000
A62: Engineering | B62: 600
A63: Soft Costs Subtotal | B63: =SUM(B60:B62) -> 12650
A64: TOTAL | B64: =B63+B59+B52 -> 153720.63
A66: Classic Package | B66: 4600
A67: Elegance Package | B67: 8800
A68: BTR Harmony Package | B68: 5900

Sheet Bayberry
A1: BAYBERRY TH BASE HOUSE COSTS
A3: ACTIVITY | B3: COSTS
A4: Dumpster | B4: 1500
A5: Utilities | B5: 300
A6: Portable toilet | B6: 437.5
A7: Permit Box | B7: 50
A8: Termite | B8: 100
A9: Lumber All Floors | B9: 14421.65
A10: Roof Trusses | B10: 3153.34
A11: Floor Trusses | B11: 2774.58
A12: Stairs | B12: 580.59
A13: Framing Labor | B13: 11704
A14: Windows Labor | B14: 242
A15: Window Material | B15: 2098.92
... A51: Foundation | B51: 8450
A52: Sticks & Bricks Subtotal | B52: =SUBTOTAL(109,B4:B51) -> 125251.84
A53: Survey | B53: 1700
A54: Grading/Lot Clear/Hauling | B54: 1700
A55: Silt Fence | B55: 2000
A56: Temp Drive | B56: 500
A57: Landscaping | B57: 2500
A58: Flatwork | B58: 2475
A59: Site Specific Subtotal | B59: =SUM(B53:B58) -> 10875
A60: Building Permits | B60: 2050
A61: Water Meter | B61: 10000
A62: Engineering | B62: 600
A63: Soft Costs Subtotal | B63: =SUM(B60:B62) -> 12650
A64: TOTAL | B64: =B63+B59+B52 -> 148776.84
A66: Classic Package | B66: 3600
A67: Elegance Package | B67: 5500
A68: BTR Harmony Package | B68: 6100

Sheet Boxelder
A1: BOXELDER TH BASE HOUSE COSTS
A3: ACTIVITY | B3: COSTS
A4: Dumpster | B4: 1500
A5: Utilities | B5: 300
A6: Portable toilet | B6: 437.5
A7: Permit Box | B7: 50
A8: Termite | B8: 100
A9: Lumber All Floors | B9: 20644.85
A10: Roof Trusses | B10: 3785.93
A11: Floor Trusses | B11: 3957.53
A12: Stairs | B12: 580.59
A13: Framing Labor | B13: 13544.6
A14: Windows Labor | B14: 220
A15: Window Material | B15: 1954.83
... A51: Foundation | B51: 9315.5
A52: Sticks & Bricks Subtotal | B52: =SUBTOTAL(109,B4:B51) -> 141492.43
A53: Survey | B53: 1700
A54: Grading/Lot Clear/Hauling | B54: 1700
A55: Silt Fence | B55: 2000
A56: Temp Drive | B56: 500
A57: Landscaping | B57: 2500
A58: Flatwork | B58: 2475
A59: Site Specific Subtotal | B59: =SUM(B53:B58) -> 10875
A60: Building Permits | B60: 2050
A61: Water Meter | B61: 10000
A62: Engineering | B62: 600
A63: Soft Costs Subtotal | B63: =SUM(B60:B62) -> 12650
A64: TOTAL | B64: =B63+B59+B52 -> 165017.43
A66: Classic Package | B66: 6300
A67: Elegance Package | B67: 9200
A68: BTR Harmony Package | B68: 4800

Sheet Bur Oak
A1: BUR OAK TH BASE HOUSE COSTS
A3: ACTIVITY | B3: COSTS
A4: Dumpster | B4: 1500
A5: Utilities | B5: 300
A6: Portable toilet | B6: 437.5
A7: Permit Box | B7: 50
A8: Termite | B8: 100
A9: Lumber All Floors | B9: 13373.2
A10: Roof Trusses | B10: 2809.95
A11: Floor Trusses | B11: 3539.25
A12: Stairs | B12: 580.59
A13: Framing Labor | B13: 12196.11
A14: Windows Labor | B14: 254
A15: Window Material | B15: 2443.92
... A51: Foundation | B51: 7692.5
A52: Sticks & Bricks Subtotal | B52: =SUBTOTAL(109,B4:B51) -> 124886
A53: Survey | B53: 1700
A54: Grading/Lot Clear/Hauling | B54: 1700
A55: Silt Fence | B55: 2000
A56: Temp Drive | B56: 500
A57: Landscaping | B57: 2500
A58: Flatwork | B58: 2475
A59: Site Specific Subtotal | B59: =SUM(B53:B58) -> 10875
A60: Building Permits | B60: 2050
A61: Water Meter | B61: 10000
A62: Engineering | B62: 600
A63: Soft Costs Subtotal | B63: =SUM(B60:B62) -> 12650
A64: TOTAL | B64: =B63+B59+B52 -> 148411
A66: Classic Package | B66: 5700
A67: Elegance Package | B67: 8500
A68: BTR Harmony Package | B68: 5200

Sheet Conifer
A1: CONIFER TH BASE HOUSE COSTS
A3: ACTIVITY | B3: COSTS
A4: Dumpster | B4: 1500
A5: Utilities | B5: 300
A6: Portable toilet | B6: 437.5
A7: Permit Box | B7: 50
A8: Termite | B8: 100
A9: Lumber All Floors | B9: 20644.85
A10: Roof Trusses | B10: 2691.98
A11: Floor Trusses | B11: 6944.44
A12: Stairs | B12: 1161.17
A13: Framing Labor | B13: 16850.16
A14: Windows Labor | B14: 264
A15: Window Material | B15: 2209.93
... A51: Foundation | B51: 6792.5
A52: Sticks & Bricks Subtotal | B52: =SUBTOTAL(109,B4:B51) -> 163028.48
A53: Survey | B53: 1700
A54: Grading/Lot Clear/Hauling | B54: 1700
A55: Silt Fence | B55: 2000
A56: Temp Drive | B56: 500
A57: Landscaping | B57: 2500
A58: Flatwork | B58: 2475
A59: Site Specific Subtotal | B59: =SUM(B53:B58) -> 10875
A60: Building Permits | B60: 2050
A61: Water Meter | B61: 10000
A62: Engineering | B62: 600
A63: Soft Costs Subtotal | B63: =SUM(B60:B62) -> 12650
A64: TOTAL | B64: =B63+B59+B52 -> 186553.48
A66: Classic Package | B66: 4700
A67: Elegance Package | B67: 5900
A68: BTR Harmony Package | B68: 7700

Sheet Cottonwood
A1: COTTONWOOD TH BASE HOUSE COSTS
A3: ACTIVITY | B3: COSTS
A4: Dumpster | B4: 1500
A5: Utilities | B5: 300
A6: Portable toilet | B6: 437.5
A7: Permit Box | B7: 50
A8: Termite | B8: 100
A9: Lumber All Floors | B9: 18522.05
A10: Roof Trusses | B10: 2444.87
A11: Floor Trusses | B11: 5675.14
A12: Stairs | B12: 1161.17
A13: Framing Labor | B13: 15790
A14: Windows Labor | B14: 264
A15: Window Material | B15: 2193.93
... A48: QI Inspection | B48: 310
A49: Mailbox
A50: Deck | B50: 0
A51: Foundation | B51: 6312.5
A52: Sticks & Bricks Subtotal | B52: =SUBTOTAL(109,B4:B51) -> 142077.91
A53: Survey | B53: 1700
A54: Grading/Lot Clear/Hauling | B54: 1700
A55: Silt Fence | B55: 2000
A56: Temp Drive | B56: 500
A57: Landscaping | B57: 2500
A58: Flatwork | B58: 2475
A59: Site Specific Subtotal | B59: =SUM(B53:B58) -> 10875
A60: Building Permits | B60: 2050
A61: Water Meter | B61: 10000
A62: Engineering | B62: 600
A63: Soft Costs Subtotal | B63: =SUM(B60:B62) -> 12650
A64: TOTAL | B64: =B63+B59+B52 -> 165602.91
A66: Classic Package | B66: 6500
A67: Elegance Package | B67: 7100
A68: BTR Harmony Package | B68: TBD

Sheet Fig
A1: FIG TH BASE HOUSE COSTS
A3: ACTIVITY | B3: COSTS
A4: Dumpster | B4: 1500
A5: Utilities | B5: 300
A6: Portable toilet | B6: 437.5
A7: Permit Box | B7: 50
A8: Termite | B8: 100
A9: Lumber All Floors | B9: 17437.45
A10: Roof Trusses | B10: 3288.78
A11: Floor Trusses | B11: 5590.86
A12: Stairs | B12: 1161.17
A13: Framing Labor | B13: 14443.8
A14: Windows Labor | B14: 182
A15: Window Material | B15: 2132.97
... A51: Foundation | B51: 6297.5
A52: Sticks & Bricks Subtotal | B52: =SUBTOTAL(109,B4:B51) -> 150174.71
A53: Survey | B53: 1700
A54: Grading/Lot Clear/Hauling | B54: 1700
A55: Silt Fence | B55: 2000
A56: Temp Drive | B56: 500
A57: Landscaping | B57: 2500
A58: Flatwork | B58: 2475
A59: Site Specific Subtotal | B59: =SUM(B53:B58) -> 10875
A60: Building Permits | B60: 2050
A61: Water Meter | B61: 10000
A62: Engineering | B62: 600
A63: Soft Costs Subtotal | B63: =SUM(B60:B62) -> 12650
A64: TOTAL | B64: =B63+B59+B52 -> 173699.71
A66: Classic Package | B66: 5700
A67: Elegance Package | B67: 8200
A68: BTR Harmony Package | B68: 9000

Sheet Fraser
A1: FRASER TH BASE HOUSE COSTS
A3: ACTIVITY | B3: COSTS
A4: Dumpster | B4: 1500
A5: Utilities | B5: 300
A6: Portable toilet | B6: 437.5
A7: Permit Box | B7: 50
A8: Termite | B8: 100
A9: Lumber All Floors | B9: 16348.51
A10: Roof Trusses | B10: 3149.92
A11: Floor Trusses | B11: 3516.08
A12: Stairs | B12: 580.59
A13: Framing Labor | B13: 13539.9
A14: Windows Labor | B14: 330
A15: Window Material | B15: 2671.15
... A51: Foundation | B51: 9680
A52: Sticks & Bricks Subtotal | B52: =SUBTOTAL(109,B4:B51) -> 133563.2
A53: Survey | B53: 1700
A54: Grading/Lot Clear/Hauling | B54: 1700
A55: Silt Fence | B55: 2000
A56: Temp Drive | B56: 500
A57: Landscaping | B57: 2500
A58: Flatwork | B58: 2475
A59: Site Specific Subtotal | B59: =SUM(B53:B58) -> 10875
A60: Building Permits | B60: 2050
A61: Water Meter | B61: 10000
A62: Engineering | B62: 600
A63: Soft Costs Subtotal | B63: =SUM(B60:B62) -> 12650
A64: TOTAL | B64: =B63+B59+B52 -> 157088.2
A66: Classic Package | B66: 3300
A67: Elegance Package | B67: 2700
A68: BTR Harmony Package | B68: TBD

Sheet Jasmine
A1: JASMINE TH BASE HOUSE COSTS
A3: ACTIVITY | B3: COSTS
A4: Dumpster | B4: 1500
A5: Utilities | B5: 300
A6: Portable toilet | B6: 437.5
A7: Permit Box | B7: 50
A8: Termite | B8: 100
A9: Lumber All Floors | B9: 12854.3
A10: Roof Trusses | B10: 3393.39
A11: Floor Trusses | B11: 3198.2
A12: Stairs | B12: 580.59
A13: Framing Labor | B13: 11125.6
A14: Windows Labor | B14: 264
A15: Window Material | B15: 2330.97
... A51: Foundation | B51: 8417.5
A52: Sticks & Bricks Subtotal | B52: =SUBTOTAL(109,B4:B51) -> 127141.84
A53: Survey | B53: 1700
A54: Grading/Lot Clear/Hauling | B54: 1700
A55: Silt Fence | B55: 2000
A56: Temp Drive | B56: 500
A57: Landscaping | B57: 2500
A58: Flatwork | B58: 2475
A59: Site Specific Subtotal | B59: =SUM(B53:B58) -> 10875
A60: Building Permits | B60: 2050
A61: Water Meter | B61: 10000
A62: Engineering | B62: 600
A63: Soft Costs Subtotal | B63: =SUM(B60:B62) -> 12650
A64: TOTAL | B64: =B63+B59+B52 -> 150666.84
A66: Classic Package | B66: 3800
A67: Elegance Package | B67: 8000
A68: BTR Harmony Package | B68: 4500

Sheet Linville
A1: LINVILLE TH BASE HOUSE COSTS
A3: ACTIVITY | B3: COSTS
A4: Dumpster | B4: 1500 | C4: =A4=D4 -> TRUE | D4: ='MODEL SUMMARY'!A4 -> Dumpster | E4: ='MODEL SUMMARY'!W4 -> 1500 | F4: =_xlfn.XLOOKUP(D4,A:A,B:B) -> 1500 | G4: =F4=E4 -> TRUE
A5: Utilities | B5: 300 | C5: =A5=D5 -> TRUE | D5: ='MODEL SUMMARY'!A5 -> Utilities | E5: ='MODEL SUMMARY'!W5 -> 300 | F5: =_xlfn.XLOOKUP(D5,A:A,B:B) -> 300 | G5: =F5=E5 -> TRUE
A6: Portable toilet | B6: 437.5 | C6: =A6=D6 -> TRUE | D6: ='MODEL SUMMARY'!A6 -> Portable toilet | E6: ='MODEL SUMMARY'!W6 -> 437.5 | F6: =_xlfn.XLOOKUP(D6,A:A,B:B) -> 437.5 | G6: =F6=E6 -> TRUE
A7: Permit Box | B7: 50 | C7: =A7=D7 -> TRUE | D7: ='MODEL SUMMARY'!A7 -> Permit Box | E7: ='MODEL SUMMARY'!W7 -> 50 | F7: =_xlfn.XLOOKUP(D7,A:A,B:B) -> 50 | G7: =F7=E7 -> TRUE
A8: Termite | B8: 100 | C8: =A8=D8 -> TRUE | D8: ='MODEL SUMMARY'!A8 -> Termite | E8: ='MODEL SUMMARY'!W8 -> 100 | F8: =_xlfn.XLOOKUP(D8,A:A,B:B) -> 100 | G8: =F8=E8 -> TRUE
A9: Lumber All Floors | B9: 14894.86 | C9: =A9=D9 -> TRUE | D9: ='MODEL SUMMARY'!A9 -> Lumber All Floors | E9: ='MODEL SUMMARY'!W9 -> 14894.86 | F9: =_xlfn.XLOOKUP(D9,A:A,B:B) -> 14894.86 | G9: =F9=E9 -> TRUE
A10: Roof Trusses | B10: 7008.79 | C10: =A10=D10 -> FALSE | D10: ='MODEL SUMMARY'!A10 -> Framing Labor | E10: ='MODEL SUMMARY'!W10 -> 16075.7 | F10: =_xlfn.XLOOKUP(D10,A:A,B:B) -> 16075.7 | G10: =F10=E10 -> TRUE
A11: Floor Trusses | B11: 4531.31 | C11: =A11=D11 -> TRUE | D11: ='MODEL SUMMARY'!A11 -> Floor Trusses | E11: ='MODEL SUMMARY'!W11 -> 4531.31 | F11: =_xlfn.XLOOKUP(D11,A:A,B:B) -> 4531.31 | G11: =F11=E11 -> TRUE
A12: Stairs | B12: 580.59 | C12: =A12=D12 -> TRUE | D12: ='MODEL SUMMARY'!A12 -> Stairs | E12: ='MODEL SUMMARY'!W12 -> 580.59 | F12: =_xlfn.XLOOKUP(D12,A:A,B:B) -> 580.59 | G12: =F12=E12 -> TRUE
A13: Framing Labor | B13: 16075.7 | C13: =A13=D13 -> FALSE | D13: ='MODEL SUMMARY'!A13 -> Roof Trusses | E13: ='MODEL SUMMARY'!W13 -> 7008.79 | F13: =_xlfn.XLOOKUP(D13,A:A,B:B) -> 7008.79 | G13: =F13=E13 -> TRUE
A14: Windows Labor | B14: 277 | C14: =A14=D14 -> FALSE | D14: ='MODEL SUMMARY'!A14 -> I-Joist/EWP | E14: ='MODEL SUMMARY'!W14 -> 0 | F14: =_xlfn.XLOOKUP(D14,A:A,B:B) -> #N/A | G14: =F14=E14 -> #N/A
A15: Window Material | B15: 2874.28 | C15: =A15=D15 -> FALSE | D15: ='MODEL SUMMARY'!A15 -> Roofing Shingle | E15: ='MODEL SUMMARY'!W15 -> 0 | F15: =_xlfn.XLOOKUP(D15,A:A,B:B) -> #N/A | G15: =F15=E15 -> #N/A
... A51: Foundation | B51: 12024.5 | C51: =A51=D51 -> FALSE | D51: ='MODEL SUMMARY'!A51 -> Interior Clean | E51: ='MODEL SUMMARY'!W51 -> 593.88 | F51: =_xlfn.XLOOKUP(D51,A:A,B:B) -> 593.88 | G51: =F51=E51 -> TRUE
A52: Sticks & Bricks Subtotal | B52: =SUBTOTAL(109,B4:B51) -> 160612.82 | C52: =A52=D52 -> FALSE | D52: ='MODEL SUMMARY'!A52 -> Gutters | E52: ='MODEL SUMMARY'!W52 -> 976 | F52: =_xlfn.XLOOKUP(D52,A:A,B:B) -> 976 | G52: =F52=E52 -> TRUE
A53: Survey | B53: 1700 | C53: =A53=D53 -> FALSE | D53: ='MODEL SUMMARY'!A53 -> QI Inspection | E53: ='MODEL SUMMARY'!W53 -> 310 | F53: =_xlfn.XLOOKUP(D53,A:A,B:B) -> 310 | G53: =F53=E53 -> TRUE
A54: Grading/Lot Clear/Hauling | B54: 1700 | C54: =A54=D54 -> FALSE | D54: ='MODEL SUMMARY'!A54 -> Deck | E54: ='MODEL SUMMARY'!W54 -> 0 | F54: =_xlfn.XLOOKUP(D54,A:A,B:B) -> 0 | G54: =F54=E54 -> TRUE
A55: Silt Fence | B55: 2000 | C55: =A55=D55 -> FALSE | D55: ='MODEL SUMMARY'!A55 -> Mailbox | E55: ='MODEL SUMMARY'!W55 -> 0 | F55: =_xlfn.XLOOKUP(D55,A:A,B:B) -> 0 | G55: =F55=E55 -> TRUE
A56: Temp Drive | B56: 500 | C56: =A56=D56 -> FALSE | D56: ='MODEL SUMMARY'!A56 -> Pressure Wash | E56: ='MODEL SUMMARY'!W56 -> 310 | F56: =_xlfn.XLOOKUP(D56,A:A,B:B) -> 310 | G56: =F56=E56 -> TRUE
A57: Landscaping | B57: 2500 | C57: =A57=D57 -> FALSE | D57: ='MODEL SUMMARY'!A57 -> Foundation | E57: ='MODEL SUMMARY'!W57 -> 12024.5 | F57: =_xlfn.XLOOKUP(D57,A:A,B:B) -> 12024.5 | G57: =F57=E57 -> TRUE
A58: Flatwork | B58: 2475 | E58: =SUM(E4:E57) -> 160612.82
A59: Site Specific Subtotal | B59: =SUM(B53:B58) -> 10875
A60: Building Permits | B60: 2050
A61: Water Meter | B61: 10000
A62: Engineering | B62: 600
A63: Soft Costs Subtotal | B63: =SUM(B60:B62) -> 12650
A64: TOTAL | B64: =B63+B59+B52 -> 184137.82
A66: Classic Package | B66: 4700
A67: Elegance Package | B67: 8900
A68: BTR Harmony Package | B68: 7300

Sheet Locust
A1: LOCUST TH BASE HOUSE COSTS
A3: ACTIVITY | B3: COSTS
A4: Dumpster | B4: 1500
A5: Utilities | B5: 300
A6: Portable toilet | B6: 437.5
A7: Permit Box | B7: 50
A8: Termite | B8: 100
A9: Lumber All Floors | B9: 14992.64
A10: Roof Trusses | B10: 4241.2
A11: Floor Trusses | B11: 4241.2
A12: Stairs | B12: 580.59
A13: Framing Labor | B13: 12057.8
A14: Windows Labor | B14: 264
A15: Window Material | B15: 2360.09
... A51: Foundation | B51: 8980
A52: Sticks & Bricks Subtotal | B52: =SUBTOTAL(109,B4:B51) -> 133947.09
A53: Survey | B53: 1700
A54: Grading/Lot Clear/Hauling | B54: 1700
A55: Silt Fence | B55: 2000
A56: Temp Drive | B56: 500
A57: Landscaping | B57: 2500
A58: Flatwork | B58: 2475
A59: Site Specific Subtotal | B59: =SUM(B53:B58) -> 10875
A60: Building Permits | B60: 2050
A61: Water Meter | B61: 10000
A62: Engineering | B62: 600
A63: Soft Costs Subtotal | B63: =SUM(B60:B62) -> 12650
A64: TOTAL | B64: =B63+B59+B52 -> 157472.09
A66: Classic Package | B66: 4600
A67: Elegance Package | B67: 7200
A68: BTR Harmony Package | B68: TBD

Sheet Palm II
A1: PALM II TH BASE HOUSE COSTS
A3: ACTIVITY | B3: COSTS
A4: Dumpster | B4: 1500
A5: Utilities | B5: 300
A6: Portable toilet | B6: 437.5
A7: Permit Box | B7: 50
A8: Termite | B8: 100
A9: Lumber All Floors | B9: 12257.66
A10: Roof Trusses | B10: 3893.18
A11: Floor Trusses | B11: 3919.99
A12: Stairs | B12: 580.59
A13: Framing Labor | B13: 12164
A14: Windows Labor | B14: 330
A15: Window Material | B15: 2654.72
... A51: Foundation | B51: 8615
A52: Sticks & Bricks Subtotal | B52: =SUBTOTAL(109,B4:B51) -> 132402.26
A53: Survey | B53: 1700
A54: Grading/Lot Clear/Hauling | B54: 1700
A55: Silt Fence | B55: 2000
A56: Temp Drive | B56: 500
A57: Landscaping | B57: 2500
A58: Flatwork | B58: 2475
A59: Site Specific Subtotal | B59: =SUM(B53:B58) -> 10875
A60: Building Permits | B60: 2050
A61: Water Meter | B61: 10000
A62: Engineering | B62: 600
A63: Soft Costs Subtotal | B63: =SUM(B60:B62) -> 12650
A64: TOTAL | B64: =B63+B59+B52 -> 155927.26
A66: Classic Package | B66: 5000
A67: Elegance Package | B67: 8500
A68: BTR Harmony Package | B68: TBD

Sheet Palmetto
A1: PALMETTO TH BASE HOUSE COSTS
A3: ACTIVITY | B3: COSTS
A4: Dumpster | B4: 1500
A5: Utilities | B5: 300
A6: Portable toilet | B6: 437.5
A7: Permit Box | B7: 50
A8: Termite | B8: 100
A9: Lumber All Floors | B9: 10894.93
A10: Roof Trusses | B10: 2966.77
A11: Floor Trusses | B11: 4152.77
A12: Stairs | B12: 580.59
A13: Framing Labor | B13: 8399.64
A14: Windows Labor | B14: 166
A15: Window Material | B15: 2177.34
... A51: Foundation | B51: 6620
A52: Sticks & Bricks Subtotal | B52: =SUBTOTAL(109,B4:B51) -> 110043.18
A53: Survey | B53: 1700
A54: Grading/Lot Clear/Hauling | B54: 1700
A55: Silt Fence | B55: 2000
A56: Temp Drive | B56: 500
A57: Landscaping | B57: 2500
A58: Flatwork | B58: 2475
A59: Site Specific Subtotal | B59: =SUM(B53:B58) -> 10875
A60: Building Permits | B60: 2050
A61: Water Meter | B61: 10000
A62: Engineering | B62: 600
A63: Soft Costs Subtotal | B63: =SUM(B60:B62) -> 12650
A64: TOTAL | B64: =B63+B59+B52 -> 133568.18
A66: Classic Package | B66: 3900
A67: Elegance Package | B67: 8200
A68: BTR Harmony Package | B68: TBD

Sheet Palmetto II
A1: PALMETTO II TH BASE HOUSE COSTS
A3: ACTIVITY | B3: COSTS
A4: Dumpster | B4: 1500
A5: Utilities | B5: 300
A6: Portable toilet | B6: 437.5
A7: Permit Box | B7: 50
A8: Termite | B8: 100
A9: Lumber All Floors | B9: 10676.17
A10: Roof Trusses | B10: 2652.45
A11: Floor Trusses | B11: 3076.33
A12: Stairs | B12: 580.59
A13: Framing Labor | B13: 10275.76
A14: Windows Labor | B14: 220
A15: Window Material | B15: 1767.17
... A51: Foundation | B51: 6890
A52: Sticks & Bricks Subtotal | B52: =SUBTOTAL(109,B4:B51) -> 111054.7
A53: Survey | B53: 1700
A54: Grading/Lot Clear/Hauling | B54: 1700
A55: Silt Fence | B55: 2000
A56: Temp Drive | B56: 500
A57: Landscaping | B57: 2500
A58: Flatwork | B58: 2475
A59: Site Specific Subtotal | B59: =SUM(B53:B58) -> 10875
A60: Building Permits | B60: 2050
A61: Water Meter | B61: 10000
A62: Engineering | B62: 600
A63: Soft Costs Subtotal | B63: =SUM(B60:B62) -> 12650
A64: TOTAL | B64: =B63+B59+B52 -> 134579.7
A66: Classic Package | B66: 4100
A67: Elegance Package | B67: 7200
A68: BTR Harmony Package | B68: 5000

Sheet Pinyon
A1: PINYON TH BASE HOUSE COSTS
A3: ACTIVITY | B3: COSTS
A4: Dumpster | B4: 1500
A5: Utilities | B5: 300
A6: Portable toilet | B6: 437.5
A7: Permit Box | B7: 50
A8: Termite | B8: 100
A9: Lumber All Floors | B9: 16813.43
A10: Roof Trusses | B10: 2724.15
A11: Floor Trusses | B11: 6815.74
A12: Stairs | B12: 1161.17
A13: Framing Labor | B13: 16065.46
A14: Windows Labor | B14: 330
A15: Window Material | B15: 2786.05
... A51: Foundation | B51: 6702.5
A52: Sticks & Bricks Subtotal | B52: =SUBTOTAL(109,B4:B51) -> 151644.3
A53: Survey | B53: 1700
A54: Grading/Lot Clear/Hauling | B54: 1700
A55: Silt Fence | B55: 2000
A56: Temp Drive | B56: 500
A57: Landscaping | B57: 2500
A58: Flatwork | B58: 2475
A59: Site Specific Subtotal | B59: =SUM(B53:B58) -> 10875
A60: Building Permits | B60: 2050
A61: Water Meter | B61: 10000
A62: Engineering | B62: 600
A63: Soft Costs Subtotal | B63: =SUM(B60:B62) -> 12650
A64: TOTAL | B64: =B63+B59+B52 -> 175169.3
A66: Classic Package | B66: 6600
A67: Elegance Package | B67: 11200
A68: BTR Harmony Package | B68: 6200

Sheet Poplar
A1: POPLAR TH BASE HOUSE COSTS
A3: ACTIVITY | B3: COSTS
A4: Dumpster | B4: 1500
A5: Utilities | B5: 300
A6: Portable toilet | B6: 437.5
A7: Permit Box | B7: 50
A8: Termite | B8: 100
A9: Lumber All Floors | B9: 16829.52
A10: Roof Trusses | B10: 3853.01
A11: Floor Trusses | B11: 2848.33
A12: Stairs | B12: 580.59
A13: Framing Labor | B13: 11939.8
A14: Windows Labor | B14: 144
A15: Window Material | B15: 1486.2
... A51: Foundation | B51: 8240
A52: Sticks & Bricks Subtotal | B52: =SUBTOTAL(109,B4:B51) -> 130813.81
A53: Survey | B53: 1700
A54: Grading/Lot Clear/Hauling | B54: 1700
A55: Silt Fence | B55: 2000
A56: Temp Drive | B56: 500
A57: Landscaping | B57: 2500
A58: Flatwork | B58: 2475
A59: Site Specific Subtotal | B59: =SUM(B53:B58) -> 10875
A60: Building Permits | B60: 2050
A61: Water Meter | B61: 10000
A62: Engineering | B62: 600
A63: Soft Costs Subtotal | B63: =SUM(B60:B62) -> 12650
A64: TOTAL | B64: =B63+B59+B52 -> 154338.81
A66: Classic Package | B66: 3900
A67: Elegance Package | B67: 8200
A68: BTR Harmony Package | B68: 3600

Sheet Sycamore
A1: SYCAMORE TH BASE HOUSE COSTS
A3: ACTIVITY | B3: COSTS
A4: Dumpster | B4: 1500
A5: Utilities | B5: 300
A6: Portable toilet | B6: 437.5
A7: Permit Box | B7: 50
A8: Termite | B8: 100
A9: Lumber All Floors | B9: 14421.58
A10: Roof Trusses | B10: 3956.29
A11: Floor Trusses | B11: 5344.62
A12: Stairs | B12: 580.59
A13: Framing Labor | B13: 14974.2
A14: Windows Labor | B14: 198
A15: Window Material | B15: 1742.92
... A51: Foundation | B51: 11022.5
A52: Sticks & Bricks Subtotal | B52: =SUBTOTAL(109,B4:B51) -> 146861.06
A53: Survey | B53: 1700
A54: Grading/Lot Clear/Hauling | B54: 1700
A55: Silt Fence | B55: 2000
A56: Temp Drive | B56: 500
A57: Landscaping | B57: 2500
A58: Flatwork | B58: 2475
A59: Site Specific Subtotal | B59: =SUM(B53:B58) -> 10875
A60: Building Permits | B60: 2050
A61: Water Meter | B61: 10000
A62: Engineering | B62: 600
A63: Soft Costs Subtotal | B63: =SUM(B60:B62) -> 12650
A64: TOTAL | B64: =B63+B59+B52 -> 170386.06
A66: Classic Package | B66: 5500
A67: Elegance Package | B67: 8600
A68: BTR Harmony Package | B68: 4400

Sheet Water & Sewer Data
C4: County | D4: Water Meter Size | E4: Water Tap Fee | F4: Water System Dev. Fee | G4: Total Water | H4: Sewer Tap Fee | I4: Sewer System Dev. Fee | J4: Total Sewer | K4: TOTAL W/S Tap/Dev. Fees | L4: Meter Charge/Unit | M4: Misc. Fees/Notes
C5: None | E5: 0 | F5: 0 | G5: =SUBTOTAL(9,D5:F5) -> 0 | H5: 0 | I5: 0 | J5: =SUBTOTAL(9,H5:I5) -> 0 | K5: =SUBTOTAL(9,D5:J5) -> 0 | L5: 0
C6: Other | G6: =SUBTOTAL(9,D6:F6) -> 0 | J6: =SUBTOTAL(9,H6:I6) -> 0 | K6: =SUBTOTAL(9,D6:J6) -> 0
C7: Alexander | D7: 3/4" | E7: 2300 | F7: 1695 | G7: =SUBTOTAL(9,D7:F7) -> 3995 | J7: =SUBTOTAL(9,H7:I7) -> 0 | K7: =SUBTOTAL(9,D7:J7) -> 3995
C8: Cabarras | D8: 5/8" & 3/4" | F8: 2968 | G8: =SUBTOTAL(9,D8:F8) -> 2968 | J8: =SUBTOTAL(9,H8:I8) -> 0 | K8: =SUBTOTAL(9,D8:J8) -> 2968
C9: Catawba | D9: 1" or Less | F9: 1660 | G9: =SUBTOTAL(9,D9:F9) -> 1660 | I9: 5691 | J9: =SUBTOTAL(9,H9:I9) -> 5691 | K9: =SUBTOTAL(9,D9:J9) -> 7351
C10: Cleveland - In District | D10: 3/4" | E10: 950 | G10: =SUBTOTAL(9,D10:F10) -> 950 | J10: =SUBTOTAL(9,H10:I10) -> 0 | K10: =SUBTOTAL(9,D10:J10) -> 950 | L10: 350
C11: Cleveland - Out of District | D11: 3/4" | E11: 1700 | G11: =SUBTOTAL(9,D11:F11) -> 1700 | J11: =SUBTOTAL(9,H11:I11) -> 0 | K11: =SUBTOTAL(9,D11:J11) -> 1700 | L11: 350
C12: Davidson | D12: 3/4" | E12: 2150 | G12: =SUBTOTAL(9,D12:F12) -> 2150 | J12: =SUBTOTAL(9,H12:I12) -> 0 | K12: =SUBTOTAL(9,D12:J12) -> 2150 | M12: Capital Recovery Fee: $1075 Paid by Developer to Davidson Co. if we install
C13: Davie | D13: 3/4" | E13: 1650 | G13: =SUBTOTAL(9,D13:F13) -> 1650 | J13: =SUBTOTAL(9,H13:I13) -> 0 | K13: =SUBTOTAL(9,D13:J13) -> 1650
C14: Forsyth | D14: 3/4" | E14: 816 | G14: =SUBTOTAL(9,D14:F14) -> 816 | H14: 2861 | J14: =SUBTOTAL(9,H14:I14) -> 2861 | K14: =SUBTOTAL(9,D14:J14) -> 3677 | L14: 159
C15: Gaston | D15: 3/4" | E15: 2243 | F15: 2120 | G15: =SUBTOTAL(9,D15:F15) -> 4363 | H15: 1380 | I15: 2260 | J15: =SUBTOTAL(9,H15:I15) -> 3640 | K15: =SUBTOTAL(9,D15:J15) -> 8003
C16: Guilford | D16: 3/4" | E16: 1782 | G16: =SUBTOTAL(9,D16:F16) -> 1782 | H16: 1516 | J16: =SUBTOTAL(9,H16:I16) -> 1516 | K16: =SUBTOTAL(9,D16:J16) -> 3298 | M16: Water:$593/Sewer:$505
C17: Iredell | D17: 5/8" & 3/4" | E17: 2800 | F17: 652 | G17: =SUBTOTAL(9,D17:F17) -> 3452 | H17: 2100 | I17: 2705 | J17: =SUBTOTAL(9,H17:I17) -> 4805 | K17: =SUBTOTAL(9,D17:J17) -> 8257 | M17: City of Statesville
C18: Lancaster | D18: 5/8" & 3/4" | E18: 2400 | G18: =SUBTOTAL(9,D18:F18) -> 2400 | H18: 3800 | J18: =SUBTOTAL(9,H18:I18) -> 3800 | K18: =SUBTOTAL(9,D18:J18) -> 6200
C19: City of Lexington | D19: 3/4" | E19: 1725 | F19: 1250 | G19: =SUBTOTAL(9,D19:F19) -> 2975 | H19: 2000 | J19: =SUBTOTAL(9,H19:I19) -> 2000 | K19: =SUBTOTAL(9,D19:J19) -> 4975 | L19: 450
C20: Lincoln | D20: 3/4" | E20: 1280 | F20: 3102 | G20: =SUBTOTAL(9,D20:F20) -> 4382 | H20: 3000 | I20: 1621 | J20: =SUBTOTAL(9,H20:I20) -> 4621 | K20: =SUBTOTAL(9,D20:J20) -> 9003 | L20: 265
C21: Mecklenburg | D21: 5/8" | E21: 4332 | F21: 1298 | G21: =SUBTOTAL(9,D21:F21) -> 5630 | H21: 5957 | I21: 5052 | J21: =SUBTOTAL(9,H21:I21) -> 11009 | K21: =SUBTOTAL(9,D21:J21) -> 16639 | L21: 182
C22: Rowan | D22: 3/4" | E22: 2675 | G22: =SUBTOTAL(9,D22:F22) -> 2675 | H22: 1975 | J22: =SUBTOTAL(9,H22:I22) -> 1975 | K22: =SUBTOTAL(9,D22:J22) -> 4650 | L22: 730
C23: Stanly | D23: 3/4" | E23: 1300 | G23: =SUBTOTAL(9,D23:F23) -> 1300 | H23: 1250 | J23: =SUBTOTAL(9,H23:I23) -> 1250 | K23: =SUBTOTAL(9,D23:J23) -> 2550 | L23: 540
C24: Union | D24: 3/4" | E24: 1740 | F24: 1678 | G24: =SUBTOTAL(9,D24:F24) -> 3418 | H24: 3080 | I24: 6412 | J24: =SUBTOTAL(9,H24:I24) -> 9492 | K24: =SUBTOTAL(9,D24:J24) -> 12910 | L24: 360
C25: York | D25: 3/4" | E25: 1725 | F25: 1250 | G25: =SUBTOTAL(9,D25:F25) -> 2975 | H25: 1500 | I25: 2000 | J25: =SUBTOTAL(9,H25:I25) -> 3500 | K25: =SUBTOTAL(9,D25:J25) -> 6475 | L25: 450 | M25: $50 Deposit
C26: Town of Clover | D26: 3/4" | E26: 1500 | G26: =SUBTOTAL(9,D26:F26) -> 1500 | H26: 2230 | J26: =SUBTOTAL(9,H26:I26) -> 2230 | K26: =SUBTOTAL(9,D26:J26) -> 3730 | L26: 150
C27: City of Statesville, NC | E27: 593 | G27: =SUBTOTAL(9,D27:F27) -> 593 | H27: 0 | J27: =SUBTOTAL(9,H27:I27) -> 0 | K27: =SUBTOTAL(9,D27:J27) -> 593
G30: Is there any fees after total water fees per county
G31: Did we develop this lot yes or no
G32: Will there be an impact fee
G33: Did we get a horizontally done lot or did we get raw land?

Sheet Fir
A1: FIR BASE HOUSE COSTS
A3: ACTIVITY | B3: COSTS
A4: Dumpster | B4: 1750
A5: Utilities | B5: 200
A6: Portable toilet | B6: 350
A7: Permit Box | B7: 50
A8: Termite | B8: 250
A9: Lumber All Floors | B9: 20960.029
A10: Framing Labor | B10: 19456
A11: Stairs | B11: 1082.68
A12: Roof Trusses | B12: 2958.25
A13: I-Joist/EWP | B13: 9288.65
A14: Roofing Shingle | B14: 3215.39
A15: Roofing Metal | B15: 0
... A21: Garage Door Labor & Material | B21: 1800
A22: Plumbing Turnkey | B22: =3864.52+3864.52+5900.37 -> 13629.41
A23: HVAC | B23: =8394+5596 -> 13990
A24: Electrical Rough & Trim | B24: =7548+5032 -> 12580
A25: Blower Test | B25: 300.11
A26: Low Voltage/AV | B26: 0
A27: Insulation | B27: =4615+150 -> 4765
A28: Drywall Material | B28: 4635.72
A29: Drywall Labor | B29: 4469.78
A30: Exterior Paint Labor & Material | B30: 0
A31: Interior Paint | B31: 3729.6
A32: Interior Trim Turnkey | B32: 5863.97
A33: Door Hardware | B33: 650.88
A34: Shelving | B34: 551.85
A35: Interior Trim Labor | B35: 0
A36: Mirrors | B36: 799.95
A37: Bath Accessories | B37: 502.32
A38: Shower Door | B38: 787.07
A39: Countertops | B39: 4555
A40: Cabinet Labor & Material | B40: 6305.54
A41: Tile Labor & Material | B41: =425.5+1531 -> 1956.5
A42: Light Fixtures | B42: 981.25
A43: Appliances | B43: 156.8
A44: Carpet Labor & Material | B44: 1730.62
A45: Hardwood Labor & Material | B45: 0
A46: LVP Labor & Material | B46: 8174
A47: Interior Clean | B47: =186.48+186.48+100 -> 472.96
A48: Gutters | B48: 500
A49: Mailbox | B49: 0
A50: Pressure Wash | B50: 300
A51: Foundation | B51: 7000
A52: Sticks & Bricks Subtotal | B52: =SUM(B4:B51) -> 181134.35
A53: Survey Set Pins | B53: 2350
A54: Stake House | B54: 0
A55: Grading/Lot Clear/Hauling | B55: 1500
A56: Silt Fence | B56: 1000
A57: Temp Drive | B57: 500
A58: Landscaping | B58: 2500
A59: Flatwork | B59: 2763
A60: Site Specific Subtotal | B60: =SUM(B53:B59) -> 10613
A61: Building Permits | B61: 2050
A62: Sewer Septic Permit | B62: 11009 | C62: NO MD | D62: 11009 | E62: MD
A63: Water Meter | B63: 5630 | D63: 5630
A64: Engineering | B64: 600
A65: Soft Costs Subtotal | B65: =SUM(B61:B64) -> 19289
A66: TOTAL | B66: =B65+B60+B52 -> 211036.35

Sheet West End
A1: WEST END TH
A3: ACTIVITY | B3: COSTS
A4: Dumpster | B4: 1750
A5: Utilities | B5: 200
A6: Portable toilet | B6: 350
A7: Permit Box | B7: 50
A8: Termite | B8: 250
A9: Lumber All Floors | B9: 17978.67
A10: Framing Labor | B10: 13664
A11: Stairs | B11: 541.34
A12: Roof Trusses | B12: 2350.87
A13: I-Joist/EWP | B13: 3871.91
A14: Roofing Shingle | B14: 1822.25
A15: Roofing Metal | B15: 0
... A51: Foundation | B51: 5778
A52: Sticks & Bricks Subtotal | B52: =SUM(B4:B51) -> 157103.61
A53: Survey Set Pins | B53: 600
A54: Stake House | B54: 600
A55: Grading/Lot Clear/Hauling | B55: 2400
A56: Silt Fence | B56: 2000
A57: Temp Drive | B57: 500
A58: Landscaping | B58: 1500
A59: Flatwork | B59: 5549.99
A60: Site Specific Subtotal | B60: =SUM(B53:B59) -> 13149.99
A61: Building Permits | B61: 1600
A62: Sewer Septic Permit
A63: Water Meter
A64: Engineering | B64: 600
A65: Soft Costs Subtotal | B65: =SUM(B61:B64) -> 2200
A66: TOTAL | B66: =B65+B60+B52 -> 172453.6

Sheet Long Farm
A1: BASE HOUSE COSTS - LONG FARM
A2: ACTIVITY | B2: COSTS | C2: VENDOR
A3: Dumpster | B3: 1750 | C3: Budget | E3: THIS PRICING IS BASED OFF THE AVERAGE PRICE PER SF PER COST CODE AND IS NOT ACTUAL BID COSTS
A4: Utilities | B4: 200 | C4: Budget
A5: Portable toilet | B5: 350 | C5: Budget
A6: Permit Box | B6: 50 | C6: Budget
A7: Termite | B7: 250 | C7: Northwest Exterminating
A8: Lumber All Floors | B8: 13058.379 | C8: Carter
A9: Framing Labor | B9: 11896.044 | C9: Carter
A10: Stairs | B10: 604.57825 | C10: Carter
A11: Roof Trusses | B11: 4412.0162 | C11: Carter
A12: I-Joist/EWP | B12: 4990.8868 | C12: Carter
A13: Roofing Shingle | B13: 3624.3295 | C13: Robert Helms Roofing
A14: Siding Material (Hardi Color Plus) | B14: 7505.5415 | C14: Alsides
A15: Siding Labor (Hardi Color Plus) | B15: 3825.435 | C15: Sarah Construction
... A41: Carpet Labor & Material | B41: 0 | C41: Builders Wholesale
A42: Hardwood Labor & Material | B42: 0
A43: LVP Labor & Material | B43: 6888.2808 | C43: Evergreen
A44: Interior Clean | B44: 418.22 | C44: Total Care Solutions
A45: Gutters | B45: 651.6 | C45: Austin Company
A46: Mailbox | B46: 0 | C46: Evergreen
A47: Pressure Wash | B47: 165 | C47: Total Care Solutions
A48: Foundation | B48: 6285.8766 | C48: Precision Performance Concrete
A49: Landscaping | B49: 3000 | C49: Southern Shade Tree (Budget)
A50: Flatwork | B50: 1500 | C50: PPC (Budget)
A51: Brick | B51: 2500 | C51: NorthStone Masonry
A52: Appliances - Refrigerator | B52: 1429.64 | C52: Ferguson
A53: 4' Black Aluminum Fence | B53: 3500 | C53: Plaza Fence
A54: Blinds | B54: 1000 | C54: Haskell's Hardware
A55: Building Permits | B55: 1600 | C55: Budget
A56: Sticks & Bricks Subtotal | B56: =SUM(B3:B55) -> 161408.98 | E56: ='Long Farm'!$B56/1629 -> 99.0847 | F56: Price Per SF
A57: Survey Set Pins | B57: 600 | C57: Budget
A58: Stake House | B58: 600 | C58: Budget
A59: Grading/Lot Clear/Hauling | B59: 1800 | C59: Budget
A60: Silt Fence | B60: 2000 | C60: Budget
A61: Temp Drive | B61: 500 | C61: Budget
A62: Site Specific Subtotal | B62: =SUM(B57:B61) -> 5500
A63: Sewer/Water Impact Fees | B63: 0 | C63: Budget
A64: Engineering | B64: 0 | C64: Budget
A65: Soft Costs Subtotal | B65: =SUM(B63:B64) -> 0
A66: TOTAL | B66: =B56+B62+B65 -> 166908.98 | E66: ='Long Farm'!$B66/1629 -> 102.461 | F66: Price Per SF
