Workbook

Sheet Assumptions
A1: RAMSEY-RED CEDAR JV PRO FORMA
A2: Edward Road - 137 Single Family Lots
A4: PHASE 1 ASSUMPTIONS
A6: Total Lots | B6: 137 | C6: lots
A7: Land Value per Lot | B7: 20000 | C7: $
A8: Horizontal Dev Cost per Lot | B8: 40000 | C8: $
A9: A&E per Lot | B9: 1500 | C9: $
A10: Amenity Package | B10: 500000 | C10: $
A11: Monument Sign | B11: 20000 | C11: $
A12: Carry Costs per Lot | B12: 1500 | C12: $
A13: Contingency % | B13: 0.1 | C13: %
A14: Const Mgmt Fee per Lot | B14: 1500 | C14: $
A15: Const Mgmt Fee Cap | B15: 250000 | C15: $
A16: Developer Fee per Lot | B16: 3000 | C16: $
A17: Lot Sales Price | B17: 70000 | C17: $
... A21: LP Buyout IRR | B21: 0.25 | C21: %
A23: PHASE 2 ASSUMPTIONS
A25: Home Sales Price | B25: 295000 | C25: $
A26: Selling Costs % | B26: 0.08 | C26: %
A27: Seller Concession | B27: 10000 | C27: $
A28: Vertical Cost (incl RCC fee) | B28: 208000 | C28: $
A29: Vertical Lender Rate | B29: 0.1 | C29: %
A30: Construction Period (mo) | B30: 6 | C30: mo
A31: Scattered Lot Fund LP Return | B31: 0.2 | C31: %

Sheet Phase 1 S&U
A1: PHASE 1: SOURCES & USES
A3: USES
A4: Land Acquisition | B4: =Assumptions!B6*Assumptions!B7 -> 2740000
A5: Horizontal Development | B5: =Assumptions!B6*Assumptions!B8 -> 5480000
A6: Architecture & Engineering | B6: =Assumptions!B6*Assumptions!B9 -> 205500
A7: Amenity Package | B7: =Assumptions!B10 -> 500000
A8: Monument Sign | B8: =Assumptions!B11 -> 20000
A9: Carry Costs (Taxes/Ins) | B9: =Assumptions!B6*Assumptions!B12 -> 205500
A10: Subtotal Hard Costs | B10: =SUM(B4:B9) -> 9151000
A11: Contingency (10%) | B11: =B10*Assumptions!B13 -> 915100
A12: Total Hard + Contingency | B12: =B10+B11 -> 10066100
A13: Construction Mgmt Fee | B13: =MIN(Assumptions!B6*Assumptions!B14,Assumptions!B15) -> 205500
A14: Developer Fee | B14: =Assumptions!B6*Assumptions!B16 -> 411000
A15: Interest Reserve (est) | B15: =B12*Assumptions!B18*Assumptions!B19*1.5 -> 792705.38
A16: TOTAL USES | B16: =B12+B13+B14+B15 -> 11475305
A18: SOURCES
A19: Senior Debt (75% LTC) | B19: =B16*Assumptions!B18 -> 8606479
A20: LP Equity (100% of equity) | B20: =B16-B19 -> 2868826.3
A21: TOTAL SOURCES | B21: =B19+B20 -> 11475305
A23: LOT SALES
A24: Lot Sales Proceeds (137 x $70k) | B24: =Assumptions!B6*Assumptions!B17 -> 9590000
A25: Gross Margin | B25: =B24-B16 -> -1885305.4

Sheet Phase 1 Waterfall
A1: PHASE 1: LP BUYOUT WATERFALL
A3: LP Investment | B3: ='Phase 1 S&U'!B20 -> 2868826.3
A4: Target IRR | B4: =Assumptions!B21 -> 0.25
A6: BUYOUT SCHEDULE
A7: Period | B7: Month | C7: Lots | D7: % Total | E7: LP Principal | F7: IRR Factor | G7: Buyout Amt | H7: Lot Proceeds | I7: GP Equity
A8: 1 | B8: 16 | C8: 20 | D8: =C8/137 -> 0.1459854 | E8: =$B$3*D8 -> 418806.77 | F8: =(1+$B$4)^(B8/12) -> 1.3465217 | G8: =E8*F8 -> 563932.39 | H8: =C8*Assumptions!$B$17 -> 1400000 | I8: =H8-G8 -> 836067.61
A9: 2 | B9: 19 | C9: 20 | D9: =C9/137 -> 0.1459854 | E9: =$B$3*D9 -> 418806.77 | F9: =(1+$B$4)^(B9/12) -> 1.4237733 | G9: =E9*F9 -> 596285.9 | H9: =C9*Assumptions!$B$17 -> 1400000 | I9: =H9-G9 -> 803714.1
A10: 3 | B10: 22 | C10: 20 | D10: =C10/137 -> 0.1459854 | E10: =$B$3*D10 -> 418806.77 | F10: =(1+$B$4)^(B10/12) -> 1.505457 | G10: =E10*F10 -> 630495.58 | H10: =C10*Assumptions!$B$17 -> 1400000 | I10: =H10-G10 -> 769504.42
A11: 4 | B11: 25 | C11: 20 | D11: =C11/137 -> 0.1459854 | E11: =$B$3*D11 -> 418806.77 | F11: =(1+$B$4)^(B11/12) -> 1.591827 | G11: =E11*F11 -> 666667.91 | H11: =C11*Assumptions!$B$17 -> 1400000 | I11: =H11-G11 -> 733332.09
A12: 5 | B12: 28 | C12: 20 | D12: =C12/137 -> 0.1459854 | E12: =$B$3*D12 -> 418806.77 | F12: =(1+$B$4)^(B12/12) -> 1.6831521 | G12: =E12*F12 -> 704915.49 | H12: =C12*Assumptions!$B$17 -> 1400000 | I12: =H12-G12 -> 695084.51
A13: 6 | B13: 31 | C13: 20 | D13: =C13/137 -> 0.1459854 | E13: =$B$3*D13 -> 418806.77 | F13: =(1+$B$4)^(B13/12) -> 1.7797167 | G13: =E13*F13 -> 745357.38 | H13: =C13*Assumptions!$B$17 -> 1400000 | I13: =H13-G13 -> 654642.62
A14: 7 | B14: 34 | C14: 17 | D14: =C14/137 -> 0.12408759 | E14: =$B$3*D14 -> 355985.75 | F14: =(1+$B$4)^(B14/12) -> 1.8818213 | G14: =E14*F14 -> 669901.55 | H14: =C14*Assumptions!$B$17 -> 1190000 | I14: =H14-G14 -> 520098.45
A15: TOTAL | C15: =SUM(C8:C14) -> 137 | E15: =SUM(E8:E14) -> 2868826.3 | G15: =SUM(G8:G14) -> 4577556.2 | H15: =SUM(H8:H14) -> 9590000 | I15: =SUM(I8:I14) -> 5012443.8
A17: SUMMARY
A18: Total LP Investment | B18: =B3 -> 2868826.3
A19: Total LP Buyout | B19: =G15 -> 4577556.2
A20: LP Profit | B20: =B19-B18 -> 1708729.9
A21: LP Multiple | B21: =B19/B18 -> 1.5956198
A23: GP ROLLED EQUITY TO PHASE 2 | B23: =I15 -> 5012443.8
A25: Ramsey (50%) | B25: =B23*0.5 -> 2506221.9
A26: Red Cedar (50%) | B26: =B23*0.5 -> 2506221.9

Sheet Phase 2 S&U
A1: PHASE 2: VERTICAL - PER HOME
A3: REVENUE
A4: Home Sales Price | B4: =Assumptions!B25 -> 295000
A6: COSTS
A7: Lot Cost | B7: =Assumptions!B17 -> 70000
A8: Vertical Construction | B8: =Assumptions!B28 -> 208000
A9: Construction Interest | B9: =B8*0.5*Assumptions!B29*(Assumptions!B30/12) -> 5200
A10: Selling Costs (8%) | B10: =B4*Assumptions!B26 -> 23600
A11: Seller Concession | B11: =Assumptions!B27 -> 10000
A12: TOTAL COST | B12: =SUM(B7:B11) -> 316800
A14: PROFIT PER HOME | B14: =B4-B12 -> -21800
A15: Margin % | B15: =B14/B4 -> -0.073898305
A17: PROJECT TOTALS (137 homes)
A18: Total Revenue | B18: =B4*137 -> 40415000
A19: Total Costs | B19: =B12*137 -> 43401600
A20: Total Profit | B20: =B14*137 -> -2986600

Sheet Phase 2 Waterfall
A1: PHASE 2: SCATTERED LOT FUND WATERFALL
A3: CAPITAL STRUCTURE
A4: GP Rolled Equity from Phase 1 | B4: ='Phase 1 Waterfall'!B23 -> 5012443.8
A5: Total Lot Cost (137 x $70k) | B5: =137*Assumptions!B17 -> 9590000
A6: Scattered Lot Fund LP Capital | B6: =B5-B4 -> 4577556.2
A8: LP RETURN CALC
A9: LP Capital | B9: =B6 -> 4577556.2
A10: Accruing Return | B10: =Assumptions!B31 -> 0.2
A11: Investment Period (months) | B11: 36
A12: Accrued Return | B12: =B9*B10*(B11/12) -> 2746533.7
A13: Total LP Payout | B13: =B9+B12 -> 7324089.9
A15: WATERFALL
A16: Gross Profit from Home Sales | B16: ='Phase 2 S&U'!B20 -> -2986600
A17: Less: LP Accrued Return | B17: =-B12 -> -2746533.7
A18: REMAINING TO GPs | B18: =B16+B17 -> -5733133.7
A20: GP SPLIT (50/50)
A21: Ramsey Roes, LLC | B21: =B18*0.5 -> -2866566.9
A22: Red Cedar Homes, LLC | B22: =B18*0.5 -> -2866566.9
A24: TOTAL GP RETURNS
A25: Phase 1 Rolled Equity | B25: =B4 -> 5012443.8
A26: Phase 2 Profit | B26: =B18 -> -5733133.7
A27: TOTAL GP VALUE | B27: =B25+B26 -> -720689.92
A29: Ramsey Total | B29: =B27*0.5 -> -360344.96
A30: Red Cedar Total | B30: =B27*0.5 -> -360344.96

Sheet Summary
A1: EXECUTIVE SUMMARY
A3: PROJECT OVERVIEW
A4: Total Lots/Homes | B4: =Assumptions!B6 -> 137
A5: Home Sales Price | B5: =Assumptions!B25 -> 295000
A6: Total Revenue | B6: ='Phase 2 S&U'!B18 -> 40415000
A8: PHASE 1: LOT DEVELOPMENT
A9: Total Development Cost | B9: ='Phase 1 S&U'!B16 -> 11475305
A10: Senior Debt | B10: ='Phase 1 S&U'!B19 -> 8606479
A11: LP Equity | B11: ='Phase 1 S&U'!B20 -> 2868826.3
A12: LP Buyout (25% IRR) | B12: ='Phase 1 Waterfall'!G15 -> 4577556.2
A13: GP Rolled Equity | B13: ='Phase 1 Waterfall'!B23 -> 5012443.8
A15: PHASE 2: VERTICAL
A16: Home Sales Revenue | B16: ='Phase 2 S&U'!B18 -> 40415000
A17: Total Costs | B17: ='Phase 2 S&U'!B19 -> 43401600
A18: Gross Profit | B18: ='Phase 2 S&U'!B20 -> -2986600
A19: Scattered Lot Fund LP Payout | B19: ='Phase 2 Waterfall'!B13 -> 7324089.9
A20: Remaining to GPs | B20: ='Phase 2 Waterfall'!B18 -> -5733133.7
A22: TOTAL GP RETURNS
A23: Phase 1 + Phase 2 | B23: ='Phase 2 Waterfall'!B27 -> -720689.92
A25: Ramsey Roes, LLC (50%) | B25: =B23*0.5 -> -360344.96
A26: Red Cedar Homes, LLC (50%) | B26: =B23*0.5 -> -360344.96
